Workbook

Sheet Customers
A1: Customer_ID | B1: Age | C1: Gender | D1: Region | E1: Occupation | F1: Marital_Status | G1: Annual_Income_EUR | H1: Tenure_Years | I1: Account_Open_Date | J1: Preferred_Channel | K1: Num_Products | L1: Checking_Balance_EUR | M1: Savings_Balance_EUR | N1: Monthly_Transactions | O1: Avg_Transaction_EUR | P1: Monthly_ATM_Withdrawals | Q1: Card_Limit_EUR | R1: Monthly_Card_Spend_EUR | S1: Mortgage_Balance_EUR | T1: Monthly_Mortgage_Payment_EUR | U1: Credit_Score | V1: Complaints_12M
A2: CL00001 | B2: 18 | C2: M | D2: Campania | E2: Employee | F2: Single | G2: 25900 | H2: 0 | I2: 46008 | J2: Online Banking | K2: 2 | L2: 5758.21 | M2: 3643.27 | N2: 21 | O2: 23.72 | P2: 2 | Q2: 0 | R2: 0 | S2: 0 | T2: 0 | U2: 598 | V2: 0
A3: CL00002 | B3: 34 | C3: M | D3: Veneto | E3: Employee | F3: Married | G3: 17200 | H3: 8 | I3: 43326 | J3: App | K3: 1 | L3: 807.12 | M3: 18365.11 | N3: 26 | O3: 24.13 | P3: 0 | Q3: 60000 | R3: 2383.65 | S3: 0 | T3: 0 | U3: 529 | V3: 0
A4: CL00003 | B4: 38 | C4: F | D4: Lombardia | E4: Self-employed | F4: Married | G4: 61200 | H4: 3 | I4: 44850 | J4: App | K4: 1 | L4: 3371.02 | M4: 12031.56 | N4: 34 | O4: 107.36 | P4: 4 | Q4: 13500 | R4: 3032.1 | S4: 0 | T4: 0 | U4: 644 | V4: 0
A5: CL00004 | B5: 60 | C5: F | D5: Puglia | E5: Employee | F5: Widowed | G5: 26100 | H5: 20 | I5: 38715 | J5: Branch | K5: 1 | L5: 1236.32 | M5: 16031.41 | N5: 18 | O5: 54.56 | P5: 6 | Q5: 3000 | R5: 989.63 | S5: 0 | T5: 0 | U5: 661 | V5: 1
A6: CL00005 | B6: 34 | C6: M | D6: Piemonte | E6: Business owner | F6: Married | G6: 90400 | H6: 3 | I6: 44941 | J6: App | K6: 1 | L6: 8268.48 | M6: 0 | N6: 45 | O6: 119.75 | P6: 2 | Q6: 0 | R6: 0 | S6: 249000 | T6: 1355 | U6: 655 | V6: 0
A7: CL00006 | B7: 33 | C7: F | D7: Marche | E7: Manual worker | F7: Married | G7: 25500 | H7: 7 | I7: 43552 | J7: App | K7: 1 | L7: 932.74 | M7: 0 | N7: 26 | O7: 33 | P7: 2 | Q7: 0 | R7: 0 | S7: 0 | T7: 0 | U7: 556 | V7: 0
A8: CL00007 | B8: 40 | C8: M | D8: Campania | E8: Self-employed | F8: Single | G8: 35300 | H8: 8 | I8: 43193 | J8: Branch | K8: 1 | L8: 4814.58 | M8: 25412.02 | N8: 24 | O8: 33.81 | P8: 7 | Q8: 6000 | R8: 3472.77 | S8: 0 | T8: 0 | U8: 611 | V8: 0
A9: CL00008 | B9: 51 | C9: M | D9: Campania | E9: Business owner | F9: Divorced | G9: 60200 | H9: 8 | I9: 43152 | J9: Phone | K9: 1 | L9: 4195.77 | M9: 0 | N9: 34 | O9: 36.06 | P9: 2 | Q9: 0 | R9: 0 | S9: 191000 | T9: 1122 | U9: 653 | V9: 0
A10: CL00009 | B10: 35 | C10: M | D10: Abruzzo | E10: Manual worker | F10: Divorced | G10: 18700 | H10: 8 | I10: 43036 | J10: App | K10: 2 | L10: 3543.25 | M10: 4344.98 | N10: 31 | O10: 37.3 | P10: 1 | Q10: 4500 | R10: 1848.95 | S10: 64000 | T10: 316 | U10: 636 | V10: 0
A11: CL00010 | B11: 42 | C11: F | D11: Piemonte | E11: Manual worker | F11: Divorced | G11: 20600 | H11: 8 | I11: 43029 | J11: Online Banking | K11: 2 | L11: 1420.04 | M11: 11463.31 | N11: 29 | O11: 35.63 | P11: 1 | Q11: 0 | R11: 0 | S11: 0 | T11: 0 | U11: 641 | V11: 2
A12: CL00011 | B12: 33 | C12: F | D12: Lombardia | E12: Teacher | F12: Married | G12: 27200 | H12: 2 | I12: 45315 | J12: Online Banking | K12: 2 | L12: 2148.99 | M12: 13164.51 | N12: 29 | O12: 42.36 | P12: 5 | Q12: 5000 | R12: 907.68 | S12: 54000 | T12: 278 | U12: 598 | V12: 1
A13: CL00012 | B13: 49 | C13: M | D13: Veneto | E13: Business owner | F13: Married | G13: 82900 | H13: 5 | I13: 44241 | J13: App | K13: 2 | L13: 3302.9 | M13: 60831.37 | N13: 43 | O13: 59.29 | P13: 0 | Q13: 12500 | R13: 834.11 | S13: 0 | T13: 0 | U13: 675 | V13: 0
... A326: CL00320 | B326: 51 | C326: F | D326: Liguria | E326: Manual worker | F326: Married | G326: 17400 | H326: 28 | I326: 35693 | J326: Online Banking | K326: 3 | L326: 1271.02 | M326: 0 | N326: 21 | O326: 61.46 | P326: 3 | Q326: 2000 | R326: 827.17 | S326: 0 | T326: 0 | U326: 682 | V326: 0
A327: CL00321 | B327: 51 | C327: M | D327: Sardegna | E327: Shopkeeper | F327: Married | H327: 15 | I327: 40599 | J327: App | K327: 6 | L327: 2011.14 | M327: 12379.47 | N327: 32 | O327: 73.22 | P327: 1 | Q327: 5000 | R327: 646.39 | S327: 100000 | T327: 601 | U327: 660 | V327: 0
A328: CL00322 | B328: 61 | C328: M | D328: Campania | E328: Employee | F328: Divorced | G328: 58600 | H328: 31 | I328: 34929 | J328: Online Banking | K328: 2 | L328: 3993.46 | M328: 99658.82 | N328: 43 | O328: 86.75 | P328: 3 | Q328: 0 | R328: 0 | S328: 247000 | T328: 1674 | U328: 654 | V328: 0
A329: CL00323 | B329: 34 | C329: F | D329: Lombardia | E329: Employee | F329: Married | G329: 27300 | H329: 7 | I329: 43566 | J329: App | K329: 3 | L329: -885.13 | M329: 12276.86 | N329: 17 | O329: 51.08 | P329: 0 | Q329: 5500 | R329: 1032.22 | S329: 120000 | T329: 775 | U329: 625 | V329: 0
A330: CL00324 | B330: 50 | C330: F | D330: Emilia-Romagna | E330: Employee | F330: Married | G330: 29000 | H330: 13 | I330: 41412 | J330: Online Banking | K330: 2 | L330: -1057.82 | M330: 14123.96 | N330: 30 | O330: 50.26 | P330: 6 | Q330: 5000 | R330: 974.87 | S330: 0 | T330: 0 | U330: 659 | V330: 0
A331: CL00325 | B331: 41 | C331: F | D331: Piemonte | E331: Manual worker | F331: Married | G331: 31500 | H331: 2 | I331: 45494 | J331: Online Banking | K331: 1 | L331: 3410.51 | M331: 0 | N331: 27 | O331: 50.32 | P331: 2 | Q331: 4000 | R331: 696.38 | S331: 0 | T331: 0 | U331: 638 | V331: 1
A332: CL00326 | B332: 39 | C332: F | D332: Puglia | E332: Manual worker | F332: Married | G332: 34900 | H332: 10 | I332: 42435 | J332: App | K332: 3 | L332: 1353.63 | M332: 35048.42 | N332: 25 | O332: 32.55 | P332: 1 | Q332: 3500 | R332: 258.68 | S332: 0 | T332: 0 | U332: 619 | V332: 1
A333: CL00327 | B333: 50 | C333: F | D333: Abruzzo | E333: Employee | F333: Married | G333: 29100 | H333: 20 | I333: 38968 | J333: App | K333: 4 | L333: 2893.47 | M333: 0 | N333: 25 | O333: 30.21 | P333: 1 | Q333: 4000 | R333: 138.62 | S333: 0 | T333: 0 | U333: 687 | V333: 0
A334: CL00328 | B334: 47 | C334: M | D334: Lazio | E334: Teacher | F334: Married | G334: 50800 | H334: 4 | I334: 44459 | J334: Phone | K334: 1 | L334: 6637.83 | M334: 11964.55 | N334: 29 | O334: 46.42 | P334: 4 | Q334: 12000 | R334: 339.45 | S334: 0 | T334: 0 | U334: 649 | V334: 1
A335: CL00329 | B335: 31 | C335: M | D335: Veneto | E335: Executive | F335: Single | G335: 94000 | H335: 5 | I335: 44095 | J335: App | K335: 1 | L335: 8052.1 | M335: 23930.35 | N335: 54 | O335: 43.37 | P335: 0 | Q335: 0 | R335: 0 | S335: 0 | T335: 0 | U335: 704 | V335: 0
A336: CL00330 | B336: 55 | C336: F | D336: Sardegna | E336: Manual worker | F336: Single | G336: 26100 | H336: 19 | I336: 39006 | J336: Branch | K336: 5 | L336: 1379 | M336: 9492.38 | N336: 17 | O336: 84.92 | P336: 4 | Q336: 3000 | R336: 1352.34 | S336: 0 | T336: 0 | U336: 635 | V336: 0
A337: CL00331 | B337: 49 | C337: M | D337: Lazio | E337: Manual worker | F337: Divorced | G337: 25500 | H337: 11 | I337: 42240 | J337: Online Banking | K337: 3 | L337: 1825.41 | M337: 13391.17 | N337: 28 | O337: 79.26 | P337: 5 | Q337: 2500 | R337: 742.45 | S337: 64000 | T337: 472 | U337: 583 | V337: 0
A338: CL00332 | B338: 57 | C338: M | D338: Lombardia | E338: Self-employed | F338: Married | G338: 73500 | H338: 13 | I338: 41493 | J338: Branch | K338: 2 | L338: 3647.27 | M338: 55919.85 | N338: 41 | O338: 69.64 | P338: 3 | Q338: 15000 | R338: 4683.93 | S338: 0 | T338: 0 | U338: 642 | V338: 1
A339: CL00333 | B339: 26 | C339: F | D339: Campania | E339: Unemployed | F339: Single | G339: 8800 | H339: 0 | I339: 45978 | J339: App | K339: 1 | L339: 554.04 | M339: 0 | N339: 48 | O339: 199 | P339: 0 | Q339: 0 | R339: 0 | S339: 0 | T339: 0 | U339: 657 | V339: 0
... A511: CL00505 | B511: 47 | C511: F | D511: Puglia | E511: Employee | F511: Single | G511: 27200 | H511: 21 | I511: 38319 | J511: Branch | K511: 3 | L511: 1895.12 | M511: 0 | N511: 28 | O511: 49.64 | P511: 2 | Q511: 6000 | R511: 1788.23 | S511: 0 | T511: 0 | U511: 644 | V511: 0
A512: CL00506 | B512: 44 | C512: F | D512: Lombardia | E512: Executive | F512: Divorced | G512: 88800 | H512: 5 | I512: 44381 | J512: App | K512: 3 | L512: 7433.02 | N512: 59 | O512: 44.22 | P512: 2 | Q512: 10500 | R512: 2460.45 | S512: 396000 | T512: 2449 | U512: 674 | V512: 1
A513: CL00507 | B513: 23 | C513: M | D513: Sardegna | E513: Retired | F513: Single | G513: 4700 | H513: 2 | I513: 45523 | J513: App | K513: 1 | L513: 603.31 | M513: 2101.95 | N513: 30 | O513: 39.73 | P513: 1 | Q513: 0 | R513: 0 | S513: 0 | T513: 0 | U513: 512 | V513: 0
A514: CL00508 | B514: 33 | C514: F | D514: Marche | E514: Manual worker | F514: Married | G514: 29700 | H514: 5 | I514: 44335 | J514: App | K514: 2 | L514: 3500.93 | M514: 19581.17 | N514: 35 | O514: 49.09 | P514: 2 | Q514: 6000 | R514: 80.7 | S514: 0 | T514: 0 | U514: 616 | V514: 0
A515: CL00509 | B515: 44 | C515: M | D515: Marche | E515: Employee | F515: Single | G515: 31800 | H515: 9 | I515: 42647 | J515: Online Banking | K515: 1 | L515: 1545.25 | M515: 0 | N515: 37 | O515: 45.03 | P515: 3 | Q515: 0 | R515: 0 | S515: 0 | T515: 0 | U515: 567 | V515: 1
A516: CL00510 | B516: 73 | C516: F | D516: Veneto | E516: Retired | F516: Married | G516: 28700 | H516: 5 | I516: 44162 | J516: Branch | K516: 3 | L516: 4140.01 | M516: 9548.4 | N516: 25 | O516: 84.65 | P516: 2 | Q516: 5500 | R516: 1330.93 | S516: 0 | T516: 0 | U516: 601 | V516: 0
A517: CL00511 | B517: 48 | C517: F | D517: Lazio | E517: Employee | F517: Married | G517: 19600 | H517: 28 | I517: 35906 | J517: Online Banking | K517: 5 | L517: 2265.44 | M517: 54829.29 | N517: 25 | O517: 43.09 | P517: 1 | Q517: 5000 | R517: 2230.35 | S517: 0 | T517: 0 | U517: 669 | V517: 0
A518: CL00512 | B518: 47 | C518: F | D518: Lombardia | E518: Employee | F518: Married | G518: 33500 | H518: 5 | I518: 44408 | J518: Branch | K518: 1 | L518: 962.15 | M518: 19435.98 | N518: 14 | O518: 39.34 | P518: 6 | Q518: 5000 | R518: 160.09 | S518: 162000 | T518: 837 | U518: 620 | V518: 0
A519: CL00513 | B519: 47 | C519: M | D519: Abruzzo | E519: Employee | F519: Married | G519: 25200 | H519: 7 | I519: 43433 | J519: Online Banking | K519: 1 | L519: 3330.14 | M519: 0 | N519: 23 | O519: 27.86 | P519: 3 | Q519: 3500 | R519: 1275.87 | S519: 0 | T519: 0 | U519: 635 | V519: 0
A520: CL00514 | B520: 29 | C520: F | D520: Sicilia | E520: Manual worker | F520: Married | G520: 19700 | H520: 7 | I520: 43507 | J520: App | K520: 1 | L520: 919.22 | M520: 17762.87 | N520: 19 | O520: 59.89 | P520: 1 | Q520: 0 | R520: 0 | S520: 0 | T520: 0 | U520: 1200 | V520: 2
A521: CL00515 | B521: 76 | C521: M | D521: Lombardia | E521: Retired | F521: Married | G521: 16700 | H521: 17 | I521: 40061 | J521: Branch | K521: 2 | L521: 2929.26 | M521: 38268.37 | N521: 16 | O521: 74.67 | P521: 2 | Q521: 0 | R521: 0 | S521: 0 | T521: 0 | U521: 623 | V521: 1
A522: CL00516 | B522: 37 | C522: M | D522: Abruzzo | E522: Employee | F522: Married | G522: 26000 | H522: 15 | I522: 40751 | J522: App | K522: 1 | L522: 2521.45 | M522: 0 | N522: 29 | O522: 48.34 | P522: 1 | Q522: 4500 | R522: 860.3 | S522: 124000 | T522: 855 | U522: 589 | V522: 1
A523: CL00517 | B523: 45 | C523: F | D523: Friuli-Venezia Giulia | E523: Self-employed | F523: Married | G523: 69100 | H523: 6 | I523: 43841 | J523: App | K523: 1 | L523: 2880.7 | M523: 28560.07 | N523: 45 | O523: 46.56 | P523: 0 | Q523: 7500 | R523: 2264.39 | S523: 255000 | T523: 1657 | U523: 585 | V523: 0
A524: CL00518 | B524: 74 | C524: M | D524: Sardegna | E524: Retired | F524: Widowed | G524: 16600 | H524: 17 | I524: 39811 | J524: Branch | K524: 3 | L524: 964.16 | M524: 0 | N524: 21 | O524: 46.93 | P524: 6 | Q524: 0 | R524: 0 | S524: 0 | T524: 0 | U524: 665 | V524: 0
... A693: CL00686 | B693: 51 | C693: F | D693: Sicilia | E693: Manual worker | F693: Married | G693: 16500 | H693: 4 | I693: 44720 | J693: App | K693: 1 | L693: 921.86 | M693: 6165.32 | N693: 16 | O693: 31.13 | P693: 1 | Q693: 3500 | R693: 903.69 | S693: 0 | T693: 0 | U693: 584 | V693: 0
A694: CL00687 | B694: 72 | C694: F | D694: Friuli-Venezia Giulia | E694: Retired | F694: Married | H694: 31 | I694: 34804 | J694: Branch | K694: 5 | L694: 2980.84 | M694: 0 | N694: 21 | O694: 36.54 | P694: 5 | Q694: 4000 | R694: 172.13 | S694: 0 | T694: 0 | U694: 696 | V694: 0
A695: CL00688 | B695: 36 | C695: F | D695: Puglia | E695: Business owner | F695: Married | G695: 72600 | H695: 9 | I695: 42970 | J695: Branch | K695: 4 | L695: 3500.91 | M695: 0 | N695: 29 | O695: 103.69 | P695: 4 | Q695: 10500 | R695: 3580.88 | S695: 263000 | T695: 1412 | U695: 683 | V695: 0
A696: CL00689 | B696: 62 | C696: F | D696: Lombardia | E696: Business owner | F696: Married | G696: 75700 | H696: 15 | I696: 40718 | J696: App | K696: 2 | L696: 4255.2 | M696: 64346.95 | N696: 46 | O696: 62.65 | P696: 1 | Q696: 0 | R696: 0 | S696: 0 | T696: 0 | U696: 722 | V696: 0
A697: CL00690 | B697: 39 | C697: F | D697: Veneto | E697: Manual worker | F697: Single | G697: 24800 | H697: 9 | I697: 42852 | J697: App | K697: 2 | L697: 2424.14 | M697: 0 | N697: 26 | O697: 35.11 | P697: 5 | Q697: 0 | R697: 0 | S697: 0 | T697: 0 | U697: 595 | V697: 1
A698: CL00691 | B698: 59 | C698: F | D698: Calabria | E698: Executive | F698: Single | G698: 120400 | H698: 13 | I698: 41373 | J698: Online Banking | K698: 4 | L698: 10789.63 | M698: 0 | N698: 56 | O698: 139.27 | P698: 3 | Q698: 15000 | R698: 4884.33 | S698: 0 | T698: 0 | U698: 771 | V698: 0
A699: CL00692 | B699: 55 | C699: M | D699: Toscana | E699: Employee | F699: Divorced | G699: 23600 | H699: 21 | I699: 38505 | J699: Online Banking | K699: 4 | L699: 2038.09 | M699: 0 | N699: 21 | O699: 45.18 | P699: 2 | Q699: 4000 | R699: 1134.11 | S699: 0 | T699: 0 | U699: 665 | V699: 0
A700: CL00693 | B700: 0 | C700: M | D700: Toscana | E700: Manual worker | F700: Widowed | G700: 26700 | H700: 13 | I700: 41462 | J700: App | K700: 3 | L700: 2572.79 | M700: 0 | N700: 29 | O700: 46.5 | P700: 1 | Q700: 5000 | R700: 448.74 | S700: 0 | T700: 0 | U700: 686 | V700: 0
A701: CL00694 | B701: 68 | C701: F | D701: Veneto | E701: Retired | F701: Married | G701: 10600 | H701: 33 | I701: 34207 | J701: Branch | K701: 5 | L701: 1292.9 | M701: 0 | N701: 15 | O701: 24.61 | P701: 6 | Q701: 3500 | R701: 3900 | S701: 0 | T701: 0 | U701: 661 | V701: 0
A702: CL00695 | B702: 49 | C702: F | D702: Puglia | E702: Unemployed | F702: Married | G702: 6900 | H702: 4 | I702: 44515 | J702: App | K702: 3 | L702: 813.87 | M702: 2057.79 | N702: 16 | O702: 29.76 | P702: 3 | Q702: 1000 | R702: 144.08 | S702: 0 | T702: 0 | U702: 546 | V702: 0
A703: CL00696 | B703: 43 | C703: M | D703: Basilicata | E703: Manual worker | F703: Divorced | G703: 22500 | H703: 10 | I703: 42433 | J703: Phone | K703: 1 | L703: 2727.74 | M703: 12459.27 | N703: 22 | O703: 38.32 | P703: 2 | Q703: 4500 | R703: 855.14 | S703: 48000 | T703: 305 | U703: 627 | V703: 0
A704: CL00697 | B704: 24 | C704: F | D704: Campania | E704: Student | F704: Single | G704: 9900 | H704: 0 | I704: 45969 | J704: App | K704: 1 | L704: 316.17 | M704: 0 | N704: 48 | O704: 199 | P704: 0 | Q704: 0 | R704: 0 | S704: 0 | T704: 0 | U704: 626 | V704: 0
A705: CL00698 | B705: 41 | C705: F | D705: Emilia-Romagna | E705: Employee | F705: Single | G705: 32900 | H705: 6 | I705: 44057 | J705: App | K705: 1 | L705: 2091.08 | M705: 21138.42 | N705: 45 | O705: 80.18 | P705: 0 | Q705: 7000 | R705: 367.89 | S705: 0 | T705: 0 | U705: 590 | V705: 0
A706: CL00699 | B706: 79 | C706: M | D706: Lazio | E706: Retired | F706: Widowed | G706: 31100 | H706: 20 | I706: 38638 | J706: Branch | K706: 2 | L706: 357.86 | M706: 21834.77 | N706: 21 | O706: 47.84 | P706: 4 | Q706: 6500 | R706: 651.68 | S706: 0 | T706: 0 | U706: 634 | V706: 0
... A728: CL00721 | B728: 53 | C728: M | D728: Veneto | E728: Shopkeeper | F728: Married | G728: 29300 | H728: 2 | I728: 45491 | J728: Online Banking | K728: 2 | L728: 4131.61 | M728: 3973.76 | N728: 35 | O728: 67.3 | P728: 3 | Q728: 7000 | R728: 2403.13 | S728: 0 | T728: 0 | U728: 520 | V728: 1
A729: CL00722 | B729: 62 | C729: F | D729: Lazio | E729: Teacher | F729: Married | G729: 51100 | H729: 32 | I729: 34342 | J729: Phone | K729: 3 | L729: 5319.66 | N729: 26 | O729: 73.13 | P729: 2 | Q729: 8500 | R729: 2405.64 | S729: 0 | T729: 0 | U729: 710 | V729: 1
A730: CL00723 | B730: 67 | C730: F | D730: Toscana | E730: Self-employed | F730: Married | G730: 50300 | H730: 21 | I730: 38597 | J730: App | K730: 3 | L730: -2278.51 | M730: 39129.36 | N730: 36 | O730: 44.37 | P730: 2 | Q730: 10500 | R730: 1526.59 | S730: 0 | T730: 0 | U730: 696 | V730: 0
A731: CL00724 | B731: 46 | C731: M | D731: Toscana | E731: Executive | F731: Married | G731: 86100 | H731: 17 | I731: 40054 | J731: Online Banking | K731: 2 | L731: 9989.16 | M731: 62770.96 | N731: 43 | O731: 131.81 | P731: 4 | Q731: 15000 | R731: 1814.1 | S731: 353000 | T731: 1888 | U731: 783 | V731: 0
A732: CL00725 | B732: 54 | C732: F | D732: Liguria | E732: Employee | F732: Divorced | G732: 34100 | H732: 9 | I732: 42897 | J732: Online Banking | K732: 2 | L732: 5825.33 | M732: 20821.21 | N732: 38 | O732: 37.72 | P732: 6 | Q732: 6000 | R732: 2534.54 | S732: 0 | T732: 0 | U732: 685 | V732: 0
A733: CL00726 | B733: 31 | C733: M | D733: Lombardia | E733: Employee | F733: Widowed | G733: 45100 | H733: 9 | I733: 42844 | J733: App | K733: 2 | L733: 2427.34 | M733: 25917.86 | N733: 30 | O733: 60.74 | P733: 1 | Q733: 7500 | R733: 5080.46 | S733: 0 | T733: 0 | U733: 587 | V733: 0
A734: CL00727 | B734: 57 | C734: F | D734: Sicilia | E734: Self-employed | F734: Single | G734: 33400 | H734: 23 | I734: 37562 | J734: Branch | K734: 1 | L734: 7531.91 | M734: 31158.74 | N734: 21 | O734: 43.37 | P734: 7 | Q734: 6500 | R734: 726.34 | S734: 137000 | T734: 680 | U734: 733 | V734: 0
A735: CL00728 | B735: 47 | C735: M | D735: Lazio | E735: Self-employed | F735: Married | G735: 56100 | H735: 15 | I735: 40469 | J735: App | K735: 3 | L735: 5731.32 | M735: 0 | N735: 45 | O735: 80.82 | P735: 0 | Q735: 0 | R735: 0 | S735: 240000 | T735: 1684 | U735: 705 | V735: 0
A736: CL00729 | B736: 47 | C736: F | D736: Lombardia | E736: Employee | F736: Divorced | G736: 26700 | H736: 14 | I736: 40846 | J736: Online Banking | K736: 1 | L736: 2855.24 | M736: 0 | N736: 39 | O736: 46.62 | P736: 2 | Q736: 5000 | R736: 819.06 | S736: 99000 | T736: 571 | U736: 587 | V736: 0
A737: CL00730 | B737: 42 | C737: F | D737: Lazio | E737: Manual worker | F737: Married | G737: 22900 | H737: 15 | I737: 40771 | J737: App | K737: 2 | L737: 934.88 | M737: 33685.55 | N737: 21 | O737: 55.93 | P737: 0 | Q737: 3500 | R737: 1171.86 | S737: 74000 | T737: 415 | U737: 635 | V737: 0
A738: CL00731 | B738: 45 | C738: M | D738: Emilia-Romagna | E738: Manual worker | F738: Married | G738: 18800 | H738: 2 | I738: 45236 | J738: App | K738: 2 | L738: 699.47 | M738: 2938.05 | N738: 26 | O738: 43.21 | P738: 1 | Q738: 3500 | R738: 580.53 | S738: 50000 | T738: 261 | U738: 557 | V738: 1
A739: CL00732 | B739: 64 | C739: M | D739: Lombardia | E739: Executive | F739: Married | G739: 63400 | H739: 16 | I739: 40322 | J739: Phone | K739: 1 | L739: -2067.26 | M739: 52379.05 | N739: 30 | O739: 42.53 | P739: 4 | Q739: 7500 | R739: 2993.67 | S739: 0 | T739: 0 | U739: 701 | V739: 0
A740: CL00733 | B740: 44 | C740: M | D740: Toscana | E740: Executive | F740: Divorced | G740: 105300 | H740: 7 | I740: 43623 | J740: Phone | K740: 2 | L740: 10700.14 | M740: 77670.04 | N740: 46 | O740: 98.26 | P740: 0 | Q740: 15000 | R740: 4311.34 | S740: 0 | T740: 0 | U740: 666 | V740: 0
A741: CL00734 | B741: 25 | C741: F | D741: Calabria | E741: Employee | F741: Single | G741: 38200 | H741: 2 | I741: 45477 | J741: Online Banking | K741: 2 | L741: 3345.72 | M741: 8952.52 | N741: 34 | O741: 31.77 | P741: 3 | Q741: 9000 | R741: 2398.17 | S741: 0 | T741: 0 | U741: 589 | V741: 0
... A846: CL00839 | B846: 54 | C846: M | D846: Sicilia | E846: Manual worker | F846: Married | G846: 36600 | H846: 21 | I846: 38592 | J846: App | K846: 3 | L846: 12760.09 | M846: 0 | N846: 27 | O846: 56.95 | P846: 0 | Q846: 7500 | R846: 682.56 | S846: 0 | T846: 0 | U846: 701 | V846: 2
A847: CL00840 | B847: 37 | C847: F | D847: Puglia | E847: Employee | F847: Married | H847: 10 | I847: 42507 | J847: App | K847: 4 | L847: 4902.9 | M847: 0 | N847: 36 | O847: 80.08 | P847: 2 | Q847: 0 | R847: 0 | S847: 104000 | T847: 516 | U847: 649 | V847: 0
A848: CL00841 | B848: 42 | C848: M | D848: Puglia | E848: Shopkeeper | F848: Single | G848: 16700 | H848: 4 | I848: 44773 | J848: Online Banking | K848: 4 | L848: 1068.74 | M848: 4555.34 | N848: 32 | O848: 32.34 | P848: 3 | Q848: 0 | R848: 0 | S848: 78000 | T848: 352 | U848: 614 | V848: 0
A849: CL00842 | B849: 32 | C849: F | D849: Umbria | E849: Shopkeeper | F849: Married | G849: 39700 | H849: 2 | I849: 45521 | J849: Online Banking | K849: 2 | L849: 1770.12 | M849: 20141.82 | N849: 42 | O849: 64 | P849: 4 | Q849: 4000 | R849: 233.56 | S849: 144000 | T849: 840 | U849: 616 | V849: 0
A850: CL00843 | B850: 53 | C850: F | D850: Lazio | E850: Employee | F850: Single | G850: 79000 | H850: 7 | I850: 43431 | J850: App | K850: 2 | L850: 2941.22 | M850: 0 | N850: 30 | O850: 78.27 | P850: 1 | Q850: 9500 | R850: 3677.07 | S850: 195000 | T850: 1272 | U850: 616 | V850: 0
A851: CL00844 | B851: 53 | C851: M | D851: Lazio | E851: Employee | F851: Married | G851: 39600 | H851: 15 | I851: 40652 | J851: App | K851: 2 | L851: 4077.6 | M851: 0 | N851: 34 | O851: 74.36 | P851: 1 | Q851: 0 | R851: 0 | S851: 94000 | T851: 430 | U851: 700 | V851: 0
A852: CL00845 | B852: 55 | C852: F | D852: Emilia-Romagna | E852: Shopkeeper | F852: Married | G852: 48000 | H852: 13 | I852: 41188 | J852: Online Banking | K852: 3 | L852: 1436.44 | M852: 0 | N852: 32 | O852: 68.26 | P852: 1 | Q852: 0 | R852: 0 | S852: 0 | T852: 0 | U852: 699 | V852: 1
A853: CL00846 | B853: 41 | C853: F | D853: Campania | E853: Manual worker | F853: Married | G853: 22800 | H853: 10 | I853: 42369 | J853: Online Banking | K853: 3 | L853: 4040.02 | M853: 16319.52 | N853: 27 | O853: 39.14 | P853: 2 | Q853: 4500 | R853: 23.18 | S853: 82000 | T853: 520 | U853: 655 | V853: 0
A854: CL00847 | B854: 59 | C854: M | D854: Campania | E854: Shopkeeper | F854: Married | G854: 27200 | H854: 15 | I854: 40674 | J854: Branch | K854: 3 | L854: 522.79 | M854: 38039.1 | N854: 20 | O854: 32.61 | P854: 4 | Q854: 3000 | R854: 1054.09 | S854: 114000 | T854: 586 | U854: 603 | V854: 1
A855: CL00848 | B855: 30 | C855: M | D855: Friuli-Venezia Giulia | E855: Executive | F855: Married | G855: 71100 | H855: 2 | I855: 45497 | J855: Branch | K855: 4 | L855: 5932.64 | M855: 25096.94 | N855: 48 | O855: 125.56 | P855: 5 | Q855: 9500 | R855: 591.95 | S855: 0 | T855: 0 | U855: 655 | V855: 1
A856: CL00849 | B856: 28 | C856: M | D856: Lombardia | E856: Retired | F856: Divorced | G856: 29200 | H856: 2 | I856: 45370 | J856: Online Banking | K856: 2 | L856: 3242.3 | M856: 10489.42 | N856: 37 | O856: 130.61 | P856: 3 | Q856: 3000 | R856: 783.53 | S856: 0 | T856: 0 | U856: 635 | V856: 2
A857: CL00850 | B857: 33 | C857: M | D857: Sardegna | E857: Manual worker | F857: Married | G857: 21000 | H857: 8 | I857: 43040 | J857: App | K857: 3 | L857: 1651.3 | M857: 11674.05 | N857: 29 | O857: 47.97 | P857: 1 | Q857: 0 | R857: 0 | S857: 80000 | T857: 417 | U857: 611 | V857: 1
A858: CL00851 | B858: 48 | C858: F | D858: Lombardia | E858: Manual worker | F858: Divorced | G858: 19500 | H858: 10 | I858: 42494 | J858: Branch | K858: 2 | L858: 1737.46 | M858: 11575.61 | N858: 16 | O858: 37.41 | P858: 5 | Q858: 2500 | R858: 458.45 | S858: 0 | T858: 0 | U858: 673 | V858: 0
A859: CL00852 | B859: 41 | C859: F | D859: Marche | E859: Business owner | F859: Married | G859: 62400 | H859: 4 | I859: 44724 | J859: App | K859: 4 | L859: 5592.79 | M859: 12610.37 | N859: 34 | O859: 63.59 | P859: 0 | Q859: 10500 | R859: 3492.3 | S859: 0 | T859: 0 | U859: 616 | V859: 0
... A977: CL00970 | B977: 62 | C977: M | D977: Piemonte | E977: Employee | F977: Married | G977: 32400 | H977: 12 | I977: 41679 | J977: Online Banking | K977: 2 | L977: 769.4 | M977: 19156.22 | N977: 30 | O977: 45.19 | P977: 4 | Q977: 7500 | R977: 5522.55 | S977: 0 | T977: 0 | U977: 712 | V977: 0
A978: CL00971 | B978: 47 | C978: M | D978: Lombardia | E978: Employee | F978: Married | G978: 25900 | H978: 10 | I978: 42341 | J978: Branch | K978: 1 | L978: 3613.77 | N978: 24 | O978: 35.16 | P978: 5 | Q978: 5000 | R978: 1545.91 | S978: 67000 | T978: 402 | U978: 620 | V978: 0
A979: CL00972 | B979: 47 | C979: M | D979: Campania | E979: Shopkeeper | F979: Married | G979: 37800 | H979: 13 | I979: 41371 | J979: Branch | K979: 1 | L979: 1301.17 | M979: 0 | N979: 25 | O979: 23.41 | P979: 5 | Q979: 5000 | R979: 1270.69 | S979: 0 | T979: 0 | U979: 676 | V979: 0
A980: CL00973 | B980: 43 | C980: M | D980: Sardegna | E980: Employee | F980: Single | G980: 24400 | H980: 3 | I980: 44850 | J980: Branch | K980: 2 | L980: 3242.74 | M980: 0 | N980: 13 | O980: 66.37 | P980: 7 | Q980: 0 | R980: 0 | S980: 118000 | T980: 781 | U980: 632 | V980: 0
A981: CL00974 | B981: 52 | C981: F | D981: Emilia-Romagna | E981: Self-employed | F981: Married | G981: 52200 | H981: 9 | I981: 42727 | J981: App | K981: 2 | L981: 13234.18 | M981: 0 | N981: 34 | O981: 81.22 | P981: 2 | Q981: 5500 | R981: 886.05 | S981: 158000 | T981: 1048 | U981: 656 | V981: 0
A982: CL00975 | B982: 37 | C982: M | D982: Piemonte | E982: Manual worker | F982: Married | G982: 18900 | H982: 10 | I982: 42410 | J982: App | K982: 1 | L982: 1006.11 | M982: 0 | N982: 26 | O982: 61.19 | P982: 0 | Q982: 4500 | R982: 743.61 | S982: 52000 | T982: 357 | U982: 617 | V982: 0
A983: CL00976 | B983: 63 | C983: F | D983: Lombardia | E983: Executive | F983: Married | G983: 177200 | H983: 16 | I983: 40085 | J983: Online Banking | K983: 5 | L983: 11005.75 | M983: 2400000 | N983: 63 | O983: 178.15 | P983: 1 | Q983: 15000 | R983: 1878.89 | S983: 0 | T983: 0 | U983: 828 | V983: 0
A984: CL00977 | B984: 69 | C984: M | D984: Marche | E984: Retired | F984: Married | G984: 35200 | H984: 31 | I984: 34780 | J984: Online Banking | K984: 1 | L984: 3852.52 | M984: 0 | N984: 24 | O984: 24.94 | P984: 3 | Q984: 5500 | R984: 2883.83 | S984: 0 | T984: 0 | U984: 612 | V984: 1
A985: CL00978 | B985: 62 | C985: M | D985: Lazio | E985: Executive | F985: Married | G985: 1350000 | H985: 26 | I985: 36763 | J985: Branch | K985: 3 | L985: 135000 | M985: 2558000 | N985: 63 | O985: 111.43 | P985: 2 | Q985: 15000 | R985: 5416.1 | S985: 0 | T985: 0 | U985: 838 | V985: 0
A986: CL00979 | B986: 40 | C986: M | D986: Campania | E986: Self-employed | F986: Single | G986: 28500 | H986: 14 | I986: 41098 | J986: Phone | K986: 3 | L986: 1142.59 | M986: 0 | N986: 24 | O986: 38 | P986: 2 | Q986: 6500 | R986: 286.16 | S986: 0 | T986: 0 | U986: 697 | V986: 0
A987: CL00980 | B987: 39 | C987: F | D987: Lazio | E987: Manual worker | F987: Single | G987: 17700 | H987: 4 | I987: 44528 | J987: App | K987: 1 | L987: 1207.17 | M987: 0 | N987: 32 | O987: 35.34 | P987: 0 | Q987: 2500 | R987: 544.43 | S987: 0 | T987: 0 | U987: 564 | V987: 1
A988: CL00981 | B988: 35 | C988: M | D988: Veneto | E988: Teacher | F988: Married | G988: 36900 | H988: 2 | I988: 45516 | J988: Online Banking | K988: 2 | L988: 5893.67 | M988: 13655.56 | N988: 34 | O988: 35.13 | P988: 2 | Q988: 8000 | R988: 1966.65 | S988: 0 | T988: 0 | U988: 576 | V988: 1
A989: CL00982 | B989: 36 | C989: M | D989: Puglia | E989: Employee | F989: Married | G989: 25700 | H989: 4 | I989: 44651 | J989: App | K989: 2 | L989: 1163.56 | M989: 8657.63 | N989: 33 | O989: 37.27 | P989: 1 | Q989: 0 | R989: 0 | S989: 0 | T989: 0 | U989: 633 | V989: 0
A990: CL00983 | B990: 41 | C990: F | D990: Lazio | E990: Executive | F990: Divorced | G990: 113400 | H990: 10 | I990: 42283 | J990: Phone | K990: 5 | L990: 16412.68 | M990: 78487.4 | N990: 51 | O990: 131.33 | P990: 5 | Q990: 11500 | R990: 4077.39 | S990: 234000 | T990: 1241 | U990: 721 | V990: 0
... A1001: CL00994 | B1001: 58 | C1001: F | D1001: Emilia-Romagna | E1001: Self-employed | F1001: Married | G1001: 54300 | H1001: 11 | I1001: 42009 | J1001: Branch | K1001: 3 | L1001: 1777.35 | M1001: 47727.63 | N1001: 25 | O1001: 108.97 | P1001: 6 | Q1001: 7500 | R1001: 1604.74 | S1001: 155000 | T1001: 852 | U1001: 556 | V1001: 1

Sheet Data_Dictionary
A1: Data dictionary — Customers sheet
A2: Demographic and behavioural extract as of 2026-09-13 for 1,000 retail customers (synthetic data). The 'Expected values' column describes the plausible range according to the business rules: any value outside this range, or inconsistent with the other columns, is a possible outlier to be verified.
A4: Column | B4: Type | C4: Description | D4: Expected values / plausible range
A5: Customer_ID | B5: Text | C5: Unique customer identifier (CL + 5 digits). | D5: Unique; format CL00001
A6: Age | B6: Integer | C6: Customer age in completed years. | D6: 18 – 100
A7: Gender | B7: Categorical | C7: Gender as recorded in the master data. | D7: M, F
A8: Region | B8: Categorical | C8: Region of residence (Italy). | D8: One of the 20 Italian regions, standard spelling
A9: Occupation | B9: Categorical | C9: Declared occupation. | D9: Employee, Manual worker, Self-employed, Executive, Business owner, Shopkeeper, Teacher, Student, Retired, Unemployed
A10: Marital_Status | B10: Categorical | C10: Marital status. | D10: Single, Married, Divorced, Widowed
A11: Annual_Income_EUR | B11: Numeric | C11: Declared gross annual income, in euros. | D11: > 0; typically 4,000 – 200,000
A12: Tenure_Years | B12: Integer | C12: Years of relationship with the bank. | D12: 0 – 40 and ≤ Age − 18
A13: Account_Open_Date | B13: Date | C13: Opening date of the first account. | D13: Between 1980 and the extraction date (2026-09-13); consistent with Tenure_Years
A14: Preferred_Channel | B14: Categorical | C14: Main contact channel. | D14: Branch, App, Online Banking, Phone
A15: Num_Products | B15: Integer | C15: Number of active products (account, cards, mortgage, investments…). | D15: 1 – 6
... A26: Complaints_12M | B26: Integer | C26: Complaints filed in the last 12 months. | D26: 0 – 5

Sheet Statistics
A1: Descriptive statistics and thresholds for detecting univariate outliers
A2: Every cell is a formula linked to the Customers sheet and updates when we change the data. The statistics are computed on the raw data, sentinels and errors included: we compare mean and median, or the number of outliers before and after cleaning, to see how much a single anomalous value distorts the thresholds.
A3: Statistic | B3: Age | C3: Annual_Income_EUR | D3: Tenure_Years | E3: Num_Products | F3: Checking_Balance_EUR | G3: Savings_Balance_EUR | H3: Monthly_Transactions | I3: Avg_Transaction_EUR | J3: Monthly_ATM_Withdrawals | K3: Card_Limit_EUR | L3: Monthly_Card_Spend_EUR | M3: Mortgage_Balance_EUR | N3: Monthly_Mortgage_Payment_EUR | O3: Credit_Score | P3: Complaints_12M
A4: Column in the Customers sheet | B4: B | C4: G | D4: H | E4: K | F4: L | G4: M | H4: N | I4: O | J4: P | K4: Q | L4: R | M4: S | N4: T | O4: U | P4: V
A5: N numeric values | B5: =COUNT(Customers!$B$2:$B$1001) -> 1000 | C5: =COUNT(Customers!$G$2:$G$1001) -> 997 | D5: =COUNT(Customers!$H$2:$H$1001) -> 1000 | E5: =COUNT(Customers!$K$2:$K$1001) -> 1000 | F5: =COUNT(Customers!$L$2:$L$1001) -> 1000 | G5: =COUNT(Customers!$M$2:$M$1001) -> 997 | H5: =COUNT(Customers!$N$2:$N$1001) -> 1000 | I5: =COUNT(Customers!$O$2:$O$1001) -> 1000 | J5: =COUNT(Customers!$P$2:$P$1001) -> 1000 | K5: =COUNT(Customers!$Q$2:$Q$1001) -> 1000 | L5: =COUNT(Customers!$R$2:$R$1001) -> 1000 | M5: =COUNT(Customers!$S$2:$S$1001) -> 1000 | N5: =COUNT(Customers!$T$2:$T$1001) -> 1000 | O5: =COUNT(Customers!$U$2:$U$1001) -> 1000 | P5: =COUNT(Customers!$V$2:$V$1001) -> 1000
A6: Blank cells | B6: =COUNTBLANK(Customers!$B$2:$B$1001) -> 0 | C6: =COUNTBLANK(Customers!$G$2:$G$1001) -> 3 | D6: =COUNTBLANK(Customers!$H$2:$H$1001) -> 0 | E6: =COUNTBLANK(Customers!$K$2:$K$1001) -> 0 | F6: =COUNTBLANK(Customers!$L$2:$L$1001) -> 0 | G6: =COUNTBLANK(Customers!$M$2:$M$1001) -> 3 | H6: =COUNTBLANK(Customers!$N$2:$N$1001) -> 0 | I6: =COUNTBLANK(Customers!$O$2:$O$1001) -> 0 | J6: =COUNTBLANK(Customers!$P$2:$P$1001) -> 0 | K6: =COUNTBLANK(Customers!$Q$2:$Q$1001) -> 0 | L6: =COUNTBLANK(Customers!$R$2:$R$1001) -> 0 | M6: =COUNTBLANK(Customers!$S$2:$S$1001) -> 0 | N6: =COUNTBLANK(Customers!$T$2:$T$1001) -> 0 | O6: =COUNTBLANK(Customers!$U$2:$U$1001) -> 0 | P6: =COUNTBLANK(Customers!$V$2:$V$1001) -> 0
A7: Mean | B7: =AVERAGE(Customers!$B$2:$B$1001) -> 48.535 | C7: =AVERAGE(Customers!$G$2:$G$1001) -> 72479.411 | D7: =AVERAGE(Customers!$H$2:$H$1001) -> 10.762 | E7: =AVERAGE(Customers!$K$2:$K$1001) -> 2.292 | F7: =AVERAGE(Customers!$L$2:$L$1001) -> 3355.9521 | G7: =AVERAGE(Customers!$M$2:$M$1001) -> 35090.563 | H7: =AVERAGE(Customers!$N$2:$N$1001) -> 30.157 | I7: =AVERAGE(Customers!$O$2:$O$1001) -> 60.02013 | J7: =AVERAGE(Customers!$P$2:$P$1001) -> 2.996 | K7: =AVERAGE(Customers!$Q$2:$Q$1001) -> 4650.5 | L7: =AVERAGE(Customers!$R$2:$R$1001) -> 1316.4016 | M7: =AVERAGE(Customers!$S$2:$S$1001) -> 39135 | N7: =AVERAGE(Customers!$T$2:$T$1001) -> 236.239 | O7: =AVERAGE(Customers!$U$2:$U$1001) -> 662.65 | P7: =AVERAGE(Customers!$V$2:$V$1001) -> 0.264
A8: Median | B8: =MEDIAN(Customers!$B$2:$B$1001) -> 47 | C8: =MEDIAN(Customers!$G$2:$G$1001) -> 30000 | D8: =MEDIAN(Customers!$H$2:$H$1001) -> 9 | E8: =MEDIAN(Customers!$K$2:$K$1001) -> 2 | F8: =MEDIAN(Customers!$L$2:$L$1001) -> 2586.535 | G8: =MEDIAN(Customers!$M$2:$M$1001) -> 12208.93 | H8: =MEDIAN(Customers!$N$2:$N$1001) -> 27 | I8: =MEDIAN(Customers!$O$2:$O$1001) -> 52.34 | J8: =MEDIAN(Customers!$P$2:$P$1001) -> 3 | K8: =MEDIAN(Customers!$Q$2:$Q$1001) -> 4000 | L8: =MEDIAN(Customers!$R$2:$R$1001) -> 763.63 | M8: =MEDIAN(Customers!$S$2:$S$1001) -> 0 | N8: =MEDIAN(Customers!$T$2:$T$1001) -> 0 | O8: =MEDIAN(Customers!$U$2:$U$1001) -> 635 | P8: =MEDIAN(Customers!$V$2:$V$1001) -> 0
A9: Standard deviation | B9: =STDEV(Customers!$B$2:$B$1001) -> 44.967286 | C9: =STDEV(Customers!$G$2:$G$1001) -> 1015307.4 | D9: =STDEV(Customers!$H$2:$H$1001) -> 7.7556112 | E9: =STDEV(Customers!$K$2:$K$1001) -> 1.2042368 | F9: =STDEV(Customers!$L$2:$L$1001) -> 28382.348 | G9: =STDEV(Customers!$M$2:$M$1001) -> 176152.28 | H9: =STDEV(Customers!$N$2:$N$1001) -> 24.869919 | I9: =STDEV(Customers!$O$2:$O$1001) -> 31.47791 | J9: =STDEV(Customers!$P$2:$P$1001) -> 2.1855802 | K9: =STDEV(Customers!$Q$2:$Q$1001) -> 4700.9785 | L9: =STDEV(Customers!$R$2:$R$1001) -> 1663.5113 | M9: =STDEV(Customers!$S$2:$S$1001) -> 76448.448 | N9: =STDEV(Customers!$T$2:$T$1001) -> 470.06818 | O9: =STDEV(Customers!$U$2:$U$1001) -> 516.40549 | P9: =STDEV(Customers!$V$2:$V$1001) -> 0.67138272
A10: Minimum | B10: =MIN(Customers!$B$2:$B$1001) -> -3 | C10: =MIN(Customers!$G$2:$G$1001) -> -999 | D10: =MIN(Customers!$H$2:$H$1001) -> 0 | E10: =MIN(Customers!$K$2:$K$1001) -> 1 | F10: =MIN(Customers!$L$2:$L$1001) -> -850000 | G10: =MIN(Customers!$M$2:$M$1001) -> 0 | H10: =MIN(Customers!$N$2:$N$1001) -> 8 | I10: =MIN(Customers!$O$2:$O$1001) -> 14.58 | J10: =MIN(Customers!$P$2:$P$1001) -> -2 | K10: =MIN(Customers!$Q$2:$Q$1001) -> 0 | L10: =MIN(Customers!$R$2:$R$1001) -> 0 | M10: =MIN(Customers!$S$2:$S$1001) -> 0 | N10: =MIN(Customers!$T$2:$T$1001) -> 0 | O10: =MIN(Customers!$U$2:$U$1001) -> 150 | P10: =MIN(Customers!$V$2:$V$1001) -> 0
A11: Maximum | B11: =MAX(Customers!$B$2:$B$1001) -> 999 | C11: =MAX(Customers!$G$2:$G$1001) -> 32000000 | D11: =MAX(Customers!$H$2:$H$1001) -> 44 | E11: =MAX(Customers!$K$2:$K$1001) -> 6 | F11: =MAX(Customers!$L$2:$L$1001) -> 185000 | G11: =MAX(Customers!$M$2:$M$1001) -> 3100000 | H11: =MAX(Customers!$N$2:$N$1001) -> 615 | I11: =MAX(Customers!$O$2:$O$1001) -> 257.18 | J11: =MAX(Customers!$P$2:$P$1001) -> 12 | K11: =MAX(Customers!$Q$2:$Q$1001) -> 60000 | L11: =MAX(Customers!$R$2:$R$1001) -> 12500 | M11: =MAX(Customers!$S$2:$S$1001) -> 520000 | N11: =MAX(Customers!$T$2:$T$1001) -> 3800 | O11: =MAX(Customers!$U$2:$U$1001) -> 9999 | P11: =MAX(Customers!$V$2:$V$1001) -> 14
A12: Q1 (25th percentile) | B12: =QUARTILE(Customers!$B$2:$B$1001,1) -> 37 | C12: =QUARTILE(Customers!$G$2:$G$1001,1) -> 21000 | D12: =QUARTILE(Customers!$H$2:$H$1001,1) -> 5 | E12: =QUARTILE(Customers!$K$2:$K$1001,1) -> 1 | F12: =QUARTILE(Customers!$L$2:$L$1001,1) -> 1226.1375 | G12: =QUARTILE(Customers!$M$2:$M$1001,1) -> 0 | H12: =QUARTILE(Customers!$N$2:$N$1001,1) -> 21 | I12: =QUARTILE(Customers!$O$2:$O$1001,1) -> 39.365 | J12: =QUARTILE(Customers!$P$2:$P$1001,1) -> 1 | K12: =QUARTILE(Customers!$Q$2:$Q$1001,1) -> 0 | L12: =QUARTILE(Customers!$R$2:$R$1001,1) -> 0 | M12: =QUARTILE(Customers!$S$2:$S$1001,1) -> 0 | N12: =QUARTILE(Customers!$T$2:$T$1001,1) -> 0 | O12: =QUARTILE(Customers!$U$2:$U$1001,1) -> 595 | P12: =QUARTILE(Customers!$V$2:$V$1001,1) -> 0
A13: Q3 (75th percentile) | B13: =QUARTILE(Customers!$B$2:$B$1001,3) -> 56 | C13: =QUARTILE(Customers!$G$2:$G$1001,3) -> 44200 | D13: =QUARTILE(Customers!$H$2:$H$1001,3) -> 15 | E13: =QUARTILE(Customers!$K$2:$K$1001,3) -> 3 | F13: =QUARTILE(Customers!$L$2:$L$1001,3) -> 4978.71 | G13: =QUARTILE(Customers!$M$2:$M$1001,3) -> 30591.65 | H13: =QUARTILE(Customers!$N$2:$N$1001,3) -> 35 | I13: =QUARTILE(Customers!$O$2:$O$1001,3) -> 71.6725 | J13: =QUARTILE(Customers!$P$2:$P$1001,3) -> 4 | K13: =QUARTILE(Customers!$Q$2:$Q$1001,3) -> 7000 | L13: =QUARTILE(Customers!$R$2:$R$1001,3) -> 1967.355 | M13: =QUARTILE(Customers!$S$2:$S$1001,3) -> 56000 | N13: =QUARTILE(Customers!$T$2:$T$1001,3) -> 326 | O13: =QUARTILE(Customers!$U$2:$U$1001,3) -> 675 | P13: =QUARTILE(Customers!$V$2:$V$1001,3) -> 0
A14: IQR = Q3 − Q1 | B14: =B13-B12 -> 19 | C14: =C13-C12 -> 23200 | D14: =D13-D12 -> 10 | E14: =E13-E12 -> 2 | F14: =F13-F12 -> 3752.5725 | G14: =G13-G12 -> 30591.65 | H14: =H13-H12 -> 14 | I14: =I13-I12 -> 32.3075 | ... P14: =P13-P12 -> 0
A15: Lower fence = Q1 − 1.5·IQR | B15: =B12-1.5*B14 -> 8.5 | C15: =C12-1.5*C14 -> -13800 | D15: =D12-1.5*D14 -> -10 | E15: =E12-1.5*E14 -> -2 | F15: =F12-1.5*F14 -> -4402.7213 | G15: =G12-1.5*G14 -> -45887.475 | H15: =H12-1.5*H14 -> 0 | I15: =I12-1.5*I14 -> -9.09625 | ... P15: =P12-1.5*P14 -> 0
A16: Upper fence = Q3 + 1.5·IQR | B16: =B13+1.5*B14 -> 84.5 | C16: =C13+1.5*C14 -> 79000 | D16: =D13+1.5*D14 -> 30 | E16: =E13+1.5*E14 -> 6 | F16: =F13+1.5*F14 -> 10607.569 | G16: =G13+1.5*G14 -> 76479.125 | H16: =H13+1.5*H14 -> 56 | I16: =I13+1.5*I14 -> 120.13375 | ... P16: =P13+1.5*P14 -> 0
A17: N values below the lower fence | B17: =COUNTIF(Customers!$B$2:$B$1001,"<"&B15) -> 2 | C17: =COUNTIF(Customers!$G$2:$G$1001,"<"&C15) -> 0 | D17: =COUNTIF(Customers!$H$2:$H$1001,"<"&D15) -> 0 | E17: =COUNTIF(Customers!$K$2:$K$1001,"<"&E15) -> 0 | F17: =COUNTIF(Customers!$L$2:$L$1001,"<"&F15) -> 1 | G17: =COUNTIF(Customers!$M$2:$M$1001,"<"&G15) -> 0 | H17: =COUNTIF(Customers!$N$2:$N$1001,"<"&H15) -> 0 | I17: =COUNTIF(Customers!$O$2:$O$1001,"<"&I15) -> 0 | J17: =COUNTIF(Customers!$P$2:$P$1001,"<"&J15) -> 0 | K17: =COUNTIF(Customers!$Q$2:$Q$1001,"<"&K15) -> 0 | L17: =COUNTIF(Customers!$R$2:$R$1001,"<"&L15) -> 0 | M17: =COUNTIF(Customers!$S$2:$S$1001,"<"&M15) -> 0 | N17: =COUNTIF(Customers!$T$2:$T$1001,"<"&N15) -> 0 | O17: =COUNTIF(Customers!$U$2:$U$1001,"<"&O15) -> 8 | P17: =COUNTIF(Customers!$V$2:$V$1001,"<"&P15) -> 0
A18: N values above the upper fence | B18: =COUNTIF(Customers!$B$2:$B$1001,">"&B16) -> 6 | C18: =COUNTIF(Customers!$G$2:$G$1001,">"&C16) -> 74 | D18: =COUNTIF(Customers!$H$2:$H$1001,">"&D16) -> 18 | E18: =COUNTIF(Customers!$K$2:$K$1001,">"&E16) -> 0 | F18: =COUNTIF(Customers!$L$2:$L$1001,">"&F16) -> 62 | G18: =COUNTIF(Customers!$M$2:$M$1001,">"&G16) -> 55 | H18: =COUNTIF(Customers!$N$2:$N$1001,">"&H16) -> 31 | I18: =COUNTIF(Customers!$O$2:$O$1001,">"&I16) -> 49 | J18: =COUNTIF(Customers!$P$2:$P$1001,">"&J16) -> 16 | K18: =COUNTIF(Customers!$Q$2:$Q$1001,">"&K16) -> 2 | L18: =COUNTIF(Customers!$R$2:$R$1001,">"&L16) -> 42 | M18: =COUNTIF(Customers!$S$2:$S$1001,">"&M16) -> 100 | N18: =COUNTIF(Customers!$T$2:$T$1001,">"&N16) -> 100 | O18: =COUNTIF(Customers!$U$2:$U$1001,">"&O16) -> 8 | P18: =COUNTIF(Customers!$V$2:$V$1001,">"&P16) -> 220
A19: z = −3 threshold (mean − 3·SD) | B19: =B7-3*B9 -> -86.366859 | C19: =C7-3*C9 -> -2973442.7 | D19: =D7-3*D9 -> -12.504834 | E19: =E7-3*E9 -> -1.3207103 | F19: =F7-3*F9 -> -81791.091 | G19: =G7-3*G9 -> -493366.26 | H19: =H7-3*H9 -> -44.452757 | I19: =I7-3*I9 -> -34.413599 | ... P19: =P7-3*P9 -> -1.7501482
A20: z = +3 threshold (mean + 3·SD) | B20: =B7+3*B9 -> 183.43686 | C20: =C7+3*C9 -> 3118401.5 | D20: =D7+3*D9 -> 34.028834 | E20: =E7+3*E9 -> 5.9047103 | F20: =F7+3*F9 -> 88502.995 | G20: =G7+3*G9 -> 563547.39 | H20: =H7+3*H9 -> 104.76676 | I20: =I7+3*I9 -> 154.45386 | ... P20: =P7+3*P9 -> 2.2781482
A21: N values with |z| > 3 | B21: =COUNTIF(Customers!$B$2:$B$1001,"<"&B19)+COUNTIF(Customers!$B$2:$B$1001,">"&B20) -> 3 | C21: =COUNTIF(Customers!$G$2:$G$1001,"<"&C19)+COUNTIF(Customers!$G$2:$G$1001,">"&C20) -> 1 | D21: =COUNTIF(Customers!$H$2:$H$1001,"<"&D19)+COUNTIF(Customers!$H$2:$H$1001,">"&D20) -> 3 | E21: =COUNTIF(Customers!$K$2:$K$1001,"<"&E19)+COUNTIF(Customers!$K$2:$K$1001,">"&E20) -> 13 | F21: =COUNTIF(Customers!$L$2:$L$1001,"<"&F19)+COUNTIF(Customers!$L$2:$L$1001,">"&F20) -> 3 | G21: =COUNTIF(Customers!$M$2:$M$1001,"<"&G19)+COUNTIF(Customers!$M$2:$M$1001,">"&G20) -> 7 | H21: =COUNTIF(Customers!$N$2:$N$1001,"<"&H19)+COUNTIF(Customers!$N$2:$N$1001,">"&H20) -> 2 | I21: =COUNTIF(Customers!$O$2:$O$1001,"<"&I19)+COUNTIF(Customers!$O$2:$O$1001,">"&I20) -> 19 | J21: =COUNTIF(Customers!$P$2:$P$1001,"<"&J19)+COUNTIF(Customers!$P$2:$P$1001,">"&J20) -> 8 | K21: =COUNTIF(Customers!$Q$2:$Q$1001,"<"&K19)+COUNTIF(Customers!$Q$2:$Q$1001,">"&K20) -> 2 | L21: =COUNTIF(Customers!$R$2:$R$1001,"<"&L19)+COUNTIF(Customers!$R$2:$R$1001,">"&L20) -> 22 | M21: =COUNTIF(Customers!$S$2:$S$1001,"<"&M19)+COUNTIF(Customers!$S$2:$S$1001,">"&M20) -> 24 | N21: =COUNTIF(Customers!$T$2:$T$1001,"<"&N19)+COUNTIF(Customers!$T$2:$T$1001,">"&N20) -> 27 | O21: =COUNTIF(Customers!$U$2:$U$1001,"<"&O19)+COUNTIF(Customers!$U$2:$U$1001,">"&O20) -> 3 | P21: =COUNTIF(Customers!$V$2:$V$1001,"<"&P19)+COUNTIF(Customers!$V$2:$V$1001,">"&P20) -> 5

Sheet Checks
A1: Customer_ID | B1: Z_Income | C1: Income outside 1.5·IQR | D1: Plausible age | E1: Tenure vs age | F1: Card spend vs limit | G1: Mortgage vs payment | H1: Payment vs monthly income | I1: Plausible date | J1: Date vs tenure | K1: Duplicate ID | L1: Duplicate record | M1: Score within scale | N1: Positive income | O1: Missing values | P1: N flags | R1: Flag summary (rows of the Customers sheet)
A2: =Customers!A2 -> CL00001 | B2: =IF(Customers!G2="","",(Customers!G2-Statistics!$C$7)/Statistics!$C$9) -> -0.045877152 | C2: =IF(Customers!G2="","",IF(OR(Customers!G2<Statistics!$C$15,Customers!G2>Statistics!$C$16),"Outside 1.5·IQR","")) | D2: =IF(OR(Customers!B2<18,Customers!B2>100),"Implausible age","") | E2: =IF(Customers!H2>Customers!B2-18,"Tenure > age-18","") | F2: =IF(Customers!R2>Customers!Q2,"Card spend > limit","") | G2: =IF(OR(AND(Customers!S2>0,Customers!T2=0),AND(Customers!S2=0,Customers!T2>0)),"Mortgage/payment inconsistent","") | H2: =IF(AND(Customers!G2<>"",Customers!G2>0,Customers!T2>Customers!G2/12),"Payment > monthly income","") | I2: =IF(OR(Customers!I2>DATE(2026,9,13),YEAR(Customers!I2)<1980),"Implausible date","") | J2: =IF(Customers!I2>DATE(2026,9,13),"",IF(ABS(INT((DATE(2026,9,13)-Customers!I2)/365.25)-Customers!H2)>1,"Date/tenure inconsistent","")) | K2: =IF(COUNTIF(Customers!$A$2:$A$1001,Customers!A2)>1,"Duplicate ID","") | L2: =IF(COUNTIFS(Customers!$B$2:$B$1001,Customers!B2,Customers!$D$2:$D$1001,Customers!D2,Customers!$G$2:$G$1001,Customers!G2,Customers!$I$2:$I$1001,Customers!I2,Customers!$L$2:$L$1001,Customers!L2)>1,"Duplicate record","") | M2: =IF(OR(Customers!U2<300,Customers!U2>850),"Score out of range","") | N2: =IF(AND(Customers!G2<>"",Customers!G2<=0),"Income ≤ 0","") | O2: =IF(OR(Customers!G2="",Customers!M2=""),"Missing value","") | P2: =SUMPRODUCT(--(C2:O2<>"")) -> 0 | R2: Check | S2: N rows
A3: =Customers!A3 -> CL00002 | B3: =IF(Customers!G3="","",(Customers!G3-Statistics!$C$7)/Statistics!$C$9) -> -0.054445986 | C3: =IF(Customers!G3="","",IF(OR(Customers!G3<Statistics!$C$15,Customers!G3>Statistics!$C$16),"Outside 1.5·IQR","")) | D3: =IF(OR(Customers!B3<18,Customers!B3>100),"Implausible age","") | E3: =IF(Customers!H3>Customers!B3-18,"Tenure > age-18","") | F3: =IF(Customers!R3>Customers!Q3,"Card spend > limit","") | G3: =IF(OR(AND(Customers!S3>0,Customers!T3=0),AND(Customers!S3=0,Customers!T3>0)),"Mortgage/payment inconsistent","") | H3: =IF(AND(Customers!G3<>"",Customers!G3>0,Customers!T3>Customers!G3/12),"Payment > monthly income","") | I3: =IF(OR(Customers!I3>DATE(2026,9,13),YEAR(Customers!I3)<1980),"Implausible date","") | J3: =IF(Customers!I3>DATE(2026,9,13),"",IF(ABS(INT((DATE(2026,9,13)-Customers!I3)/365.25)-Customers!H3)>1,"Date/tenure inconsistent","")) | K3: =IF(COUNTIF(Customers!$A$2:$A$1001,Customers!A3)>1,"Duplicate ID","") | L3: =IF(COUNTIFS(Customers!$B$2:$B$1001,Customers!B3,Customers!$D$2:$D$1001,Customers!D3,Customers!$G$2:$G$1001,Customers!G3,Customers!$I$2:$I$1001,Customers!I3,Customers!$L$2:$L$1001,Customers!L3)>1,"Duplicate record","") | M3: =IF(OR(Customers!U3<300,Customers!U3>850),"Score out of range","") | N3: =IF(AND(Customers!G3<>"",Customers!G3<=0),"Income ≤ 0","") | O3: =IF(OR(Customers!G3="",Customers!M3=""),"Missing value","") | P3: =SUMPRODUCT(--(C3:O3<>"")) -> 0 | R3: |Z_Income| > 3 | S3: =COUNTIF(B$2:B$1001,">3")+COUNTIF(B$2:B$1001,"<-3") -> 1
A4: =Customers!A4 -> CL00003 | B4: =IF(Customers!G4="","",(Customers!G4-Statistics!$C$7)/Statistics!$C$9) -> -0.011109356 | C4: =IF(Customers!G4="","",IF(OR(Customers!G4<Statistics!$C$15,Customers!G4>Statistics!$C$16),"Outside 1.5·IQR","")) | D4: =IF(OR(Customers!B4<18,Customers!B4>100),"Implausible age","") | E4: =IF(Customers!H4>Customers!B4-18,"Tenure > age-18","") | F4: =IF(Customers!R4>Customers!Q4,"Card spend > limit","") | G4: =IF(OR(AND(Customers!S4>0,Customers!T4=0),AND(Customers!S4=0,Customers!T4>0)),"Mortgage/payment inconsistent","") | H4: =IF(AND(Customers!G4<>"",Customers!G4>0,Customers!T4>Customers!G4/12),"Payment > monthly income","") | I4: =IF(OR(Customers!I4>DATE(2026,9,13),YEAR(Customers!I4)<1980),"Implausible date","") | J4: =IF(Customers!I4>DATE(2026,9,13),"",IF(ABS(INT((DATE(2026,9,13)-Customers!I4)/365.25)-Customers!H4)>1,"Date/tenure inconsistent","")) | K4: =IF(COUNTIF(Customers!$A$2:$A$1001,Customers!A4)>1,"Duplicate ID","") | L4: =IF(COUNTIFS(Customers!$B$2:$B$1001,Customers!B4,Customers!$D$2:$D$1001,Customers!D4,Customers!$G$2:$G$1001,Customers!G4,Customers!$I$2:$I$1001,Customers!I4,Customers!$L$2:$L$1001,Customers!L4)>1,"Duplicate record","") | M4: =IF(OR(Customers!U4<300,Customers!U4>850),"Score out of range","") | N4: =IF(AND(Customers!G4<>"",Customers!G4<=0),"Income ≤ 0","") | O4: =IF(OR(Customers!G4="",Customers!M4=""),"Missing value","") | P4: =SUMPRODUCT(--(C4:O4<>"")) -> 0 | R4: Income outside 1.5·IQR | S4: =SUMPRODUCT(--(C$2:C$1001<>"")) -> 74
A5: =Customers!A5 -> CL00004 | B5: =IF(Customers!G5="","",(Customers!G5-Statistics!$C$7)/Statistics!$C$9) -> -0.045680168 | C5: =IF(Customers!G5="","",IF(OR(Customers!G5<Statistics!$C$15,Customers!G5>Statistics!$C$16),"Outside 1.5·IQR","")) | D5: =IF(OR(Customers!B5<18,Customers!B5>100),"Implausible age","") | E5: =IF(Customers!H5>Customers!B5-18,"Tenure > age-18","") | F5: =IF(Customers!R5>Customers!Q5,"Card spend > limit","") | G5: =IF(OR(AND(Customers!S5>0,Customers!T5=0),AND(Customers!S5=0,Customers!T5>0)),"Mortgage/payment inconsistent","") | H5: =IF(AND(Customers!G5<>"",Customers!G5>0,Customers!T5>Customers!G5/12),"Payment > monthly income","") | I5: =IF(OR(Customers!I5>DATE(2026,9,13),YEAR(Customers!I5)<1980),"Implausible date","") | J5: =IF(Customers!I5>DATE(2026,9,13),"",IF(ABS(INT((DATE(2026,9,13)-Customers!I5)/365.25)-Customers!H5)>1,"Date/tenure inconsistent","")) | K5: =IF(COUNTIF(Customers!$A$2:$A$1001,Customers!A5)>1,"Duplicate ID","") | L5: =IF(COUNTIFS(Customers!$B$2:$B$1001,Customers!B5,Customers!$D$2:$D$1001,Customers!D5,Customers!$G$2:$G$1001,Customers!G5,Customers!$I$2:$I$1001,Customers!I5,Customers!$L$2:$L$1001,Customers!L5)>1,"Duplicate record","") | M5: =IF(OR(Customers!U5<300,Customers!U5>850),"Score out of range","") | N5: =IF(AND(Customers!G5<>"",Customers!G5<=0),"Income ≤ 0","") | O5: =IF(OR(Customers!G5="",Customers!M5=""),"Missing value","") | P5: =SUMPRODUCT(--(C5:O5<>"")) -> 0 | R5: Plausible age | S5: =SUMPRODUCT(--(D$2:D$1001<>"")) -> 5
A6: =Customers!A6 -> CL00005 | B6: =IF(Customers!G6="","",(Customers!G6-Statistics!$C$7)/Statistics!$C$9) -> 0.017650407 | C6: =IF(Customers!G6="","",IF(OR(Customers!G6<Statistics!$C$15,Customers!G6>Statistics!$C$16),"Outside 1.5·IQR","")) -> Outside 1.5·IQR | D6: =IF(OR(Customers!B6<18,Customers!B6>100),"Implausible age","") | E6: =IF(Customers!H6>Customers!B6-18,"Tenure > age-18","") | F6: =IF(Customers!R6>Customers!Q6,"Card spend > limit","") | G6: =IF(OR(AND(Customers!S6>0,Customers!T6=0),AND(Customers!S6=0,Customers!T6>0)),"Mortgage/payment inconsistent","") | H6: =IF(AND(Customers!G6<>"",Customers!G6>0,Customers!T6>Customers!G6/12),"Payment > monthly income","") | I6: =IF(OR(Customers!I6>DATE(2026,9,13),YEAR(Customers!I6)<1980),"Implausible date","") | J6: =IF(Customers!I6>DATE(2026,9,13),"",IF(ABS(INT((DATE(2026,9,13)-Customers!I6)/365.25)-Customers!H6)>1,"Date/tenure inconsistent","")) | K6: =IF(COUNTIF(Customers!$A$2:$A$1001,Customers!A6)>1,"Duplicate ID","") | L6: =IF(COUNTIFS(Customers!$B$2:$B$1001,Customers!B6,Customers!$D$2:$D$1001,Customers!D6,Customers!$G$2:$G$1001,Customers!G6,Customers!$I$2:$I$1001,Customers!I6,Customers!$L$2:$L$1001,Customers!L6)>1,"Duplicate record","") | M6: =IF(OR(Customers!U6<300,Customers!U6>850),"Score out of range","") | N6: =IF(AND(Customers!G6<>"",Customers!G6<=0),"Income ≤ 0","") | O6: =IF(OR(Customers!G6="",Customers!M6=""),"Missing value","") | P6: =SUMPRODUCT(--(C6:O6<>"")) -> 1 | R6: Tenure vs age | S6: =SUMPRODUCT(--(E$2:E$1001<>"")) -> 5
A7: =Customers!A7 -> CL00006 | B7: =IF(Customers!G7="","",(Customers!G7-Statistics!$C$7)/Statistics!$C$9) -> -0.046271122 | C7: =IF(Customers!G7="","",IF(OR(Customers!G7<Statistics!$C$15,Customers!G7>Statistics!$C$16),"Outside 1.5·IQR","")) | D7: =IF(OR(Customers!B7<18,Customers!B7>100),"Implausible age","") | E7: =IF(Customers!H7>Customers!B7-18,"Tenure > age-18","") | F7: =IF(Customers!R7>Customers!Q7,"Card spend > limit","") | G7: =IF(OR(AND(Customers!S7>0,Customers!T7=0),AND(Customers!S7=0,Customers!T7>0)),"Mortgage/payment inconsistent","") | H7: =IF(AND(Customers!G7<>"",Customers!G7>0,Customers!T7>Customers!G7/12),"Payment > monthly income","") | I7: =IF(OR(Customers!I7>DATE(2026,9,13),YEAR(Customers!I7)<1980),"Implausible date","") | J7: =IF(Customers!I7>DATE(2026,9,13),"",IF(ABS(INT((DATE(2026,9,13)-Customers!I7)/365.25)-Customers!H7)>1,"Date/tenure inconsistent","")) | K7: =IF(COUNTIF(Customers!$A$2:$A$1001,Customers!A7)>1,"Duplicate ID","") | L7: =IF(COUNTIFS(Customers!$B$2:$B$1001,Customers!B7,Customers!$D$2:$D$1001,Customers!D7,Customers!$G$2:$G$1001,Customers!G7,Customers!$I$2:$I$1001,Customers!I7,Customers!$L$2:$L$1001,Customers!L7)>1,"Duplicate record","") | M7: =IF(OR(Customers!U7<300,Customers!U7>850),"Score out of range","") | N7: =IF(AND(Customers!G7<>"",Customers!G7<=0),"Income ≤ 0","") | O7: =IF(OR(Customers!G7="",Customers!M7=""),"Missing value","") | P7: =SUMPRODUCT(--(C7:O7<>"")) -> 0 | R7: Card spend vs limit | S7: =SUMPRODUCT(--(F$2:F$1001<>"")) -> 3
A8: =Customers!A8 -> CL00007 | B8: =IF(Customers!G8="","",(Customers!G8-Statistics!$C$7)/Statistics!$C$9) -> -0.036618872 | C8: =IF(Customers!G8="","",IF(OR(Customers!G8<Statistics!$C$15,Customers!G8>Statistics!$C$16),"Outside 1.5·IQR","")) | D8: =IF(OR(Customers!B8<18,Customers!B8>100),"Implausible age","") | E8: =IF(Customers!H8>Customers!B8-18,"Tenure > age-18","") | F8: =IF(Customers!R8>Customers!Q8,"Card spend > limit","") | G8: =IF(OR(AND(Customers!S8>0,Customers!T8=0),AND(Customers!S8=0,Customers!T8>0)),"Mortgage/payment inconsistent","") | H8: =IF(AND(Customers!G8<>"",Customers!G8>0,Customers!T8>Customers!G8/12),"Payment > monthly income","") | I8: =IF(OR(Customers!I8>DATE(2026,9,13),YEAR(Customers!I8)<1980),"Implausible date","") | J8: =IF(Customers!I8>DATE(2026,9,13),"",IF(ABS(INT((DATE(2026,9,13)-Customers!I8)/365.25)-Customers!H8)>1,"Date/tenure inconsistent","")) | K8: =IF(COUNTIF(Customers!$A$2:$A$1001,Customers!A8)>1,"Duplicate ID","") | L8: =IF(COUNTIFS(Customers!$B$2:$B$1001,Customers!B8,Customers!$D$2:$D$1001,Customers!D8,Customers!$G$2:$G$1001,Customers!G8,Customers!$I$2:$I$1001,Customers!I8,Customers!$L$2:$L$1001,Customers!L8)>1,"Duplicate record","") | M8: =IF(OR(Customers!U8<300,Customers!U8>850),"Score out of range","") | N8: =IF(AND(Customers!G8<>"",Customers!G8<=0),"Income ≤ 0","") | O8: =IF(OR(Customers!G8="",Customers!M8=""),"Missing value","") | P8: =SUMPRODUCT(--(C8:O8<>"")) -> 0 | R8: Mortgage vs payment | S8: =SUMPRODUCT(--(G$2:G$1001<>"")) -> 4
A9: =Customers!A9 -> CL00008 | B9: =IF(Customers!G9="","",(Customers!G9-Statistics!$C$7)/Statistics!$C$9) -> -0.01209428 | C9: =IF(Customers!G9="","",IF(OR(Customers!G9<Statistics!$C$15,Customers!G9>Statistics!$C$16),"Outside 1.5·IQR","")) | D9: =IF(OR(Customers!B9<18,Customers!B9>100),"Implausible age","") | E9: =IF(Customers!H9>Customers!B9-18,"Tenure > age-18","") | F9: =IF(Customers!R9>Customers!Q9,"Card spend > limit","") | G9: =IF(OR(AND(Customers!S9>0,Customers!T9=0),AND(Customers!S9=0,Customers!T9>0)),"Mortgage/payment inconsistent","") | H9: =IF(AND(Customers!G9<>"",Customers!G9>0,Customers!T9>Customers!G9/12),"Payment > monthly income","") | I9: =IF(OR(Customers!I9>DATE(2026,9,13),YEAR(Customers!I9)<1980),"Implausible date","") | J9: =IF(Customers!I9>DATE(2026,9,13),"",IF(ABS(INT((DATE(2026,9,13)-Customers!I9)/365.25)-Customers!H9)>1,"Date/tenure inconsistent","")) | K9: =IF(COUNTIF(Customers!$A$2:$A$1001,Customers!A9)>1,"Duplicate ID","") | L9: =IF(COUNTIFS(Customers!$B$2:$B$1001,Customers!B9,Customers!$D$2:$D$1001,Customers!D9,Customers!$G$2:$G$1001,Customers!G9,Customers!$I$2:$I$1001,Customers!I9,Customers!$L$2:$L$1001,Customers!L9)>1,"Duplicate record","") | M9: =IF(OR(Customers!U9<300,Customers!U9>850),"Score out of range","") | N9: =IF(AND(Customers!G9<>"",Customers!G9<=0),"Income ≤ 0","") | O9: =IF(OR(Customers!G9="",Customers!M9=""),"Missing value","") | P9: =SUMPRODUCT(--(C9:O9<>"")) -> 0 | R9: Payment vs monthly income | S9: =SUMPRODUCT(--(H$2:H$1001<>"")) -> 3
A10: =Customers!A10 -> CL00009 | B10: =IF(Customers!G10="","",(Customers!G10-Statistics!$C$7)/Statistics!$C$9) -> -0.052968601 | C10: =IF(Customers!G10="","",IF(OR(Customers!G10<Statistics!$C$15,Customers!G10>Statistics!$C$16),"Outside 1.5·IQR","")) | D10: =IF(OR(Customers!B10<18,Customers!B10>100),"Implausible age","") | E10: =IF(Customers!H10>Customers!B10-18,"Tenure > age-18","") | F10: =IF(Customers!R10>Customers!Q10,"Card spend > limit","") | G10: =IF(OR(AND(Customers!S10>0,Customers!T10=0),AND(Customers!S10=0,Customers!T10>0)),"Mortgage/payment inconsistent","") | H10: =IF(AND(Customers!G10<>"",Customers!G10>0,Customers!T10>Customers!G10/12),"Payment > monthly income","") | I10: =IF(OR(Customers!I10>DATE(2026,9,13),YEAR(Customers!I10)<1980),"Implausible date","") | J10: =IF(Customers!I10>DATE(2026,9,13),"",IF(ABS(INT((DATE(2026,9,13)-Customers!I10)/365.25)-Customers!H10)>1,"Date/tenure inconsistent","")) | K10: =IF(COUNTIF(Customers!$A$2:$A$1001,Customers!A10)>1,"Duplicate ID","") | L10: =IF(COUNTIFS(Customers!$B$2:$B$1001,Customers!B10,Customers!$D$2:$D$1001,Customers!D10,Customers!$G$2:$G$1001,Customers!G10,Customers!$I$2:$I$1001,Customers!I10,Customers!$L$2:$L$1001,Customers!L10)>1,"Duplicate record","") | M10: =IF(OR(Customers!U10<300,Customers!U10>850),"Score out of range","") | N10: =IF(AND(Customers!G10<>"",Customers!G10<=0),"Income ≤ 0","") | O10: =IF(OR(Customers!G10="",Customers!M10=""),"Missing value","") | P10: =SUMPRODUCT(--(C10:O10<>"")) -> 0 | R10: Plausible date | S10: =SUMPRODUCT(--(I$2:I$1001<>"")) -> 4
A11: =Customers!A11 -> CL00010 | B11: =IF(Customers!G11="","",(Customers!G11-Statistics!$C$7)/Statistics!$C$9) -> -0.051097246 | C11: =IF(Customers!G11="","",IF(OR(Customers!G11<Statistics!$C$15,Customers!G11>Statistics!$C$16),"Outside 1.5·IQR","")) | D11: =IF(OR(Customers!B11<18,Customers!B11>100),"Implausible age","") | E11: =IF(Customers!H11>Customers!B11-18,"Tenure > age-18","") | F11: =IF(Customers!R11>Customers!Q11,"Card spend > limit","") | G11: =IF(OR(AND(Customers!S11>0,Customers!T11=0),AND(Customers!S11=0,Customers!T11>0)),"Mortgage/payment inconsistent","") | H11: =IF(AND(Customers!G11<>"",Customers!G11>0,Customers!T11>Customers!G11/12),"Payment > monthly income","") | I11: =IF(OR(Customers!I11>DATE(2026,9,13),YEAR(Customers!I11)<1980),"Implausible date","") | J11: =IF(Customers!I11>DATE(2026,9,13),"",IF(ABS(INT((DATE(2026,9,13)-Customers!I11)/365.25)-Customers!H11)>1,"Date/tenure inconsistent","")) | K11: =IF(COUNTIF(Customers!$A$2:$A$1001,Customers!A11)>1,"Duplicate ID","") | L11: =IF(COUNTIFS(Customers!$B$2:$B$1001,Customers!B11,Customers!$D$2:$D$1001,Customers!D11,Customers!$G$2:$G$1001,Customers!G11,Customers!$I$2:$I$1001,Customers!I11,Customers!$L$2:$L$1001,Customers!L11)>1,"Duplicate record","") | M11: =IF(OR(Customers!U11<300,Customers!U11>850),"Score out of range","") | N11: =IF(AND(Customers!G11<>"",Customers!G11<=0),"Income ≤ 0","") | O11: =IF(OR(Customers!G11="",Customers!M11=""),"Missing value","") | P11: =SUMPRODUCT(--(C11:O11<>"")) -> 0 | R11: Date vs tenure | S11: =SUMPRODUCT(--(J$2:J$1001<>"")) -> 4
A12: =Customers!A12 -> CL00011 | B12: =IF(Customers!G12="","",(Customers!G12-Statistics!$C$7)/Statistics!$C$9) -> -0.044596752 | C12: =IF(Customers!G12="","",IF(OR(Customers!G12<Statistics!$C$15,Customers!G12>Statistics!$C$16),"Outside 1.5·IQR","")) | D12: =IF(OR(Customers!B12<18,Customers!B12>100),"Implausible age","") | E12: =IF(Customers!H12>Customers!B12-18,"Tenure > age-18","") | F12: =IF(Customers!R12>Customers!Q12,"Card spend > limit","") | G12: =IF(OR(AND(Customers!S12>0,Customers!T12=0),AND(Customers!S12=0,Customers!T12>0)),"Mortgage/payment inconsistent","") | H12: =IF(AND(Customers!G12<>"",Customers!G12>0,Customers!T12>Customers!G12/12),"Payment > monthly income","") | I12: =IF(OR(Customers!I12>DATE(2026,9,13),YEAR(Customers!I12)<1980),"Implausible date","") | J12: =IF(Customers!I12>DATE(2026,9,13),"",IF(ABS(INT((DATE(2026,9,13)-Customers!I12)/365.25)-Customers!H12)>1,"Date/tenure inconsistent","")) | K12: =IF(COUNTIF(Customers!$A$2:$A$1001,Customers!A12)>1,"Duplicate ID","") | L12: =IF(COUNTIFS(Customers!$B$2:$B$1001,Customers!B12,Customers!$D$2:$D$1001,Customers!D12,Customers!$G$2:$G$1001,Customers!G12,Customers!$I$2:$I$1001,Customers!I12,Customers!$L$2:$L$1001,Customers!L12)>1,"Duplicate record","") | M12: =IF(OR(Customers!U12<300,Customers!U12>850),"Score out of range","") | N12: =IF(AND(Customers!G12<>"",Customers!G12<=0),"Income ≤ 0","") | O12: =IF(OR(Customers!G12="",Customers!M12=""),"Missing value","") | P12: =SUMPRODUCT(--(C12:O12<>"")) -> 0 | R12: Duplicate ID | S12: =SUMPRODUCT(--(K$2:K$1001<>"")) -> 6
A13: =Customers!A13 -> CL00012 | B13: =IF(Customers!G13="","",(Customers!G13-Statistics!$C$7)/Statistics!$C$9) -> 0.010263482 | C13: =IF(Customers!G13="","",IF(OR(Customers!G13<Statistics!$C$15,Customers!G13>Statistics!$C$16),"Outside 1.5·IQR","")) -> Outside 1.5·IQR | D13: =IF(OR(Customers!B13<18,Customers!B13>100),"Implausible age","") | E13: =IF(Customers!H13>Customers!B13-18,"Tenure > age-18","") | F13: =IF(Customers!R13>Customers!Q13,"Card spend > limit","") | G13: =IF(OR(AND(Customers!S13>0,Customers!T13=0),AND(Customers!S13=0,Customers!T13>0)),"Mortgage/payment inconsistent","") | H13: =IF(AND(Customers!G13<>"",Customers!G13>0,Customers!T13>Customers!G13/12),"Payment > monthly income","") | I13: =IF(OR(Customers!I13>DATE(2026,9,13),YEAR(Customers!I13)<1980),"Implausible date","") | J13: =IF(Customers!I13>DATE(2026,9,13),"",IF(ABS(INT((DATE(2026,9,13)-Customers!I13)/365.25)-Customers!H13)>1,"Date/tenure inconsistent","")) | K13: =IF(COUNTIF(Customers!$A$2:$A$1001,Customers!A13)>1,"Duplicate ID","") | L13: =IF(COUNTIFS(Customers!$B$2:$B$1001,Customers!B13,Customers!$D$2:$D$1001,Customers!D13,Customers!$G$2:$G$1001,Customers!G13,Customers!$I$2:$I$1001,Customers!I13,Customers!$L$2:$L$1001,Customers!L13)>1,"Duplicate record","") | M13: =IF(OR(Customers!U13<300,Customers!U13>850),"Score out of range","") | N13: =IF(AND(Customers!G13<>"",Customers!G13<=0),"Income ≤ 0","") | O13: =IF(OR(Customers!G13="",Customers!M13=""),"Missing value","") | P13: =SUMPRODUCT(--(C13:O13<>"")) -> 1 | R13: Duplicate record | S13: =SUMPRODUCT(--(L$2:L$1001<>"")) -> 12
A14: =Customers!A14 -> CL00013 | B14: =IF(Customers!G14="","",(Customers!G14-Statistics!$C$7)/Statistics!$C$9) -> -0.023223914 | C14: =IF(Customers!G14="","",IF(OR(Customers!G14<Statistics!$C$15,Customers!G14>Statistics!$C$16),"Outside 1.5·IQR","")) | D14: =IF(OR(Customers!B14<18,Customers!B14>100),"Implausible age","") | E14: =IF(Customers!H14>Customers!B14-18,"Tenure > age-18","") | F14: =IF(Customers!R14>Customers!Q14,"Card spend > limit","") | G14: =IF(OR(AND(Customers!S14>0,Customers!T14=0),AND(Customers!S14=0,Customers!T14>0)),"Mortgage/payment inconsistent","") | H14: =IF(AND(Customers!G14<>"",Customers!G14>0,Customers!T14>Customers!G14/12),"Payment > monthly income","") | I14: =IF(OR(Customers!I14>DATE(2026,9,13),YEAR(Customers!I14)<1980),"Implausible date","") | J14: =IF(Customers!I14>DATE(2026,9,13),"",IF(ABS(INT((DATE(2026,9,13)-Customers!I14)/365.25)-Customers!H14)>1,"Date/tenure inconsistent","")) | K14: =IF(COUNTIF(Customers!$A$2:$A$1001,Customers!A14)>1,"Duplicate ID","") | L14: =IF(COUNTIFS(Customers!$B$2:$B$1001,Customers!B14,Customers!$D$2:$D$1001,Customers!D14,Customers!$G$2:$G$1001,Customers!G14,Customers!$I$2:$I$1001,Customers!I14,Customers!$L$2:$L$1001,Customers!L14)>1,"Duplicate record","") | M14: =IF(OR(Customers!U14<300,Customers!U14>850),"Score out of range","") | N14: =IF(AND(Customers!G14<>"",Customers!G14<=0),"Income ≤ 0","") | O14: =IF(OR(Customers!G14="",Customers!M14=""),"Missing value","") | P14: =SUMPRODUCT(--(C14:O14<>"")) -> 0 | R14: Score within scale | S14: =SUMPRODUCT(--(M$2:M$1001<>"")) -> 5
A15: =Customers!A15 -> CL00014 | B15: =IF(Customers!G15="","",(Customers!G15-Statistics!$C$7)/Statistics!$C$9) -> -0.049225892 | C15: =IF(Customers!G15="","",IF(OR(Customers!G15<Statistics!$C$15,Customers!G15>Statistics!$C$16),"Outside 1.5·IQR","")) | D15: =IF(OR(Customers!B15<18,Customers!B15>100),"Implausible age","") | E15: =IF(Customers!H15>Customers!B15-18,"Tenure > age-18","") | F15: =IF(Customers!R15>Customers!Q15,"Card spend > limit","") | G15: =IF(OR(AND(Customers!S15>0,Customers!T15=0),AND(Customers!S15=0,Customers!T15>0)),"Mortgage/payment inconsistent","") | H15: =IF(AND(Customers!G15<>"",Customers!G15>0,Customers!T15>Customers!G15/12),"Payment > monthly income","") | I15: =IF(OR(Customers!I15>DATE(2026,9,13),YEAR(Customers!I15)<1980),"Implausible date","") | J15: =IF(Customers!I15>DATE(2026,9,13),"",IF(ABS(INT((DATE(2026,9,13)-Customers!I15)/365.25)-Customers!H15)>1,"Date/tenure inconsistent","")) | K15: =IF(COUNTIF(Customers!$A$2:$A$1001,Customers!A15)>1,"Duplicate ID","") | L15: =IF(COUNTIFS(Customers!$B$2:$B$1001,Customers!B15,Customers!$D$2:$D$1001,Customers!D15,Customers!$G$2:$G$1001,Customers!G15,Customers!$I$2:$I$1001,Customers!I15,Customers!$L$2:$L$1001,Customers!L15)>1,"Duplicate record","") | M15: =IF(OR(Customers!U15<300,Customers!U15>850),"Score out of range","") | N15: =IF(AND(Customers!G15<>"",Customers!G15<=0),"Income ≤ 0","") | O15: =IF(OR(Customers!G15="",Customers!M15=""),"Missing value","") | P15: =SUMPRODUCT(--(C15:O15<>"")) -> 0 | R15: Positive income | S15: =SUMPRODUCT(--(N$2:N$1001<>"")) -> 4
A16: =Customers!A16 -> CL00015 | B16: =IF(Customers!G16="","",(Customers!G16-Statistics!$C$7)/Statistics!$C$9) -> -0.049225892 | C16: =IF(Customers!G16="","",IF(OR(Customers!G16<Statistics!$C$15,Customers!G16>Statistics!$C$16),"Outside 1.5·IQR","")) | D16: =IF(OR(Customers!B16<18,Customers!B16>100),"Implausible age","") | E16: =IF(Customers!H16>Customers!B16-18,"Tenure > age-18","") | F16: =IF(Customers!R16>Customers!Q16,"Card spend > limit","") | G16: =IF(OR(AND(Customers!S16>0,Customers!T16=0),AND(Customers!S16=0,Customers!T16>0)),"Mortgage/payment inconsistent","") | H16: =IF(AND(Customers!G16<>"",Customers!G16>0,Customers!T16>Customers!G16/12),"Payment > monthly income","") | I16: =IF(OR(Customers!I16>DATE(2026,9,13),YEAR(Customers!I16)<1980),"Implausible date","") | J16: =IF(Customers!I16>DATE(2026,9,13),"",IF(ABS(INT((DATE(2026,9,13)-Customers!I16)/365.25)-Customers!H16)>1,"Date/tenure inconsistent","")) | K16: =IF(COUNTIF(Customers!$A$2:$A$1001,Customers!A16)>1,"Duplicate ID","") | L16: =IF(COUNTIFS(Customers!$B$2:$B$1001,Customers!B16,Customers!$D$2:$D$1001,Customers!D16,Customers!$G$2:$G$1001,Customers!G16,Customers!$I$2:$I$1001,Customers!I16,Customers!$L$2:$L$1001,Customers!L16)>1,"Duplicate record","") | M16: =IF(OR(Customers!U16<300,Customers!U16>850),"Score out of range","") | N16: =IF(AND(Customers!G16<>"",Customers!G16<=0),"Income ≤ 0","") | O16: =IF(OR(Customers!G16="",Customers!M16=""),"Missing value","") | P16: =SUMPRODUCT(--(C16:O16<>"")) -> 0 | R16: Missing values | S16: =SUMPRODUCT(--(O$2:O$1001<>"")) -> 6
A17: =Customers!A17 -> CL00016 | B17: =IF(Customers!G17="","",(Customers!G17-Statistics!$C$7)/Statistics!$C$9) -> -0.050900262 | C17: =IF(Customers!G17="","",IF(OR(Customers!G17<Statistics!$C$15,Customers!G17>Statistics!$C$16),"Outside 1.5·IQR","")) | D17: =IF(OR(Customers!B17<18,Customers!B17>100),"Implausible age","") | E17: =IF(Customers!H17>Customers!B17-18,"Tenure > age-18","") | F17: =IF(Customers!R17>Customers!Q17,"Card spend > limit","") | G17: =IF(OR(AND(Customers!S17>0,Customers!T17=0),AND(Customers!S17=0,Customers!T17>0)),"Mortgage/payment inconsistent","") | H17: =IF(AND(Customers!G17<>"",Customers!G17>0,Customers!T17>Customers!G17/12),"Payment > monthly income","") | I17: =IF(OR(Customers!I17>DATE(2026,9,13),YEAR(Customers!I17)<1980),"Implausible date","") | J17: =IF(Customers!I17>DATE(2026,9,13),"",IF(ABS(INT((DATE(2026,9,13)-Customers!I17)/365.25)-Customers!H17)>1,"Date/tenure inconsistent","")) | K17: =IF(COUNTIF(Customers!$A$2:$A$1001,Customers!A17)>1,"Duplicate ID","") | L17: =IF(COUNTIFS(Customers!$B$2:$B$1001,Customers!B17,Customers!$D$2:$D$1001,Customers!D17,Customers!$G$2:$G$1001,Customers!G17,Customers!$I$2:$I$1001,Customers!I17,Customers!$L$2:$L$1001,Customers!L17)>1,"Duplicate record","") | M17: =IF(OR(Customers!U17<300,Customers!U17>850),"Score out of range","") | N17: =IF(AND(Customers!G17<>"",Customers!G17<=0),"Income ≤ 0","") | O17: =IF(OR(Customers!G17="",Customers!M17=""),"Missing value","") | P17: =SUMPRODUCT(--(C17:O17<>"")) -> 0 | R17: Rows with at least one flag | S17: =COUNTIF(P$2:P$1001,">0") -> 124
A18: =Customers!A18 -> CL00017 | B18: =IF(Customers!G18="","",(Customers!G18-Statistics!$C$7)/Statistics!$C$9) -> -0.052377647 | C18: =IF(Customers!G18="","",IF(OR(Customers!G18<Statistics!$C$15,Customers!G18>Statistics!$C$16),"Outside 1.5·IQR","")) | D18: =IF(OR(Customers!B18<18,Customers!B18>100),"Implausible age","") | E18: =IF(Customers!H18>Customers!B18-18,"Tenure > age-18","") | F18: =IF(Customers!R18>Customers!Q18,"Card spend > limit","") | G18: =IF(OR(AND(Customers!S18>0,Customers!T18=0),AND(Customers!S18=0,Customers!T18>0)),"Mortgage/payment inconsistent","") | H18: =IF(AND(Customers!G18<>"",Customers!G18>0,Customers!T18>Customers!G18/12),"Payment > monthly income","") | I18: =IF(OR(Customers!I18>DATE(2026,9,13),YEAR(Customers!I18)<1980),"Implausible date","") | J18: =IF(Customers!I18>DATE(2026,9,13),"",IF(ABS(INT((DATE(2026,9,13)-Customers!I18)/365.25)-Customers!H18)>1,"Date/tenure inconsistent","")) | K18: =IF(COUNTIF(Customers!$A$2:$A$1001,Customers!A18)>1,"Duplicate ID","") | L18: =IF(COUNTIFS(Customers!$B$2:$B$1001,Customers!B18,Customers!$D$2:$D$1001,Customers!D18,Customers!$G$2:$G$1001,Customers!G18,Customers!$I$2:$I$1001,Customers!I18,Customers!$L$2:$L$1001,Customers!L18)>1,"Duplicate record","") | M18: =IF(OR(Customers!U18<300,Customers!U18>850),"Score out of range","") | N18: =IF(AND(Customers!G18<>"",Customers!G18<=0),"Income ≤ 0","") | O18: =IF(OR(Customers!G18="",Customers!M18=""),"Missing value","") | P18: =SUMPRODUCT(--(C18:O18<>"")) -> 0
A19: =Customers!A19 -> CL00018 | B19: =IF(Customers!G19="","",(Customers!G19-Statistics!$C$7)/Statistics!$C$9) -> -0.026671146 | C19: =IF(Customers!G19="","",IF(OR(Customers!G19<Statistics!$C$15,Customers!G19>Statistics!$C$16),"Outside 1.5·IQR","")) | D19: =IF(OR(Customers!B19<18,Customers!B19>100),"Implausible age","") | E19: =IF(Customers!H19>Customers!B19-18,"Tenure > age-18","") | F19: =IF(Customers!R19>Customers!Q19,"Card spend > limit","") | G19: =IF(OR(AND(Customers!S19>0,Customers!T19=0),AND(Customers!S19=0,Customers!T19>0)),"Mortgage/payment inconsistent","") | H19: =IF(AND(Customers!G19<>"",Customers!G19>0,Customers!T19>Customers!G19/12),"Payment > monthly income","") | I19: =IF(OR(Customers!I19>DATE(2026,9,13),YEAR(Customers!I19)<1980),"Implausible date","") | J19: =IF(Customers!I19>DATE(2026,9,13),"",IF(ABS(INT((DATE(2026,9,13)-Customers!I19)/365.25)-Customers!H19)>1,"Date/tenure inconsistent","")) | K19: =IF(COUNTIF(Customers!$A$2:$A$1001,Customers!A19)>1,"Duplicate ID","") | L19: =IF(COUNTIFS(Customers!$B$2:$B$1001,Customers!B19,Customers!$D$2:$D$1001,Customers!D19,Customers!$G$2:$G$1001,Customers!G19,Customers!$I$2:$I$1001,Customers!I19,Customers!$L$2:$L$1001,Customers!L19)>1,"Duplicate record","") | M19: =IF(OR(Customers!U19<300,Customers!U19>850),"Score out of range","") | N19: =IF(AND(Customers!G19<>"",Customers!G19<=0),"Income ≤ 0","") | O19: =IF(OR(Customers!G19="",Customers!M19=""),"Missing value","") | P19: =SUMPRODUCT(--(C19:O19<>"")) -> 0 | R19: The formulas use only basic functions (IF, COUNTIF, COUNTIFS, SUMPRODUCT) and refer to the thresholds in the Statistics sheet. The extraction date (2026-09-13) is fixed in the formulas with DATE(2026,9,13); in class we can replace it with TODAY().
A20: =Customers!A20 -> CL00019 | B20: =IF(Customers!G20="","",(Customers!G20-Statistics!$C$7)/Statistics!$C$9) -> -0.066363559 | C20: =IF(Customers!G20="","",IF(OR(Customers!G20<Statistics!$C$15,Customers!G20>Statistics!$C$16),"Outside 1.5·IQR","")) | D20: =IF(OR(Customers!B20<18,Customers!B20>100),"Implausible age","") | E20: =IF(Customers!H20>Customers!B20-18,"Tenure > age-18","") | F20: =IF(Customers!R20>Customers!Q20,"Card spend > limit","") | G20: =IF(OR(AND(Customers!S20>0,Customers!T20=0),AND(Customers!S20=0,Customers!T20>0)),"Mortgage/payment inconsistent","") | H20: =IF(AND(Customers!G20<>"",Customers!G20>0,Customers!T20>Customers!G20/12),"Payment > monthly income","") | I20: =IF(OR(Customers!I20>DATE(2026,9,13),YEAR(Customers!I20)<1980),"Implausible date","") | J20: =IF(Customers!I20>DATE(2026,9,13),"",IF(ABS(INT((DATE(2026,9,13)-Customers!I20)/365.25)-Customers!H20)>1,"Date/tenure inconsistent","")) | K20: =IF(COUNTIF(Customers!$A$2:$A$1001,Customers!A20)>1,"Duplicate ID","") | L20: =IF(COUNTIFS(Customers!$B$2:$B$1001,Customers!B20,Customers!$D$2:$D$1001,Customers!D20,Customers!$G$2:$G$1001,Customers!G20,Customers!$I$2:$I$1001,Customers!I20,Customers!$L$2:$L$1001,Customers!L20)>1,"Duplicate record","") | M20: =IF(OR(Customers!U20<300,Customers!U20>850),"Score out of range","") | N20: =IF(AND(Customers!G20<>"",Customers!G20<=0),"Income ≤ 0","") | O20: =IF(OR(Customers!G20="",Customers!M20=""),"Missing value","") | P20: =SUMPRODUCT(--(C20:O20<>"")) -> 0
A21: =Customers!A21 -> CL00020 | B21: =IF(Customers!G21="","",(Customers!G21-Statistics!$C$7)/Statistics!$C$9) -> -0.0026390148 | C21: =IF(Customers!G21="","",IF(OR(Customers!G21<Statistics!$C$15,Customers!G21>Statistics!$C$16),"Outside 1.5·IQR","")) | D21: =IF(OR(Customers!B21<18,Customers!B21>100),"Implausible age","") | E21: =IF(Customers!H21>Customers!B21-18,"Tenure > age-18","") | F21: =IF(Customers!R21>Customers!Q21,"Card spend > limit","") | G21: =IF(OR(AND(Customers!S21>0,Customers!T21=0),AND(Customers!S21=0,Customers!T21>0)),"Mortgage/payment inconsistent","") | H21: =IF(AND(Customers!G21<>"",Customers!G21>0,Customers!T21>Customers!G21/12),"Payment > monthly income","") | I21: =IF(OR(Customers!I21>DATE(2026,9,13),YEAR(Customers!I21)<1980),"Implausible date","") | J21: =IF(Customers!I21>DATE(2026,9,13),"",IF(ABS(INT((DATE(2026,9,13)-Customers!I21)/365.25)-Customers!H21)>1,"Date/tenure inconsistent","")) | K21: =IF(COUNTIF(Customers!$A$2:$A$1001,Customers!A21)>1,"Duplicate ID","") | L21: =IF(COUNTIFS(Customers!$B$2:$B$1001,Customers!B21,Customers!$D$2:$D$1001,Customers!D21,Customers!$G$2:$G$1001,Customers!G21,Customers!$I$2:$I$1001,Customers!I21,Customers!$L$2:$L$1001,Customers!L21)>1,"Duplicate record","") | M21: =IF(OR(Customers!U21<300,Customers!U21>850),"Score out of range","") | N21: =IF(AND(Customers!G21<>"",Customers!G21<=0),"Income ≤ 0","") | O21: =IF(OR(Customers!G21="",Customers!M21=""),"Missing value","") | P21: =SUMPRODUCT(--(C21:O21<>"")) -> 0
A22: =Customers!A22 -> CL00021 | B22: =IF(Customers!G22="","",(Customers!G22-Statistics!$C$7)/Statistics!$C$9) -> 0.0058313264 | C22: =IF(Customers!G22="","",IF(OR(Customers!G22<Statistics!$C$15,Customers!G22>Statistics!$C$16),"Outside 1.5·IQR","")) | D22: =IF(OR(Customers!B22<18,Customers!B22>100),"Implausible age","") | E22: =IF(Customers!H22>Customers!B22-18,"Tenure > age-18","") | F22: =IF(Customers!R22>Customers!Q22,"Card spend > limit","") | G22: =IF(OR(AND(Customers!S22>0,Customers!T22=0),AND(Customers!S22=0,Customers!T22>0)),"Mortgage/payment inconsistent","") | H22: =IF(AND(Customers!G22<>"",Customers!G22>0,Customers!T22>Customers!G22/12),"Payment > monthly income","") | I22: =IF(OR(Customers!I22>DATE(2026,9,13),YEAR(Customers!I22)<1980),"Implausible date","") | J22: =IF(Customers!I22>DATE(2026,9,13),"",IF(ABS(INT((DATE(2026,9,13)-Customers!I22)/365.25)-Customers!H22)>1,"Date/tenure inconsistent","")) | K22: =IF(COUNTIF(Customers!$A$2:$A$1001,Customers!A22)>1,"Duplicate ID","") | L22: =IF(COUNTIFS(Customers!$B$2:$B$1001,Customers!B22,Customers!$D$2:$D$1001,Customers!D22,Customers!$G$2:$G$1001,Customers!G22,Customers!$I$2:$I$1001,Customers!I22,Customers!$L$2:$L$1001,Customers!L22)>1,"Duplicate record","") | M22: =IF(OR(Customers!U22<300,Customers!U22>850),"Score out of range","") | N22: =IF(AND(Customers!G22<>"",Customers!G22<=0),"Income ≤ 0","") | O22: =IF(OR(Customers!G22="",Customers!M22=""),"Missing value","") | P22: =SUMPRODUCT(--(C22:O22<>"")) -> 0
A23: =Customers!A23 -> CL00022 | B23: =IF(Customers!G23="","",(Customers!G23-Statistics!$C$7)/Statistics!$C$9) -> -0.049422877 | C23: =IF(Customers!G23="","",IF(OR(Customers!G23<Statistics!$C$15,Customers!G23>Statistics!$C$16),"Outside 1.5·IQR","")) | D23: =IF(OR(Customers!B23<18,Customers!B23>100),"Implausible age","") | E23: =IF(Customers!H23>Customers!B23-18,"Tenure > age-18","") | F23: =IF(Customers!R23>Customers!Q23,"Card spend > limit","") | G23: =IF(OR(AND(Customers!S23>0,Customers!T23=0),AND(Customers!S23=0,Customers!T23>0)),"Mortgage/payment inconsistent","") | H23: =IF(AND(Customers!G23<>"",Customers!G23>0,Customers!T23>Customers!G23/12),"Payment > monthly income","") | I23: =IF(OR(Customers!I23>DATE(2026,9,13),YEAR(Customers!I23)<1980),"Implausible date","") | J23: =IF(Customers!I23>DATE(2026,9,13),"",IF(ABS(INT((DATE(2026,9,13)-Customers!I23)/365.25)-Customers!H23)>1,"Date/tenure inconsistent","")) | K23: =IF(COUNTIF(Customers!$A$2:$A$1001,Customers!A23)>1,"Duplicate ID","") | L23: =IF(COUNTIFS(Customers!$B$2:$B$1001,Customers!B23,Customers!$D$2:$D$1001,Customers!D23,Customers!$G$2:$G$1001,Customers!G23,Customers!$I$2:$I$1001,Customers!I23,Customers!$L$2:$L$1001,Customers!L23)>1,"Duplicate record","") | M23: =IF(OR(Customers!U23<300,Customers!U23>850),"Score out of range","") | N23: =IF(AND(Customers!G23<>"",Customers!G23<=0),"Income ≤ 0","") | O23: =IF(OR(Customers!G23="",Customers!M23=""),"Missing value","") | P23: =SUMPRODUCT(--(C23:O23<>"")) -> 0
A24: =Customers!A24 -> CL00023 | B24: =IF(Customers!G24="","",(Customers!G24-Statistics!$C$7)/Statistics!$C$9) -> -0.019185728 | C24: =IF(Customers!G24="","",IF(OR(Customers!G24<Statistics!$C$15,Customers!G24>Statistics!$C$16),"Outside 1.5·IQR","")) | D24: =IF(OR(Customers!B24<18,Customers!B24>100),"Implausible age","") | E24: =IF(Customers!H24>Customers!B24-18,"Tenure > age-18","") | F24: =IF(Customers!R24>Customers!Q24,"Card spend > limit","") | G24: =IF(OR(AND(Customers!S24>0,Customers!T24=0),AND(Customers!S24=0,Customers!T24>0)),"Mortgage/payment inconsistent","") | H24: =IF(AND(Customers!G24<>"",Customers!G24>0,Customers!T24>Customers!G24/12),"Payment > monthly income","") | I24: =IF(OR(Customers!I24>DATE(2026,9,13),YEAR(Customers!I24)<1980),"Implausible date","") | J24: =IF(Customers!I24>DATE(2026,9,13),"",IF(ABS(INT((DATE(2026,9,13)-Customers!I24)/365.25)-Customers!H24)>1,"Date/tenure inconsistent","")) | K24: =IF(COUNTIF(Customers!$A$2:$A$1001,Customers!A24)>1,"Duplicate ID","") | L24: =IF(COUNTIFS(Customers!$B$2:$B$1001,Customers!B24,Customers!$D$2:$D$1001,Customers!D24,Customers!$G$2:$G$1001,Customers!G24,Customers!$I$2:$I$1001,Customers!I24,Customers!$L$2:$L$1001,Customers!L24)>1,"Duplicate record","") | M24: =IF(OR(Customers!U24<300,Customers!U24>850),"Score out of range","") | N24: =IF(AND(Customers!G24<>"",Customers!G24<=0),"Income ≤ 0","") | O24: =IF(OR(Customers!G24="",Customers!M24=""),"Missing value","") | P24: =SUMPRODUCT(--(C24:O24<>"")) -> 0
A25: =Customers!A25 -> CL00024 | B25: =IF(Customers!G25="","",(Customers!G25-Statistics!$C$7)/Statistics!$C$9) -> -0.038391734 | C25: =IF(Customers!G25="","",IF(OR(Customers!G25<Statistics!$C$15,Customers!G25>Statistics!$C$16),"Outside 1.5·IQR","")) | D25: =IF(OR(Customers!B25<18,Customers!B25>100),"Implausible age","") | E25: =IF(Customers!H25>Customers!B25-18,"Tenure > age-18","") | F25: =IF(Customers!R25>Customers!Q25,"Card spend > limit","") | G25: =IF(OR(AND(Customers!S25>0,Customers!T25=0),AND(Customers!S25=0,Customers!T25>0)),"Mortgage/payment inconsistent","") | H25: =IF(AND(Customers!G25<>"",Customers!G25>0,Customers!T25>Customers!G25/12),"Payment > monthly income","") | I25: =IF(OR(Customers!I25>DATE(2026,9,13),YEAR(Customers!I25)<1980),"Implausible date","") | J25: =IF(Customers!I25>DATE(2026,9,13),"",IF(ABS(INT((DATE(2026,9,13)-Customers!I25)/365.25)-Customers!H25)>1,"Date/tenure inconsistent","")) | K25: =IF(COUNTIF(Customers!$A$2:$A$1001,Customers!A25)>1,"Duplicate ID","") | L25: =IF(COUNTIFS(Customers!$B$2:$B$1001,Customers!B25,Customers!$D$2:$D$1001,Customers!D25,Customers!$G$2:$G$1001,Customers!G25,Customers!$I$2:$I$1001,Customers!I25,Customers!$L$2:$L$1001,Customers!L25)>1,"Duplicate record","") | M25: =IF(OR(Customers!U25<300,Customers!U25>850),"Score out of range","") | N25: =IF(AND(Customers!G25<>"",Customers!G25<=0),"Income ≤ 0","") | O25: =IF(OR(Customers!G25="",Customers!M25=""),"Missing value","") | P25: =SUMPRODUCT(--(C25:O25<>"")) -> 0
A26: =Customers!A26 -> CL00025 | B26: =IF(Customers!G26="","",(Customers!G26-Statistics!$C$7)/Statistics!$C$9) -> -0.0040179076 | C26: =IF(Customers!G26="","",IF(OR(Customers!G26<Statistics!$C$15,Customers!G26>Statistics!$C$16),"Outside 1.5·IQR","")) | D26: =IF(OR(Customers!B26<18,Customers!B26>100),"Implausible age","") | E26: =IF(Customers!H26>Customers!B26-18,"Tenure > age-18","") | F26: =IF(Customers!R26>Customers!Q26,"Card spend > limit","") | G26: =IF(OR(AND(Customers!S26>0,Customers!T26=0),AND(Customers!S26=0,Customers!T26>0)),"Mortgage/payment inconsistent","") | H26: =IF(AND(Customers!G26<>"",Customers!G26>0,Customers!T26>Customers!G26/12),"Payment > monthly income","") | I26: =IF(OR(Customers!I26>DATE(2026,9,13),YEAR(Customers!I26)<1980),"Implausible date","") | J26: =IF(Customers!I26>DATE(2026,9,13),"",IF(ABS(INT((DATE(2026,9,13)-Customers!I26)/365.25)-Customers!H26)>1,"Date/tenure inconsistent","")) | K26: =IF(COUNTIF(Customers!$A$2:$A$1001,Customers!A26)>1,"Duplicate ID","") | L26: =IF(COUNTIFS(Customers!$B$2:$B$1001,Customers!B26,Customers!$D$2:$D$1001,Customers!D26,Customers!$G$2:$G$1001,Customers!G26,Customers!$I$2:$I$1001,Customers!I26,Customers!$L$2:$L$1001,Customers!L26)>1,"Duplicate record","") | M26: =IF(OR(Customers!U26<300,Customers!U26>850),"Score out of range","") | N26: =IF(AND(Customers!G26<>"",Customers!G26<=0),"Income ≤ 0","") | O26: =IF(OR(Customers!G26="",Customers!M26=""),"Missing value","") | P26: =SUMPRODUCT(--(C26:O26<>"")) -> 0
A27: =Customers!A27 -> CL00026 | B27: =IF(Customers!G27="","",(Customers!G27-Statistics!$C$7)/Statistics!$C$9) -> -0.039179673 | C27: =IF(Customers!G27="","",IF(OR(Customers!G27<Statistics!$C$15,Customers!G27>Statistics!$C$16),"Outside 1.5·IQR","")) | D27: =IF(OR(Customers!B27<18,Customers!B27>100),"Implausible age","") | E27: =IF(Customers!H27>Customers!B27-18,"Tenure > age-18","") | F27: =IF(Customers!R27>Customers!Q27,"Card spend > limit","") | G27: =IF(OR(AND(Customers!S27>0,Customers!T27=0),AND(Customers!S27=0,Customers!T27>0)),"Mortgage/payment inconsistent","") | H27: =IF(AND(Customers!G27<>"",Customers!G27>0,Customers!T27>Customers!G27/12),"Payment > monthly income","") | I27: =IF(OR(Customers!I27>DATE(2026,9,13),YEAR(Customers!I27)<1980),"Implausible date","") | J27: =IF(Customers!I27>DATE(2026,9,13),"",IF(ABS(INT((DATE(2026,9,13)-Customers!I27)/365.25)-Customers!H27)>1,"Date/tenure inconsistent","")) | K27: =IF(COUNTIF(Customers!$A$2:$A$1001,Customers!A27)>1,"Duplicate ID","") | L27: =IF(COUNTIFS(Customers!$B$2:$B$1001,Customers!B27,Customers!$D$2:$D$1001,Customers!D27,Customers!$G$2:$G$1001,Customers!G27,Customers!$I$2:$I$1001,Customers!I27,Customers!$L$2:$L$1001,Customers!L27)>1,"Duplicate record","") | M27: =IF(OR(Customers!U27<300,Customers!U27>850),"Score out of range","") | N27: =IF(AND(Customers!G27<>"",Customers!G27<=0),"Income ≤ 0","") | O27: =IF(OR(Customers!G27="",Customers!M27=""),"Missing value","") | P27: =SUMPRODUCT(--(C27:O27<>"")) -> 0
A28: =Customers!A28 -> CL00027 | B28: =IF(Customers!G28="","",(Customers!G28-Statistics!$C$7)/Statistics!$C$9) -> -0.027459085 | C28: =IF(Customers!G28="","",IF(OR(Customers!G28<Statistics!$C$15,Customers!G28>Statistics!$C$16),"Outside 1.5·IQR","")) | D28: =IF(OR(Customers!B28<18,Customers!B28>100),"Implausible age","") | E28: =IF(Customers!H28>Customers!B28-18,"Tenure > age-18","") | F28: =IF(Customers!R28>Customers!Q28,"Card spend > limit","") | G28: =IF(OR(AND(Customers!S28>0,Customers!T28=0),AND(Customers!S28=0,Customers!T28>0)),"Mortgage/payment inconsistent","") | H28: =IF(AND(Customers!G28<>"",Customers!G28>0,Customers!T28>Customers!G28/12),"Payment > monthly income","") | I28: =IF(OR(Customers!I28>DATE(2026,9,13),YEAR(Customers!I28)<1980),"Implausible date","") | J28: =IF(Customers!I28>DATE(2026,9,13),"",IF(ABS(INT((DATE(2026,9,13)-Customers!I28)/365.25)-Customers!H28)>1,"Date/tenure inconsistent","")) | K28: =IF(COUNTIF(Customers!$A$2:$A$1001,Customers!A28)>1,"Duplicate ID","") | L28: =IF(COUNTIFS(Customers!$B$2:$B$1001,Customers!B28,Customers!$D$2:$D$1001,Customers!D28,Customers!$G$2:$G$1001,Customers!G28,Customers!$I$2:$I$1001,Customers!I28,Customers!$L$2:$L$1001,Customers!L28)>1,"Duplicate record","") | M28: =IF(OR(Customers!U28<300,Customers!U28>850),"Score out of range","") | N28: =IF(AND(Customers!G28<>"",Customers!G28<=0),"Income ≤ 0","") | O28: =IF(OR(Customers!G28="",Customers!M28=""),"Missing value","") | P28: =SUMPRODUCT(--(C28:O28<>"")) -> 0
A29: =Customers!A29 -> CL00028 | B29: =IF(Customers!G29="","",(Customers!G29-Statistics!$C$7)/Statistics!$C$9) -> -0.044399767 | C29: =IF(Customers!G29="","",IF(OR(Customers!G29<Statistics!$C$15,Customers!G29>Statistics!$C$16),"Outside 1.5·IQR","")) | D29: =IF(OR(Customers!B29<18,Customers!B29>100),"Implausible age","") | E29: =IF(Customers!H29>Customers!B29-18,"Tenure > age-18","") | F29: =IF(Customers!R29>Customers!Q29,"Card spend > limit","") | G29: =IF(OR(AND(Customers!S29>0,Customers!T29=0),AND(Customers!S29=0,Customers!T29>0)),"Mortgage/payment inconsistent","") | H29: =IF(AND(Customers!G29<>"",Customers!G29>0,Customers!T29>Customers!G29/12),"Payment > monthly income","") | I29: =IF(OR(Customers!I29>DATE(2026,9,13),YEAR(Customers!I29)<1980),"Implausible date","") | J29: =IF(Customers!I29>DATE(2026,9,13),"",IF(ABS(INT((DATE(2026,9,13)-Customers!I29)/365.25)-Customers!H29)>1,"Date/tenure inconsistent","")) | K29: =IF(COUNTIF(Customers!$A$2:$A$1001,Customers!A29)>1,"Duplicate ID","") | L29: =IF(COUNTIFS(Customers!$B$2:$B$1001,Customers!B29,Customers!$D$2:$D$1001,Customers!D29,Customers!$G$2:$G$1001,Customers!G29,Customers!$I$2:$I$1001,Customers!I29,Customers!$L$2:$L$1001,Customers!L29)>1,"Duplicate record","") | M29: =IF(OR(Customers!U29<300,Customers!U29>850),"Score out of range","") | N29: =IF(AND(Customers!G29<>"",Customers!G29<=0),"Income ≤ 0","") | O29: =IF(OR(Customers!G29="",Customers!M29=""),"Missing value","") | P29: =SUMPRODUCT(--(C29:O29<>"")) -> 0
A30: =Customers!A30 -> CL00029 | B30: =IF(Customers!G30="","",(Customers!G30-Statistics!$C$7)/Statistics!$C$9) -> -0.05375654 | C30: =IF(Customers!G30="","",IF(OR(Customers!G30<Statistics!$C$15,Customers!G30>Statistics!$C$16),"Outside 1.5·IQR","")) | D30: =IF(OR(Customers!B30<18,Customers!B30>100),"Implausible age","") | E30: =IF(Customers!H30>Customers!B30-18,"Tenure > age-18","") | F30: =IF(Customers!R30>Customers!Q30,"Card spend > limit","") | G30: =IF(OR(AND(Customers!S30>0,Customers!T30=0),AND(Customers!S30=0,Customers!T30>0)),"Mortgage/payment inconsistent","") | H30: =IF(AND(Customers!G30<>"",Customers!G30>0,Customers!T30>Customers!G30/12),"Payment > monthly income","") | I30: =IF(OR(Customers!I30>DATE(2026,9,13),YEAR(Customers!I30)<1980),"Implausible date","") | J30: =IF(Customers!I30>DATE(2026,9,13),"",IF(ABS(INT((DATE(2026,9,13)-Customers!I30)/365.25)-Customers!H30)>1,"Date/tenure inconsistent","")) | K30: =IF(COUNTIF(Customers!$A$2:$A$1001,Customers!A30)>1,"Duplicate ID","") | L30: =IF(COUNTIFS(Customers!$B$2:$B$1001,Customers!B30,Customers!$D$2:$D$1001,Customers!D30,Customers!$G$2:$G$1001,Customers!G30,Customers!$I$2:$I$1001,Customers!I30,Customers!$L$2:$L$1001,Customers!L30)>1,"Duplicate record","") | M30: =IF(OR(Customers!U30<300,Customers!U30>850),"Score out of range","") | N30: =IF(AND(Customers!G30<>"",Customers!G30<=0),"Income ≤ 0","") | O30: =IF(OR(Customers!G30="",Customers!M30=""),"Missing value","") | P30: =SUMPRODUCT(--(C30:O30<>"")) -> 0
A31: =Customers!A31 -> CL00030 | B31: =IF(Customers!G31="","",(Customers!G31-Statistics!$C$7)/Statistics!$C$9) -> -0.019087236 | C31: =IF(Customers!G31="","",IF(OR(Customers!G31<Statistics!$C$15,Customers!G31>Statistics!$C$16),"Outside 1.5·IQR","")) | D31: =IF(OR(Customers!B31<18,Customers!B31>100),"Implausible age","") | E31: =IF(Customers!H31>Customers!B31-18,"Tenure > age-18","") | F31: =IF(Customers!R31>Customers!Q31,"Card spend > limit","") | G31: =IF(OR(AND(Customers!S31>0,Customers!T31=0),AND(Customers!S31=0,Customers!T31>0)),"Mortgage/payment inconsistent","") | H31: =IF(AND(Customers!G31<>"",Customers!G31>0,Customers!T31>Customers!G31/12),"Payment > monthly income","") | I31: =IF(OR(Customers!I31>DATE(2026,9,13),YEAR(Customers!I31)<1980),"Implausible date","") | J31: =IF(Customers!I31>DATE(2026,9,13),"",IF(ABS(INT((DATE(2026,9,13)-Customers!I31)/365.25)-Customers!H31)>1,"Date/tenure inconsistent","")) | K31: =IF(COUNTIF(Customers!$A$2:$A$1001,Customers!A31)>1,"Duplicate ID","") | L31: =IF(COUNTIFS(Customers!$B$2:$B$1001,Customers!B31,Customers!$D$2:$D$1001,Customers!D31,Customers!$G$2:$G$1001,Customers!G31,Customers!$I$2:$I$1001,Customers!I31,Customers!$L$2:$L$1001,Customers!L31)>1,"Duplicate record","") | M31: =IF(OR(Customers!U31<300,Customers!U31>850),"Score out of range","") | N31: =IF(AND(Customers!G31<>"",Customers!G31<=0),"Income ≤ 0","") | O31: =IF(OR(Customers!G31="",Customers!M31=""),"Missing value","") | P31: =SUMPRODUCT(--(C31:O31<>"")) -> 0
... A1001: =Customers!A1001 -> CL00994 | B1001: =IF(Customers!G1001="","",(Customers!G1001-Statistics!$C$7)/Statistics!$C$9) -> -0.017905328 | C1001: =IF(Customers!G1001="","",IF(OR(Customers!G1001<Statistics!$C$15,Customers!G1001>Statistics!$C$16),"Outside 1.5·IQR","")) | D1001: =IF(OR(Customers!B1001<18,Customers!B1001>100),"Implausible age","") | E1001: =IF(Customers!H1001>Customers!B1001-18,"Tenure > age-18","") | F1001: =IF(Customers!R1001>Customers!Q1001,"Card spend > limit","") | G1001: =IF(OR(AND(Customers!S1001>0,Customers!T1001=0),AND(Customers!S1001=0,Customers!T1001>0)),"Mortgage/payment inconsistent","") | H1001: =IF(AND(Customers!G1001<>"",Customers!G1001>0,Customers!T1001>Customers!G1001/12),"Payment > monthly income","") | I1001: =IF(OR(Customers!I1001>DATE(2026,9,13),YEAR(Customers!I1001)<1980),"Implausible date","") | J1001: =IF(Customers!I1001>DATE(2026,9,13),"",IF(ABS(INT((DATE(2026,9,13)-Customers!I1001)/365.25)-Customers!H1001)>1,"Date/tenure inconsistent","")) | K1001: =IF(COUNTIF(Customers!$A$2:$A$1001,Customers!A1001)>1,"Duplicate ID","") | L1001: =IF(COUNTIFS(Customers!$B$2:$B$1001,Customers!B1001,Customers!$D$2:$D$1001,Customers!D1001,Customers!$G$2:$G$1001,Customers!G1001,Customers!$I$2:$I$1001,Customers!I1001,Customers!$L$2:$L$1001,Customers!L1001)>1,"Duplicate record","") | M1001: =IF(OR(Customers!U1001<300,Customers!U1001>850),"Score out of range","") | N1001: =IF(AND(Customers!G1001<>"",Customers!G1001<=0),"Income ≤ 0","") | O1001: =IF(OR(Customers!G1001="",Customers!M1001=""),"Missing value","") | P1001: =SUMPRODUCT(--(C1001:O1001<>"")) -> 0

Sheet Outlier_Key_Trainer
A1: Key to the injected outliers — trainer-only sheet
A2: The participants' file (bank_customers_outliers.xlsx) contains only the Customers and Data_Dictionary sheets. Here we list the 95 anomalies injected in a controlled way (out of 1,000 rows); the remaining rows come from realistic distributions and may contain 'natural' extreme values, useful for discussing in class the difference between an outlier and an error. We always speak of 'possible outliers to be verified': an extreme value is not automatically an error, and a plausible value can hide an inconsistency. Excel row = row in the Customers sheet (header in row 1).
A4: No. | B4: Category | C4: Type of anomaly | D4: Customer_ID | E4: Excel row | F4: Column(s) involved | G4: Anomalous value(s) | H4: Why it is 'to be verified' | I4: How to spot it in Excel
A5: 1 | B5: A. Extreme values (univariate) | C5: Very high income (plausible HNW customer) | D5: CL00199 | E5: 204 | F5: Annual_Income_EUR | G5: €1,850,000 | H5: Income of €1,850,000, far beyond the rest of the distribution, but consistent with occupation (Business owner), savings and card limit: probably a genuine high-net-worth customer, to be confirmed rather than deleted. It still shows up as 'outside' in the box plot and under the IQR rule. | I5: Sort the column descending; Box & Whisker chart (Insert > Statistic Chart); z-score with =(G2-AVERAGE(G:G))/STDEV(G:G); 1.5·IQR rule with QUARTILE (see the Statistics sheet); Conditional Formatting > Top/Bottom Rules.
A6: 2 | B6: A. Extreme values (univariate) | C6: Very high income (plausible HNW customer) | D6: CL00406 | E6: 412 | F6: Annual_Income_EUR | G6: €820,000 | H6: Income of €820,000, far beyond the rest of the distribution, but consistent with occupation (Executive), savings and card limit: probably a genuine high-net-worth customer, to be confirmed rather than deleted. It still shows up as 'outside' in the box plot and under the IQR rule. | I6: Sort the column descending; Box & Whisker chart (Insert > Statistic Chart); z-score with =(G2-AVERAGE(G:G))/STDEV(G:G); 1.5·IQR rule with QUARTILE (see the Statistics sheet); Conditional Formatting > Top/Bottom Rules.
A7: 3 | B7: A. Extreme values (univariate) | C7: Very high number of complaints | D7: CL00464 | E7: 470 | F7: Complaints_12M | G7: 14 | H7: 14 complaints in 12 months (almost every customer has 0 or 1): customer at high risk of churn. A 'business' outlier rather than an error — exactly the case we want to catch. | I7: Sort the column descending; Box & Whisker chart (Insert > Statistic Chart); z-score with =(G2-AVERAGE(G:G))/STDEV(G:G); 1.5·IQR rule with QUARTILE (see the Statistics sheet); Conditional Formatting > Top/Bottom Rules.
A8: 4 | B8: A. Extreme values (univariate) | C8: Very high number of transactions | D8: CL00646 | E8: 652 | F8: Monthly_Transactions | G8: 615 | H8: 615 transactions per month against a median of around 30: plausible for a shopkeeper, but we should confirm it is not a business account loaded as a retail one. | I8: Sort the column descending; Box & Whisker chart (Insert > Statistic Chart); z-score with =(G2-AVERAGE(G:G))/STDEV(G:G); 1.5·IQR rule with QUARTILE (see the Statistics sheet); Conditional Formatting > Top/Bottom Rules.
A9: 5 | B9: A. Extreme values (univariate) | C9: Very high savings balance | D9: CL00762 | E9: 769 | F9: Savings_Balance_EUR | G9: €3,100,000 | H9: Savings of €3,100,000 on an income of €58,000: extreme but plausible for a 64-year-old customer with 16 years of tenure (inheritance, sale of a business). To be verified, not discarded. | I9: Sort the column descending; Box & Whisker chart (Insert > Statistic Chart); z-score with =(G2-AVERAGE(G:G))/STDEV(G:G); 1.5·IQR rule with QUARTILE (see the Statistics sheet); Conditional Formatting > Top/Bottom Rules.
A10: 6 | B10: A. Extreme values (univariate) | C10: Very high age (plausible) | D10: CL00938 | E10: 945 | F10: Age; Tenure_Years | G10: 97 years; 44 years of tenure | H10: Age 97 and 44 years of tenure: extreme but possible for a long-standing retired customer; we should check that the master data is up to date (is the customer still alive?). | I10: Sort the column descending; Box & Whisker chart (Insert > Statistic Chart); z-score with =(G2-AVERAGE(G:G))/STDEV(G:G); 1.5·IQR rule with QUARTILE (see the Statistics sheet); Conditional Formatting > Top/Bottom Rules.
A11: 7 | B11: A. Extreme values (univariate) | C11: Very high number of transactions | D11: CL00948 | E11: 955 | F11: Monthly_Transactions | G11: 420 | H11: 420 transactions per month against a median of around 30: plausible for a business owner, but we should confirm it is not a business account loaded as a retail one. | I11: Sort the column descending; Box & Whisker chart (Insert > Statistic Chart); z-score with =(G2-AVERAGE(G:G))/STDEV(G:G); 1.5·IQR rule with QUARTILE (see the Statistics sheet); Conditional Formatting > Top/Bottom Rules.
A12: 8 | B12: A. Extreme values (univariate) | C12: Very high savings balance | D12: CL00976 | E12: 983 | F12: Savings_Balance_EUR | G12: €2,400,000 | H12: Savings of €2,400,000 on an income of €177,200: extreme but plausible for a 63-year-old customer with 16 years of tenure (inheritance, sale of a business). To be verified, not discarded. | I12: Sort the column descending; Box & Whisker chart (Insert > Statistic Chart); z-score with =(G2-AVERAGE(G:G))/STDEV(G:G); 1.5·IQR rule with QUARTILE (see the Statistics sheet); Conditional Formatting > Top/Bottom Rules.
A13: 9 | B13: A. Extreme values (univariate) | C13: Very high income (plausible HNW customer) | D13: CL00978 | E13: 985 | F13: Annual_Income_EUR | G13: €1,350,000 | H13: Income of €1,350,000, far beyond the rest of the distribution, but consistent with occupation (Executive), savings and card limit: probably a genuine high-net-worth customer, to be confirmed rather than deleted. It still shows up as 'outside' in the box plot and under the IQR rule. | I13: Sort the column descending; Box & Whisker chart (Insert > Statistic Chart); z-score with =(G2-AVERAGE(G:G))/STDEV(G:G); 1.5·IQR rule with QUARTILE (see the Statistics sheet); Conditional Formatting > Top/Bottom Rules.
A14: 10 | B14: B. Impossible values / data-entry errors | C14: Impossible age | D14: CL00045 | E14: 46 | F14: Age | G14: 187 | H14: Age of 187: impossible value (outside the 18–100 range). Typical typing error or empty field filled in by the system. Note that Tenure_Years (8) also becomes inconsistent with the age. | I14: MIN/MAX of the column; number filter (e.g. Age < 18 or > 100); Conditional Formatting on the plausible range; Data > Data Validation > Circle Invalid Data.
A15: 11 | B15: B. Impossible values / data-entry errors | C15: Income expressed in thousands | D15: CL00231 | E15: 236 | F15: Annual_Income_EUR | G15: €42 | H15: Income of €42: most likely expressed in thousands (€42,000). A unit-of-measure error, not a poor customer: savings (€12,996.20) and occupation (Employee) confirm it. | I15: MIN/MAX of the column; number filter (e.g. Age < 18 or > 100); Conditional Formatting on the plausible range; Data > Data Validation > Circle Invalid Data.
A16: 12 | B16: B. Impossible values / data-entry errors | C16: Income with extra zeros | D16: CL00427 | E16: 433 | F16: Annual_Income_EUR | G16: €32,000,000 | H16: Income of €32,000,000 for an Employee with a card limit of €7,000 and savings of €6,763.79: almost certainly extra zeros (€32,000 real). A single value this large shifts the mean and standard deviation of the whole column and 'masks' the other outliers in the z-score. | I16: MIN/MAX of the column; number filter (e.g. Age < 18 or > 100); Conditional Formatting on the plausible range; Data > Data Validation > Circle Invalid Data.
... A99: 95 | B99: H. Collective outlier (cluster) | C99: Member of the anomalous cluster | D99: CL00962 | E99: 969 | F99: Account_Open_Date; Region; Preferred_Channel; Monthly_Transactions; Avg_Transaction_EUR | G99: 48 transactions × €199.00, opened Nov 2025 | H99: Part of a group of 12 accounts opened in November 2025 in Campania via the App by customers aged 21–27, all with 48 transactions per month of €199.00 (≈ €9,550 flowing through) on balances below €1,000 and incomes below €14,000. Taken individually every value is normal: it is the group that is anomalous (collective outlier, pattern consistent with 'money mule' accounts). | I99: Pivot table by opening month (Group dates) × Region × Channel; =COUNTIFS(N:N,48,O:O,199); sort by Monthly_Transactions and average amount; scatter plot Transactions vs Checking balance.
B101: Summary by category
B102: A. Extreme values (univariate) | C102: =COUNTIF($B$5:$B$99,B102) -> 9
B103: B. Impossible values / data-entry errors | C103: =COUNTIF($B$5:$B$99,B103) -> 10
B104: C. Sentinel and missing values | C104: =COUNTIF($B$5:$B$99,B104) -> 15
B105: D. Cross-column inconsistencies (contextual) | C105: =COUNTIF($B$5:$B$99,B105) -> 22
B106: E. Date anomalies | C106: =COUNTIF($B$5:$B$99,B106) -> 4
B107: F. Categorical and formatting anomalies | C107: =COUNTIF($B$5:$B$99,B107) -> 17
B108: G. Duplicates | C108: =COUNTIF($B$5:$B$99,B108) -> 6
B109: H. Collective outlier (cluster) | C109: =COUNTIF($B$5:$B$99,B109) -> 12
B110: Total injected anomalies | C110: =COUNTA($A$5:$A$99) -> 95
