Workbook

Sheet Customers
A1: Customer_ID | B1: Age | C1: Gender | D1: Region | E1: Occupation | F1: Marital_Status | G1: Annual_Income_EUR | H1: Tenure_Years | I1: Account_Open_Date | J1: Preferred_Channel | K1: Num_Products | L1: Checking_Balance_EUR | M1: Savings_Balance_EUR | N1: Monthly_Transactions | O1: Avg_Transaction_EUR | P1: Monthly_ATM_Withdrawals | Q1: Card_Limit_EUR | R1: Monthly_Card_Spend_EUR | S1: Mortgage_Balance_EUR | T1: Monthly_Mortgage_Payment_EUR | U1: Credit_Score | V1: Complaints_12M
A2: CL00001 | B2: 57 | C2: F | D2: Marche | E2: Shopkeeper | F2: Married | G2: 30100 | H2: 4 | I2: 44721 | J2: Branch | K2: 2 | L2: 6763.27 | M2: 12100.75 | N2: 23 | O2: 36.84 | P2: 1 | S2: 93000 | T2: 603 | U2: 698
A3: CL00002 | B3: 60 | C3: M | D3: Abruzzo | E3: Business owner | F3: Married | G3: 117400 | H3: 13 | I3: 41314 | J3: Branch | K3: 3 | L3: 39402.14 | M3: 124631.07 | N3: 49 | O3: 65.95 | P3: 1 | Q3: 15000 | R3: 3434.25 | S3: 0 | T3: 0 | U3: 700
A4: CL00003 | B4: 42 | C4: F | D4: Molise | E4: Business owner | F4: Married | G4: 55600 | H4: 11 | I4: 41985 | J4: App | K4: 2 | L4: 2962.55 | M4: 70371.89 | N4: 33 | O4: 85.29 | P4: 1 | Q4: 11000 | R4: 3647.56 | U4: 749
A5: CL00004 | B5: 44 | C5: F | D5: Umbria | E5: Employee | F5: Single | G5: 30200 | H5: 13 | I5: 41353 | J5: App | K5: 2 | L5: 3055.07 | M5: 31571.98 | N5: 17 | O5: 30.81 | P5: 1 | Q5: 6000 | R5: 2242.95 | S5: 0 | T5: 0 | U5: 601 | V5: 0
A6: CL00005 | B6: 68 | C6: F | D6: Lombardia | E6: Retired | F6: Married | G6: 21800 | H6: 8 | I6: 43047 | J6: Phone | K6: 1 | L6: 1554.39 | M6: 27565.84 | N6: 24 | O6: 29.47 | P6: 4 | Q6: 5000 | R6: 1312.86 | U6: 568 | V6: 1
A7: CL00006 | B7: 56 | C7: F | D7: Sardegna | E7: Shopkeeper | F7: Married | G7: 42300 | H7: 25 | I7: 36979 | J7: Branch | K7: 2 | L7: 879.82 | N7: 34 | O7: 90.6 | P7: 4 | Q7: 4500 | R7: 1699.41 | S7: 0 | T7: 0 | U7: 618 | V7: 2
A8: CL00007 | B8: 67 | C8: F | D8: Lombardia | E8: Retired | F8: Married | G8: 28300 | H8: 2 | I8: 45278 | J8: Online Banking | K8: 2 | L8: 6616.63 | M8: 2752.06 | N8: 30 | O8: 76 | P8: 2 | Q8: 4000 | R8: 2532.26 | U8: 666
A9: CL00008 | B9: 43 | C9: M | D9: Calabria | E9: Teacher | F9: Married | G9: 28300 | H9: 10 | I9: 42273 | J9: App | K9: 4 | L9: -56.68 | M9: 28860.26 | N9: 23 | O9: 49.11 | P9: 3 | Q9: 3000 | R9: 363.95 | S9: 49000 | T9: 228 | U9: 544 | V9: 1
A10: CL00009 | B10: 25 | C10: M | D10: Campania | E10: Manual worker | G10: 17700 | H10: 3 | I10: 45141 | J10: Online Banking | K10: 2 | L10: 795.78 | M10: 8855.03 | N10: 25 | O10: 32.4 | P10: 3 | Q10: 0 | R10: 0 | S10: 0 | T10: 0 | U10: 536 | V10: 0
A11: CL00010 | B11: 36 | C11: M | D11: Piemonte | E11: Employee | F11: Single | G11: 32600 | H11: 7 | I11: 43377 | J11: App | K11: 1 | L11: -244.9 | M11: 0 | N11: 33 | O11: 68.04 | P11: 0 | Q11: 6000 | R11: 1052.22 | S11: 0 | T11: 0 | U11: 662
A12: CL00011 | B12: 60 | C12: M | D12: Veneto | E12: Business owner | F12: Married | G12: 105900 | H12: 21 | I12: 38567 | J12: Online Banking | K12: 2 | L12: 8804.34 | M12: 0 | N12: 59 | O12: 87.83 | P12: 5 | Q12: 15000 | R12: 6697.75 | S12: 0 | T12: 0 | U12: 703 | V12: 0
A13: CL00012 | B13: 45 | C13: F | D13: Piemonte | E13: Employee | F13: Married | G13: 49600 | H13: 15 | I13: 40620 | J13: App | K13: 4 | M13: 0 | N13: 30 | O13: 69.35 | P13: 1 | Q13: 5000 | R13: 1097.89 | S13: 0 | T13: 0 | U13: 679 | V13: 0
A14: CL00013 | C14: M | D14: Lombardia | E14: Employee | F14: Married | G14: 38900 | H14: 20 | I14: 38827 | J14: Phone | K14: 2 | L14: 15176.28 | M14: 80694.88 | N14: 13 | O14: 56.28 | P14: 3 | Q14: 8500 | R14: 899.82 | S14: 0 | T14: 0 | U14: 613 | V14: 0
A15: CL00014 | C15: F | D15: Veneto | E15: Teacher | F15: Divorced | G15: 59700 | H15: 10 | I15: 42311 | J15: Online Banking | K15: 1 | L15: 12795 | M15: 36893.27 | N15: 48 | O15: 68.66 | P15: 7 | Q15: 0 | R15: 0 | S15: 0 | T15: 0 | U15: 593 | V15: 0
A16: CL00015 | B16: 42 | C16: M | D16: Sicilia | E16: Self-employed | F16: Single | G16: 52200 | H16: 16 | I16: 40327 | J16: Branch | K16: 4 | L16: 3728.87 | M16: 0 | N16: 33 | O16: 89.35 | P16: 5 | Q16: 7000 | R16: 949.31 | U16: 615 | V16: 0
A17: CL00016 | B17: 31 | C17: M | D17: Sicilia | E17: Self-employed | F17: Married | H17: 0 | I17: 46160 | J17: Branch | K17: 2 | L17: 5266.87 | M17: 0 | N17: 31 | O17: 89.7 | P17: 3 | Q17: 9000 | R17: 1322.05 | S17: 253000 | T17: 1628 | U17: 588 | V17: 0
A18: CL00017 | B18: 43 | C18: M | D18: Campania | E18: Employee | F18: Married | G18: 40700 | H18: 9 | I18: 42938 | J18: App | K18: 3 | L18: 1646.05 | M18: 0 | N18: 35 | O18: 105.7 | P18: 2 | Q18: 6500 | R18: 1763.53 | S18: 184000 | T18: 1282 | U18: 571 | V18: 0
A19: CL00018 | B19: 53 | C19: F | D19: Lazio | E19: Employee | F19: Divorced | G19: 27800 | H19: 19 | I19: 39246 | J19: App | K19: 2 | L19: 5894.62 | M19: 57173.93 | N19: 34 | O19: 50.09 | P19: NA | Q19: 0 | R19: 0 | U19: 643
A20: CL00019 | B20: 20 | C20: M | D20: Sicilia | E20: Employee | F20: Single | G20: 34200 | H20: 1 | I20: 45754 | J20: App | K20: 3 | L20: 1656.94 | M20: 7347.5 | N20: 23 | O20: 60.38 | P20: 0 | Q20: 6500 | R20: 2565.57 | S20: 0 | T20: 0 | U20: 643 | V20: 0
A21: CL00020 | B21: 30 | C21: Unknown | D21: Veneto | E21: Manual worker | F21: Divorced | G21: 14100 | J21: Online Banking | K21: 5 | L21: 672.51 | M21: 3621.8 | N21: 19 | O21: 39.07 | P21: 3 | Q21: 1500 | R21: 593.08 | S21: 0 | T21: 0 | U21: 653
A22: CL00021 | B22: 52 | C22: M | D22: Lombardia | E22: Manual worker | F22: Married | G22: 22400 | H22: 10 | I22: 42446 | J22: Branch | K22: 3 | L22: 2244.58 | M22: 13467.23 | N22: 19 | O22: 28.21 | P22: 1 | S22: 0 | T22: 0 | U22: 623 | V22: 0
A23: CL00022 | B23: 41 | C23: F | D23: Marche | E23: Employee | F23: - | G23: 34800 | H23: 2 | I23: 45375 | J23: App | K23: 2 | L23: 4224.83 | M23: 0 | N23: 30 | O23: 48.02 | P23: 2 | S23: 169000 | U23: 569 | V23: 1
A24: CL00023 | B24: 45 | C24: F | D24: Lazio | E24: Shopkeeper | F24: Married | G24: 28600 | H24: 6 | I24: 44032 | J24: Branch | K24: 2 | L24: 6510.71 | M24: 18628.5 | N24: 23 | O24: 48.33 | P24: 3 | S24: 0 | T24: 0 | U24: 573 | V24: 0
A25: CL00024 | B25: 37 | C25: F | D25: Trentino-Alto Adige | E25: Employee | F25: Married | G25: 24300 | H25: 18 | I25: 39685 | J25: Online Banking | K25: 2 | L25: 6958.53 | M25: 30755.83 | N25: 33 | O25: 38.48 | P25: 1 | Q25: 4000 | R25: 1294.17 | S25: 109000 | T25: 693 | U25: 632 | V25: 0
A26: CL00025 | B26: 51 | C26: M | D26: Piemonte | E26: Employee | F26: Single | G26: 30000 | H26: 10 | I26: 42387 | J26: Branch | K26: 2 | L26: 3700.02 | M26: 10653.7 | N26: 17 | O26: 35.47 | P26: 4 | Q26: 5500 | R26: 209.96 | S26: 82000 | T26: 410 | U26: 661 | V26: 0
A27: CL00026 | B27: 26 | C27: M | D27: Umbria | E27: Employee | F27: Married | G27: 17100 | H27: 5 | I27: 44314 | J27: App | K27: 1 | L27: 1758.1 | M27: 7178.85 | N27: 25 | O27: 58.79 | P27: 1 | S27: 0 | T27: 0 | U27: 641 | V27: 0
A28: CL00027 | B28: 47 | C28: F | D28: Lombardia | E28: Teacher | F28: Married | G28: 35900 | H28: 0 | I28: 46253 | J28: Branch | K28: 3 | L28: 1203.46 | M28: 5520.98 | N28: 21 | O28: 44.29 | P28: 4 | Q28: 0 | R28: 0 | S28: 157000 | T28: 895 | U28: 620
A29: CL00028 | B29: 52 | C29: F | D29: Trentino-Alto Adige | E29: Employee | F29: Married | G29: 25600 | H29: 15 | I29: 40784 | J29: Online Banking | K29: 5 | L29: -307.03 | M29: 0 | N29: 38 | O29: 74.03 | P29: 1 | Q29: 6500 | R29: 3641.59 | S29: 116000 | U29: 613 | V29: 0
A30: CL00029 | B30: 41 | C30: F | D30: Abruzzo | E30: Employee | F30: Single | G30: 23700 | H30: 19 | I30: 39287 | J30: App | K30: 3 | L30: 674.12 | M30: 16518.46 | N30: 27 | O30: 25.96 | P30: 0 | Q30: 3500 | R30: 688.38 | S30: 96000 | T30: 525 | U30: 713 | V30: 0
A31: CL00030 | B31: 38 | C31: F | D31: Campania | E31: Manual worker | F31: Married | G31: 16700 | H31: 8 | I31: 43210 | J31: App | K31: 2 | L31: 531.48 | M31: 0 | N31: 30 | O31: 17.93 | P31: 0 | Q31: 2000 | R31: 546.28 | S31: 0 | T31: 0 | U31: 552 | V31: 1
A32: CL00031 | B32: 44 | C32: M | D32: Abruzzo | E32: Manual worker | F32: Married | G32: 25300 | H32: 13 | I32: 41193 | J32: App | K32: 2 | L32: 2536.09 | M32: 0 | N32: 24 | O32: 56.79 | P32: 1 | Q32: 3500 | R32: 1580.53 | U32: 607 | V32: 0
A33: CL00032 | B33: 66 | C33: M | D33: Veneto | E33: Retired | F33: Divorced | G33: 13100 | H33: 15 | I33: 40635 | J33: Online Banking | K33: 4 | L33: 1386.33 | M33: 17215.76 | N33: 30 | O33: 50.2 | P33: 3 | Q33: 0 | R33: 0 | U33: 624 | V33: 0
A34: CL00033 | B34: 36 | C34: F | D34: Veneto | E34: Employee | F34: Married | G34: 18700 | H34: 12 | I34: 41756 | J34: Branch | K34: 1 | L34: 1371.55 | M34: 16459.23 | N34: 11 | O34: 41.56 | P34: 4 | Q34: 4000 | R34: 1155.74 | S34: 86000 | T34: 617 | U34: 607 | V34: 0
A35: CL00034 | B35: 45 | C35: F | D35: Lazio | E35: Shopkeeper | F35: Single | G35: 23300 | H35: 2 | I35: 25569 | J35: Branch | K35: 1 | L35: 1259.53 | M35: 14213 | N35: 12 | O35: 34.95 | P35: 3 | Q35: 3500 | R35: 1356.12 | S35: 100000 | T35: 643 | U35: 568 | V35: 0
A36: CL00035 | B36: 36 | C36: M | D36: Campania | E36: Self-employed | F36: Married | G36: 51000 | H36: 6 | I36: 43790 | J36: App | K36: 1 | L36: 6099.38 | M36: 22383.75 | N36: 38 | O36: 101.68 | P36: 0 | Q36: 12500 | S36: 0 | T36: 0 | U36: 602
A37: CL00036 | B37: 39 | C37: M | D37: Piemonte | E37: Employee | F37: Married | G37: 22400 | H37: 8 | I37: 43227 | J37: App | K37: 2 | L37: 1467.27 | M37: 9674.73 | N37: 23 | O37: 78.83 | P37: 3 | Q37: 3000 | R37: 1153.09 | S37: 83000 | T37: 445 | U37: 589 | V37: 0
A38: CL00037 | B38: 51 | C38: M | D38: Lombardia | E38: Employee | F38: Married | G38: 21500 | H38: 2 | I38: 45264 | J38: App | K38: 2 | L38: 2144.1 | M38: 6464.68 | N38: 27 | O38: 21.36 | P38: 1 | Q38: 3500 | R38: 1723.34 | S38: 34000 | T38: 163 | U38: 554 | V38: 0
A39: CL00038 | B39: 43 | C39: F | D39: Sardegna | E39: Self-employed | F39: Single | G39: 62500 | H39: 1 | I39: 45797 | J39: Online Banking | K39: 2 | L39: 1634.33 | M39: 9260.84 | N39: 50 | O39: 52.49 | P39: 1 | Q39: 9000 | R39: 770.96 | S39: 0 | T39: 0 | U39: 700
A40: CL00039 | B40: 52 | C40: M | D40: Piemonte | E40: Unemployed | F40: Married | G40: 5300 | H40: 15 | I40: 40470 | J40: App | K40: 3 | L40: 1378.01 | N40: 25 | O40: 51.26 | P40: 2 | Q40: 1000 | R40: 45.67 | U40: 563 | V40: 0
A41: CL00040 | B41: 57 | C41: F | D41: Lazio | E41: Teacher | F41: Single | G41: 16300 | H41: 8 | I41: 43186 | J41: Branch | K41: 2 | L41: 811.76 | M41: 6215.83 | N41: 18 | O41: 34.3 | P41: 5 | Q41: 2000 | R41: 170.33 | U41: 663 | V41: 0
A42: CL00041 | B42: 54 | C42: F | D42: Campania | E42: Executive | F42: Single | G42: 91200 | H42: 22 | I42: 38030 | J42: Branch | K42: 3 | L42: 39501.44 | M42: 144926.85 | N42: 46 | O42: 112.99 | P42: 2 | S42: 328000 | U42: 744 | V42: 1
A43: CL00042 | B43: 18 | C43: M | D43: Toscana | F43: Single | G43: 4800 | H43: 0 | I43: 25569 | J43: App | K43: 1 | L43: 198.18 | M43: 590.47 | N43: 9999 | O43: 30.36 | P43: 0 | Q43: 1000 | R43: 49.19 | S43: 0 | T43: 0 | U43: 592 | V43: 0
A44: CL00043 | B44: 59 | C44: M | D44: Emilia-Romagna | E44: Teacher | F44: Single | G44: 50700 | H44: 33 | I44: 34167 | J44: Online Banking | K44: 5 | L44: 10744.44 | M44: 69846.17 | N44: 37 | O44: 63.66 | P44: 2 | Q44: 11000 | R44: 501.13 | S44: 237000 | U44: 688 | V44: 0
A45: CL00044 | B45: 26 | C45: F | D45: Lombardia | E45: Executive | F45: Single | G45: 92600 | H45: 4 | I45: 44544
A46: CL00045 | B46: 36 | C46: M | D46: Calabria | E46: Employee | F46: Widowed | G46: 33500 | H46: 1 | I46: 45663 | J46: Branch | K46: 1 | L46: 884.14 | M46: 9764.09 | N46: 18 | O46: 43.96 | P46: 6 | Q46: 5500 | R46: 868.76 | S46: 0 | T46: 0 | V46: 1
A47: CL00046 | B47: 77 | C47: M | D47: Lazio | E47: Retired | G47: 24100 | H47: 11 | I47: 42252 | J47: Online Banking | K47: 1 | L47: 1789.43 | M47: 22888.41 | N47: 38 | O47: 33.26 | P47: 3 | Q47: 4000 | R47: 867.48 | U47: 605
A48: CL00047 | B48: 0 | C48: F | D48: Lombardia | E48: Retired | F48: Married | G48: 26200 | I48: 44219 | J48: Branch | K48: 3 | L48: 1141.59 | M48: 15234.56 | N48: 24 | O48: 44.62 | P48: 5 | Q48: 4500 | R48: 610.35 | S48: 0 | T48: 0 | U48: 581 | V48: 0
A49: CL00048 | B49: 78 | C49: M | D49: Trentino-Alto Adige | E49: Retired | F49: Widowed | G49: 34000 | H49: 17 | I49: 39960 | J49: App | K49: 2 | L49: 3133.2 | M49: 28556.96 | N49: 38 | O49: 48.86 | P49: 0 | Q49: 6000 | R49: 2243.79 | S49: 143000 | T49: 958 | U49: 710 | V49: 0
A50: CL00049 | C50: M | D50: Puglia | E50: Retired | F50: Widowed | G50: 20700 | H50: 11 | I50: 42230 | J50: Branch | K50: 3 | L50: 3341.95 | M50: 21287.63 | N50: 18 | O50: 67.98 | P50: 4 | Q50: 4000 | R50: 218.39 | S50: 0 | T50: 0 | U50: 701 | V50: 0
A51: CL00050 | B51: 66 | C51: M | D51: Lombardia | E51: Retired | F51: Married | G51: 48700 | H51: 11 | I51: 41951 | J51: Online Banking | K51: 3 | L51: 3252.38 | M51: 47621.94 | N51: 34 | O51: 98.42 | P51: 4 | Q51: 10000 | R51: 809.29 | S51: 0 | T51: 0 | U51: 637 | V51: 1
A52: CL00051 | B52: 68 | C52: F | D52: Toscana | E52: Retired | F52: Married | G52: 32600 | H52: 17 | I52: 39799 | J52: Phone | K52: 3 | L52: 2048.45 | M52: 0 | N52: 18 | O52: 73.98 | P52: 4 | Q52: 6000 | R52: 1460.15 | S52: 142000 | T52: 743 | U52: 710 | V52: 0
A53: CL00052 | B53: 40 | C53: M | D53: Piemonte | E53: Teacher | F53: Divorced | G53: 22600 | H53: 11 | I53: 42169 | J53: App | K53: 2 | L53: 5430.61 | M53: 10399.85 | N53: 22 | O53: 40.35 | P53: 0 | Q53: 3500 | R53: 1724.01 | S53: 97000 | T53: 712 | U53: 652
A54: CL00053 | B54: 44 | C54: M | D54: n.d. | E54: Business owner | F54: Married | G54: 56000 | H54: 5 | I54: 44336 | J54: Branch | K54: 1 | L54: 6520.82 | M54: 16749.87 | N54: 30 | O54: 38.89 | P54: 3 | Q54: 0 | R54: 0 | S54: 0 | T54: 0 | U54: 680 | V54: 0
A55: CL00054 | B55: 51 | C55: F | D55: Marche | E55: Manual worker | F55: Single | G55: 19400 | H55: 14 | I55: 40997 | J55: Branch | K55: 2 | L55: 1880.09 | M55: 18597.72 | N55: 19 | O55: 44.6 | P55: 3 | Q55: 3000 | R55: 348.33 | U55: 665 | V55: 0
A56: CL00055 | B56: 64 | C56: M | D56: Sicilia | E56: Unemployed | F56: Married | G56: 5800 | H56: 20 | I56: 38743 | J56: Online Banking | K56: 3 | L56: 654.25 | M56: 13338.78 | N56: 27 | O56: 33.94 | P56: 4 | Q56: 1500 | R56: 609.52 | S56: 0 | T56: 0 | U56: 655 | V56: 0
A57: CL00056 | B57: 56 | C57: M | D57: Toscana | E57: Unemployed | F57: Single | G57: 4700 | H57: 4 | I57: 44526 | J57: Phone | K57: 2 | L57: 534.64 | M57: 3116.73 | N57: 8 | O57: 27.86 | P57: 5 | Q57: 500 | S57: 15000 | T57: 100 | U57: 577 | V57: 0
A58: CL00057 | B58: 44 | C58: F | D58: Veneto | E58: Manual worker | F58: Married | G58: 27600 | I58: 40690 | J58: App | K58: 2 | L58: 1378.47 | M58: 13274.8 | N58: 26 | O58: 37.13 | P58: 2 | Q58: 7000 | R58: 1835.52 | S58: 118000 | T58: 654 | U58: 640 | V58: 1
A59: CL00058 | B59: 60 | C59: F | D59: Lazio | E59: Teacher | F59: Married | G59: 45300 | H59: 8 | I59: 43084 | J59: Phone | K59: 2 | L59: 5255.26 | M59: 0 | N59: 24 | O59: 46.94 | P59: NA | Q59: 10000 | R59: 1647.41 | S59: 0 | T59: 0 | U59: 710
A60: CL00059 | B60: 46 | C60: F | D60: Toscana | E60: Teacher | F60: Married | G60: 29100 | H60: 3 | I60: 45132 | J60: Online Banking | K60: 2 | L60: 1660.2 | M60: 0 | N60: 21 | O60: 68.19 | P60: 2 | Q60: 4500 | R60: 945.26 | U60: 533 | V60: 1
A61: CL00060 | B61: 63 | C61: M | D61: Piemonte | E61: Unemployed | F61: Widowed | G61: 7100 | H61: 16 | I61: 40281 | J61: Branch | K61: 2 | L61: 665.45 | M61: 7474.15 | N61: 18 | O61: 36.19 | P61: 8 | Q61: 1000 | U61: 619 | V61: 0
A62: CL00061 | B62: 54 | C62: M | D62: Veneto | E62: Employee | F62: Married | G62: 29900 | H62: 14 | I62: 41022 | J62: App | K62: 2 | L62: 5990.11 | M62: 27303.9 | N62: 20 | O62: 33.6 | P62: 1 | S62: 65000 | T62: 340 | U62: 683 | V62: 0
A63: CL00062 | B63: 59 | C63: F | D63: Lombardia | E63: Employee | F63: Single | G63: 27500 | H63: 6 | I63: 43890 | J63: Online Banking | K63: 1 | L63: 3828.22 | M63: 18748.89 | N63: 32 | O63: 58.17 | P63: 2 | Q63: 5000 | R63: 515.32 | S63: 91000 | T63: 602 | U63: 678 | V63: 1
A64: CL00063 | B64: 47 | C64: F | D64: Sardegna | E64: Shopkeeper | F64: Single | G64: 33100 | H64: 5 | I64: 44444 | J64: Online Banking | K64: 1 | L64: 4240.95 | M64: 10068.95 | N64: 24 | O64: 42.52 | P64: 5 | S64: 95000 | T64: 638 | U64: 644
A65: CL00064 | B65: 57 | C65: F | D65: Toscana | E65: Unemployed | F65: Married | G65: 3900 | H65: 17 | I65: 40027 | J65: Branch | K65: 2 | L65: 82.14 | M65: 5223.19 | N65: 20 | O65: 39.63 | P65: 1 | Q65: 1000 | R65: 242.72 | S65: 0 | T65: 0 | U65: 501
A66: CL00065 | B66: 32 | C66: F | D66: Sicilia | E66: Manual worker | F66: Married | G66: 24100 | H66: 10 | I66: 42401 | J66: Online Banking | K66: 5 | L66: -2312.35 | M66: 0 | N66: 25 | O66: 50.85 | P66: 3 | Q66: 6000 | R66: 2041.08 | S66: 0 | T66: 0 | U66: 621
A67: CL00066 | B67: 35 | C67: M | D67: Emilia-Romagna | E67: Manual worker | F67: Married | G67: 11500 | H67: 4 | I67: 44580 | J67: Branch | K67: 4 | L67: 1630.07 | M67: 8790.6 | N67: 24 | O67: 31.57 | P67: 5 | Q67: 1000 | R67: 646.82 | S67: 0 | T67: 0 | U67: 578 | V67: 0
A68: CL00067 | B68: 0 | C68: F | D68: Toscana | E68: Shopkeeper | F68: Divorced | G68: 47800 | H68: 4 | I68: 44758 | J68: Branch | K68: 2 | L68: 5843.71 | M68: 0 | N68: 34 | O68: 54.25 | P68: 3 | Q68: 5000 | R68: 2511.46 | S68: 79000 | T68: 494 | U68: 618 | V68: 0
A69: CL00068 | B69: 40 | C69: M | D69: Emilia-Romagna | E69: Employee | F69: Divorced | G69: 37400 | H69: 7 | I69: 43676 | J69: App | K69: 4 | L69: -2194.61 | M69: 0 | N69: 31 | O69: 84.84 | P69: 1 | Q69: 8500 | R69: 3006.73 | U69: 520 | V69: 0
A70: CL00069 | B70: 42 | C70: F | D70: Veneto | E70: Employee | F70: Single | H70: 11 | I70: 42002 | J70: Online Banking | K70: 4 | L70: 1075.5 | M70: 11507.28 | N70: 29 | O70: 46.3 | P70: 3 | Q70: 3500 | R70: 930.04 | S70: 59000 | T70: 351 | U70: 594 | V70: 0
A71: CL00070 | B71: 40 | C71: M | D71: Emilia-Romagna | E71: Unemployed | F71: Single | G71: 4100 | H71: 12 | I71: 41700 | K71: 2 | L71: 182.64 | M71: 1200 | N71: 26 | O71: 21.47 | P71: 2 | Q71: 0 | R71: 0 | S71: 0 | T71: 0 | U71: 522 | V71: 0
A72: CL00071 | B72: 53 | C72: M | D72: Friuli-Venezia Giulia | E72: Unemployed | F72: Single | G72: 5000 | H72: 20 | I72: 38623 | J72: Online Banking | K72: 2 | L72: 295.92 | M72: 15835.47 | N72: 17 | O72: 23.48 | P72: 3 | Q72: 1000 | R72: 534.42 | U72: 552 | V72: 1
A73: CL00072 | B73: 22 | C73: M | D73: Piemonte | E73: Student | F73: Single | G73: 5300 | H73: 2 | I73: 45467 | J73: App | K73: 1 | L73: 670.71 | M73: 0 | N73: 19 | O73: 38.48 | P73: 1 | S73: 0 | T73: 0 | U73: 601 | V73: 0
A74: CL00073 | B74: 66 | C74: F | D74: Liguria | E74: Retired | F74: Married | G74: 29800 | H74: 5 | I74: 44159 | J74: Branch | K74: 3 | L74: 1125.54 | M74: 9802.01 | N74: 8 | O74: 92.27 | P74: 7 | Q74: 5000 | R74: 1417.78 | U74: 523 | V74: 1
A75: CL00074 | B75: 54 | C75: M | D75: Veneto | E75: Executive | F75: Married | G75: 71900 | H75: 10 | I75: 42615 | J75: Branch | K75: 1 | L75: 4720.71 | M75: 53660.43 | N75: 33 | O75: 57.46 | P75: 5 | Q75: 7000 | R75: 2566.08 | S75: 0 | T75: 0 | U75: 679 | V75: 0
A76: CL00075 | B76: 53 | C76: M | D76: Lombardia | E76: Executive | F76: Married | G76: 94200 | H76: 14 | I76: 41123 | J76: Online Banking | K76: 2 | L76: 5931.39 | N76: 49 | O76: 44.16 | P76: 2 | Q76: 15000 | R76: 6795.14 | S76: 0 | T76: 0 | U76: 631 | V76: 0
A77: CL00076 | B77: 53 | C77: F | D77: Lazio | E77: Employee | F77: Married | G77: 40500 | H77: 9 | I77: 42788 | J77: Branch | K77: 2 | L77: 4774.43 | N77: 22 | O77: 90.75 | P77: 4 | Q77: 7500 | R77: 2440.24 | U77: 629 | V77: 0
A78: CL00077 | B78: 52 | C78: M | D78: Piemonte | E78: Self-employed | F78: Single | G78: 41600 | H78: 20 | I78: 38627 | J78: Branch | K78: 2 | L78: 10328.3 | M78: 52405.08 | N78: 32 | O78: 60.94 | P78: 4 | Q78: 7500 | R78: 2747.46 | S78: 0 | T78: 0 | U78: 680
A79: CL00078 | C79: M | D79: Emilia-Romagna | E79: Teacher | F79: Single | G79: 34100 | H79: 8 | I79: 43269 | J79: Branch | K79: ? | L79: 1793.66 | M79: 8814.95 | N79: 19 | O79: 38.24 | P79: 6 | U79: 577 | V79: 3
A80: CL00079 | B80: 36 | C80: M | D80: Calabria | E80: Manual worker | F80: Married | G80: 25500 | H80: 7 | I80: 43509 | J80: App | K80: 3 | L80: 1307.96 | M80: 13485.03 | N80: 35 | O80: 102.07 | P80: 0 | Q80: 6500 | R80: 2543.9 | U80: 624 | V80: 0
A81: CL00080 | B81: 32 | C81: F | D81: Veneto | E81: Executive | F81: - | G81: 152500 | H81: 3 | I81: 45118 | J81: App | K81: 1 | L81: -326.06 | M81: 0 | N81: 75 | O81: 61.41 | P81: 4 | Q81: 0 | R81: 0 | S81: 0 | T81: 0 | U81: 646 | V81: 1
A82: CL00081 | B82: 40 | C82: M | D82: Lazio | E82: Employee | F82: Single | G82: 36700 | H82: 4 | I82: 44738 | J82: Phone | K82: 1 | L82: 6158.46 | M82: 17039.79 | N82: 24 | O82: 44.35 | P82: 6 | Q82: 4500 | R82: 1584.86 | S82: 155000 | T82: 1009 | U82: 549 | V82: 1
A83: CL00082 | B83: 50 | C83: F | D83: Lazio | E83: Manual worker | F83: Married | G83: 23200 | H83: 6 | I83: 43737 | J83: App | K83: 2 | L83: 3450.67 | M83: 9475.1 | N83: 26 | O83: 50.23 | P83: 0 | Q83: 5500 | R83: 144.31 | U83: 612 | V83: 0
A84: CL00083 | B84: 58 | C84: F | D84: Lombardia | E84: Employee | F84: Married | G84: 39000 | H84: 12 | I84: 41820 | J84: Branch | K84: 1 | L84: 4002.71 | M84: 0 | N84: 26 | O84: 56 | P84: 3 | Q84: 0 | R84: 0 | S84: 0 | T84: 0 | U84: 712 | V84: 0
A85: CL00084 | B85: 50 | C85: M | D85: Lombardia | E85: Employee | F85: Single | G85: 38200 | H85: 6 | I85: 44037 | J85: App | K85: 4 | L85: 1743.62 | M85: 22708.59 | N85: 34 | O85: 40.32 | P85: 2 | Q85: 7500 | R85: 291.96 | S85: 0 | T85: 0 | U85: 642 | V85: 2
A86: CL00085 | C86: M | D86: Lazio | E86: Business owner | F86: Single | H86: 4 | I86: 44807 | J86: Online Banking | K86: 1 | M86: 13810.82 | N86: 43 | O86: 62.14 | P86: 0 | Q86: 9000 | R86: 4196.25 | S86: 156000 | T86: 1059 | U86: 692 | V86: 0
A87: CL00086 | B87: 51 | C87: M | D87: Lombardia | E87: Shopkeeper | F87: Married | G87: 41300 | H87: 15 | I87: 40720 | J87: Online Banking | L87: 1052.82 | M87: 27544.83 | N87: 25 | P87: 3 | Q87: 5500 | R87: 2626.87 | S87: 197000 | T87: 1256 | U87: 593 | V87: 1
A88: CL00087 | B88: 56 | C88: M | D88: Lombardia | E88: Business owner | F88: Married | G88: 64300 | H88: 12 | I88: 41558 | J88: Online Banking | K88: 2 | L88: 11044.43 | M88: 0 | N88: 37 | O88: 102.99 | P88: 5 | Q88: 13500 | R88: 3090.99 | S88: 206000 | T88: 1131 | U88: 676 | V88: 1
A89: CL00088 | B89: 42 | C89: M | D89: Lombardia | E89: Employee | F89: Single | G89: 22000 | H89: 9 | I89: 42793 | J89: N/A | K89: 2 | L89: 2067.67 | M89: 0 | N89: 31 | O89: 33.1 | P89: 1 | Q89: 5000 | R89: 2937.9 | U89: 510 | V89: 1
A90: CL00089 | B90: 50 | C90: F | D90: Veneto | E90: Employee | F90: Divorced | G90: 28600 | H90: 25 | I90: 37094 | J90: Online Banking | K90: 5 | L90: 4864.75 | M90: 35477.03 | N90: 30 | O90: 72.56 | P90: 5 | Q90: 4000 | R90: 2693.8 | S90: 96000 | T90: 661 | U90: 648 | V90: 2
A91: CL00090 | B91: 63 | C91: M | D91: Toscana | E91: Teacher | F91: Married | G91: 31000 | H91: 2 | I91: 45291 | J91: Branch | K91: 1 | L91: 3793.89 | N91: 18 | O91: 54 | P91: 2 | Q91: 6000 | R91: 1148.6 | S91: 114000 | T91: 845 | U91: 614 | V91: 0
A92: CL00091 | B92: 40 | C92: F | D92: Toscana | E92: Employee | F92: Single | G92: 26100 | H92: 8 | I92: 43058 | J92: Branch | K92: 2 | L92: 4191.52 | M92: 13911.02 | N92: 27 | O92: 46.22 | P92: 5 | Q92: 5500 | R92: 3144.1 | S92: 69000 | T92: 337 | U92: 686 | V92: 0
A93: CL00092 | B93: 78 | C93: F | D93: Emilia-Romagna | E93: Retired | F93: Married | G93: 19600 | H93: 25 | I93: 36801 | J93: Online Banking | K93: 4 | L93: -315.81 | M93: 25911.63 | N93: 25 | O93: 43.83 | P93: 1 | Q93: 3000 | R93: 839.18 | U93: 627 | V93: 2
A94: CL00093 | B94: 47 | C94: F | D94: Calabria | E94: Employee | F94: Single | G94: 30900 | H94: 19 | I94: 39304 | J94: Online Banking | K94: 4 | L94: 957 | M94: 43038.18 | N94: 23 | O94: 136.94 | P94: 3 | S94: 75000 | T94: 371 | U94: 722 | V94: 0
A95: CL00094 | B95: 73 | C95: M | D95: Veneto | E95: Retired | F95: Married | G95: 38500 | H95: 27 | I95: 36119 | J95: Branch | K95: 3 | L95: 2326.1 | M95: 52594.91 | N95: 23 | O95: 74.19 | P95: 8 | Q95: 9000 | R95: 1347.27 | S95: 0 | T95: 0 | U95: 702 | V95: 0
A96: CL00095 | B96: 55 | C96: F | D96: Puglia | E96: Employee | F96: Married | G96: 30800 | H96: 18 | I96: 39544 | J96: Branch | K96: 5 | L96: 4841.22 | M96: 48592.18 | N96: 20 | O96: 32.35 | P96: 2 | Q96: 5500 | R96: 64.01 | S96: 94000 | T96: 427 | U96: 641
A97: CL00096 | B97: 39 | C97: F | D97: Puglia | E97: Executive | F97: Married | G97: 120500 | H97: 11 | I97: 41916 | J97: Online Banking | K97: 1 | L97: 9892.11 | M97: 0 | N97: 53 | O97: 293.38 | P97: 2 | Q97: 15000 | R97: 2635.75 | S97: 0 | T97: 0 | U97: 704 | V97: 0
A98: CL00097 | B98: 61 | C98: M | D98: Sicilia | E98: Manual worker | F98: Married | G98: 34300 | H98: 18 | I98: 39652 | J98: Phone | L98: 2603.25 | N98: 28 | O98: 40.78 | P98: 1 | Q98: 8000 | R98: 3528.13 | U98: 695 | V98: 1
A99: CL00098 | B99: 66 | C99: F | E99: Retired | F99: Married | G99: 18200 | H99: 5 | I99: 44323 | J99: Online Banking | K99: 3 | L99: 1209.11 | M99: 0 | N99: 20 | O99: 47.44 | P99: 4 | Q99: 4500 | R99: 1078.32 | S99: 0 | T99: 0 | U99: 542 | V99: 0
A100: CL00099 | B100: 25 | C100: M | D100: Emilia-Romagna | E100: Self-employed | F100: Single | G100: 43200 | H100: 1 | I100: 45864 | J100: Online Banking | K100: 1 | L100: 2093.47 | N100: 38 | O100: 47.76 | P100: 2 | Q100: 9500 | R100: 3180.74 | S100: 0 | T100: 0 | U100: 672
...

Sheet Data_Dictionary
A1: Data dictionary — Customers sheet
A2: Demographic and behavioural extract as of 2026-09-13 for 1,000 retail customers (synthetic data), assembled from three source systems (master data, accounts, cards & loans). 'Expected values' is the plausible range according to the business rules. The second table lists the only missing-value conventions the source systems document: anything else that looks like a placeholder is undocumented and has to be investigated.
A4: Column | B4: Type | C4: Description | D4: Expected values | E4: Excel column
A5: Customer_ID | B5: Text (key) | C5: Unique customer identifier. | D5: Unique; format CL00001 | E5: A
A6: Age | B6: Integer | C6: Customer age in completed years. | D6: 18 – 100 | E6: B
A7: Gender | B7: Categorical | C7: Gender as recorded in the master data. | D7: M, F | E7: C
A8: Region | B8: Categorical | C8: Region of residence (Italy). | D8: One of the 20 Italian regions, standard spelling | E8: D
A9: Occupation | B9: Categorical | C9: Declared occupation. | D9: Employee, Manual worker, Self-employed, Executive, Business owner, Shopkeeper, Teacher, Student, Retired, Unemployed | E9: E
A10: Marital_Status | B10: Categorical | C10: Marital status. | D10: Single, Married, Divorced, Widowed | E10: F
A11: Annual_Income_EUR | B11: Numeric | C11: Declared gross annual income, in euros. | D11: > 0; typically 4,000 – 200,000 | E11: G
A12: Tenure_Years | B12: Integer | C12: Years of relationship with the bank. | D12: 0 – 40 and ≤ Age − 18 | E12: H
A13: Account_Open_Date | B13: Date | C13: Opening date of the first account. | D13: Between 1980 and the extraction date (2026-09-13); consistent with Tenure_Years | E13: I
A14: Preferred_Channel | B14: Categorical | C14: Main contact channel. | D14: Branch, App, Online Banking, Phone | E14: J
A15: Num_Products | B15: Integer | C15: Number of active products (account, cards, mortgage, investments…). | D15: 1 – 6 | E15: K
... A26: Complaints_12M | B26: Integer | C26: Complaints filed in the last 12 months. | D26: 0 – 5 | E26: V
A29: Missing-value conventions documented by the source systems
A30: Column | B30: Code | C30: Meaning
A31: Card_Limit_EUR | B31: 0 | C31: No credit card. A blank is NOT documented.
A32: Monthly_Card_Spend_EUR | B32: 0 | C32: No credit card (always 0 when Card_Limit_EUR is 0).
A33: Mortgage_Balance_EUR | B33: 0 | C33: No mortgage. A blank is NOT documented.
A34: Monthly_Mortgage_Payment_EUR | B34: 0 | C34: No mortgage (always 0 when Mortgage_Balance_EUR is 0).
A35: Avg_Transaction_EUR | B35: (blank) | C35: Undefined when Monthly_Transactions is 0 (dormant account).
A36: Any other column | B36: — | C36: No missing-value code is documented by the source systems.

Sheet Codes
A1: Codes we treat as missing
A2: One list, referenced by every formula in Clean and Missing_Profile: when a new placeholder shows up in a feed we add it here and the whole workbook follows. Case-insensitive; leading/trailing spaces are removed with TRIM before the comparison.
A4: Text placeholder | B4: Where it typically comes from
A5: N/A | B5: Manual data entry, CSV exports
A6: NA | B6: R / statistical exports
A7: n.a. | B7: Manual data entry
A8: n.d. | B8: Italian back-office ('non disponibile')
A9: ? | B9: Legacy data-entry masks
A10: - | B10: Reports where blank cells are rendered as a dash
A11: -- | B11: Same as '-'
A12: Unknown | B12: CRM default category
A13: NULL | B13: Database exports that print NULL literally
A14: None | B14: Python / pandas exports
A17: Numeric sentinels — column-specific, therefore written in the formula of that column
A18: Column | B18: Value | C18: Why we treat it as missing
A19: Age | B19: 0 | C19: An age of 0 is impossible for a bank customer: a default value written by the loader.
A20: Annual_Income_EUR | B20: -999 | C20: Negative income, always the same figure: the classic legacy 'not available' code.
A21: Monthly_Transactions | B21: 9999 | C21: Out of scale and repeated identically; a placeholder, not a heavy user.
A22: Credit_Score | B22: 0 | C22: The score ranges 300 – 850; 0 means 'not computed'.
A23: Account_Open_Date | B23: 1970-01-01 | C23: Unix epoch: what a system writes when the date field was empty at load time.
A26: Values that are NOT missing (recoverable or structural)
A27: Numbers stored as text | B27: e.g. '35000' with the green triangle: AVERAGE, SUM and COUNT skip them silently. Clean converts them with VALUE().
A28: Structural blanks | B28: No card, no mortgage, dormant account, no complaints: the value does not exist. We replace them with the documented constant (0), never with a mean.
A29: Whitespace-only cells | B29: Look empty, but COUNTBLANK does not count them and a filter shows them as a separate item. Clean maps them to a true blank.
A30: 'Unknown' in a categorical column | B30: We normalise it to blank in Clean and then decide, per column, whether to keep an explicit 'Unknown' category (usually yes) or impute the mode.

Sheet Missing_Profile
A1: Missing-value profile — one row per column, all live formulas on the Customers sheet
A2: Step 1: how much is missing, where, and in which disguise. Blank cells are only part of the story: whitespace-only cells, text placeholders (list in Codes) and numeric sentinels (column I, editable) are missing values too; numbers stored as text are not missing but are ignored by every statistical function. The summary on top uses the row-level view of Missing_Matrix.
A4: Cells in the Customers table | B4: =ROWS(Customers!$A$2:$A$1001)*COLUMNS(Customers!$A$1:$V$1) -> 22000
A5: Effective missing cells (blank + whitespace + placeholders + sentinels) | B5: =SUM(K13:K34) -> 1598
A6: % of cells missing | B6: =B5/B4 -> 0.072636364
A7: Rows with at least one missing value | B7: =COUNTIF(Missing_Matrix!$W$2:$W$1001,">0") -> 705
A8: Complete rows (what listwise deletion would keep) | B8: =COUNTIF(Missing_Matrix!$W$2:$W$1001,0) -> 295
A9: Ghost records (only the ID is populated) | B9: =COUNTIF(Missing_Matrix!$Z$2:$Z$1001,"Ghost record") -> 4
A10: Mostly-empty records (more than half of the columns missing) | B10: =COUNTIF(Missing_Matrix!$Z$2:$Z$1001,"Mostly empty") -> 6
A12: # | B12: Column | C12: Col | D12: Type | E12: Rows | F12: Blank cells COUNTBLANK | G12: Whitespace-only LEN(TRIM())=0 | H12: Text placeholders (list in Codes) | I12: Numeric sentinel (edit here) | J12: Sentinel cells COUNTIF | K12: Effective missing | L12: % missing | M12: Numbers stored as text (recoverable) | N12: Of which structural (not applicable) | O12: What we do
A13: 1 | B13: Customer_ID | C13: A | D13: Text (key) | E13: =ROWS(Customers!A$2:A$1001) -> 1000 | F13: =COUNTBLANK(Customers!A$2:A$1001) -> 0 | G13: =SUMPRODUCT((LEN(Customers!A$2:A$1001)>0)*(LEN(TRIM(Customers!A$2:A$1001))=0)) -> 0 | H13: =SUMPRODUCT(--ISNUMBER(MATCH(TRIM(Customers!A$2:A$1001&""),Codes!$A$5:$A$14,0))) -> 0 | J13: =IF(I13="",0,COUNTIF(Customers!A$2:A$1001,I13)) -> 0 | K13: =F13+G13+H13+J13 -> 0 | L13: =K13/E13 -> 0 | M13: =SUMPRODUCT(ISTEXT(Customers!A$2:A$1001)*ISNUMBER(VALUE(Customers!A$2:A$1001))) -> 0 | O13: Key: must never be missing. Ghost records are found through the other columns.
A14: 2 | B14: Age | C14: B | D14: Integer | E14: =ROWS(Customers!B$2:B$1001) -> 1000 | F14: =COUNTBLANK(Customers!B$2:B$1001) -> 24 | G14: =SUMPRODUCT((LEN(Customers!B$2:B$1001)>0)*(LEN(TRIM(Customers!B$2:B$1001))=0)) -> 0 | H14: =SUMPRODUCT(--ISNUMBER(MATCH(TRIM(Customers!B$2:B$1001&""),Codes!$A$5:$A$14,0))) -> 0 | I14: 0 | J14: =IF(I14="",0,COUNTIF(Customers!B$2:B$1001,I14)) -> 10 | K14: =F14+G14+H14+J14 -> 34 | L14: =K14/E14 -> 0.034 | M14: =SUMPRODUCT(ISTEXT(Customers!B$2:B$1001)*ISNUMBER(VALUE(Customers!B$2:B$1001))) -> 0 | O14: Median imputation + missing flag; 0 is treated as missing first.
A15: 3 | B15: Gender | C15: C | D15: Categorical | E15: =ROWS(Customers!C$2:C$1001) -> 1000 | F15: =COUNTBLANK(Customers!C$2:C$1001) -> 14 | G15: =SUMPRODUCT((LEN(Customers!C$2:C$1001)>0)*(LEN(TRIM(Customers!C$2:C$1001))=0)) -> 0 | H15: =SUMPRODUCT(--ISNUMBER(MATCH(TRIM(Customers!C$2:C$1001&""),Codes!$A$5:$A$14,0))) -> 10 | J15: =IF(I15="",0,COUNTIF(Customers!C$2:C$1001,I15)) -> 0 | K15: =F15+G15+H15+J15 -> 24 | L15: =K15/E15 -> 0.024 | M15: =SUMPRODUCT(ISTEXT(Customers!C$2:C$1001)*ISNUMBER(VALUE(Customers!C$2:C$1001))) -> 0 | O15: Keep an explicit 'Unknown' category (mode imputation would hide the information).
A16: 4 | B16: Region | C16: D | D16: Categorical | E16: =ROWS(Customers!D$2:D$1001) -> 1000 | F16: =COUNTBLANK(Customers!D$2:D$1001) -> 14 | G16: =SUMPRODUCT((LEN(Customers!D$2:D$1001)>0)*(LEN(TRIM(Customers!D$2:D$1001))=0)) -> 5 | H16: =SUMPRODUCT(--ISNUMBER(MATCH(TRIM(Customers!D$2:D$1001&""),Codes!$A$5:$A$14,0))) -> 5 | J16: =IF(I16="",0,COUNTIF(Customers!D$2:D$1001,I16)) -> 0 | K16: =F16+G16+H16+J16 -> 24 | L16: =K16/E16 -> 0.024 | M16: =SUMPRODUCT(ISTEXT(Customers!D$2:D$1001)*ISNUMBER(VALUE(Customers!D$2:D$1001))) -> 0 | O16: TRIM, then explicit 'Unknown' category.
A17: 5 | B17: Occupation | C17: E | D17: Categorical | E17: =ROWS(Customers!E$2:E$1001) -> 1000 | F17: =COUNTBLANK(Customers!E$2:E$1001) -> 19 | G17: =SUMPRODUCT((LEN(Customers!E$2:E$1001)>0)*(LEN(TRIM(Customers!E$2:E$1001))=0)) -> 0 | H17: =SUMPRODUCT(--ISNUMBER(MATCH(TRIM(Customers!E$2:E$1001&""),Codes!$A$5:$A$14,0))) -> 5 | J17: =IF(I17="",0,COUNTIF(Customers!E$2:E$1001,I17)) -> 0 | K17: =F17+G17+H17+J17 -> 24 | L17: =K17/E17 -> 0.024 | M17: =SUMPRODUCT(ISTEXT(Customers!E$2:E$1001)*ISNUMBER(VALUE(Customers!E$2:E$1001))) -> 0 | O17: Explicit 'Unknown' category; note that the group-based imputation of Income then needs a fallback.
A18: 6 | B18: Marital_Status | C18: F | D18: Categorical | E18: =ROWS(Customers!F$2:F$1001) -> 1000 | F18: =COUNTBLANK(Customers!F$2:F$1001) -> 14 | G18: =SUMPRODUCT((LEN(Customers!F$2:F$1001)>0)*(LEN(TRIM(Customers!F$2:F$1001))=0)) -> 0 | H18: =SUMPRODUCT(--ISNUMBER(MATCH(TRIM(Customers!F$2:F$1001&""),Codes!$A$5:$A$14,0))) -> 10 | J18: =IF(I18="",0,COUNTIF(Customers!F$2:F$1001,I18)) -> 0 | K18: =F18+G18+H18+J18 -> 24 | L18: =K18/E18 -> 0.024 | M18: =SUMPRODUCT(ISTEXT(Customers!F$2:F$1001)*ISNUMBER(VALUE(Customers!F$2:F$1001))) -> 0 | O18: Explicit 'Unknown' category.
A19: 7 | B19: Annual_Income_EUR | C19: G | D19: Numeric | E19: =ROWS(Customers!G$2:G$1001) -> 1000 | F19: =COUNTBLANK(Customers!G$2:G$1001) -> 52 | G19: =SUMPRODUCT((LEN(Customers!G$2:G$1001)>0)*(LEN(TRIM(Customers!G$2:G$1001))=0)) -> 0 | H19: =SUMPRODUCT(--ISNUMBER(MATCH(TRIM(Customers!G$2:G$1001&""),Codes!$A$5:$A$14,0))) -> 21 | I19: -999 | J19: =IF(I19="",0,COUNTIF(Customers!G$2:G$1001,I19)) -> 10 | K19: =F19+G19+H19+J19 -> 83 | L19: =K19/E19 -> 0.083 | M19: =SUMPRODUCT(ISTEXT(Customers!G$2:G$1001)*ISNUMBER(VALUE(Customers!G$2:G$1001))) -> 6 | O19: Group median by Occupation + missing flag (MAR). Convert the text numbers with VALUE first.
A20: 8 | B20: Tenure_Years | C20: H | D20: Integer | E20: =ROWS(Customers!H$2:H$1001) -> 1000 | F20: =COUNTBLANK(Customers!H$2:H$1001) -> 34 | G20: =SUMPRODUCT((LEN(Customers!H$2:H$1001)>0)*(LEN(TRIM(Customers!H$2:H$1001))=0)) -> 0 | H20: =SUMPRODUCT(--ISNUMBER(MATCH(TRIM(Customers!H$2:H$1001&""),Codes!$A$5:$A$14,0))) -> 0 | J20: =IF(I20="",0,COUNTIF(Customers!H$2:H$1001,I20)) -> 0 | K20: =F20+G20+H20+J20 -> 34 | L20: =K20/E20 -> 0.034 | M20: =SUMPRODUCT(ISTEXT(Customers!H$2:H$1001)*ISNUMBER(VALUE(Customers!H$2:H$1001))) -> 0 | O20: Derive from Account_Open_Date with DATEDIF; median only as a fallback.
A21: 9 | B21: Account_Open_Date | C21: I | D21: Date | E21: =ROWS(Customers!I$2:I$1001) -> 1000 | F21: =COUNTBLANK(Customers!I$2:I$1001) -> 24 | G21: =SUMPRODUCT((LEN(Customers!I$2:I$1001)>0)*(LEN(TRIM(Customers!I$2:I$1001))=0)) -> 0 | H21: =SUMPRODUCT(--ISNUMBER(MATCH(TRIM(Customers!I$2:I$1001&""),Codes!$A$5:$A$14,0))) -> 0 | I21: 25569 | J21: =IF(I21="",0,COUNTIF(Customers!I$2:I$1001,I21)) -> 8 | K21: =F21+G21+H21+J21 -> 32 | L21: =K21/E21 -> 0.032 | M21: =SUMPRODUCT(ISTEXT(Customers!I$2:I$1001)*ISNUMBER(VALUE(Customers!I$2:I$1001))) -> 0 | O21: Derive from Tenure_Years (approximate) or leave blank; never impute a mean date.
A22: 10 | B22: Preferred_Channel | C22: J | D22: Categorical | E22: =ROWS(Customers!J$2:J$1001) -> 1000 | F22: =COUNTBLANK(Customers!J$2:J$1001) -> 20 | G22: =SUMPRODUCT((LEN(Customers!J$2:J$1001)>0)*(LEN(TRIM(Customers!J$2:J$1001))=0)) -> 0 | H22: =SUMPRODUCT(--ISNUMBER(MATCH(TRIM(Customers!J$2:J$1001&""),Codes!$A$5:$A$14,0))) -> 15 | J22: =IF(I22="",0,COUNTIF(Customers!J$2:J$1001,I22)) -> 0 | K22: =F22+G22+H22+J22 -> 35 | L22: =K22/E22 -> 0.035 | M22: =SUMPRODUCT(ISTEXT(Customers!J$2:J$1001)*ISNUMBER(VALUE(Customers!J$2:J$1001))) -> 0 | O22: Explicit 'Unknown' category — compare with the mode in Strategies.
A23: 11 | B23: Num_Products | C23: K | D23: Integer | E23: =ROWS(Customers!K$2:K$1001) -> 1000 | F23: =COUNTBLANK(Customers!K$2:K$1001) -> 20 | G23: =SUMPRODUCT((LEN(Customers!K$2:K$1001)>0)*(LEN(TRIM(Customers!K$2:K$1001))=0)) -> 0 | H23: =SUMPRODUCT(--ISNUMBER(MATCH(TRIM(Customers!K$2:K$1001&""),Codes!$A$5:$A$14,0))) -> 15 | J23: =IF(I23="",0,COUNTIF(Customers!K$2:K$1001,I23)) -> 0 | K23: =F23+G23+H23+J23 -> 35 | L23: =K23/E23 -> 0.035 | M23: =SUMPRODUCT(ISTEXT(Customers!K$2:K$1001)*ISNUMBER(VALUE(Customers!K$2:K$1001))) -> 0 | O23: Median (integer) imputation.
A24: 12 | B24: Checking_Balance_EUR | C24: L | D24: Numeric | E24: =ROWS(Customers!L$2:L$1001) -> 1000 | F24: =COUNTBLANK(Customers!L$2:L$1001) -> 30 | G24: =SUMPRODUCT((LEN(Customers!L$2:L$1001)>0)*(LEN(TRIM(Customers!L$2:L$1001))=0)) -> 0 | H24: =SUMPRODUCT(--ISNUMBER(MATCH(TRIM(Customers!L$2:L$1001&""),Codes!$A$5:$A$14,0))) -> 0 | J24: =IF(I24="",0,COUNTIF(Customers!L$2:L$1001,I24)) -> 0 | K24: =F24+G24+H24+J24 -> 30 | L24: =K24/E24 -> 0.03 | M24: =SUMPRODUCT(ISTEXT(Customers!L$2:L$1001)*ISNUMBER(VALUE(Customers!L$2:L$1001))) -> 0 | O24: Median imputation.
A25: 13 | B25: Savings_Balance_EUR | C25: M | D25: Numeric | E25: =ROWS(Customers!M$2:M$1001) -> 1000 | F25: =COUNTBLANK(Customers!M$2:M$1001) -> 84 | G25: =SUMPRODUCT((LEN(Customers!M$2:M$1001)>0)*(LEN(TRIM(Customers!M$2:M$1001))=0)) -> 0 | H25: =SUMPRODUCT(--ISNUMBER(MATCH(TRIM(Customers!M$2:M$1001&""),Codes!$A$5:$A$14,0))) -> 0 | J25: =IF(I25="",0,COUNTIF(Customers!M$2:M$1001,I25)) -> 0 | K25: =F25+G25+H25+J25 -> 84 | L25: =K25/E25 -> 0.084 | M25: =SUMPRODUCT(ISTEXT(Customers!M$2:M$1001)*ISNUMBER(VALUE(Customers!M$2:M$1001))) -> 0 | O25: Missing rate grows with wealth (MNAR): no single value is unbiased. Median + flag, and ask the data owner.
A26: 14 | B26: Monthly_Transactions | C26: N | D26: Integer | E26: =ROWS(Customers!N$2:N$1001) -> 1000 | F26: =COUNTBLANK(Customers!N$2:N$1001) -> 20 | G26: =SUMPRODUCT((LEN(Customers!N$2:N$1001)>0)*(LEN(TRIM(Customers!N$2:N$1001))=0)) -> 0 | H26: =SUMPRODUCT(--ISNUMBER(MATCH(TRIM(Customers!N$2:N$1001&""),Codes!$A$5:$A$14,0))) -> 0 | I26: 9999 | J26: =IF(I26="",0,COUNTIF(Customers!N$2:N$1001,I26)) -> 10 | K26: =F26+G26+H26+J26 -> 30 | L26: =K26/E26 -> 0.03 | M26: =SUMPRODUCT(ISTEXT(Customers!N$2:N$1001)*ISNUMBER(VALUE(Customers!N$2:N$1001))) -> 0 | O26: 9999 is a sentinel; the 0s are real (dormant accounts). Median for the true blanks.
A27: 15 | B27: Avg_Transaction_EUR | C27: O | D27: Numeric | E27: =ROWS(Customers!O$2:O$1001) -> 1000 | F27: =COUNTBLANK(Customers!O$2:O$1001) -> 45 | G27: =SUMPRODUCT((LEN(Customers!O$2:O$1001)>0)*(LEN(TRIM(Customers!O$2:O$1001))=0)) -> 0 | H27: =SUMPRODUCT(--ISNUMBER(MATCH(TRIM(Customers!O$2:O$1001&""),Codes!$A$5:$A$14,0))) -> 0 | J27: =IF(I27="",0,COUNTIF(Customers!O$2:O$1001,I27)) -> 0 | K27: =F27+G27+H27+J27 -> 45 | L27: =K27/E27 -> 0.045 | M27: =SUMPRODUCT(ISTEXT(Customers!O$2:O$1001)*ISNUMBER(VALUE(Customers!O$2:O$1001))) -> 0 | N27: =COUNTIFS(Customers!O$2:O$1001,"",Customers!N$2:N$1001,0) -> 20 | O27: Structural when Monthly_Transactions = 0 (leave blank or 0); median for the other blanks.
A28: 16 | B28: Monthly_ATM_Withdrawals | C28: P | D28: Integer | E28: =ROWS(Customers!P$2:P$1001) -> 1000 | F28: =COUNTBLANK(Customers!P$2:P$1001) -> 20 | G28: =SUMPRODUCT((LEN(Customers!P$2:P$1001)>0)*(LEN(TRIM(Customers!P$2:P$1001))=0)) -> 0 | H28: =SUMPRODUCT(--ISNUMBER(MATCH(TRIM(Customers!P$2:P$1001&""),Codes!$A$5:$A$14,0))) -> 5 | J28: =IF(I28="",0,COUNTIF(Customers!P$2:P$1001,I28)) -> 0 | K28: =F28+G28+H28+J28 -> 25 | L28: =K28/E28 -> 0.025 | M28: =SUMPRODUCT(ISTEXT(Customers!P$2:P$1001)*ISNUMBER(VALUE(Customers!P$2:P$1001))) -> 0 | O28: Median imputation; 'NA' is a text placeholder.
A29: 17 | B29: Card_Limit_EUR | C29: Q | D29: Numeric | E29: =ROWS(Customers!Q$2:Q$1001) -> 1000 | F29: =COUNTBLANK(Customers!Q$2:Q$1001) -> 127 | G29: =SUMPRODUCT((LEN(Customers!Q$2:Q$1001)>0)*(LEN(TRIM(Customers!Q$2:Q$1001))=0)) -> 0 | H29: =SUMPRODUCT(--ISNUMBER(MATCH(TRIM(Customers!Q$2:Q$1001&""),Codes!$A$5:$A$14,0))) -> 0 | J29: =IF(I29="",0,COUNTIF(Customers!Q$2:Q$1001,I29)) -> 0 | K29: =F29+G29+H29+J29 -> 127 | L29: =K29/E29 -> 0.127 | M29: =SUMPRODUCT(ISTEXT(Customers!Q$2:Q$1001)*ISNUMBER(VALUE(Customers!Q$2:Q$1001))) -> 0 | N29: =COUNTIFS(Customers!Q$2:Q$1001,"",Customers!R$2:R$1001,"") -> 119 | O29: Blank + blank spend = no card → 0. Blank with a spend present = genuinely missing → verify.
A30: 18 | B30: Monthly_Card_Spend_EUR | C30: R | D30: Numeric | E30: =ROWS(Customers!R$2:R$1001) -> 1000 | F30: =COUNTBLANK(Customers!R$2:R$1001) -> 134 | G30: =SUMPRODUCT((LEN(Customers!R$2:R$1001)>0)*(LEN(TRIM(Customers!R$2:R$1001))=0)) -> 0 | H30: =SUMPRODUCT(--ISNUMBER(MATCH(TRIM(Customers!R$2:R$1001&""),Codes!$A$5:$A$14,0))) -> 0 | J30: =IF(I30="",0,COUNTIF(Customers!R$2:R$1001,I30)) -> 0 | K30: =F30+G30+H30+J30 -> 134 | L30: =K30/E30 -> 0.134 | M30: =SUMPRODUCT(ISTEXT(Customers!R$2:R$1001)*ISNUMBER(VALUE(Customers!R$2:R$1001))) -> 0 | N30: =COUNTIFS(Customers!Q$2:Q$1001,"",Customers!R$2:R$1001,"") -> 119 | O30: Blank + blank limit = no card → 0. Blank with a limit present → limit × average spend/limit ratio.
A31: 19 | B31: Mortgage_Balance_EUR | C31: S | D31: Numeric | E31: =ROWS(Customers!S$2:S$1001) -> 1000 | F31: =COUNTBLANK(Customers!S$2:S$1001) -> 256 | G31: =SUMPRODUCT((LEN(Customers!S$2:S$1001)>0)*(LEN(TRIM(Customers!S$2:S$1001))=0)) -> 0 | H31: =SUMPRODUCT(--ISNUMBER(MATCH(TRIM(Customers!S$2:S$1001&""),Codes!$A$5:$A$14,0))) -> 0 | J31: =IF(I31="",0,COUNTIF(Customers!S$2:S$1001,I31)) -> 0 | K31: =F31+G31+H31+J31 -> 256 | L31: =K31/E31 -> 0.256 | M31: =SUMPRODUCT(ISTEXT(Customers!S$2:S$1001)*ISNUMBER(VALUE(Customers!S$2:S$1001))) -> 0 | N31: =COUNTIFS(Customers!S$2:S$1001,"",Customers!T$2:T$1001,"") -> 251 | O31: Blank + blank payment = no mortgage → 0. Blank with a payment present → verify.
A32: 20 | B32: Monthly_Mortgage_Payment_EUR | C32: T | D32: Numeric | E32: =ROWS(Customers!T$2:T$1001) -> 1000 | F32: =COUNTBLANK(Customers!T$2:T$1001) -> 261 | G32: =SUMPRODUCT((LEN(Customers!T$2:T$1001)>0)*(LEN(TRIM(Customers!T$2:T$1001))=0)) -> 0 | H32: =SUMPRODUCT(--ISNUMBER(MATCH(TRIM(Customers!T$2:T$1001&""),Codes!$A$5:$A$14,0))) -> 0 | J32: =IF(I32="",0,COUNTIF(Customers!T$2:T$1001,I32)) -> 0 | K32: =F32+G32+H32+J32 -> 261 | L32: =K32/E32 -> 0.261 | M32: =SUMPRODUCT(ISTEXT(Customers!T$2:T$1001)*ISNUMBER(VALUE(Customers!T$2:T$1001))) -> 0 | N32: =COUNTIFS(Customers!S$2:S$1001,"",Customers!T$2:T$1001,"") -> 251 | O32: Blank + blank balance = no mortgage → 0. Blank with a balance present → balance × average payment/balance ratio.
A33: 21 | B33: Credit_Score | C33: U | D33: Integer | E33: =ROWS(Customers!U$2:U$1001) -> 1000 | F33: =COUNTBLANK(Customers!U$2:U$1001) -> 35 | G33: =SUMPRODUCT((LEN(Customers!U$2:U$1001)>0)*(LEN(TRIM(Customers!U$2:U$1001))=0)) -> 0 | H33: =SUMPRODUCT(--ISNUMBER(MATCH(TRIM(Customers!U$2:U$1001&""),Codes!$A$5:$A$14,0))) -> 0 | I33: 0 | J33: =IF(I33="",0,COUNTIF(Customers!U$2:U$1001,I33)) -> 8 | K33: =F33+G33+H33+J33 -> 43 | L33: =K33/E33 -> 0.043 | M33: =SUMPRODUCT(ISTEXT(Customers!U$2:U$1001)*ISNUMBER(VALUE(Customers!U$2:U$1001))) -> 0 | O33: Mean (symmetric distribution) or median; 0 is a sentinel.
A34: 22 | B34: Complaints_12M | C34: V | D34: Integer | E34: =ROWS(Customers!V$2:V$1001) -> 1000 | F34: =COUNTBLANK(Customers!V$2:V$1001) -> 214 | G34: =SUMPRODUCT((LEN(Customers!V$2:V$1001)>0)*(LEN(TRIM(Customers!V$2:V$1001))=0)) -> 0 | H34: =SUMPRODUCT(--ISNUMBER(MATCH(TRIM(Customers!V$2:V$1001&""),Codes!$A$5:$A$14,0))) -> 0 | J34: =IF(I34="",0,COUNTIF(Customers!V$2:V$1001,I34)) -> 0 | K34: =F34+G34+H34+J34 -> 214 | L34: =K34/E34 -> 0.214 | M34: =SUMPRODUCT(ISTEXT(Customers!V$2:V$1001)*ISNUMBER(VALUE(Customers!V$2:V$1001))) -> 0 | N34: ? — a blank may mean 0, ask the data owner | O34: Blank probably means 0, but not always: constant 0 + missing flag, and ask the data owner.
B35: Total | F35: =SUM(F13:F34) -> 1461 | G35: =SUM(G13:G34) -> 5 | H35: =SUM(H13:H34) -> 86 | J35: =SUM(J13:J34) -> 46 | K35: =SUM(K13:K34) -> 1598 | L35: =K35/B4 -> 0.072636364 | M35: =SUM(M13:M34) -> 6
A37: Reading the table: 'Effective missing' = blank + whitespace + placeholder + sentinel. The Codes sheet holds the placeholder list; the sentinel in column I can be changed and the counts follow. Numbers stored as text are counted separately because they are recoverable with VALUE(), yet AVERAGE/SUM/COUNT ignore them until we convert them.

Sheet Missing_Matrix
A1: Customer_ID | B1: Age | C1: Gender | D1: Region | E1: Occupation | F1: Marital_Status | G1: Annual_Income_EUR | H1: Tenure_Years | I1: Account_Open_Date | J1: Preferred_Channel | K1: Num_Products | L1: Checking_Balance_EUR | M1: Savings_Balance_EUR | N1: Monthly_Transactions | O1: Avg_Transaction_EUR | P1: Monthly_ATM_Withdrawals | Q1: Card_Limit_EUR | R1: Monthly_Card_Spend_EUR | S1: Mortgage_Balance_EUR | T1: Monthly_Mortgage_Payment_EUR | U1: Credit_Score | V1: Complaints_12M | W1: Missing cells in row | X1: Status | Y1: % of columns missing | Z1: Record type
A2: =Clean!A2 -> CL00001 | B2: =IF(Clean!B2="",1,0) -> 0 | C2: =IF(Clean!C2="",1,0) -> 0 | D2: =IF(Clean!D2="",1,0) -> 0 | E2: =IF(Clean!E2="",1,0) -> 0 | F2: =IF(Clean!F2="",1,0) -> 0 | G2: =IF(Clean!G2="",1,0) -> 0 | H2: =IF(Clean!H2="",1,0) -> 0 | I2: =IF(Clean!I2="",1,0) -> 0 | ... V2: =IF(Clean!V2="",1,0) -> 1 | W2: =SUM(B2:V2) -> 3 | X2: =IF(W2=0,"Complete","Incomplete") -> Incomplete | Y2: =W2/21 -> 0.14285714 | Z2: =IF(W2=21,"Ghost record",IF(W2>=11,"Mostly empty",IF(W2=0,"Complete","Partial"))) -> Partial
A3: =Clean!A3 -> CL00002 | B3: =IF(Clean!B3="",1,0) -> 0 | C3: =IF(Clean!C3="",1,0) -> 0 | D3: =IF(Clean!D3="",1,0) -> 0 | E3: =IF(Clean!E3="",1,0) -> 0 | F3: =IF(Clean!F3="",1,0) -> 0 | G3: =IF(Clean!G3="",1,0) -> 0 | H3: =IF(Clean!H3="",1,0) -> 0 | I3: =IF(Clean!I3="",1,0) -> 0 | ... V3: =IF(Clean!V3="",1,0) -> 1 | W3: =SUM(B3:V3) -> 1 | X3: =IF(W3=0,"Complete","Incomplete") -> Incomplete | Y3: =W3/21 -> 0.047619048 | Z3: =IF(W3=21,"Ghost record",IF(W3>=11,"Mostly empty",IF(W3=0,"Complete","Partial"))) -> Partial
A4: =Clean!A4 -> CL00003 | B4: =IF(Clean!B4="",1,0) -> 0 | C4: =IF(Clean!C4="",1,0) -> 0 | D4: =IF(Clean!D4="",1,0) -> 0 | E4: =IF(Clean!E4="",1,0) -> 0 | F4: =IF(Clean!F4="",1,0) -> 0 | G4: =IF(Clean!G4="",1,0) -> 0 | H4: =IF(Clean!H4="",1,0) -> 0 | I4: =IF(Clean!I4="",1,0) -> 0 | ... V4: =IF(Clean!V4="",1,0) -> 1 | W4: =SUM(B4:V4) -> 3 | X4: =IF(W4=0,"Complete","Incomplete") -> Incomplete | Y4: =W4/21 -> 0.14285714 | Z4: =IF(W4=21,"Ghost record",IF(W4>=11,"Mostly empty",IF(W4=0,"Complete","Partial"))) -> Partial
A5: =Clean!A5 -> CL00004 | B5: =IF(Clean!B5="",1,0) -> 0 | C5: =IF(Clean!C5="",1,0) -> 0 | D5: =IF(Clean!D5="",1,0) -> 0 | E5: =IF(Clean!E5="",1,0) -> 0 | F5: =IF(Clean!F5="",1,0) -> 0 | G5: =IF(Clean!G5="",1,0) -> 0 | H5: =IF(Clean!H5="",1,0) -> 0 | I5: =IF(Clean!I5="",1,0) -> 0 | ... V5: =IF(Clean!V5="",1,0) -> 0 | W5: =SUM(B5:V5) -> 0 | X5: =IF(W5=0,"Complete","Incomplete") -> Complete | Y5: =W5/21 -> 0 | Z5: =IF(W5=21,"Ghost record",IF(W5>=11,"Mostly empty",IF(W5=0,"Complete","Partial"))) -> Complete
A6: =Clean!A6 -> CL00005 | B6: =IF(Clean!B6="",1,0) -> 0 | C6: =IF(Clean!C6="",1,0) -> 0 | D6: =IF(Clean!D6="",1,0) -> 0 | E6: =IF(Clean!E6="",1,0) -> 0 | F6: =IF(Clean!F6="",1,0) -> 0 | G6: =IF(Clean!G6="",1,0) -> 0 | H6: =IF(Clean!H6="",1,0) -> 0 | I6: =IF(Clean!I6="",1,0) -> 0 | ... V6: =IF(Clean!V6="",1,0) -> 0 | W6: =SUM(B6:V6) -> 2 | X6: =IF(W6=0,"Complete","Incomplete") -> Incomplete | Y6: =W6/21 -> 0.095238095 | Z6: =IF(W6=21,"Ghost record",IF(W6>=11,"Mostly empty",IF(W6=0,"Complete","Partial"))) -> Partial
A7: =Clean!A7 -> CL00006 | B7: =IF(Clean!B7="",1,0) -> 0 | C7: =IF(Clean!C7="",1,0) -> 0 | D7: =IF(Clean!D7="",1,0) -> 0 | E7: =IF(Clean!E7="",1,0) -> 0 | F7: =IF(Clean!F7="",1,0) -> 0 | G7: =IF(Clean!G7="",1,0) -> 0 | H7: =IF(Clean!H7="",1,0) -> 0 | I7: =IF(Clean!I7="",1,0) -> 0 | ... V7: =IF(Clean!V7="",1,0) -> 0 | W7: =SUM(B7:V7) -> 1 | X7: =IF(W7=0,"Complete","Incomplete") -> Incomplete | Y7: =W7/21 -> 0.047619048 | Z7: =IF(W7=21,"Ghost record",IF(W7>=11,"Mostly empty",IF(W7=0,"Complete","Partial"))) -> Partial
A8: =Clean!A8 -> CL00007 | B8: =IF(Clean!B8="",1,0) -> 0 | C8: =IF(Clean!C8="",1,0) -> 0 | D8: =IF(Clean!D8="",1,0) -> 0 | E8: =IF(Clean!E8="",1,0) -> 0 | F8: =IF(Clean!F8="",1,0) -> 0 | G8: =IF(Clean!G8="",1,0) -> 0 | H8: =IF(Clean!H8="",1,0) -> 0 | I8: =IF(Clean!I8="",1,0) -> 0 | ... V8: =IF(Clean!V8="",1,0) -> 1 | W8: =SUM(B8:V8) -> 3 | X8: =IF(W8=0,"Complete","Incomplete") -> Incomplete | Y8: =W8/21 -> 0.14285714 | Z8: =IF(W8=21,"Ghost record",IF(W8>=11,"Mostly empty",IF(W8=0,"Complete","Partial"))) -> Partial
A9: =Clean!A9 -> CL00008 | B9: =IF(Clean!B9="",1,0) -> 0 | C9: =IF(Clean!C9="",1,0) -> 0 | D9: =IF(Clean!D9="",1,0) -> 0 | E9: =IF(Clean!E9="",1,0) -> 0 | F9: =IF(Clean!F9="",1,0) -> 0 | G9: =IF(Clean!G9="",1,0) -> 0 | H9: =IF(Clean!H9="",1,0) -> 0 | I9: =IF(Clean!I9="",1,0) -> 0 | ... V9: =IF(Clean!V9="",1,0) -> 0 | W9: =SUM(B9:V9) -> 0 | X9: =IF(W9=0,"Complete","Incomplete") -> Complete | Y9: =W9/21 -> 0 | Z9: =IF(W9=21,"Ghost record",IF(W9>=11,"Mostly empty",IF(W9=0,"Complete","Partial"))) -> Complete
A10: =Clean!A10 -> CL00009 | B10: =IF(Clean!B10="",1,0) -> 0 | C10: =IF(Clean!C10="",1,0) -> 0 | D10: =IF(Clean!D10="",1,0) -> 0 | E10: =IF(Clean!E10="",1,0) -> 0 | F10: =IF(Clean!F10="",1,0) -> 1 | G10: =IF(Clean!G10="",1,0) -> 0 | H10: =IF(Clean!H10="",1,0) -> 0 | I10: =IF(Clean!I10="",1,0) -> 0 | ... V10: =IF(Clean!V10="",1,0) -> 0 | W10: =SUM(B10:V10) -> 1 | X10: =IF(W10=0,"Complete","Incomplete") -> Incomplete | Y10: =W10/21 -> 0.047619048 | Z10: =IF(W10=21,"Ghost record",IF(W10>=11,"Mostly empty",IF(W10=0,"Complete","Partial"))) -> Partial
A11: =Clean!A11 -> CL00010 | B11: =IF(Clean!B11="",1,0) -> 0 | C11: =IF(Clean!C11="",1,0) -> 0 | D11: =IF(Clean!D11="",1,0) -> 0 | E11: =IF(Clean!E11="",1,0) -> 0 | F11: =IF(Clean!F11="",1,0) -> 0 | G11: =IF(Clean!G11="",1,0) -> 0 | H11: =IF(Clean!H11="",1,0) -> 0 | I11: =IF(Clean!I11="",1,0) -> 0 | ... V11: =IF(Clean!V11="",1,0) -> 1 | W11: =SUM(B11:V11) -> 1 | X11: =IF(W11=0,"Complete","Incomplete") -> Incomplete | Y11: =W11/21 -> 0.047619048 | Z11: =IF(W11=21,"Ghost record",IF(W11>=11,"Mostly empty",IF(W11=0,"Complete","Partial"))) -> Partial
A12: =Clean!A12 -> CL00011 | B12: =IF(Clean!B12="",1,0) -> 0 | C12: =IF(Clean!C12="",1,0) -> 0 | D12: =IF(Clean!D12="",1,0) -> 0 | E12: =IF(Clean!E12="",1,0) -> 0 | F12: =IF(Clean!F12="",1,0) -> 0 | G12: =IF(Clean!G12="",1,0) -> 0 | H12: =IF(Clean!H12="",1,0) -> 0 | I12: =IF(Clean!I12="",1,0) -> 0 | ... V12: =IF(Clean!V12="",1,0) -> 0 | W12: =SUM(B12:V12) -> 0 | X12: =IF(W12=0,"Complete","Incomplete") -> Complete | Y12: =W12/21 -> 0 | Z12: =IF(W12=21,"Ghost record",IF(W12>=11,"Mostly empty",IF(W12=0,"Complete","Partial"))) -> Complete
A13: =Clean!A13 -> CL00012 | B13: =IF(Clean!B13="",1,0) -> 0 | C13: =IF(Clean!C13="",1,0) -> 0 | D13: =IF(Clean!D13="",1,0) -> 0 | E13: =IF(Clean!E13="",1,0) -> 0 | F13: =IF(Clean!F13="",1,0) -> 0 | G13: =IF(Clean!G13="",1,0) -> 0 | H13: =IF(Clean!H13="",1,0) -> 0 | I13: =IF(Clean!I13="",1,0) -> 0 | ... V13: =IF(Clean!V13="",1,0) -> 0 | W13: =SUM(B13:V13) -> 1 | X13: =IF(W13=0,"Complete","Incomplete") -> Incomplete | Y13: =W13/21 -> 0.047619048 | Z13: =IF(W13=21,"Ghost record",IF(W13>=11,"Mostly empty",IF(W13=0,"Complete","Partial"))) -> Partial
... A1001: =Clean!A1001 -> CL01000 | B1001: =IF(Clean!B1001="",1,0) -> 0 | C1001: =IF(Clean!C1001="",1,0) -> 0 | D1001: =IF(Clean!D1001="",1,0) -> 0 | E1001: =IF(Clean!E1001="",1,0) -> 1 | F1001: =IF(Clean!F1001="",1,0) -> 0 | G1001: =IF(Clean!G1001="",1,0) -> 0 | H1001: =IF(Clean!H1001="",1,0) -> 0 | I1001: =IF(Clean!I1001="",1,0) -> 0 | ... V1001: =IF(Clean!V1001="",1,0) -> 0 | W1001: =SUM(B1001:V1001) -> 1 | X1001: =IF(W1001=0,"Complete","Incomplete") -> Incomplete | Y1001: =W1001/21 -> 0.047619048 | Z1001: =IF(W1001=21,"Ghost record",IF(W1001>=11,"Mostly empty",IF(W1001=0,"Complete","Partial"))) -> Partial
A1003: Missing per column | B1003: =SUM(B2:B1001) -> 34 | C1003: =SUM(C2:C1001) -> 24 | D1003: =SUM(D2:D1001) -> 24 | E1003: =SUM(E2:E1001) -> 24 | F1003: =SUM(F2:F1001) -> 24 | G1003: =SUM(G2:G1001) -> 83 | H1003: =SUM(H2:H1001) -> 34 | I1003: =SUM(I2:I1001) -> 32 | ... V1003: =SUM(V2:V1001) -> 214
A1004: % missing | B1004: =B1003/1000 -> 0.034 | C1004: =C1003/1000 -> 0.024 | D1004: =D1003/1000 -> 0.024 | E1004: =E1003/1000 -> 0.024 | F1004: =F1003/1000 -> 0.024 | G1004: =G1003/1000 -> 0.083 | H1004: =H1003/1000 -> 0.034 | I1004: =I1003/1000 -> 0.032 | ... V1004: =V1003/1000 -> 0.214

Sheet Clean
A1: Customer_ID | B1: Age | C1: Gender | D1: Region | E1: Occupation | F1: Marital_Status | G1: Annual_Income_EUR | H1: Tenure_Years | I1: Account_Open_Date | J1: Preferred_Channel | K1: Num_Products | L1: Checking_Balance_EUR | M1: Savings_Balance_EUR | N1: Monthly_Transactions | O1: Avg_Transaction_EUR | P1: Monthly_ATM_Withdrawals | Q1: Card_Limit_EUR | R1: Monthly_Card_Spend_EUR | S1: Mortgage_Balance_EUR | T1: Monthly_Mortgage_Payment_EUR | U1: Credit_Score | V1: Complaints_12M
A2: =Customers!A2 -> CL00001 | B2: =IF(OR(TRIM(Customers!B2&"")="",ISNUMBER(MATCH(TRIM(Customers!B2&""),Codes!$A$5:$A$14,0)),Customers!B2=0),"",IF(ISNUMBER(Customers!B2),Customers!B2,IFERROR(VALUE(Customers!B2),""))) -> 57 | C2: =IF(OR(TRIM(Customers!C2&"")="",ISNUMBER(MATCH(TRIM(Customers!C2&""),Codes!$A$5:$A$14,0))),"",TRIM(Customers!C2)) -> F | D2: =IF(OR(TRIM(Customers!D2&"")="",ISNUMBER(MATCH(TRIM(Customers!D2&""),Codes!$A$5:$A$14,0))),"",TRIM(Customers!D2)) -> Marche | E2: =IF(OR(TRIM(Customers!E2&"")="",ISNUMBER(MATCH(TRIM(Customers!E2&""),Codes!$A$5:$A$14,0))),"",TRIM(Customers!E2)) -> Shopkeeper | F2: =IF(OR(TRIM(Customers!F2&"")="",ISNUMBER(MATCH(TRIM(Customers!F2&""),Codes!$A$5:$A$14,0))),"",TRIM(Customers!F2)) -> Married | G2: =IF(OR(TRIM(Customers!G2&"")="",ISNUMBER(MATCH(TRIM(Customers!G2&""),Codes!$A$5:$A$14,0)),Customers!G2=-999),"",IF(ISNUMBER(Customers!G2),Customers!G2,IFERROR(VALUE(Customers!G2),""))) -> 30100 | H2: =IF(OR(TRIM(Customers!H2&"")="",ISNUMBER(MATCH(TRIM(Customers!H2&""),Codes!$A$5:$A$14,0))),"",IF(ISNUMBER(Customers!H2),Customers!H2,IFERROR(VALUE(Customers!H2),""))) -> 4 | I2: =IF(OR(TRIM(Customers!I2&"")="",ISNUMBER(MATCH(TRIM(Customers!I2&""),Codes!$A$5:$A$14,0)),Customers!I2=DATE(1970,1,1)),"",IF(ISNUMBER(Customers!I2),Customers!I2,IFERROR(DATEVALUE(Customers!I2),""))) -> 44721 | J2: =IF(OR(TRIM(Customers!J2&"")="",ISNUMBER(MATCH(TRIM(Customers!J2&""),Codes!$A$5:$A$14,0))),"",TRIM(Customers!J2)) -> Branch | K2: =IF(OR(TRIM(Customers!K2&"")="",ISNUMBER(MATCH(TRIM(Customers!K2&""),Codes!$A$5:$A$14,0))),"",IF(ISNUMBER(Customers!K2),Customers!K2,IFERROR(VALUE(Customers!K2),""))) -> 2 | L2: =IF(OR(TRIM(Customers!L2&"")="",ISNUMBER(MATCH(TRIM(Customers!L2&""),Codes!$A$5:$A$14,0))),"",IF(ISNUMBER(Customers!L2),Customers!L2,IFERROR(VALUE(Customers!L2),""))) -> 6763.27 | M2: =IF(OR(TRIM(Customers!M2&"")="",ISNUMBER(MATCH(TRIM(Customers!M2&""),Codes!$A$5:$A$14,0))),"",IF(ISNUMBER(Customers!M2),Customers!M2,IFERROR(VALUE(Customers!M2),""))) -> 12100.75 | N2: =IF(OR(TRIM(Customers!N2&"")="",ISNUMBER(MATCH(TRIM(Customers!N2&""),Codes!$A$5:$A$14,0)),Customers!N2=9999),"",IF(ISNUMBER(Customers!N2),Customers!N2,IFERROR(VALUE(Customers!N2),""))) -> 23 | O2: =IF(OR(TRIM(Customers!O2&"")="",ISNUMBER(MATCH(TRIM(Customers!O2&""),Codes!$A$5:$A$14,0))),"",IF(ISNUMBER(Customers!O2),Customers!O2,IFERROR(VALUE(Customers!O2),""))) -> 36.84 | P2: =IF(OR(TRIM(Customers!P2&"")="",ISNUMBER(MATCH(TRIM(Customers!P2&""),Codes!$A$5:$A$14,0))),"",IF(ISNUMBER(Customers!P2),Customers!P2,IFERROR(VALUE(Customers!P2),""))) -> 1 | Q2: =IF(OR(TRIM(Customers!Q2&"")="",ISNUMBER(MATCH(TRIM(Customers!Q2&""),Codes!$A$5:$A$14,0))),"",IF(ISNUMBER(Customers!Q2),Customers!Q2,IFERROR(VALUE(Customers!Q2),""))) | R2: =IF(OR(TRIM(Customers!R2&"")="",ISNUMBER(MATCH(TRIM(Customers!R2&""),Codes!$A$5:$A$14,0))),"",IF(ISNUMBER(Customers!R2),Customers!R2,IFERROR(VALUE(Customers!R2),""))) | S2: =IF(OR(TRIM(Customers!S2&"")="",ISNUMBER(MATCH(TRIM(Customers!S2&""),Codes!$A$5:$A$14,0))),"",IF(ISNUMBER(Customers!S2),Customers!S2,IFERROR(VALUE(Customers!S2),""))) -> 93000 | T2: =IF(OR(TRIM(Customers!T2&"")="",ISNUMBER(MATCH(TRIM(Customers!T2&""),Codes!$A$5:$A$14,0))),"",IF(ISNUMBER(Customers!T2),Customers!T2,IFERROR(VALUE(Customers!T2),""))) -> 603 | U2: =IF(OR(TRIM(Customers!U2&"")="",ISNUMBER(MATCH(TRIM(Customers!U2&""),Codes!$A$5:$A$14,0)),Customers!U2=0),"",IF(ISNUMBER(Customers!U2),Customers!U2,IFERROR(VALUE(Customers!U2),""))) -> 698 | V2: =IF(OR(TRIM(Customers!V2&"")="",ISNUMBER(MATCH(TRIM(Customers!V2&""),Codes!$A$5:$A$14,0))),"",IF(ISNUMBER(Customers!V2),Customers!V2,IFERROR(VALUE(Customers!V2),"")))
A3: =Customers!A3 -> CL00002 | B3: =IF(OR(TRIM(Customers!B3&"")="",ISNUMBER(MATCH(TRIM(Customers!B3&""),Codes!$A$5:$A$14,0)),Customers!B3=0),"",IF(ISNUMBER(Customers!B3),Customers!B3,IFERROR(VALUE(Customers!B3),""))) -> 60 | C3: =IF(OR(TRIM(Customers!C3&"")="",ISNUMBER(MATCH(TRIM(Customers!C3&""),Codes!$A$5:$A$14,0))),"",TRIM(Customers!C3)) -> M | D3: =IF(OR(TRIM(Customers!D3&"")="",ISNUMBER(MATCH(TRIM(Customers!D3&""),Codes!$A$5:$A$14,0))),"",TRIM(Customers!D3)) -> Abruzzo | E3: =IF(OR(TRIM(Customers!E3&"")="",ISNUMBER(MATCH(TRIM(Customers!E3&""),Codes!$A$5:$A$14,0))),"",TRIM(Customers!E3)) -> Business owner | F3: =IF(OR(TRIM(Customers!F3&"")="",ISNUMBER(MATCH(TRIM(Customers!F3&""),Codes!$A$5:$A$14,0))),"",TRIM(Customers!F3)) -> Married | G3: =IF(OR(TRIM(Customers!G3&"")="",ISNUMBER(MATCH(TRIM(Customers!G3&""),Codes!$A$5:$A$14,0)),Customers!G3=-999),"",IF(ISNUMBER(Customers!G3),Customers!G3,IFERROR(VALUE(Customers!G3),""))) -> 117400 | H3: =IF(OR(TRIM(Customers!H3&"")="",ISNUMBER(MATCH(TRIM(Customers!H3&""),Codes!$A$5:$A$14,0))),"",IF(ISNUMBER(Customers!H3),Customers!H3,IFERROR(VALUE(Customers!H3),""))) -> 13 | I3: =IF(OR(TRIM(Customers!I3&"")="",ISNUMBER(MATCH(TRIM(Customers!I3&""),Codes!$A$5:$A$14,0)),Customers!I3=DATE(1970,1,1)),"",IF(ISNUMBER(Customers!I3),Customers!I3,IFERROR(DATEVALUE(Customers!I3),""))) -> 41314 | J3: =IF(OR(TRIM(Customers!J3&"")="",ISNUMBER(MATCH(TRIM(Customers!J3&""),Codes!$A$5:$A$14,0))),"",TRIM(Customers!J3)) -> Branch | K3: =IF(OR(TRIM(Customers!K3&"")="",ISNUMBER(MATCH(TRIM(Customers!K3&""),Codes!$A$5:$A$14,0))),"",IF(ISNUMBER(Customers!K3),Customers!K3,IFERROR(VALUE(Customers!K3),""))) -> 3 | L3: =IF(OR(TRIM(Customers!L3&"")="",ISNUMBER(MATCH(TRIM(Customers!L3&""),Codes!$A$5:$A$14,0))),"",IF(ISNUMBER(Customers!L3),Customers!L3,IFERROR(VALUE(Customers!L3),""))) -> 39402.14 | M3: =IF(OR(TRIM(Customers!M3&"")="",ISNUMBER(MATCH(TRIM(Customers!M3&""),Codes!$A$5:$A$14,0))),"",IF(ISNUMBER(Customers!M3),Customers!M3,IFERROR(VALUE(Customers!M3),""))) -> 124631.07 | N3: =IF(OR(TRIM(Customers!N3&"")="",ISNUMBER(MATCH(TRIM(Customers!N3&""),Codes!$A$5:$A$14,0)),Customers!N3=9999),"",IF(ISNUMBER(Customers!N3),Customers!N3,IFERROR(VALUE(Customers!N3),""))) -> 49 | O3: =IF(OR(TRIM(Customers!O3&"")="",ISNUMBER(MATCH(TRIM(Customers!O3&""),Codes!$A$5:$A$14,0))),"",IF(ISNUMBER(Customers!O3),Customers!O3,IFERROR(VALUE(Customers!O3),""))) -> 65.95 | P3: =IF(OR(TRIM(Customers!P3&"")="",ISNUMBER(MATCH(TRIM(Customers!P3&""),Codes!$A$5:$A$14,0))),"",IF(ISNUMBER(Customers!P3),Customers!P3,IFERROR(VALUE(Customers!P3),""))) -> 1 | Q3: =IF(OR(TRIM(Customers!Q3&"")="",ISNUMBER(MATCH(TRIM(Customers!Q3&""),Codes!$A$5:$A$14,0))),"",IF(ISNUMBER(Customers!Q3),Customers!Q3,IFERROR(VALUE(Customers!Q3),""))) -> 15000 | R3: =IF(OR(TRIM(Customers!R3&"")="",ISNUMBER(MATCH(TRIM(Customers!R3&""),Codes!$A$5:$A$14,0))),"",IF(ISNUMBER(Customers!R3),Customers!R3,IFERROR(VALUE(Customers!R3),""))) -> 3434.25 | S3: =IF(OR(TRIM(Customers!S3&"")="",ISNUMBER(MATCH(TRIM(Customers!S3&""),Codes!$A$5:$A$14,0))),"",IF(ISNUMBER(Customers!S3),Customers!S3,IFERROR(VALUE(Customers!S3),""))) -> 0 | T3: =IF(OR(TRIM(Customers!T3&"")="",ISNUMBER(MATCH(TRIM(Customers!T3&""),Codes!$A$5:$A$14,0))),"",IF(ISNUMBER(Customers!T3),Customers!T3,IFERROR(VALUE(Customers!T3),""))) -> 0 | U3: =IF(OR(TRIM(Customers!U3&"")="",ISNUMBER(MATCH(TRIM(Customers!U3&""),Codes!$A$5:$A$14,0)),Customers!U3=0),"",IF(ISNUMBER(Customers!U3),Customers!U3,IFERROR(VALUE(Customers!U3),""))) -> 700 | V3: =IF(OR(TRIM(Customers!V3&"")="",ISNUMBER(MATCH(TRIM(Customers!V3&""),Codes!$A$5:$A$14,0))),"",IF(ISNUMBER(Customers!V3),Customers!V3,IFERROR(VALUE(Customers!V3),"")))
A4: =Customers!A4 -> CL00003 | B4: =IF(OR(TRIM(Customers!B4&"")="",ISNUMBER(MATCH(TRIM(Customers!B4&""),Codes!$A$5:$A$14,0)),Customers!B4=0),"",IF(ISNUMBER(Customers!B4),Customers!B4,IFERROR(VALUE(Customers!B4),""))) -> 42 | C4: =IF(OR(TRIM(Customers!C4&"")="",ISNUMBER(MATCH(TRIM(Customers!C4&""),Codes!$A$5:$A$14,0))),"",TRIM(Customers!C4)) -> F | D4: =IF(OR(TRIM(Customers!D4&"")="",ISNUMBER(MATCH(TRIM(Customers!D4&""),Codes!$A$5:$A$14,0))),"",TRIM(Customers!D4)) -> Molise | E4: =IF(OR(TRIM(Customers!E4&"")="",ISNUMBER(MATCH(TRIM(Customers!E4&""),Codes!$A$5:$A$14,0))),"",TRIM(Customers!E4)) -> Business owner | F4: =IF(OR(TRIM(Customers!F4&"")="",ISNUMBER(MATCH(TRIM(Customers!F4&""),Codes!$A$5:$A$14,0))),"",TRIM(Customers!F4)) -> Married | G4: =IF(OR(TRIM(Customers!G4&"")="",ISNUMBER(MATCH(TRIM(Customers!G4&""),Codes!$A$5:$A$14,0)),Customers!G4=-999),"",IF(ISNUMBER(Customers!G4),Customers!G4,IFERROR(VALUE(Customers!G4),""))) -> 55600 | H4: =IF(OR(TRIM(Customers!H4&"")="",ISNUMBER(MATCH(TRIM(Customers!H4&""),Codes!$A$5:$A$14,0))),"",IF(ISNUMBER(Customers!H4),Customers!H4,IFERROR(VALUE(Customers!H4),""))) -> 11 | I4: =IF(OR(TRIM(Customers!I4&"")="",ISNUMBER(MATCH(TRIM(Customers!I4&""),Codes!$A$5:$A$14,0)),Customers!I4=DATE(1970,1,1)),"",IF(ISNUMBER(Customers!I4),Customers!I4,IFERROR(DATEVALUE(Customers!I4),""))) -> 41985 | J4: =IF(OR(TRIM(Customers!J4&"")="",ISNUMBER(MATCH(TRIM(Customers!J4&""),Codes!$A$5:$A$14,0))),"",TRIM(Customers!J4)) -> App | K4: =IF(OR(TRIM(Customers!K4&"")="",ISNUMBER(MATCH(TRIM(Customers!K4&""),Codes!$A$5:$A$14,0))),"",IF(ISNUMBER(Customers!K4),Customers!K4,IFERROR(VALUE(Customers!K4),""))) -> 2 | L4: =IF(OR(TRIM(Customers!L4&"")="",ISNUMBER(MATCH(TRIM(Customers!L4&""),Codes!$A$5:$A$14,0))),"",IF(ISNUMBER(Customers!L4),Customers!L4,IFERROR(VALUE(Customers!L4),""))) -> 2962.55 | M4: =IF(OR(TRIM(Customers!M4&"")="",ISNUMBER(MATCH(TRIM(Customers!M4&""),Codes!$A$5:$A$14,0))),"",IF(ISNUMBER(Customers!M4),Customers!M4,IFERROR(VALUE(Customers!M4),""))) -> 70371.89 | N4: =IF(OR(TRIM(Customers!N4&"")="",ISNUMBER(MATCH(TRIM(Customers!N4&""),Codes!$A$5:$A$14,0)),Customers!N4=9999),"",IF(ISNUMBER(Customers!N4),Customers!N4,IFERROR(VALUE(Customers!N4),""))) -> 33 | O4: =IF(OR(TRIM(Customers!O4&"")="",ISNUMBER(MATCH(TRIM(Customers!O4&""),Codes!$A$5:$A$14,0))),"",IF(ISNUMBER(Customers!O4),Customers!O4,IFERROR(VALUE(Customers!O4),""))) -> 85.29 | P4: =IF(OR(TRIM(Customers!P4&"")="",ISNUMBER(MATCH(TRIM(Customers!P4&""),Codes!$A$5:$A$14,0))),"",IF(ISNUMBER(Customers!P4),Customers!P4,IFERROR(VALUE(Customers!P4),""))) -> 1 | Q4: =IF(OR(TRIM(Customers!Q4&"")="",ISNUMBER(MATCH(TRIM(Customers!Q4&""),Codes!$A$5:$A$14,0))),"",IF(ISNUMBER(Customers!Q4),Customers!Q4,IFERROR(VALUE(Customers!Q4),""))) -> 11000 | R4: =IF(OR(TRIM(Customers!R4&"")="",ISNUMBER(MATCH(TRIM(Customers!R4&""),Codes!$A$5:$A$14,0))),"",IF(ISNUMBER(Customers!R4),Customers!R4,IFERROR(VALUE(Customers!R4),""))) -> 3647.56 | S4: =IF(OR(TRIM(Customers!S4&"")="",ISNUMBER(MATCH(TRIM(Customers!S4&""),Codes!$A$5:$A$14,0))),"",IF(ISNUMBER(Customers!S4),Customers!S4,IFERROR(VALUE(Customers!S4),""))) | T4: =IF(OR(TRIM(Customers!T4&"")="",ISNUMBER(MATCH(TRIM(Customers!T4&""),Codes!$A$5:$A$14,0))),"",IF(ISNUMBER(Customers!T4),Customers!T4,IFERROR(VALUE(Customers!T4),""))) | U4: =IF(OR(TRIM(Customers!U4&"")="",ISNUMBER(MATCH(TRIM(Customers!U4&""),Codes!$A$5:$A$14,0)),Customers!U4=0),"",IF(ISNUMBER(Customers!U4),Customers!U4,IFERROR(VALUE(Customers!U4),""))) -> 749 | V4: =IF(OR(TRIM(Customers!V4&"")="",ISNUMBER(MATCH(TRIM(Customers!V4&""),Codes!$A$5:$A$14,0))),"",IF(ISNUMBER(Customers!V4),Customers!V4,IFERROR(VALUE(Customers!V4),"")))
A5: =Customers!A5 -> CL00004 | B5: =IF(OR(TRIM(Customers!B5&"")="",ISNUMBER(MATCH(TRIM(Customers!B5&""),Codes!$A$5:$A$14,0)),Customers!B5=0),"",IF(ISNUMBER(Customers!B5),Customers!B5,IFERROR(VALUE(Customers!B5),""))) -> 44 | C5: =IF(OR(TRIM(Customers!C5&"")="",ISNUMBER(MATCH(TRIM(Customers!C5&""),Codes!$A$5:$A$14,0))),"",TRIM(Customers!C5)) -> F | D5: =IF(OR(TRIM(Customers!D5&"")="",ISNUMBER(MATCH(TRIM(Customers!D5&""),Codes!$A$5:$A$14,0))),"",TRIM(Customers!D5)) -> Umbria | E5: =IF(OR(TRIM(Customers!E5&"")="",ISNUMBER(MATCH(TRIM(Customers!E5&""),Codes!$A$5:$A$14,0))),"",TRIM(Customers!E5)) -> Employee | F5: =IF(OR(TRIM(Customers!F5&"")="",ISNUMBER(MATCH(TRIM(Customers!F5&""),Codes!$A$5:$A$14,0))),"",TRIM(Customers!F5)) -> Single | G5: =IF(OR(TRIM(Customers!G5&"")="",ISNUMBER(MATCH(TRIM(Customers!G5&""),Codes!$A$5:$A$14,0)),Customers!G5=-999),"",IF(ISNUMBER(Customers!G5),Customers!G5,IFERROR(VALUE(Customers!G5),""))) -> 30200 | H5: =IF(OR(TRIM(Customers!H5&"")="",ISNUMBER(MATCH(TRIM(Customers!H5&""),Codes!$A$5:$A$14,0))),"",IF(ISNUMBER(Customers!H5),Customers!H5,IFERROR(VALUE(Customers!H5),""))) -> 13 | I5: =IF(OR(TRIM(Customers!I5&"")="",ISNUMBER(MATCH(TRIM(Customers!I5&""),Codes!$A$5:$A$14,0)),Customers!I5=DATE(1970,1,1)),"",IF(ISNUMBER(Customers!I5),Customers!I5,IFERROR(DATEVALUE(Customers!I5),""))) -> 41353 | J5: =IF(OR(TRIM(Customers!J5&"")="",ISNUMBER(MATCH(TRIM(Customers!J5&""),Codes!$A$5:$A$14,0))),"",TRIM(Customers!J5)) -> App | K5: =IF(OR(TRIM(Customers!K5&"")="",ISNUMBER(MATCH(TRIM(Customers!K5&""),Codes!$A$5:$A$14,0))),"",IF(ISNUMBER(Customers!K5),Customers!K5,IFERROR(VALUE(Customers!K5),""))) -> 2 | L5: =IF(OR(TRIM(Customers!L5&"")="",ISNUMBER(MATCH(TRIM(Customers!L5&""),Codes!$A$5:$A$14,0))),"",IF(ISNUMBER(Customers!L5),Customers!L5,IFERROR(VALUE(Customers!L5),""))) -> 3055.07 | M5: =IF(OR(TRIM(Customers!M5&"")="",ISNUMBER(MATCH(TRIM(Customers!M5&""),Codes!$A$5:$A$14,0))),"",IF(ISNUMBER(Customers!M5),Customers!M5,IFERROR(VALUE(Customers!M5),""))) -> 31571.98 | N5: =IF(OR(TRIM(Customers!N5&"")="",ISNUMBER(MATCH(TRIM(Customers!N5&""),Codes!$A$5:$A$14,0)),Customers!N5=9999),"",IF(ISNUMBER(Customers!N5),Customers!N5,IFERROR(VALUE(Customers!N5),""))) -> 17 | O5: =IF(OR(TRIM(Customers!O5&"")="",ISNUMBER(MATCH(TRIM(Customers!O5&""),Codes!$A$5:$A$14,0))),"",IF(ISNUMBER(Customers!O5),Customers!O5,IFERROR(VALUE(Customers!O5),""))) -> 30.81 | P5: =IF(OR(TRIM(Customers!P5&"")="",ISNUMBER(MATCH(TRIM(Customers!P5&""),Codes!$A$5:$A$14,0))),"",IF(ISNUMBER(Customers!P5),Customers!P5,IFERROR(VALUE(Customers!P5),""))) -> 1 | Q5: =IF(OR(TRIM(Customers!Q5&"")="",ISNUMBER(MATCH(TRIM(Customers!Q5&""),Codes!$A$5:$A$14,0))),"",IF(ISNUMBER(Customers!Q5),Customers!Q5,IFERROR(VALUE(Customers!Q5),""))) -> 6000 | R5: =IF(OR(TRIM(Customers!R5&"")="",ISNUMBER(MATCH(TRIM(Customers!R5&""),Codes!$A$5:$A$14,0))),"",IF(ISNUMBER(Customers!R5),Customers!R5,IFERROR(VALUE(Customers!R5),""))) -> 2242.95 | S5: =IF(OR(TRIM(Customers!S5&"")="",ISNUMBER(MATCH(TRIM(Customers!S5&""),Codes!$A$5:$A$14,0))),"",IF(ISNUMBER(Customers!S5),Customers!S5,IFERROR(VALUE(Customers!S5),""))) -> 0 | T5: =IF(OR(TRIM(Customers!T5&"")="",ISNUMBER(MATCH(TRIM(Customers!T5&""),Codes!$A$5:$A$14,0))),"",IF(ISNUMBER(Customers!T5),Customers!T5,IFERROR(VALUE(Customers!T5),""))) -> 0 | U5: =IF(OR(TRIM(Customers!U5&"")="",ISNUMBER(MATCH(TRIM(Customers!U5&""),Codes!$A$5:$A$14,0)),Customers!U5=0),"",IF(ISNUMBER(Customers!U5),Customers!U5,IFERROR(VALUE(Customers!U5),""))) -> 601 | V5: =IF(OR(TRIM(Customers!V5&"")="",ISNUMBER(MATCH(TRIM(Customers!V5&""),Codes!$A$5:$A$14,0))),"",IF(ISNUMBER(Customers!V5),Customers!V5,IFERROR(VALUE(Customers!V5),""))) -> 0
A6: =Customers!A6 -> CL00005 | B6: =IF(OR(TRIM(Customers!B6&"")="",ISNUMBER(MATCH(TRIM(Customers!B6&""),Codes!$A$5:$A$14,0)),Customers!B6=0),"",IF(ISNUMBER(Customers!B6),Customers!B6,IFERROR(VALUE(Customers!B6),""))) -> 68 | C6: =IF(OR(TRIM(Customers!C6&"")="",ISNUMBER(MATCH(TRIM(Customers!C6&""),Codes!$A$5:$A$14,0))),"",TRIM(Customers!C6)) -> F | D6: =IF(OR(TRIM(Customers!D6&"")="",ISNUMBER(MATCH(TRIM(Customers!D6&""),Codes!$A$5:$A$14,0))),"",TRIM(Customers!D6)) -> Lombardia | E6: =IF(OR(TRIM(Customers!E6&"")="",ISNUMBER(MATCH(TRIM(Customers!E6&""),Codes!$A$5:$A$14,0))),"",TRIM(Customers!E6)) -> Retired | F6: =IF(OR(TRIM(Customers!F6&"")="",ISNUMBER(MATCH(TRIM(Customers!F6&""),Codes!$A$5:$A$14,0))),"",TRIM(Customers!F6)) -> Married | G6: =IF(OR(TRIM(Customers!G6&"")="",ISNUMBER(MATCH(TRIM(Customers!G6&""),Codes!$A$5:$A$14,0)),Customers!G6=-999),"",IF(ISNUMBER(Customers!G6),Customers!G6,IFERROR(VALUE(Customers!G6),""))) -> 21800 | H6: =IF(OR(TRIM(Customers!H6&"")="",ISNUMBER(MATCH(TRIM(Customers!H6&""),Codes!$A$5:$A$14,0))),"",IF(ISNUMBER(Customers!H6),Customers!H6,IFERROR(VALUE(Customers!H6),""))) -> 8 | I6: =IF(OR(TRIM(Customers!I6&"")="",ISNUMBER(MATCH(TRIM(Customers!I6&""),Codes!$A$5:$A$14,0)),Customers!I6=DATE(1970,1,1)),"",IF(ISNUMBER(Customers!I6),Customers!I6,IFERROR(DATEVALUE(Customers!I6),""))) -> 43047 | J6: =IF(OR(TRIM(Customers!J6&"")="",ISNUMBER(MATCH(TRIM(Customers!J6&""),Codes!$A$5:$A$14,0))),"",TRIM(Customers!J6)) -> Phone | K6: =IF(OR(TRIM(Customers!K6&"")="",ISNUMBER(MATCH(TRIM(Customers!K6&""),Codes!$A$5:$A$14,0))),"",IF(ISNUMBER(Customers!K6),Customers!K6,IFERROR(VALUE(Customers!K6),""))) -> 1 | L6: =IF(OR(TRIM(Customers!L6&"")="",ISNUMBER(MATCH(TRIM(Customers!L6&""),Codes!$A$5:$A$14,0))),"",IF(ISNUMBER(Customers!L6),Customers!L6,IFERROR(VALUE(Customers!L6),""))) -> 1554.39 | M6: =IF(OR(TRIM(Customers!M6&"")="",ISNUMBER(MATCH(TRIM(Customers!M6&""),Codes!$A$5:$A$14,0))),"",IF(ISNUMBER(Customers!M6),Customers!M6,IFERROR(VALUE(Customers!M6),""))) -> 27565.84 | N6: =IF(OR(TRIM(Customers!N6&"")="",ISNUMBER(MATCH(TRIM(Customers!N6&""),Codes!$A$5:$A$14,0)),Customers!N6=9999),"",IF(ISNUMBER(Customers!N6),Customers!N6,IFERROR(VALUE(Customers!N6),""))) -> 24 | O6: =IF(OR(TRIM(Customers!O6&"")="",ISNUMBER(MATCH(TRIM(Customers!O6&""),Codes!$A$5:$A$14,0))),"",IF(ISNUMBER(Customers!O6),Customers!O6,IFERROR(VALUE(Customers!O6),""))) -> 29.47 | P6: =IF(OR(TRIM(Customers!P6&"")="",ISNUMBER(MATCH(TRIM(Customers!P6&""),Codes!$A$5:$A$14,0))),"",IF(ISNUMBER(Customers!P6),Customers!P6,IFERROR(VALUE(Customers!P6),""))) -> 4 | Q6: =IF(OR(TRIM(Customers!Q6&"")="",ISNUMBER(MATCH(TRIM(Customers!Q6&""),Codes!$A$5:$A$14,0))),"",IF(ISNUMBER(Customers!Q6),Customers!Q6,IFERROR(VALUE(Customers!Q6),""))) -> 5000 | R6: =IF(OR(TRIM(Customers!R6&"")="",ISNUMBER(MATCH(TRIM(Customers!R6&""),Codes!$A$5:$A$14,0))),"",IF(ISNUMBER(Customers!R6),Customers!R6,IFERROR(VALUE(Customers!R6),""))) -> 1312.86 | S6: =IF(OR(TRIM(Customers!S6&"")="",ISNUMBER(MATCH(TRIM(Customers!S6&""),Codes!$A$5:$A$14,0))),"",IF(ISNUMBER(Customers!S6),Customers!S6,IFERROR(VALUE(Customers!S6),""))) | T6: =IF(OR(TRIM(Customers!T6&"")="",ISNUMBER(MATCH(TRIM(Customers!T6&""),Codes!$A$5:$A$14,0))),"",IF(ISNUMBER(Customers!T6),Customers!T6,IFERROR(VALUE(Customers!T6),""))) | U6: =IF(OR(TRIM(Customers!U6&"")="",ISNUMBER(MATCH(TRIM(Customers!U6&""),Codes!$A$5:$A$14,0)),Customers!U6=0),"",IF(ISNUMBER(Customers!U6),Customers!U6,IFERROR(VALUE(Customers!U6),""))) -> 568 | V6: =IF(OR(TRIM(Customers!V6&"")="",ISNUMBER(MATCH(TRIM(Customers!V6&""),Codes!$A$5:$A$14,0))),"",IF(ISNUMBER(Customers!V6),Customers!V6,IFERROR(VALUE(Customers!V6),""))) -> 1
A7: =Customers!A7 -> CL00006 | B7: =IF(OR(TRIM(Customers!B7&"")="",ISNUMBER(MATCH(TRIM(Customers!B7&""),Codes!$A$5:$A$14,0)),Customers!B7=0),"",IF(ISNUMBER(Customers!B7),Customers!B7,IFERROR(VALUE(Customers!B7),""))) -> 56 | C7: =IF(OR(TRIM(Customers!C7&"")="",ISNUMBER(MATCH(TRIM(Customers!C7&""),Codes!$A$5:$A$14,0))),"",TRIM(Customers!C7)) -> F | D7: =IF(OR(TRIM(Customers!D7&"")="",ISNUMBER(MATCH(TRIM(Customers!D7&""),Codes!$A$5:$A$14,0))),"",TRIM(Customers!D7)) -> Sardegna | E7: =IF(OR(TRIM(Customers!E7&"")="",ISNUMBER(MATCH(TRIM(Customers!E7&""),Codes!$A$5:$A$14,0))),"",TRIM(Customers!E7)) -> Shopkeeper | F7: =IF(OR(TRIM(Customers!F7&"")="",ISNUMBER(MATCH(TRIM(Customers!F7&""),Codes!$A$5:$A$14,0))),"",TRIM(Customers!F7)) -> Married | G7: =IF(OR(TRIM(Customers!G7&"")="",ISNUMBER(MATCH(TRIM(Customers!G7&""),Codes!$A$5:$A$14,0)),Customers!G7=-999),"",IF(ISNUMBER(Customers!G7),Customers!G7,IFERROR(VALUE(Customers!G7),""))) -> 42300 | H7: =IF(OR(TRIM(Customers!H7&"")="",ISNUMBER(MATCH(TRIM(Customers!H7&""),Codes!$A$5:$A$14,0))),"",IF(ISNUMBER(Customers!H7),Customers!H7,IFERROR(VALUE(Customers!H7),""))) -> 25 | I7: =IF(OR(TRIM(Customers!I7&"")="",ISNUMBER(MATCH(TRIM(Customers!I7&""),Codes!$A$5:$A$14,0)),Customers!I7=DATE(1970,1,1)),"",IF(ISNUMBER(Customers!I7),Customers!I7,IFERROR(DATEVALUE(Customers!I7),""))) -> 36979 | J7: =IF(OR(TRIM(Customers!J7&"")="",ISNUMBER(MATCH(TRIM(Customers!J7&""),Codes!$A$5:$A$14,0))),"",TRIM(Customers!J7)) -> Branch | K7: =IF(OR(TRIM(Customers!K7&"")="",ISNUMBER(MATCH(TRIM(Customers!K7&""),Codes!$A$5:$A$14,0))),"",IF(ISNUMBER(Customers!K7),Customers!K7,IFERROR(VALUE(Customers!K7),""))) -> 2 | L7: =IF(OR(TRIM(Customers!L7&"")="",ISNUMBER(MATCH(TRIM(Customers!L7&""),Codes!$A$5:$A$14,0))),"",IF(ISNUMBER(Customers!L7),Customers!L7,IFERROR(VALUE(Customers!L7),""))) -> 879.82 | M7: =IF(OR(TRIM(Customers!M7&"")="",ISNUMBER(MATCH(TRIM(Customers!M7&""),Codes!$A$5:$A$14,0))),"",IF(ISNUMBER(Customers!M7),Customers!M7,IFERROR(VALUE(Customers!M7),""))) | N7: =IF(OR(TRIM(Customers!N7&"")="",ISNUMBER(MATCH(TRIM(Customers!N7&""),Codes!$A$5:$A$14,0)),Customers!N7=9999),"",IF(ISNUMBER(Customers!N7),Customers!N7,IFERROR(VALUE(Customers!N7),""))) -> 34 | O7: =IF(OR(TRIM(Customers!O7&"")="",ISNUMBER(MATCH(TRIM(Customers!O7&""),Codes!$A$5:$A$14,0))),"",IF(ISNUMBER(Customers!O7),Customers!O7,IFERROR(VALUE(Customers!O7),""))) -> 90.6 | P7: =IF(OR(TRIM(Customers!P7&"")="",ISNUMBER(MATCH(TRIM(Customers!P7&""),Codes!$A$5:$A$14,0))),"",IF(ISNUMBER(Customers!P7),Customers!P7,IFERROR(VALUE(Customers!P7),""))) -> 4 | Q7: =IF(OR(TRIM(Customers!Q7&"")="",ISNUMBER(MATCH(TRIM(Customers!Q7&""),Codes!$A$5:$A$14,0))),"",IF(ISNUMBER(Customers!Q7),Customers!Q7,IFERROR(VALUE(Customers!Q7),""))) -> 4500 | R7: =IF(OR(TRIM(Customers!R7&"")="",ISNUMBER(MATCH(TRIM(Customers!R7&""),Codes!$A$5:$A$14,0))),"",IF(ISNUMBER(Customers!R7),Customers!R7,IFERROR(VALUE(Customers!R7),""))) -> 1699.41 | S7: =IF(OR(TRIM(Customers!S7&"")="",ISNUMBER(MATCH(TRIM(Customers!S7&""),Codes!$A$5:$A$14,0))),"",IF(ISNUMBER(Customers!S7),Customers!S7,IFERROR(VALUE(Customers!S7),""))) -> 0 | T7: =IF(OR(TRIM(Customers!T7&"")="",ISNUMBER(MATCH(TRIM(Customers!T7&""),Codes!$A$5:$A$14,0))),"",IF(ISNUMBER(Customers!T7),Customers!T7,IFERROR(VALUE(Customers!T7),""))) -> 0 | U7: =IF(OR(TRIM(Customers!U7&"")="",ISNUMBER(MATCH(TRIM(Customers!U7&""),Codes!$A$5:$A$14,0)),Customers!U7=0),"",IF(ISNUMBER(Customers!U7),Customers!U7,IFERROR(VALUE(Customers!U7),""))) -> 618 | V7: =IF(OR(TRIM(Customers!V7&"")="",ISNUMBER(MATCH(TRIM(Customers!V7&""),Codes!$A$5:$A$14,0))),"",IF(ISNUMBER(Customers!V7),Customers!V7,IFERROR(VALUE(Customers!V7),""))) -> 2
A8: =Customers!A8 -> CL00007 | B8: =IF(OR(TRIM(Customers!B8&"")="",ISNUMBER(MATCH(TRIM(Customers!B8&""),Codes!$A$5:$A$14,0)),Customers!B8=0),"",IF(ISNUMBER(Customers!B8),Customers!B8,IFERROR(VALUE(Customers!B8),""))) -> 67 | C8: =IF(OR(TRIM(Customers!C8&"")="",ISNUMBER(MATCH(TRIM(Customers!C8&""),Codes!$A$5:$A$14,0))),"",TRIM(Customers!C8)) -> F | D8: =IF(OR(TRIM(Customers!D8&"")="",ISNUMBER(MATCH(TRIM(Customers!D8&""),Codes!$A$5:$A$14,0))),"",TRIM(Customers!D8)) -> Lombardia | E8: =IF(OR(TRIM(Customers!E8&"")="",ISNUMBER(MATCH(TRIM(Customers!E8&""),Codes!$A$5:$A$14,0))),"",TRIM(Customers!E8)) -> Retired | F8: =IF(OR(TRIM(Customers!F8&"")="",ISNUMBER(MATCH(TRIM(Customers!F8&""),Codes!$A$5:$A$14,0))),"",TRIM(Customers!F8)) -> Married | G8: =IF(OR(TRIM(Customers!G8&"")="",ISNUMBER(MATCH(TRIM(Customers!G8&""),Codes!$A$5:$A$14,0)),Customers!G8=-999),"",IF(ISNUMBER(Customers!G8),Customers!G8,IFERROR(VALUE(Customers!G8),""))) -> 28300 | H8: =IF(OR(TRIM(Customers!H8&"")="",ISNUMBER(MATCH(TRIM(Customers!H8&""),Codes!$A$5:$A$14,0))),"",IF(ISNUMBER(Customers!H8),Customers!H8,IFERROR(VALUE(Customers!H8),""))) -> 2 | I8: =IF(OR(TRIM(Customers!I8&"")="",ISNUMBER(MATCH(TRIM(Customers!I8&""),Codes!$A$5:$A$14,0)),Customers!I8=DATE(1970,1,1)),"",IF(ISNUMBER(Customers!I8),Customers!I8,IFERROR(DATEVALUE(Customers!I8),""))) -> 45278 | J8: =IF(OR(TRIM(Customers!J8&"")="",ISNUMBER(MATCH(TRIM(Customers!J8&""),Codes!$A$5:$A$14,0))),"",TRIM(Customers!J8)) -> Online Banking | K8: =IF(OR(TRIM(Customers!K8&"")="",ISNUMBER(MATCH(TRIM(Customers!K8&""),Codes!$A$5:$A$14,0))),"",IF(ISNUMBER(Customers!K8),Customers!K8,IFERROR(VALUE(Customers!K8),""))) -> 2 | L8: =IF(OR(TRIM(Customers!L8&"")="",ISNUMBER(MATCH(TRIM(Customers!L8&""),Codes!$A$5:$A$14,0))),"",IF(ISNUMBER(Customers!L8),Customers!L8,IFERROR(VALUE(Customers!L8),""))) -> 6616.63 | M8: =IF(OR(TRIM(Customers!M8&"")="",ISNUMBER(MATCH(TRIM(Customers!M8&""),Codes!$A$5:$A$14,0))),"",IF(ISNUMBER(Customers!M8),Customers!M8,IFERROR(VALUE(Customers!M8),""))) -> 2752.06 | N8: =IF(OR(TRIM(Customers!N8&"")="",ISNUMBER(MATCH(TRIM(Customers!N8&""),Codes!$A$5:$A$14,0)),Customers!N8=9999),"",IF(ISNUMBER(Customers!N8),Customers!N8,IFERROR(VALUE(Customers!N8),""))) -> 30 | O8: =IF(OR(TRIM(Customers!O8&"")="",ISNUMBER(MATCH(TRIM(Customers!O8&""),Codes!$A$5:$A$14,0))),"",IF(ISNUMBER(Customers!O8),Customers!O8,IFERROR(VALUE(Customers!O8),""))) -> 76 | P8: =IF(OR(TRIM(Customers!P8&"")="",ISNUMBER(MATCH(TRIM(Customers!P8&""),Codes!$A$5:$A$14,0))),"",IF(ISNUMBER(Customers!P8),Customers!P8,IFERROR(VALUE(Customers!P8),""))) -> 2 | Q8: =IF(OR(TRIM(Customers!Q8&"")="",ISNUMBER(MATCH(TRIM(Customers!Q8&""),Codes!$A$5:$A$14,0))),"",IF(ISNUMBER(Customers!Q8),Customers!Q8,IFERROR(VALUE(Customers!Q8),""))) -> 4000 | R8: =IF(OR(TRIM(Customers!R8&"")="",ISNUMBER(MATCH(TRIM(Customers!R8&""),Codes!$A$5:$A$14,0))),"",IF(ISNUMBER(Customers!R8),Customers!R8,IFERROR(VALUE(Customers!R8),""))) -> 2532.26 | S8: =IF(OR(TRIM(Customers!S8&"")="",ISNUMBER(MATCH(TRIM(Customers!S8&""),Codes!$A$5:$A$14,0))),"",IF(ISNUMBER(Customers!S8),Customers!S8,IFERROR(VALUE(Customers!S8),""))) | T8: =IF(OR(TRIM(Customers!T8&"")="",ISNUMBER(MATCH(TRIM(Customers!T8&""),Codes!$A$5:$A$14,0))),"",IF(ISNUMBER(Customers!T8),Customers!T8,IFERROR(VALUE(Customers!T8),""))) | U8: =IF(OR(TRIM(Customers!U8&"")="",ISNUMBER(MATCH(TRIM(Customers!U8&""),Codes!$A$5:$A$14,0)),Customers!U8=0),"",IF(ISNUMBER(Customers!U8),Customers!U8,IFERROR(VALUE(Customers!U8),""))) -> 666 | V8: =IF(OR(TRIM(Customers!V8&"")="",ISNUMBER(MATCH(TRIM(Customers!V8&""),Codes!$A$5:$A$14,0))),"",IF(ISNUMBER(Customers!V8),Customers!V8,IFERROR(VALUE(Customers!V8),"")))
A9: =Customers!A9 -> CL00008 | B9: =IF(OR(TRIM(Customers!B9&"")="",ISNUMBER(MATCH(TRIM(Customers!B9&""),Codes!$A$5:$A$14,0)),Customers!B9=0),"",IF(ISNUMBER(Customers!B9),Customers!B9,IFERROR(VALUE(Customers!B9),""))) -> 43 | C9: =IF(OR(TRIM(Customers!C9&"")="",ISNUMBER(MATCH(TRIM(Customers!C9&""),Codes!$A$5:$A$14,0))),"",TRIM(Customers!C9)) -> M | D9: =IF(OR(TRIM(Customers!D9&"")="",ISNUMBER(MATCH(TRIM(Customers!D9&""),Codes!$A$5:$A$14,0))),"",TRIM(Customers!D9)) -> Calabria | E9: =IF(OR(TRIM(Customers!E9&"")="",ISNUMBER(MATCH(TRIM(Customers!E9&""),Codes!$A$5:$A$14,0))),"",TRIM(Customers!E9)) -> Teacher | F9: =IF(OR(TRIM(Customers!F9&"")="",ISNUMBER(MATCH(TRIM(Customers!F9&""),Codes!$A$5:$A$14,0))),"",TRIM(Customers!F9)) -> Married | G9: =IF(OR(TRIM(Customers!G9&"")="",ISNUMBER(MATCH(TRIM(Customers!G9&""),Codes!$A$5:$A$14,0)),Customers!G9=-999),"",IF(ISNUMBER(Customers!G9),Customers!G9,IFERROR(VALUE(Customers!G9),""))) -> 28300 | H9: =IF(OR(TRIM(Customers!H9&"")="",ISNUMBER(MATCH(TRIM(Customers!H9&""),Codes!$A$5:$A$14,0))),"",IF(ISNUMBER(Customers!H9),Customers!H9,IFERROR(VALUE(Customers!H9),""))) -> 10 | I9: =IF(OR(TRIM(Customers!I9&"")="",ISNUMBER(MATCH(TRIM(Customers!I9&""),Codes!$A$5:$A$14,0)),Customers!I9=DATE(1970,1,1)),"",IF(ISNUMBER(Customers!I9),Customers!I9,IFERROR(DATEVALUE(Customers!I9),""))) -> 42273 | J9: =IF(OR(TRIM(Customers!J9&"")="",ISNUMBER(MATCH(TRIM(Customers!J9&""),Codes!$A$5:$A$14,0))),"",TRIM(Customers!J9)) -> App | K9: =IF(OR(TRIM(Customers!K9&"")="",ISNUMBER(MATCH(TRIM(Customers!K9&""),Codes!$A$5:$A$14,0))),"",IF(ISNUMBER(Customers!K9),Customers!K9,IFERROR(VALUE(Customers!K9),""))) -> 4 | L9: =IF(OR(TRIM(Customers!L9&"")="",ISNUMBER(MATCH(TRIM(Customers!L9&""),Codes!$A$5:$A$14,0))),"",IF(ISNUMBER(Customers!L9),Customers!L9,IFERROR(VALUE(Customers!L9),""))) -> -56.68 | M9: =IF(OR(TRIM(Customers!M9&"")="",ISNUMBER(MATCH(TRIM(Customers!M9&""),Codes!$A$5:$A$14,0))),"",IF(ISNUMBER(Customers!M9),Customers!M9,IFERROR(VALUE(Customers!M9),""))) -> 28860.26 | N9: =IF(OR(TRIM(Customers!N9&"")="",ISNUMBER(MATCH(TRIM(Customers!N9&""),Codes!$A$5:$A$14,0)),Customers!N9=9999),"",IF(ISNUMBER(Customers!N9),Customers!N9,IFERROR(VALUE(Customers!N9),""))) -> 23 | O9: =IF(OR(TRIM(Customers!O9&"")="",ISNUMBER(MATCH(TRIM(Customers!O9&""),Codes!$A$5:$A$14,0))),"",IF(ISNUMBER(Customers!O9),Customers!O9,IFERROR(VALUE(Customers!O9),""))) -> 49.11 | P9: =IF(OR(TRIM(Customers!P9&"")="",ISNUMBER(MATCH(TRIM(Customers!P9&""),Codes!$A$5:$A$14,0))),"",IF(ISNUMBER(Customers!P9),Customers!P9,IFERROR(VALUE(Customers!P9),""))) -> 3 | Q9: =IF(OR(TRIM(Customers!Q9&"")="",ISNUMBER(MATCH(TRIM(Customers!Q9&""),Codes!$A$5:$A$14,0))),"",IF(ISNUMBER(Customers!Q9),Customers!Q9,IFERROR(VALUE(Customers!Q9),""))) -> 3000 | R9: =IF(OR(TRIM(Customers!R9&"")="",ISNUMBER(MATCH(TRIM(Customers!R9&""),Codes!$A$5:$A$14,0))),"",IF(ISNUMBER(Customers!R9),Customers!R9,IFERROR(VALUE(Customers!R9),""))) -> 363.95 | S9: =IF(OR(TRIM(Customers!S9&"")="",ISNUMBER(MATCH(TRIM(Customers!S9&""),Codes!$A$5:$A$14,0))),"",IF(ISNUMBER(Customers!S9),Customers!S9,IFERROR(VALUE(Customers!S9),""))) -> 49000 | T9: =IF(OR(TRIM(Customers!T9&"")="",ISNUMBER(MATCH(TRIM(Customers!T9&""),Codes!$A$5:$A$14,0))),"",IF(ISNUMBER(Customers!T9),Customers!T9,IFERROR(VALUE(Customers!T9),""))) -> 228 | U9: =IF(OR(TRIM(Customers!U9&"")="",ISNUMBER(MATCH(TRIM(Customers!U9&""),Codes!$A$5:$A$14,0)),Customers!U9=0),"",IF(ISNUMBER(Customers!U9),Customers!U9,IFERROR(VALUE(Customers!U9),""))) -> 544 | V9: =IF(OR(TRIM(Customers!V9&"")="",ISNUMBER(MATCH(TRIM(Customers!V9&""),Codes!$A$5:$A$14,0))),"",IF(ISNUMBER(Customers!V9),Customers!V9,IFERROR(VALUE(Customers!V9),""))) -> 1
A10: =Customers!A10 -> CL00009 | B10: =IF(OR(TRIM(Customers!B10&"")="",ISNUMBER(MATCH(TRIM(Customers!B10&""),Codes!$A$5:$A$14,0)),Customers!B10=0),"",IF(ISNUMBER(Customers!B10),Customers!B10,IFERROR(VALUE(Customers!B10),""))) -> 25 | C10: =IF(OR(TRIM(Customers!C10&"")="",ISNUMBER(MATCH(TRIM(Customers!C10&""),Codes!$A$5:$A$14,0))),"",TRIM(Customers!C10)) -> M | D10: =IF(OR(TRIM(Customers!D10&"")="",ISNUMBER(MATCH(TRIM(Customers!D10&""),Codes!$A$5:$A$14,0))),"",TRIM(Customers!D10)) -> Campania | E10: =IF(OR(TRIM(Customers!E10&"")="",ISNUMBER(MATCH(TRIM(Customers!E10&""),Codes!$A$5:$A$14,0))),"",TRIM(Customers!E10)) -> Manual worker | F10: =IF(OR(TRIM(Customers!F10&"")="",ISNUMBER(MATCH(TRIM(Customers!F10&""),Codes!$A$5:$A$14,0))),"",TRIM(Customers!F10)) | G10: =IF(OR(TRIM(Customers!G10&"")="",ISNUMBER(MATCH(TRIM(Customers!G10&""),Codes!$A$5:$A$14,0)),Customers!G10=-999),"",IF(ISNUMBER(Customers!G10),Customers!G10,IFERROR(VALUE(Customers!G10),""))) -> 17700 | H10: =IF(OR(TRIM(Customers!H10&"")="",ISNUMBER(MATCH(TRIM(Customers!H10&""),Codes!$A$5:$A$14,0))),"",IF(ISNUMBER(Customers!H10),Customers!H10,IFERROR(VALUE(Customers!H10),""))) -> 3 | I10: =IF(OR(TRIM(Customers!I10&"")="",ISNUMBER(MATCH(TRIM(Customers!I10&""),Codes!$A$5:$A$14,0)),Customers!I10=DATE(1970,1,1)),"",IF(ISNUMBER(Customers!I10),Customers!I10,IFERROR(DATEVALUE(Customers!I10),""))) -> 45141 | J10: =IF(OR(TRIM(Customers!J10&"")="",ISNUMBER(MATCH(TRIM(Customers!J10&""),Codes!$A$5:$A$14,0))),"",TRIM(Customers!J10)) -> Online Banking | K10: =IF(OR(TRIM(Customers!K10&"")="",ISNUMBER(MATCH(TRIM(Customers!K10&""),Codes!$A$5:$A$14,0))),"",IF(ISNUMBER(Customers!K10),Customers!K10,IFERROR(VALUE(Customers!K10),""))) -> 2 | L10: =IF(OR(TRIM(Customers!L10&"")="",ISNUMBER(MATCH(TRIM(Customers!L10&""),Codes!$A$5:$A$14,0))),"",IF(ISNUMBER(Customers!L10),Customers!L10,IFERROR(VALUE(Customers!L10),""))) -> 795.78 | M10: =IF(OR(TRIM(Customers!M10&"")="",ISNUMBER(MATCH(TRIM(Customers!M10&""),Codes!$A$5:$A$14,0))),"",IF(ISNUMBER(Customers!M10),Customers!M10,IFERROR(VALUE(Customers!M10),""))) -> 8855.03 | N10: =IF(OR(TRIM(Customers!N10&"")="",ISNUMBER(MATCH(TRIM(Customers!N10&""),Codes!$A$5:$A$14,0)),Customers!N10=9999),"",IF(ISNUMBER(Customers!N10),Customers!N10,IFERROR(VALUE(Customers!N10),""))) -> 25 | O10: =IF(OR(TRIM(Customers!O10&"")="",ISNUMBER(MATCH(TRIM(Customers!O10&""),Codes!$A$5:$A$14,0))),"",IF(ISNUMBER(Customers!O10),Customers!O10,IFERROR(VALUE(Customers!O10),""))) -> 32.4 | P10: =IF(OR(TRIM(Customers!P10&"")="",ISNUMBER(MATCH(TRIM(Customers!P10&""),Codes!$A$5:$A$14,0))),"",IF(ISNUMBER(Customers!P10),Customers!P10,IFERROR(VALUE(Customers!P10),""))) -> 3 | Q10: =IF(OR(TRIM(Customers!Q10&"")="",ISNUMBER(MATCH(TRIM(Customers!Q10&""),Codes!$A$5:$A$14,0))),"",IF(ISNUMBER(Customers!Q10),Customers!Q10,IFERROR(VALUE(Customers!Q10),""))) -> 0 | R10: =IF(OR(TRIM(Customers!R10&"")="",ISNUMBER(MATCH(TRIM(Customers!R10&""),Codes!$A$5:$A$14,0))),"",IF(ISNUMBER(Customers!R10),Customers!R10,IFERROR(VALUE(Customers!R10),""))) -> 0 | S10: =IF(OR(TRIM(Customers!S10&"")="",ISNUMBER(MATCH(TRIM(Customers!S10&""),Codes!$A$5:$A$14,0))),"",IF(ISNUMBER(Customers!S10),Customers!S10,IFERROR(VALUE(Customers!S10),""))) -> 0 | T10: =IF(OR(TRIM(Customers!T10&"")="",ISNUMBER(MATCH(TRIM(Customers!T10&""),Codes!$A$5:$A$14,0))),"",IF(ISNUMBER(Customers!T10),Customers!T10,IFERROR(VALUE(Customers!T10),""))) -> 0 | U10: =IF(OR(TRIM(Customers!U10&"")="",ISNUMBER(MATCH(TRIM(Customers!U10&""),Codes!$A$5:$A$14,0)),Customers!U10=0),"",IF(ISNUMBER(Customers!U10),Customers!U10,IFERROR(VALUE(Customers!U10),""))) -> 536 | V10: =IF(OR(TRIM(Customers!V10&"")="",ISNUMBER(MATCH(TRIM(Customers!V10&""),Codes!$A$5:$A$14,0))),"",IF(ISNUMBER(Customers!V10),Customers!V10,IFERROR(VALUE(Customers!V10),""))) -> 0
A11: =Customers!A11 -> CL00010 | B11: =IF(OR(TRIM(Customers!B11&"")="",ISNUMBER(MATCH(TRIM(Customers!B11&""),Codes!$A$5:$A$14,0)),Customers!B11=0),"",IF(ISNUMBER(Customers!B11),Customers!B11,IFERROR(VALUE(Customers!B11),""))) -> 36 | C11: =IF(OR(TRIM(Customers!C11&"")="",ISNUMBER(MATCH(TRIM(Customers!C11&""),Codes!$A$5:$A$14,0))),"",TRIM(Customers!C11)) -> M | D11: =IF(OR(TRIM(Customers!D11&"")="",ISNUMBER(MATCH(TRIM(Customers!D11&""),Codes!$A$5:$A$14,0))),"",TRIM(Customers!D11)) -> Piemonte | E11: =IF(OR(TRIM(Customers!E11&"")="",ISNUMBER(MATCH(TRIM(Customers!E11&""),Codes!$A$5:$A$14,0))),"",TRIM(Customers!E11)) -> Employee | F11: =IF(OR(TRIM(Customers!F11&"")="",ISNUMBER(MATCH(TRIM(Customers!F11&""),Codes!$A$5:$A$14,0))),"",TRIM(Customers!F11)) -> Single | G11: =IF(OR(TRIM(Customers!G11&"")="",ISNUMBER(MATCH(TRIM(Customers!G11&""),Codes!$A$5:$A$14,0)),Customers!G11=-999),"",IF(ISNUMBER(Customers!G11),Customers!G11,IFERROR(VALUE(Customers!G11),""))) -> 32600 | H11: =IF(OR(TRIM(Customers!H11&"")="",ISNUMBER(MATCH(TRIM(Customers!H11&""),Codes!$A$5:$A$14,0))),"",IF(ISNUMBER(Customers!H11),Customers!H11,IFERROR(VALUE(Customers!H11),""))) -> 7 | I11: =IF(OR(TRIM(Customers!I11&"")="",ISNUMBER(MATCH(TRIM(Customers!I11&""),Codes!$A$5:$A$14,0)),Customers!I11=DATE(1970,1,1)),"",IF(ISNUMBER(Customers!I11),Customers!I11,IFERROR(DATEVALUE(Customers!I11),""))) -> 43377 | J11: =IF(OR(TRIM(Customers!J11&"")="",ISNUMBER(MATCH(TRIM(Customers!J11&""),Codes!$A$5:$A$14,0))),"",TRIM(Customers!J11)) -> App | K11: =IF(OR(TRIM(Customers!K11&"")="",ISNUMBER(MATCH(TRIM(Customers!K11&""),Codes!$A$5:$A$14,0))),"",IF(ISNUMBER(Customers!K11),Customers!K11,IFERROR(VALUE(Customers!K11),""))) -> 1 | L11: =IF(OR(TRIM(Customers!L11&"")="",ISNUMBER(MATCH(TRIM(Customers!L11&""),Codes!$A$5:$A$14,0))),"",IF(ISNUMBER(Customers!L11),Customers!L11,IFERROR(VALUE(Customers!L11),""))) -> -244.9 | M11: =IF(OR(TRIM(Customers!M11&"")="",ISNUMBER(MATCH(TRIM(Customers!M11&""),Codes!$A$5:$A$14,0))),"",IF(ISNUMBER(Customers!M11),Customers!M11,IFERROR(VALUE(Customers!M11),""))) -> 0 | N11: =IF(OR(TRIM(Customers!N11&"")="",ISNUMBER(MATCH(TRIM(Customers!N11&""),Codes!$A$5:$A$14,0)),Customers!N11=9999),"",IF(ISNUMBER(Customers!N11),Customers!N11,IFERROR(VALUE(Customers!N11),""))) -> 33 | O11: =IF(OR(TRIM(Customers!O11&"")="",ISNUMBER(MATCH(TRIM(Customers!O11&""),Codes!$A$5:$A$14,0))),"",IF(ISNUMBER(Customers!O11),Customers!O11,IFERROR(VALUE(Customers!O11),""))) -> 68.04 | P11: =IF(OR(TRIM(Customers!P11&"")="",ISNUMBER(MATCH(TRIM(Customers!P11&""),Codes!$A$5:$A$14,0))),"",IF(ISNUMBER(Customers!P11),Customers!P11,IFERROR(VALUE(Customers!P11),""))) -> 0 | Q11: =IF(OR(TRIM(Customers!Q11&"")="",ISNUMBER(MATCH(TRIM(Customers!Q11&""),Codes!$A$5:$A$14,0))),"",IF(ISNUMBER(Customers!Q11),Customers!Q11,IFERROR(VALUE(Customers!Q11),""))) -> 6000 | R11: =IF(OR(TRIM(Customers!R11&"")="",ISNUMBER(MATCH(TRIM(Customers!R11&""),Codes!$A$5:$A$14,0))),"",IF(ISNUMBER(Customers!R11),Customers!R11,IFERROR(VALUE(Customers!R11),""))) -> 1052.22 | S11: =IF(OR(TRIM(Customers!S11&"")="",ISNUMBER(MATCH(TRIM(Customers!S11&""),Codes!$A$5:$A$14,0))),"",IF(ISNUMBER(Customers!S11),Customers!S11,IFERROR(VALUE(Customers!S11),""))) -> 0 | T11: =IF(OR(TRIM(Customers!T11&"")="",ISNUMBER(MATCH(TRIM(Customers!T11&""),Codes!$A$5:$A$14,0))),"",IF(ISNUMBER(Customers!T11),Customers!T11,IFERROR(VALUE(Customers!T11),""))) -> 0 | U11: =IF(OR(TRIM(Customers!U11&"")="",ISNUMBER(MATCH(TRIM(Customers!U11&""),Codes!$A$5:$A$14,0)),Customers!U11=0),"",IF(ISNUMBER(Customers!U11),Customers!U11,IFERROR(VALUE(Customers!U11),""))) -> 662 | V11: =IF(OR(TRIM(Customers!V11&"")="",ISNUMBER(MATCH(TRIM(Customers!V11&""),Codes!$A$5:$A$14,0))),"",IF(ISNUMBER(Customers!V11),Customers!V11,IFERROR(VALUE(Customers!V11),"")))
A12: =Customers!A12 -> CL00011 | B12: =IF(OR(TRIM(Customers!B12&"")="",ISNUMBER(MATCH(TRIM(Customers!B12&""),Codes!$A$5:$A$14,0)),Customers!B12=0),"",IF(ISNUMBER(Customers!B12),Customers!B12,IFERROR(VALUE(Customers!B12),""))) -> 60 | C12: =IF(OR(TRIM(Customers!C12&"")="",ISNUMBER(MATCH(TRIM(Customers!C12&""),Codes!$A$5:$A$14,0))),"",TRIM(Customers!C12)) -> M | D12: =IF(OR(TRIM(Customers!D12&"")="",ISNUMBER(MATCH(TRIM(Customers!D12&""),Codes!$A$5:$A$14,0))),"",TRIM(Customers!D12)) -> Veneto | E12: =IF(OR(TRIM(Customers!E12&"")="",ISNUMBER(MATCH(TRIM(Customers!E12&""),Codes!$A$5:$A$14,0))),"",TRIM(Customers!E12)) -> Business owner | F12: =IF(OR(TRIM(Customers!F12&"")="",ISNUMBER(MATCH(TRIM(Customers!F12&""),Codes!$A$5:$A$14,0))),"",TRIM(Customers!F12)) -> Married | G12: =IF(OR(TRIM(Customers!G12&"")="",ISNUMBER(MATCH(TRIM(Customers!G12&""),Codes!$A$5:$A$14,0)),Customers!G12=-999),"",IF(ISNUMBER(Customers!G12),Customers!G12,IFERROR(VALUE(Customers!G12),""))) -> 105900 | H12: =IF(OR(TRIM(Customers!H12&"")="",ISNUMBER(MATCH(TRIM(Customers!H12&""),Codes!$A$5:$A$14,0))),"",IF(ISNUMBER(Customers!H12),Customers!H12,IFERROR(VALUE(Customers!H12),""))) -> 21 | I12: =IF(OR(TRIM(Customers!I12&"")="",ISNUMBER(MATCH(TRIM(Customers!I12&""),Codes!$A$5:$A$14,0)),Customers!I12=DATE(1970,1,1)),"",IF(ISNUMBER(Customers!I12),Customers!I12,IFERROR(DATEVALUE(Customers!I12),""))) -> 38567 | J12: =IF(OR(TRIM(Customers!J12&"")="",ISNUMBER(MATCH(TRIM(Customers!J12&""),Codes!$A$5:$A$14,0))),"",TRIM(Customers!J12)) -> Online Banking | K12: =IF(OR(TRIM(Customers!K12&"")="",ISNUMBER(MATCH(TRIM(Customers!K12&""),Codes!$A$5:$A$14,0))),"",IF(ISNUMBER(Customers!K12),Customers!K12,IFERROR(VALUE(Customers!K12),""))) -> 2 | L12: =IF(OR(TRIM(Customers!L12&"")="",ISNUMBER(MATCH(TRIM(Customers!L12&""),Codes!$A$5:$A$14,0))),"",IF(ISNUMBER(Customers!L12),Customers!L12,IFERROR(VALUE(Customers!L12),""))) -> 8804.34 | M12: =IF(OR(TRIM(Customers!M12&"")="",ISNUMBER(MATCH(TRIM(Customers!M12&""),Codes!$A$5:$A$14,0))),"",IF(ISNUMBER(Customers!M12),Customers!M12,IFERROR(VALUE(Customers!M12),""))) -> 0 | N12: =IF(OR(TRIM(Customers!N12&"")="",ISNUMBER(MATCH(TRIM(Customers!N12&""),Codes!$A$5:$A$14,0)),Customers!N12=9999),"",IF(ISNUMBER(Customers!N12),Customers!N12,IFERROR(VALUE(Customers!N12),""))) -> 59 | O12: =IF(OR(TRIM(Customers!O12&"")="",ISNUMBER(MATCH(TRIM(Customers!O12&""),Codes!$A$5:$A$14,0))),"",IF(ISNUMBER(Customers!O12),Customers!O12,IFERROR(VALUE(Customers!O12),""))) -> 87.83 | P12: =IF(OR(TRIM(Customers!P12&"")="",ISNUMBER(MATCH(TRIM(Customers!P12&""),Codes!$A$5:$A$14,0))),"",IF(ISNUMBER(Customers!P12),Customers!P12,IFERROR(VALUE(Customers!P12),""))) -> 5 | Q12: =IF(OR(TRIM(Customers!Q12&"")="",ISNUMBER(MATCH(TRIM(Customers!Q12&""),Codes!$A$5:$A$14,0))),"",IF(ISNUMBER(Customers!Q12),Customers!Q12,IFERROR(VALUE(Customers!Q12),""))) -> 15000 | R12: =IF(OR(TRIM(Customers!R12&"")="",ISNUMBER(MATCH(TRIM(Customers!R12&""),Codes!$A$5:$A$14,0))),"",IF(ISNUMBER(Customers!R12),Customers!R12,IFERROR(VALUE(Customers!R12),""))) -> 6697.75 | S12: =IF(OR(TRIM(Customers!S12&"")="",ISNUMBER(MATCH(TRIM(Customers!S12&""),Codes!$A$5:$A$14,0))),"",IF(ISNUMBER(Customers!S12),Customers!S12,IFERROR(VALUE(Customers!S12),""))) -> 0 | T12: =IF(OR(TRIM(Customers!T12&"")="",ISNUMBER(MATCH(TRIM(Customers!T12&""),Codes!$A$5:$A$14,0))),"",IF(ISNUMBER(Customers!T12),Customers!T12,IFERROR(VALUE(Customers!T12),""))) -> 0 | U12: =IF(OR(TRIM(Customers!U12&"")="",ISNUMBER(MATCH(TRIM(Customers!U12&""),Codes!$A$5:$A$14,0)),Customers!U12=0),"",IF(ISNUMBER(Customers!U12),Customers!U12,IFERROR(VALUE(Customers!U12),""))) -> 703 | V12: =IF(OR(TRIM(Customers!V12&"")="",ISNUMBER(MATCH(TRIM(Customers!V12&""),Codes!$A$5:$A$14,0))),"",IF(ISNUMBER(Customers!V12),Customers!V12,IFERROR(VALUE(Customers!V12),""))) -> 0
A13: =Customers!A13 -> CL00012 | B13: =IF(OR(TRIM(Customers!B13&"")="",ISNUMBER(MATCH(TRIM(Customers!B13&""),Codes!$A$5:$A$14,0)),Customers!B13=0),"",IF(ISNUMBER(Customers!B13),Customers!B13,IFERROR(VALUE(Customers!B13),""))) -> 45 | C13: =IF(OR(TRIM(Customers!C13&"")="",ISNUMBER(MATCH(TRIM(Customers!C13&""),Codes!$A$5:$A$14,0))),"",TRIM(Customers!C13)) -> F | D13: =IF(OR(TRIM(Customers!D13&"")="",ISNUMBER(MATCH(TRIM(Customers!D13&""),Codes!$A$5:$A$14,0))),"",TRIM(Customers!D13)) -> Piemonte | E13: =IF(OR(TRIM(Customers!E13&"")="",ISNUMBER(MATCH(TRIM(Customers!E13&""),Codes!$A$5:$A$14,0))),"",TRIM(Customers!E13)) -> Employee | F13: =IF(OR(TRIM(Customers!F13&"")="",ISNUMBER(MATCH(TRIM(Customers!F13&""),Codes!$A$5:$A$14,0))),"",TRIM(Customers!F13)) -> Married | G13: =IF(OR(TRIM(Customers!G13&"")="",ISNUMBER(MATCH(TRIM(Customers!G13&""),Codes!$A$5:$A$14,0)),Customers!G13=-999),"",IF(ISNUMBER(Customers!G13),Customers!G13,IFERROR(VALUE(Customers!G13),""))) -> 49600 | H13: =IF(OR(TRIM(Customers!H13&"")="",ISNUMBER(MATCH(TRIM(Customers!H13&""),Codes!$A$5:$A$14,0))),"",IF(ISNUMBER(Customers!H13),Customers!H13,IFERROR(VALUE(Customers!H13),""))) -> 15 | I13: =IF(OR(TRIM(Customers!I13&"")="",ISNUMBER(MATCH(TRIM(Customers!I13&""),Codes!$A$5:$A$14,0)),Customers!I13=DATE(1970,1,1)),"",IF(ISNUMBER(Customers!I13),Customers!I13,IFERROR(DATEVALUE(Customers!I13),""))) -> 40620 | J13: =IF(OR(TRIM(Customers!J13&"")="",ISNUMBER(MATCH(TRIM(Customers!J13&""),Codes!$A$5:$A$14,0))),"",TRIM(Customers!J13)) -> App | K13: =IF(OR(TRIM(Customers!K13&"")="",ISNUMBER(MATCH(TRIM(Customers!K13&""),Codes!$A$5:$A$14,0))),"",IF(ISNUMBER(Customers!K13),Customers!K13,IFERROR(VALUE(Customers!K13),""))) -> 4 | L13: =IF(OR(TRIM(Customers!L13&"")="",ISNUMBER(MATCH(TRIM(Customers!L13&""),Codes!$A$5:$A$14,0))),"",IF(ISNUMBER(Customers!L13),Customers!L13,IFERROR(VALUE(Customers!L13),""))) | M13: =IF(OR(TRIM(Customers!M13&"")="",ISNUMBER(MATCH(TRIM(Customers!M13&""),Codes!$A$5:$A$14,0))),"",IF(ISNUMBER(Customers!M13),Customers!M13,IFERROR(VALUE(Customers!M13),""))) -> 0 | N13: =IF(OR(TRIM(Customers!N13&"")="",ISNUMBER(MATCH(TRIM(Customers!N13&""),Codes!$A$5:$A$14,0)),Customers!N13=9999),"",IF(ISNUMBER(Customers!N13),Customers!N13,IFERROR(VALUE(Customers!N13),""))) -> 30 | O13: =IF(OR(TRIM(Customers!O13&"")="",ISNUMBER(MATCH(TRIM(Customers!O13&""),Codes!$A$5:$A$14,0))),"",IF(ISNUMBER(Customers!O13),Customers!O13,IFERROR(VALUE(Customers!O13),""))) -> 69.35 | P13: =IF(OR(TRIM(Customers!P13&"")="",ISNUMBER(MATCH(TRIM(Customers!P13&""),Codes!$A$5:$A$14,0))),"",IF(ISNUMBER(Customers!P13),Customers!P13,IFERROR(VALUE(Customers!P13),""))) -> 1 | Q13: =IF(OR(TRIM(Customers!Q13&"")="",ISNUMBER(MATCH(TRIM(Customers!Q13&""),Codes!$A$5:$A$14,0))),"",IF(ISNUMBER(Customers!Q13),Customers!Q13,IFERROR(VALUE(Customers!Q13),""))) -> 5000 | R13: =IF(OR(TRIM(Customers!R13&"")="",ISNUMBER(MATCH(TRIM(Customers!R13&""),Codes!$A$5:$A$14,0))),"",IF(ISNUMBER(Customers!R13),Customers!R13,IFERROR(VALUE(Customers!R13),""))) -> 1097.89 | S13: =IF(OR(TRIM(Customers!S13&"")="",ISNUMBER(MATCH(TRIM(Customers!S13&""),Codes!$A$5:$A$14,0))),"",IF(ISNUMBER(Customers!S13),Customers!S13,IFERROR(VALUE(Customers!S13),""))) -> 0 | T13: =IF(OR(TRIM(Customers!T13&"")="",ISNUMBER(MATCH(TRIM(Customers!T13&""),Codes!$A$5:$A$14,0))),"",IF(ISNUMBER(Customers!T13),Customers!T13,IFERROR(VALUE(Customers!T13),""))) -> 0 | U13: =IF(OR(TRIM(Customers!U13&"")="",ISNUMBER(MATCH(TRIM(Customers!U13&""),Codes!$A$5:$A$14,0)),Customers!U13=0),"",IF(ISNUMBER(Customers!U13),Customers!U13,IFERROR(VALUE(Customers!U13),""))) -> 679 | V13: =IF(OR(TRIM(Customers!V13&"")="",ISNUMBER(MATCH(TRIM(Customers!V13&""),Codes!$A$5:$A$14,0))),"",IF(ISNUMBER(Customers!V13),Customers!V13,IFERROR(VALUE(Customers!V13),""))) -> 0
... A1001: =Customers!A1001 -> CL01000 | B1001: =IF(OR(TRIM(Customers!B1001&"")="",ISNUMBER(MATCH(TRIM(Customers!B1001&""),Codes!$A$5:$A$14,0)),Customers!B1001=0),"",IF(ISNUMBER(Customers!B1001),Customers!B1001,IFERROR(VALUE(Customers!B1001),""))) -> 59 | C1001: =IF(OR(TRIM(Customers!C1001&"")="",ISNUMBER(MATCH(TRIM(Customers!C1001&""),Codes!$A$5:$A$14,0))),"",TRIM(Customers!C1001)) -> F | D1001: =IF(OR(TRIM(Customers!D1001&"")="",ISNUMBER(MATCH(TRIM(Customers!D1001&""),Codes!$A$5:$A$14,0))),"",TRIM(Customers!D1001)) -> Lazio | E1001: =IF(OR(TRIM(Customers!E1001&"")="",ISNUMBER(MATCH(TRIM(Customers!E1001&""),Codes!$A$5:$A$14,0))),"",TRIM(Customers!E1001)) | F1001: =IF(OR(TRIM(Customers!F1001&"")="",ISNUMBER(MATCH(TRIM(Customers!F1001&""),Codes!$A$5:$A$14,0))),"",TRIM(Customers!F1001)) -> Married | G1001: =IF(OR(TRIM(Customers!G1001&"")="",ISNUMBER(MATCH(TRIM(Customers!G1001&""),Codes!$A$5:$A$14,0)),Customers!G1001=-999),"",IF(ISNUMBER(Customers!G1001),Customers!G1001,IFERROR(VALUE(Customers!G1001),""))) -> 30900 | H1001: =IF(OR(TRIM(Customers!H1001&"")="",ISNUMBER(MATCH(TRIM(Customers!H1001&""),Codes!$A$5:$A$14,0))),"",IF(ISNUMBER(Customers!H1001),Customers!H1001,IFERROR(VALUE(Customers!H1001),""))) -> 23 | I1001: =IF(OR(TRIM(Customers!I1001&"")="",ISNUMBER(MATCH(TRIM(Customers!I1001&""),Codes!$A$5:$A$14,0)),Customers!I1001=DATE(1970,1,1)),"",IF(ISNUMBER(Customers!I1001),Customers!I1001,IFERROR(DATEVALUE(Customers!I1001),""))) -> 37735 | J1001: =IF(OR(TRIM(Customers!J1001&"")="",ISNUMBER(MATCH(TRIM(Customers!J1001&""),Codes!$A$5:$A$14,0))),"",TRIM(Customers!J1001)) -> Branch | K1001: =IF(OR(TRIM(Customers!K1001&"")="",ISNUMBER(MATCH(TRIM(Customers!K1001&""),Codes!$A$5:$A$14,0))),"",IF(ISNUMBER(Customers!K1001),Customers!K1001,IFERROR(VALUE(Customers!K1001),""))) -> 3 | L1001: =IF(OR(TRIM(Customers!L1001&"")="",ISNUMBER(MATCH(TRIM(Customers!L1001&""),Codes!$A$5:$A$14,0))),"",IF(ISNUMBER(Customers!L1001),Customers!L1001,IFERROR(VALUE(Customers!L1001),""))) -> 1873.36 | M1001: =IF(OR(TRIM(Customers!M1001&"")="",ISNUMBER(MATCH(TRIM(Customers!M1001&""),Codes!$A$5:$A$14,0))),"",IF(ISNUMBER(Customers!M1001),Customers!M1001,IFERROR(VALUE(Customers!M1001),""))) -> 36369.97 | N1001: =IF(OR(TRIM(Customers!N1001&"")="",ISNUMBER(MATCH(TRIM(Customers!N1001&""),Codes!$A$5:$A$14,0)),Customers!N1001=9999),"",IF(ISNUMBER(Customers!N1001),Customers!N1001,IFERROR(VALUE(Customers!N1001),""))) -> 15 | O1001: =IF(OR(TRIM(Customers!O1001&"")="",ISNUMBER(MATCH(TRIM(Customers!O1001&""),Codes!$A$5:$A$14,0))),"",IF(ISNUMBER(Customers!O1001),Customers!O1001,IFERROR(VALUE(Customers!O1001),""))) -> 28.77 | P1001: =IF(OR(TRIM(Customers!P1001&"")="",ISNUMBER(MATCH(TRIM(Customers!P1001&""),Codes!$A$5:$A$14,0))),"",IF(ISNUMBER(Customers!P1001),Customers!P1001,IFERROR(VALUE(Customers!P1001),""))) -> 5 | Q1001: =IF(OR(TRIM(Customers!Q1001&"")="",ISNUMBER(MATCH(TRIM(Customers!Q1001&""),Codes!$A$5:$A$14,0))),"",IF(ISNUMBER(Customers!Q1001),Customers!Q1001,IFERROR(VALUE(Customers!Q1001),""))) -> 7500 | R1001: =IF(OR(TRIM(Customers!R1001&"")="",ISNUMBER(MATCH(TRIM(Customers!R1001&""),Codes!$A$5:$A$14,0))),"",IF(ISNUMBER(Customers!R1001),Customers!R1001,IFERROR(VALUE(Customers!R1001),""))) -> 711.51 | S1001: =IF(OR(TRIM(Customers!S1001&"")="",ISNUMBER(MATCH(TRIM(Customers!S1001&""),Codes!$A$5:$A$14,0))),"",IF(ISNUMBER(Customers!S1001),Customers!S1001,IFERROR(VALUE(Customers!S1001),""))) -> 52000 | T1001: =IF(OR(TRIM(Customers!T1001&"")="",ISNUMBER(MATCH(TRIM(Customers!T1001&""),Codes!$A$5:$A$14,0))),"",IF(ISNUMBER(Customers!T1001),Customers!T1001,IFERROR(VALUE(Customers!T1001),""))) -> 363 | U1001: =IF(OR(TRIM(Customers!U1001&"")="",ISNUMBER(MATCH(TRIM(Customers!U1001&""),Codes!$A$5:$A$14,0)),Customers!U1001=0),"",IF(ISNUMBER(Customers!U1001),Customers!U1001,IFERROR(VALUE(Customers!U1001),""))) -> 683 | V1001: =IF(OR(TRIM(Customers!V1001&"")="",ISNUMBER(MATCH(TRIM(Customers!V1001&""),Codes!$A$5:$A$14,0))),"",IF(ISNUMBER(Customers!V1001),Customers!V1001,IFERROR(VALUE(Customers!V1001),""))) -> 1

Sheet Imputed
A1: Customer_ID | B1: Age (clean) | C1: Age → median | D1: Age missing flag | E1: Occupation (clean) | F1: Occupation → 'Unknown' | G1: Income (clean) | H1: Income → mean | I1: Income → median | J1: Income → group median by Occupation | K1: Income missing flag | L1: Tenure (clean) | M1: Open date (clean) | N1: Tenure → derived from date | O1: Tenure source | P1: Savings (clean) | Q1: Savings → median | R1: Savings missing flag | S1: Credit score (clean) | T1: Credit score → mean | U1: Channel (clean) | V1: Channel → mode | W1: Channel → 'Unknown' | X1: Card limit (clean) | Y1: Card spend (clean) | Z1: Card limit → handled | AA1: Card spend → handled (limit × ratio) | AB1: Card status | AC1: Mortgage balance (clean) | AD1: Mortgage payment (clean) | AE1: Mortgage balance → handled | AF1: Mortgage payment → handled (balance × ratio) | AG1: Complaints (clean) | AH1: Complaints → 0 (NULL means 0) | AI1: Complaints missing flag | AJ1: Missing cells in row | AK1: Listwise deletion (all 21 columns) | AL1: Listwise deletion (8 model columns)
A2: =Clean!A2 -> CL00001 | B2: =Clean!B2 -> 57 | C2: =IF(B2="",Strategies!$B$5,B2) -> 57 | D2: =IF(B2="",1,0) -> 0 | E2: =Clean!E2 -> Shopkeeper | F2: =IF(E2="","Unknown",E2) -> Shopkeeper | G2: =Clean!G2 -> 30100 | H2: =IF(G2="",Strategies!$B$7,G2) -> 30100 | I2: =IF(G2="",Strategies!$B$8,G2) -> 30100 | J2: =IF(G2="",IFERROR(VLOOKUP(E2,Strategies!$A$26:$G$35,7,FALSE()),Strategies!$B$8),G2) -> 30100 | K2: =IF(G2="",1,0) -> 0 | L2: =Clean!H2 -> 4 | M2: =Clean!I2 -> 44721 | N2: =IF(L2="",IF(M2="",Strategies!$B$6,DATEDIF(M2,DATE(2026,9,13),"y")),L2) -> 4 | O2: =IF(L2<>"","observed",IF(M2<>"","derived from date","median (fallback)")) -> observed | P2: =Clean!M2 -> 12100.75 | Q2: =IF(P2="",Strategies!$B$9,P2) -> 12100.75 | R2: =IF(P2="",1,0) -> 0 | S2: =Clean!U2 -> 698 | T2: =IF(S2="",Strategies!$B$10,S2) -> 698 | U2: =Clean!J2 -> Branch | V2: =IF(U2="",Strategies!$B$11,U2) -> Branch | W2: =IF(U2="","Unknown",U2) -> Branch | X2: =Clean!Q2 | Y2: =Clean!R2 | Z2: =IF(X2="",IF(Y2="",0,""),X2) -> 0 | AA2: =IF(Y2="",IF(X2="",0,IF(X2=0,0,ROUND(X2*Strategies!$B$12,2))),Y2) -> 0 | AB2: =IF(AND(X2="",Y2=""),"no card (structural)",IF(X2="","limit missing – verify",IF(Y2="","spend imputed by ratio","complete"))) -> no card (structural) | AC2: =Clean!S2 -> 93000 | AD2: =Clean!T2 -> 603 | AE2: =IF(AC2="",IF(AD2="",0,""),AC2) -> 93000 | AF2: =IF(AD2="",IF(AC2="",0,IF(AC2=0,0,ROUND(AC2*Strategies!$B$13,0))),AD2) -> 603 | AG2: =Clean!V2 | AH2: =IF(AG2="",0,AG2) -> 0 | AI2: =IF(AG2="",1,0) -> 1 | AJ2: =Missing_Matrix!W2 -> 3 | AK2: =IF(AJ2=0,"keep","drop") -> drop | AL2: =IF(Missing_Matrix!B2+Missing_Matrix!G2+Missing_Matrix!H2+Missing_Matrix!J2+Missing_Matrix!K2+Missing_Matrix!L2+Missing_Matrix!M2+Missing_Matrix!U2=0,"keep","drop") -> keep
A3: =Clean!A3 -> CL00002 | B3: =Clean!B3 -> 60 | C3: =IF(B3="",Strategies!$B$5,B3) -> 60 | D3: =IF(B3="",1,0) -> 0 | E3: =Clean!E3 -> Business owner | F3: =IF(E3="","Unknown",E3) -> Business owner | G3: =Clean!G3 -> 117400 | H3: =IF(G3="",Strategies!$B$7,G3) -> 117400 | I3: =IF(G3="",Strategies!$B$8,G3) -> 117400 | J3: =IF(G3="",IFERROR(VLOOKUP(E3,Strategies!$A$26:$G$35,7,FALSE()),Strategies!$B$8),G3) -> 117400 | K3: =IF(G3="",1,0) -> 0 | L3: =Clean!H3 -> 13 | M3: =Clean!I3 -> 41314 | N3: =IF(L3="",IF(M3="",Strategies!$B$6,DATEDIF(M3,DATE(2026,9,13),"y")),L3) -> 13 | O3: =IF(L3<>"","observed",IF(M3<>"","derived from date","median (fallback)")) -> observed | P3: =Clean!M3 -> 124631.07 | Q3: =IF(P3="",Strategies!$B$9,P3) -> 124631.07 | R3: =IF(P3="",1,0) -> 0 | S3: =Clean!U3 -> 700 | T3: =IF(S3="",Strategies!$B$10,S3) -> 700 | U3: =Clean!J3 -> Branch | V3: =IF(U3="",Strategies!$B$11,U3) -> Branch | W3: =IF(U3="","Unknown",U3) -> Branch | X3: =Clean!Q3 -> 15000 | Y3: =Clean!R3 -> 3434.25 | Z3: =IF(X3="",IF(Y3="",0,""),X3) -> 15000 | AA3: =IF(Y3="",IF(X3="",0,IF(X3=0,0,ROUND(X3*Strategies!$B$12,2))),Y3) -> 3434.25 | AB3: =IF(AND(X3="",Y3=""),"no card (structural)",IF(X3="","limit missing – verify",IF(Y3="","spend imputed by ratio","complete"))) -> complete | AC3: =Clean!S3 -> 0 | AD3: =Clean!T3 -> 0 | AE3: =IF(AC3="",IF(AD3="",0,""),AC3) -> 0 | AF3: =IF(AD3="",IF(AC3="",0,IF(AC3=0,0,ROUND(AC3*Strategies!$B$13,0))),AD3) -> 0 | AG3: =Clean!V3 | AH3: =IF(AG3="",0,AG3) -> 0 | AI3: =IF(AG3="",1,0) -> 1 | AJ3: =Missing_Matrix!W3 -> 1 | AK3: =IF(AJ3=0,"keep","drop") -> drop | AL3: =IF(Missing_Matrix!B3+Missing_Matrix!G3+Missing_Matrix!H3+Missing_Matrix!J3+Missing_Matrix!K3+Missing_Matrix!L3+Missing_Matrix!M3+Missing_Matrix!U3=0,"keep","drop") -> keep
A4: =Clean!A4 -> CL00003 | B4: =Clean!B4 -> 42 | C4: =IF(B4="",Strategies!$B$5,B4) -> 42 | D4: =IF(B4="",1,0) -> 0 | E4: =Clean!E4 -> Business owner | F4: =IF(E4="","Unknown",E4) -> Business owner | G4: =Clean!G4 -> 55600 | H4: =IF(G4="",Strategies!$B$7,G4) -> 55600 | I4: =IF(G4="",Strategies!$B$8,G4) -> 55600 | J4: =IF(G4="",IFERROR(VLOOKUP(E4,Strategies!$A$26:$G$35,7,FALSE()),Strategies!$B$8),G4) -> 55600 | K4: =IF(G4="",1,0) -> 0 | L4: =Clean!H4 -> 11 | M4: =Clean!I4 -> 41985 | N4: =IF(L4="",IF(M4="",Strategies!$B$6,DATEDIF(M4,DATE(2026,9,13),"y")),L4) -> 11 | O4: =IF(L4<>"","observed",IF(M4<>"","derived from date","median (fallback)")) -> observed | P4: =Clean!M4 -> 70371.89 | Q4: =IF(P4="",Strategies!$B$9,P4) -> 70371.89 | R4: =IF(P4="",1,0) -> 0 | S4: =Clean!U4 -> 749 | T4: =IF(S4="",Strategies!$B$10,S4) -> 749 | U4: =Clean!J4 -> App | V4: =IF(U4="",Strategies!$B$11,U4) -> App | W4: =IF(U4="","Unknown",U4) -> App | X4: =Clean!Q4 -> 11000 | Y4: =Clean!R4 -> 3647.56 | Z4: =IF(X4="",IF(Y4="",0,""),X4) -> 11000 | AA4: =IF(Y4="",IF(X4="",0,IF(X4=0,0,ROUND(X4*Strategies!$B$12,2))),Y4) -> 3647.56 | AB4: =IF(AND(X4="",Y4=""),"no card (structural)",IF(X4="","limit missing – verify",IF(Y4="","spend imputed by ratio","complete"))) -> complete | AC4: =Clean!S4 | AD4: =Clean!T4 | AE4: =IF(AC4="",IF(AD4="",0,""),AC4) -> 0 | AF4: =IF(AD4="",IF(AC4="",0,IF(AC4=0,0,ROUND(AC4*Strategies!$B$13,0))),AD4) -> 0 | AG4: =Clean!V4 | AH4: =IF(AG4="",0,AG4) -> 0 | AI4: =IF(AG4="",1,0) -> 1 | AJ4: =Missing_Matrix!W4 -> 3 | AK4: =IF(AJ4=0,"keep","drop") -> drop | AL4: =IF(Missing_Matrix!B4+Missing_Matrix!G4+Missing_Matrix!H4+Missing_Matrix!J4+Missing_Matrix!K4+Missing_Matrix!L4+Missing_Matrix!M4+Missing_Matrix!U4=0,"keep","drop") -> keep
A5: =Clean!A5 -> CL00004 | B5: =Clean!B5 -> 44 | C5: =IF(B5="",Strategies!$B$5,B5) -> 44 | D5: =IF(B5="",1,0) -> 0 | E5: =Clean!E5 -> Employee | F5: =IF(E5="","Unknown",E5) -> Employee | G5: =Clean!G5 -> 30200 | H5: =IF(G5="",Strategies!$B$7,G5) -> 30200 | I5: =IF(G5="",Strategies!$B$8,G5) -> 30200 | J5: =IF(G5="",IFERROR(VLOOKUP(E5,Strategies!$A$26:$G$35,7,FALSE()),Strategies!$B$8),G5) -> 30200 | K5: =IF(G5="",1,0) -> 0 | L5: =Clean!H5 -> 13 | M5: =Clean!I5 -> 41353 | N5: =IF(L5="",IF(M5="",Strategies!$B$6,DATEDIF(M5,DATE(2026,9,13),"y")),L5) -> 13 | O5: =IF(L5<>"","observed",IF(M5<>"","derived from date","median (fallback)")) -> observed | P5: =Clean!M5 -> 31571.98 | Q5: =IF(P5="",Strategies!$B$9,P5) -> 31571.98 | R5: =IF(P5="",1,0) -> 0 | S5: =Clean!U5 -> 601 | T5: =IF(S5="",Strategies!$B$10,S5) -> 601 | U5: =Clean!J5 -> App | V5: =IF(U5="",Strategies!$B$11,U5) -> App | W5: =IF(U5="","Unknown",U5) -> App | X5: =Clean!Q5 -> 6000 | Y5: =Clean!R5 -> 2242.95 | Z5: =IF(X5="",IF(Y5="",0,""),X5) -> 6000 | AA5: =IF(Y5="",IF(X5="",0,IF(X5=0,0,ROUND(X5*Strategies!$B$12,2))),Y5) -> 2242.95 | AB5: =IF(AND(X5="",Y5=""),"no card (structural)",IF(X5="","limit missing – verify",IF(Y5="","spend imputed by ratio","complete"))) -> complete | AC5: =Clean!S5 -> 0 | AD5: =Clean!T5 -> 0 | AE5: =IF(AC5="",IF(AD5="",0,""),AC5) -> 0 | AF5: =IF(AD5="",IF(AC5="",0,IF(AC5=0,0,ROUND(AC5*Strategies!$B$13,0))),AD5) -> 0 | AG5: =Clean!V5 -> 0 | AH5: =IF(AG5="",0,AG5) -> 0 | AI5: =IF(AG5="",1,0) -> 0 | AJ5: =Missing_Matrix!W5 -> 0 | AK5: =IF(AJ5=0,"keep","drop") -> keep | AL5: =IF(Missing_Matrix!B5+Missing_Matrix!G5+Missing_Matrix!H5+Missing_Matrix!J5+Missing_Matrix!K5+Missing_Matrix!L5+Missing_Matrix!M5+Missing_Matrix!U5=0,"keep","drop") -> keep
A6: =Clean!A6 -> CL00005 | B6: =Clean!B6 -> 68 | C6: =IF(B6="",Strategies!$B$5,B6) -> 68 | D6: =IF(B6="",1,0) -> 0 | E6: =Clean!E6 -> Retired | F6: =IF(E6="","Unknown",E6) -> Retired | G6: =Clean!G6 -> 21800 | H6: =IF(G6="",Strategies!$B$7,G6) -> 21800 | I6: =IF(G6="",Strategies!$B$8,G6) -> 21800 | J6: =IF(G6="",IFERROR(VLOOKUP(E6,Strategies!$A$26:$G$35,7,FALSE()),Strategies!$B$8),G6) -> 21800 | K6: =IF(G6="",1,0) -> 0 | L6: =Clean!H6 -> 8 | M6: =Clean!I6 -> 43047 | N6: =IF(L6="",IF(M6="",Strategies!$B$6,DATEDIF(M6,DATE(2026,9,13),"y")),L6) -> 8 | O6: =IF(L6<>"","observed",IF(M6<>"","derived from date","median (fallback)")) -> observed | P6: =Clean!M6 -> 27565.84 | Q6: =IF(P6="",Strategies!$B$9,P6) -> 27565.84 | R6: =IF(P6="",1,0) -> 0 | S6: =Clean!U6 -> 568 | T6: =IF(S6="",Strategies!$B$10,S6) -> 568 | U6: =Clean!J6 -> Phone | V6: =IF(U6="",Strategies!$B$11,U6) -> Phone | W6: =IF(U6="","Unknown",U6) -> Phone | X6: =Clean!Q6 -> 5000 | Y6: =Clean!R6 -> 1312.86 | Z6: =IF(X6="",IF(Y6="",0,""),X6) -> 5000 | AA6: =IF(Y6="",IF(X6="",0,IF(X6=0,0,ROUND(X6*Strategies!$B$12,2))),Y6) -> 1312.86 | AB6: =IF(AND(X6="",Y6=""),"no card (structural)",IF(X6="","limit missing – verify",IF(Y6="","spend imputed by ratio","complete"))) -> complete | AC6: =Clean!S6 | AD6: =Clean!T6 | AE6: =IF(AC6="",IF(AD6="",0,""),AC6) -> 0 | AF6: =IF(AD6="",IF(AC6="",0,IF(AC6=0,0,ROUND(AC6*Strategies!$B$13,0))),AD6) -> 0 | AG6: =Clean!V6 -> 1 | AH6: =IF(AG6="",0,AG6) -> 1 | AI6: =IF(AG6="",1,0) -> 0 | AJ6: =Missing_Matrix!W6 -> 2 | AK6: =IF(AJ6=0,"keep","drop") -> drop | AL6: =IF(Missing_Matrix!B6+Missing_Matrix!G6+Missing_Matrix!H6+Missing_Matrix!J6+Missing_Matrix!K6+Missing_Matrix!L6+Missing_Matrix!M6+Missing_Matrix!U6=0,"keep","drop") -> keep
A7: =Clean!A7 -> CL00006 | B7: =Clean!B7 -> 56 | C7: =IF(B7="",Strategies!$B$5,B7) -> 56 | D7: =IF(B7="",1,0) -> 0 | E7: =Clean!E7 -> Shopkeeper | F7: =IF(E7="","Unknown",E7) -> Shopkeeper | G7: =Clean!G7 -> 42300 | H7: =IF(G7="",Strategies!$B$7,G7) -> 42300 | I7: =IF(G7="",Strategies!$B$8,G7) -> 42300 | J7: =IF(G7="",IFERROR(VLOOKUP(E7,Strategies!$A$26:$G$35,7,FALSE()),Strategies!$B$8),G7) -> 42300 | K7: =IF(G7="",1,0) -> 0 | L7: =Clean!H7 -> 25 | M7: =Clean!I7 -> 36979 | N7: =IF(L7="",IF(M7="",Strategies!$B$6,DATEDIF(M7,DATE(2026,9,13),"y")),L7) -> 25 | O7: =IF(L7<>"","observed",IF(M7<>"","derived from date","median (fallback)")) -> observed | P7: =Clean!M7 | Q7: =IF(P7="",Strategies!$B$9,P7) -> 10652.68 | R7: =IF(P7="",1,0) -> 1 | S7: =Clean!U7 -> 618 | T7: =IF(S7="",Strategies!$B$10,S7) -> 618 | U7: =Clean!J7 -> Branch | V7: =IF(U7="",Strategies!$B$11,U7) -> Branch | W7: =IF(U7="","Unknown",U7) -> Branch | X7: =Clean!Q7 -> 4500 | Y7: =Clean!R7 -> 1699.41 | Z7: =IF(X7="",IF(Y7="",0,""),X7) -> 4500 | AA7: =IF(Y7="",IF(X7="",0,IF(X7=0,0,ROUND(X7*Strategies!$B$12,2))),Y7) -> 1699.41 | AB7: =IF(AND(X7="",Y7=""),"no card (structural)",IF(X7="","limit missing – verify",IF(Y7="","spend imputed by ratio","complete"))) -> complete | AC7: =Clean!S7 -> 0 | AD7: =Clean!T7 -> 0 | AE7: =IF(AC7="",IF(AD7="",0,""),AC7) -> 0 | AF7: =IF(AD7="",IF(AC7="",0,IF(AC7=0,0,ROUND(AC7*Strategies!$B$13,0))),AD7) -> 0 | AG7: =Clean!V7 -> 2 | AH7: =IF(AG7="",0,AG7) -> 2 | AI7: =IF(AG7="",1,0) -> 0 | AJ7: =Missing_Matrix!W7 -> 1 | AK7: =IF(AJ7=0,"keep","drop") -> drop | AL7: =IF(Missing_Matrix!B7+Missing_Matrix!G7+Missing_Matrix!H7+Missing_Matrix!J7+Missing_Matrix!K7+Missing_Matrix!L7+Missing_Matrix!M7+Missing_Matrix!U7=0,"keep","drop") -> drop
A8: =Clean!A8 -> CL00007 | B8: =Clean!B8 -> 67 | C8: =IF(B8="",Strategies!$B$5,B8) -> 67 | D8: =IF(B8="",1,0) -> 0 | E8: =Clean!E8 -> Retired | F8: =IF(E8="","Unknown",E8) -> Retired | G8: =Clean!G8 -> 28300 | H8: =IF(G8="",Strategies!$B$7,G8) -> 28300 | I8: =IF(G8="",Strategies!$B$8,G8) -> 28300 | J8: =IF(G8="",IFERROR(VLOOKUP(E8,Strategies!$A$26:$G$35,7,FALSE()),Strategies!$B$8),G8) -> 28300 | K8: =IF(G8="",1,0) -> 0 | L8: =Clean!H8 -> 2 | M8: =Clean!I8 -> 45278 | N8: =IF(L8="",IF(M8="",Strategies!$B$6,DATEDIF(M8,DATE(2026,9,13),"y")),L8) -> 2 | O8: =IF(L8<>"","observed",IF(M8<>"","derived from date","median (fallback)")) -> observed | P8: =Clean!M8 -> 2752.06 | Q8: =IF(P8="",Strategies!$B$9,P8) -> 2752.06 | R8: =IF(P8="",1,0) -> 0 | S8: =Clean!U8 -> 666 | T8: =IF(S8="",Strategies!$B$10,S8) -> 666 | U8: =Clean!J8 -> Online Banking | V8: =IF(U8="",Strategies!$B$11,U8) -> Online Banking | W8: =IF(U8="","Unknown",U8) -> Online Banking | X8: =Clean!Q8 -> 4000 | Y8: =Clean!R8 -> 2532.26 | Z8: =IF(X8="",IF(Y8="",0,""),X8) -> 4000 | AA8: =IF(Y8="",IF(X8="",0,IF(X8=0,0,ROUND(X8*Strategies!$B$12,2))),Y8) -> 2532.26 | AB8: =IF(AND(X8="",Y8=""),"no card (structural)",IF(X8="","limit missing – verify",IF(Y8="","spend imputed by ratio","complete"))) -> complete | AC8: =Clean!S8 | AD8: =Clean!T8 | AE8: =IF(AC8="",IF(AD8="",0,""),AC8) -> 0 | AF8: =IF(AD8="",IF(AC8="",0,IF(AC8=0,0,ROUND(AC8*Strategies!$B$13,0))),AD8) -> 0 | AG8: =Clean!V8 | AH8: =IF(AG8="",0,AG8) -> 0 | AI8: =IF(AG8="",1,0) -> 1 | AJ8: =Missing_Matrix!W8 -> 3 | AK8: =IF(AJ8=0,"keep","drop") -> drop | AL8: =IF(Missing_Matrix!B8+Missing_Matrix!G8+Missing_Matrix!H8+Missing_Matrix!J8+Missing_Matrix!K8+Missing_Matrix!L8+Missing_Matrix!M8+Missing_Matrix!U8=0,"keep","drop") -> keep
A9: =Clean!A9 -> CL00008 | B9: =Clean!B9 -> 43 | C9: =IF(B9="",Strategies!$B$5,B9) -> 43 | D9: =IF(B9="",1,0) -> 0 | E9: =Clean!E9 -> Teacher | F9: =IF(E9="","Unknown",E9) -> Teacher | G9: =Clean!G9 -> 28300 | H9: =IF(G9="",Strategies!$B$7,G9) -> 28300 | I9: =IF(G9="",Strategies!$B$8,G9) -> 28300 | J9: =IF(G9="",IFERROR(VLOOKUP(E9,Strategies!$A$26:$G$35,7,FALSE()),Strategies!$B$8),G9) -> 28300 | K9: =IF(G9="",1,0) -> 0 | L9: =Clean!H9 -> 10 | M9: =Clean!I9 -> 42273 | N9: =IF(L9="",IF(M9="",Strategies!$B$6,DATEDIF(M9,DATE(2026,9,13),"y")),L9) -> 10 | O9: =IF(L9<>"","observed",IF(M9<>"","derived from date","median (fallback)")) -> observed | P9: =Clean!M9 -> 28860.26 | Q9: =IF(P9="",Strategies!$B$9,P9) -> 28860.26 | R9: =IF(P9="",1,0) -> 0 | S9: =Clean!U9 -> 544 | T9: =IF(S9="",Strategies!$B$10,S9) -> 544 | U9: =Clean!J9 -> App | V9: =IF(U9="",Strategies!$B$11,U9) -> App | W9: =IF(U9="","Unknown",U9) -> App | X9: =Clean!Q9 -> 3000 | Y9: =Clean!R9 -> 363.95 | Z9: =IF(X9="",IF(Y9="",0,""),X9) -> 3000 | AA9: =IF(Y9="",IF(X9="",0,IF(X9=0,0,ROUND(X9*Strategies!$B$12,2))),Y9) -> 363.95 | AB9: =IF(AND(X9="",Y9=""),"no card (structural)",IF(X9="","limit missing – verify",IF(Y9="","spend imputed by ratio","complete"))) -> complete | AC9: =Clean!S9 -> 49000 | AD9: =Clean!T9 -> 228 | AE9: =IF(AC9="",IF(AD9="",0,""),AC9) -> 49000 | AF9: =IF(AD9="",IF(AC9="",0,IF(AC9=0,0,ROUND(AC9*Strategies!$B$13,0))),AD9) -> 228 | AG9: =Clean!V9 -> 1 | AH9: =IF(AG9="",0,AG9) -> 1 | AI9: =IF(AG9="",1,0) -> 0 | AJ9: =Missing_Matrix!W9 -> 0 | AK9: =IF(AJ9=0,"keep","drop") -> keep | AL9: =IF(Missing_Matrix!B9+Missing_Matrix!G9+Missing_Matrix!H9+Missing_Matrix!J9+Missing_Matrix!K9+Missing_Matrix!L9+Missing_Matrix!M9+Missing_Matrix!U9=0,"keep","drop") -> keep
A10: =Clean!A10 -> CL00009 | B10: =Clean!B10 -> 25 | C10: =IF(B10="",Strategies!$B$5,B10) -> 25 | D10: =IF(B10="",1,0) -> 0 | E10: =Clean!E10 -> Manual worker | F10: =IF(E10="","Unknown",E10) -> Manual worker | G10: =Clean!G10 -> 17700 | H10: =IF(G10="",Strategies!$B$7,G10) -> 17700 | I10: =IF(G10="",Strategies!$B$8,G10) -> 17700 | J10: =IF(G10="",IFERROR(VLOOKUP(E10,Strategies!$A$26:$G$35,7,FALSE()),Strategies!$B$8),G10) -> 17700 | K10: =IF(G10="",1,0) -> 0 | L10: =Clean!H10 -> 3 | M10: =Clean!I10 -> 45141 | N10: =IF(L10="",IF(M10="",Strategies!$B$6,DATEDIF(M10,DATE(2026,9,13),"y")),L10) -> 3 | O10: =IF(L10<>"","observed",IF(M10<>"","derived from date","median (fallback)")) -> observed | P10: =Clean!M10 -> 8855.03 | Q10: =IF(P10="",Strategies!$B$9,P10) -> 8855.03 | R10: =IF(P10="",1,0) -> 0 | S10: =Clean!U10 -> 536 | T10: =IF(S10="",Strategies!$B$10,S10) -> 536 | U10: =Clean!J10 -> Online Banking | V10: =IF(U10="",Strategies!$B$11,U10) -> Online Banking | W10: =IF(U10="","Unknown",U10) -> Online Banking | X10: =Clean!Q10 -> 0 | Y10: =Clean!R10 -> 0 | Z10: =IF(X10="",IF(Y10="",0,""),X10) -> 0 | AA10: =IF(Y10="",IF(X10="",0,IF(X10=0,0,ROUND(X10*Strategies!$B$12,2))),Y10) -> 0 | AB10: =IF(AND(X10="",Y10=""),"no card (structural)",IF(X10="","limit missing – verify",IF(Y10="","spend imputed by ratio","complete"))) -> complete | AC10: =Clean!S10 -> 0 | AD10: =Clean!T10 -> 0 | AE10: =IF(AC10="",IF(AD10="",0,""),AC10) -> 0 | AF10: =IF(AD10="",IF(AC10="",0,IF(AC10=0,0,ROUND(AC10*Strategies!$B$13,0))),AD10) -> 0 | AG10: =Clean!V10 -> 0 | AH10: =IF(AG10="",0,AG10) -> 0 | AI10: =IF(AG10="",1,0) -> 0 | AJ10: =Missing_Matrix!W10 -> 1 | AK10: =IF(AJ10=0,"keep","drop") -> drop | AL10: =IF(Missing_Matrix!B10+Missing_Matrix!G10+Missing_Matrix!H10+Missing_Matrix!J10+Missing_Matrix!K10+Missing_Matrix!L10+Missing_Matrix!M10+Missing_Matrix!U10=0,"keep","drop") -> keep
A11: =Clean!A11 -> CL00010 | B11: =Clean!B11 -> 36 | C11: =IF(B11="",Strategies!$B$5,B11) -> 36 | D11: =IF(B11="",1,0) -> 0 | E11: =Clean!E11 -> Employee | F11: =IF(E11="","Unknown",E11) -> Employee | G11: =Clean!G11 -> 32600 | H11: =IF(G11="",Strategies!$B$7,G11) -> 32600 | I11: =IF(G11="",Strategies!$B$8,G11) -> 32600 | J11: =IF(G11="",IFERROR(VLOOKUP(E11,Strategies!$A$26:$G$35,7,FALSE()),Strategies!$B$8),G11) -> 32600 | K11: =IF(G11="",1,0) -> 0 | L11: =Clean!H11 -> 7 | M11: =Clean!I11 -> 43377 | N11: =IF(L11="",IF(M11="",Strategies!$B$6,DATEDIF(M11,DATE(2026,9,13),"y")),L11) -> 7 | O11: =IF(L11<>"","observed",IF(M11<>"","derived from date","median (fallback)")) -> observed | P11: =Clean!M11 -> 0 | Q11: =IF(P11="",Strategies!$B$9,P11) -> 0 | R11: =IF(P11="",1,0) -> 0 | S11: =Clean!U11 -> 662 | T11: =IF(S11="",Strategies!$B$10,S11) -> 662 | U11: =Clean!J11 -> App | V11: =IF(U11="",Strategies!$B$11,U11) -> App | W11: =IF(U11="","Unknown",U11) -> App | X11: =Clean!Q11 -> 6000 | Y11: =Clean!R11 -> 1052.22 | Z11: =IF(X11="",IF(Y11="",0,""),X11) -> 6000 | AA11: =IF(Y11="",IF(X11="",0,IF(X11=0,0,ROUND(X11*Strategies!$B$12,2))),Y11) -> 1052.22 | AB11: =IF(AND(X11="",Y11=""),"no card (structural)",IF(X11="","limit missing – verify",IF(Y11="","spend imputed by ratio","complete"))) -> complete | AC11: =Clean!S11 -> 0 | AD11: =Clean!T11 -> 0 | AE11: =IF(AC11="",IF(AD11="",0,""),AC11) -> 0 | AF11: =IF(AD11="",IF(AC11="",0,IF(AC11=0,0,ROUND(AC11*Strategies!$B$13,0))),AD11) -> 0 | AG11: =Clean!V11 | AH11: =IF(AG11="",0,AG11) -> 0 | AI11: =IF(AG11="",1,0) -> 1 | AJ11: =Missing_Matrix!W11 -> 1 | AK11: =IF(AJ11=0,"keep","drop") -> drop | AL11: =IF(Missing_Matrix!B11+Missing_Matrix!G11+Missing_Matrix!H11+Missing_Matrix!J11+Missing_Matrix!K11+Missing_Matrix!L11+Missing_Matrix!M11+Missing_Matrix!U11=0,"keep","drop") -> keep
A12: =Clean!A12 -> CL00011 | B12: =Clean!B12 -> 60 | C12: =IF(B12="",Strategies!$B$5,B12) -> 60 | D12: =IF(B12="",1,0) -> 0 | E12: =Clean!E12 -> Business owner | F12: =IF(E12="","Unknown",E12) -> Business owner | G12: =Clean!G12 -> 105900 | H12: =IF(G12="",Strategies!$B$7,G12) -> 105900 | I12: =IF(G12="",Strategies!$B$8,G12) -> 105900 | J12: =IF(G12="",IFERROR(VLOOKUP(E12,Strategies!$A$26:$G$35,7,FALSE()),Strategies!$B$8),G12) -> 105900 | K12: =IF(G12="",1,0) -> 0 | L12: =Clean!H12 -> 21 | M12: =Clean!I12 -> 38567 | N12: =IF(L12="",IF(M12="",Strategies!$B$6,DATEDIF(M12,DATE(2026,9,13),"y")),L12) -> 21 | O12: =IF(L12<>"","observed",IF(M12<>"","derived from date","median (fallback)")) -> observed | P12: =Clean!M12 -> 0 | Q12: =IF(P12="",Strategies!$B$9,P12) -> 0 | R12: =IF(P12="",1,0) -> 0 | S12: =Clean!U12 -> 703 | T12: =IF(S12="",Strategies!$B$10,S12) -> 703 | U12: =Clean!J12 -> Online Banking | V12: =IF(U12="",Strategies!$B$11,U12) -> Online Banking | W12: =IF(U12="","Unknown",U12) -> Online Banking | X12: =Clean!Q12 -> 15000 | Y12: =Clean!R12 -> 6697.75 | Z12: =IF(X12="",IF(Y12="",0,""),X12) -> 15000 | AA12: =IF(Y12="",IF(X12="",0,IF(X12=0,0,ROUND(X12*Strategies!$B$12,2))),Y12) -> 6697.75 | AB12: =IF(AND(X12="",Y12=""),"no card (structural)",IF(X12="","limit missing – verify",IF(Y12="","spend imputed by ratio","complete"))) -> complete | AC12: =Clean!S12 -> 0 | AD12: =Clean!T12 -> 0 | AE12: =IF(AC12="",IF(AD12="",0,""),AC12) -> 0 | AF12: =IF(AD12="",IF(AC12="",0,IF(AC12=0,0,ROUND(AC12*Strategies!$B$13,0))),AD12) -> 0 | AG12: =Clean!V12 -> 0 | AH12: =IF(AG12="",0,AG12) -> 0 | AI12: =IF(AG12="",1,0) -> 0 | AJ12: =Missing_Matrix!W12 -> 0 | AK12: =IF(AJ12=0,"keep","drop") -> keep | AL12: =IF(Missing_Matrix!B12+Missing_Matrix!G12+Missing_Matrix!H12+Missing_Matrix!J12+Missing_Matrix!K12+Missing_Matrix!L12+Missing_Matrix!M12+Missing_Matrix!U12=0,"keep","drop") -> keep
A13: =Clean!A13 -> CL00012 | B13: =Clean!B13 -> 45 | C13: =IF(B13="",Strategies!$B$5,B13) -> 45 | D13: =IF(B13="",1,0) -> 0 | E13: =Clean!E13 -> Employee | F13: =IF(E13="","Unknown",E13) -> Employee | G13: =Clean!G13 -> 49600 | H13: =IF(G13="",Strategies!$B$7,G13) -> 49600 | I13: =IF(G13="",Strategies!$B$8,G13) -> 49600 | J13: =IF(G13="",IFERROR(VLOOKUP(E13,Strategies!$A$26:$G$35,7,FALSE()),Strategies!$B$8),G13) -> 49600 | K13: =IF(G13="",1,0) -> 0 | L13: =Clean!H13 -> 15 | M13: =Clean!I13 -> 40620 | N13: =IF(L13="",IF(M13="",Strategies!$B$6,DATEDIF(M13,DATE(2026,9,13),"y")),L13) -> 15 | O13: =IF(L13<>"","observed",IF(M13<>"","derived from date","median (fallback)")) -> observed | P13: =Clean!M13 -> 0 | Q13: =IF(P13="",Strategies!$B$9,P13) -> 0 | R13: =IF(P13="",1,0) -> 0 | S13: =Clean!U13 -> 679 | T13: =IF(S13="",Strategies!$B$10,S13) -> 679 | U13: =Clean!J13 -> App | V13: =IF(U13="",Strategies!$B$11,U13) -> App | W13: =IF(U13="","Unknown",U13) -> App | X13: =Clean!Q13 -> 5000 | Y13: =Clean!R13 -> 1097.89 | Z13: =IF(X13="",IF(Y13="",0,""),X13) -> 5000 | AA13: =IF(Y13="",IF(X13="",0,IF(X13=0,0,ROUND(X13*Strategies!$B$12,2))),Y13) -> 1097.89 | AB13: =IF(AND(X13="",Y13=""),"no card (structural)",IF(X13="","limit missing – verify",IF(Y13="","spend imputed by ratio","complete"))) -> complete | AC13: =Clean!S13 -> 0 | AD13: =Clean!T13 -> 0 | AE13: =IF(AC13="",IF(AD13="",0,""),AC13) -> 0 | AF13: =IF(AD13="",IF(AC13="",0,IF(AC13=0,0,ROUND(AC13*Strategies!$B$13,0))),AD13) -> 0 | AG13: =Clean!V13 -> 0 | AH13: =IF(AG13="",0,AG13) -> 0 | AI13: =IF(AG13="",1,0) -> 0 | AJ13: =Missing_Matrix!W13 -> 1 | AK13: =IF(AJ13=0,"keep","drop") -> drop | AL13: =IF(Missing_Matrix!B13+Missing_Matrix!G13+Missing_Matrix!H13+Missing_Matrix!J13+Missing_Matrix!K13+Missing_Matrix!L13+Missing_Matrix!M13+Missing_Matrix!U13=0,"keep","drop") -> drop
... A1001: =Clean!A1001 -> CL01000 | B1001: =Clean!B1001 -> 59 | C1001: =IF(B1001="",Strategies!$B$5,B1001) -> 59 | D1001: =IF(B1001="",1,0) -> 0 | E1001: =Clean!E1001 | F1001: =IF(E1001="","Unknown",E1001) -> Unknown | G1001: =Clean!G1001 -> 30900 | H1001: =IF(G1001="",Strategies!$B$7,G1001) -> 30900 | I1001: =IF(G1001="",Strategies!$B$8,G1001) -> 30900 | J1001: =IF(G1001="",IFERROR(VLOOKUP(E1001,Strategies!$A$26:$G$35,7,FALSE()),Strategies!$B$8),G1001) -> 30900 | K1001: =IF(G1001="",1,0) -> 0 | L1001: =Clean!H1001 -> 23 | M1001: =Clean!I1001 -> 37735 | N1001: =IF(L1001="",IF(M1001="",Strategies!$B$6,DATEDIF(M1001,DATE(2026,9,13),"y")),L1001) -> 23 | O1001: =IF(L1001<>"","observed",IF(M1001<>"","derived from date","median (fallback)")) -> observed | P1001: =Clean!M1001 -> 36369.97 | Q1001: =IF(P1001="",Strategies!$B$9,P1001) -> 36369.97 | R1001: =IF(P1001="",1,0) -> 0 | S1001: =Clean!U1001 -> 683 | T1001: =IF(S1001="",Strategies!$B$10,S1001) -> 683 | U1001: =Clean!J1001 -> Branch | V1001: =IF(U1001="",Strategies!$B$11,U1001) -> Branch | W1001: =IF(U1001="","Unknown",U1001) -> Branch | X1001: =Clean!Q1001 -> 7500 | Y1001: =Clean!R1001 -> 711.51 | Z1001: =IF(X1001="",IF(Y1001="",0,""),X1001) -> 7500 | AA1001: =IF(Y1001="",IF(X1001="",0,IF(X1001=0,0,ROUND(X1001*Strategies!$B$12,2))),Y1001) -> 711.51 | AB1001: =IF(AND(X1001="",Y1001=""),"no card (structural)",IF(X1001="","limit missing – verify",IF(Y1001="","spend imputed by ratio","complete"))) -> complete | AC1001: =Clean!S1001 -> 52000 | AD1001: =Clean!T1001 -> 363 | AE1001: =IF(AC1001="",IF(AD1001="",0,""),AC1001) -> 52000 | AF1001: =IF(AD1001="",IF(AC1001="",0,IF(AC1001=0,0,ROUND(AC1001*Strategies!$B$13,0))),AD1001) -> 363 | AG1001: =Clean!V1001 -> 1 | AH1001: =IF(AG1001="",0,AG1001) -> 1 | AI1001: =IF(AG1001="",1,0) -> 0 | AJ1001: =Missing_Matrix!W1001 -> 1 | AK1001: =IF(AJ1001=0,"keep","drop") -> drop | AL1001: =IF(Missing_Matrix!B1001+Missing_Matrix!G1001+Missing_Matrix!H1001+Missing_Matrix!J1001+Missing_Matrix!K1001+Missing_Matrix!L1001+Missing_Matrix!M1001+Missing_Matrix!U1001=0,"keep","drop") -> keep

Sheet Strategies
A1: Strategies — reference values, listwise deletion, group profiles, and (trainer only) accuracy vs. the truth
A2: Sections 1–4 are what participants can build from Clean alone. Section 5 uses Ground_Truth, which they do not have: it measures what each strategy does to the mean, the variance and the individual values.
A4: 1. Reference values used by the Imputed sheet (computed once, referenced 1,000 times)
A5: Age — median | B5: =MEDIAN(Clean!$B$2:$B$1001) -> 47 | C5: MEDIAN ignores the blanks and is robust to the extremes.
A6: Tenure_Years — median (fallback only) | B6: =MEDIAN(Clean!$H$2:$H$1001) -> 9 | C6: Used only when Account_Open_Date is missing too.
A7: Annual_Income_EUR — mean of the known values | B7: =ROUND(AVERAGE(Clean!$G$2:$G$1001),0) -> 34752 | C7: AVERAGE skips text; that is why the Clean sheet must be the source, not Customers.
A8: Annual_Income_EUR — median of the known values | B8: =MEDIAN(Clean!$G$2:$G$1001) -> 29500
A9: Savings_Balance_EUR — median | B9: =MEDIAN(Clean!$M$2:$M$1001) -> 10652.68
A10: Credit_Score — mean (rounded) | B10: =ROUND(AVERAGE(Clean!$U$2:$U$1001),0) -> 630 | C10: Roughly symmetric distribution: the mean is acceptable here.
A11: Preferred_Channel — mode | B11: =B$46 -> App | C11: From the frequency table in section 4.
A12: Card spend / card limit ratio (rows where both are known) | B12: =SUMIFS(Clean!$R$2:$R$1001,Clean!$Q$2:$Q$1001,">0",Clean!$R$2:$R$1001,">=0")/SUMIFS(Clean!$Q$2:$Q$1001,Clean!$Q$2:$Q$1001,">0",Clean!$R$2:$R$1001,">=0") -> 0.26569102 | C12: Ratio of the sums = a regression through the origin; the numeric criteria skip blanks automatically.
A13: Mortgage payment / balance ratio (rows where both are known) | B13: =SUMIFS(Clean!$T$2:$T$1001,Clean!$S$2:$S$1001,">0",Clean!$T$2:$T$1001,">=0")/SUMIFS(Clean!$S$2:$S$1001,Clean!$S$2:$S$1001,">0",Clean!$T$2:$T$1001,">=0") -> 0.0060816142
A15: 2. Listwise deletion — how many rows would survive?
A16: Rows in the file | B16: =ROWS(Clean!$A$2:$A$1001) -> 1000
A17: Complete rows (no missing value in any of the 21 columns) | B17: =COUNTIF(Missing_Matrix!$W$2:$W$1001,0) -> 295 | C17: COUNTIF on 'Missing cells in row' of Missing_Matrix.
A18: % of rows kept | B18: =B17/B16 -> 0.295 | C18: Most of the loss comes from structural blanks (cards, mortgages, complaints).
A19: Complete rows on the 8 model columns only (Age, Income, Tenure, Channel, Products, Checking, Savings, Score) | B19: =SUMPRODUCT(--((Missing_Matrix!$B$2:$B$1001+Missing_Matrix!$G$2:$G$1001+Missing_Matrix!$H$2:$H$1001+Missing_Matrix!$J$2:$J$1001+Missing_Matrix!$K$2:$K$1001+Missing_Matrix!$L$2:$L$1001+Missing_Matrix!$M$2:$M$1001+Missing_Matrix!$U$2:$U$1001)=0)) -> 723 | C19: Deleting on the columns we actually use is a different decision.
A20: % of rows kept | B20: =B19/B16 -> 0.723
A21: Ghost records (only the ID) | B21: =COUNTIF(Missing_Matrix!$Z$2:$Z$1001,"Ghost record") -> 4 | C21: Drop them: there is nothing to impute.
A22: Mostly-empty records (more than half of the columns) | B22: =COUNTIF(Missing_Matrix!$Z$2:$Z$1001,"Mostly empty") -> 6 | C22: Drop or send back to the source: imputing 13 columns invents a customer.
A24: 3. Is the missingness random? Annual_Income_EUR by Occupation (MAR) — also the lookup table for the group median
A25: Occupation | B25: Customers | C25: Income missing | D25: Missing rate | E25: Known incomes | F25: Mean income (known) | G25: Median income (known)
A26: Employee | B26: =COUNTIF(Clean!$E$2:$E$1001,$A26) -> 290 | C26: =SUMPRODUCT((Clean!$E$2:$E$1001=$A26)*(Clean!$G$2:$G$1001="")) -> 14 | D26: =IF(B26=0,"",C26/B26) -> 0.048275862 | E26: =COUNTIFS(Clean!$E$2:$E$1001,$A26,Clean!$G$2:$G$1001,">0") -> 276 | F26: =IFERROR(ROUND(AVERAGEIFS(Clean!$G$2:$G$1001,Clean!$E$2:$E$1001,$A26),0),"") -> 33188 | G26: {=IFERROR(MEDIAN(IF((Clean!$E$2:$E$1001=$A26)*ISNUMBER(Clean!$G$2:$G$1001),Clean!$G$2:$G$1001)),"")} -> 31600
A27: Manual worker | B27: =COUNTIF(Clean!$E$2:$E$1001,$A27) -> 178 | C27: =SUMPRODUCT((Clean!$E$2:$E$1001=$A27)*(Clean!$G$2:$G$1001="")) -> 4 | D27: =IF(B27=0,"",C27/B27) -> 0.02247191 | E27: =COUNTIFS(Clean!$E$2:$E$1001,$A27,Clean!$G$2:$G$1001,">0") -> 174 | F27: =IFERROR(ROUND(AVERAGEIFS(Clean!$G$2:$G$1001,Clean!$E$2:$E$1001,$A27),0),"") -> 23272 | G27: {=IFERROR(MEDIAN(IF((Clean!$E$2:$E$1001=$A27)*ISNUMBER(Clean!$G$2:$G$1001),Clean!$G$2:$G$1001)),"")} -> 21500
A28: Self-employed | B28: =COUNTIF(Clean!$E$2:$E$1001,$A28) -> 110 | C28: =SUMPRODUCT((Clean!$E$2:$E$1001=$A28)*(Clean!$G$2:$G$1001="")) -> 29 | D28: =IF(B28=0,"",C28/B28) -> 0.26363636 | E28: =COUNTIFS(Clean!$E$2:$E$1001,$A28,Clean!$G$2:$G$1001,">0") -> 81 | F28: =IFERROR(ROUND(AVERAGEIFS(Clean!$G$2:$G$1001,Clean!$E$2:$E$1001,$A28),0),"") -> 55573 | G28: {=IFERROR(MEDIAN(IF((Clean!$E$2:$E$1001=$A28)*ISNUMBER(Clean!$G$2:$G$1001),Clean!$G$2:$G$1001)),"")} -> 50600
A29: Executive | B29: =COUNTIF(Clean!$E$2:$E$1001,$A29) -> 51 | C29: =SUMPRODUCT((Clean!$E$2:$E$1001=$A29)*(Clean!$G$2:$G$1001="")) -> 3 | D29: =IF(B29=0,"",C29/B29) -> 0.058823529 | E29: =COUNTIFS(Clean!$E$2:$E$1001,$A29,Clean!$G$2:$G$1001,">0") -> 48 | F29: =IFERROR(ROUND(AVERAGEIFS(Clean!$G$2:$G$1001,Clean!$E$2:$E$1001,$A29),0),"") -> 99290 | G29: {=IFERROR(MEDIAN(IF((Clean!$E$2:$E$1001=$A29)*ISNUMBER(Clean!$G$2:$G$1001),Clean!$G$2:$G$1001)),"")} -> 97200
A30: Business owner | B30: =COUNTIF(Clean!$E$2:$E$1001,$A30) -> 53 | C30: =SUMPRODUCT((Clean!$E$2:$E$1001=$A30)*(Clean!$G$2:$G$1001="")) -> 16 | D30: =IF(B30=0,"",C30/B30) -> 0.30188679 | E30: =COUNTIFS(Clean!$E$2:$E$1001,$A30,Clean!$G$2:$G$1001,">0") -> 37 | F30: =IFERROR(ROUND(AVERAGEIFS(Clean!$G$2:$G$1001,Clean!$E$2:$E$1001,$A30),0),"") -> 66859 | G30: {=IFERROR(MEDIAN(IF((Clean!$E$2:$E$1001=$A30)*ISNUMBER(Clean!$G$2:$G$1001),Clean!$G$2:$G$1001)),"")} -> 64000
A31: Shopkeeper | B31: =COUNTIF(Clean!$E$2:$E$1001,$A31) -> 71 | C31: =SUMPRODUCT((Clean!$E$2:$E$1001=$A31)*(Clean!$G$2:$G$1001="")) -> 2 | D31: =IF(B31=0,"",C31/B31) -> 0.028169014 | E31: =COUNTIFS(Clean!$E$2:$E$1001,$A31,Clean!$G$2:$G$1001,">0") -> 69 | F31: =IFERROR(ROUND(AVERAGEIFS(Clean!$G$2:$G$1001,Clean!$E$2:$E$1001,$A31),0),"") -> 32925 | G31: {=IFERROR(MEDIAN(IF((Clean!$E$2:$E$1001=$A31)*ISNUMBER(Clean!$G$2:$G$1001),Clean!$G$2:$G$1001)),"")} -> 32300
A32: Teacher | B32: =COUNTIF(Clean!$E$2:$E$1001,$A32) -> 66 | C32: =SUMPRODUCT((Clean!$E$2:$E$1001=$A32)*(Clean!$G$2:$G$1001="")) -> 1 | D32: =IF(B32=0,"",C32/B32) -> 0.015151515 | E32: =COUNTIFS(Clean!$E$2:$E$1001,$A32,Clean!$G$2:$G$1001,">0") -> 65 | F32: =IFERROR(ROUND(AVERAGEIFS(Clean!$G$2:$G$1001,Clean!$E$2:$E$1001,$A32),0),"") -> 31762 | G32: {=IFERROR(MEDIAN(IF((Clean!$E$2:$E$1001=$A32)*ISNUMBER(Clean!$G$2:$G$1001),Clean!$G$2:$G$1001)),"")} -> 29400
A33: Student | B33: =COUNTIF(Clean!$E$2:$E$1001,$A33) -> 29 | C33: =SUMPRODUCT((Clean!$E$2:$E$1001=$A33)*(Clean!$G$2:$G$1001="")) -> 2 | D33: =IF(B33=0,"",C33/B33) -> 0.068965517 | E33: =COUNTIFS(Clean!$E$2:$E$1001,$A33,Clean!$G$2:$G$1001,">0") -> 27 | F33: =IFERROR(ROUND(AVERAGEIFS(Clean!$G$2:$G$1001,Clean!$E$2:$E$1001,$A33),0),"") -> 6067 | G33: {=IFERROR(MEDIAN(IF((Clean!$E$2:$E$1001=$A33)*ISNUMBER(Clean!$G$2:$G$1001),Clean!$G$2:$G$1001)),"")} -> 5900
A34: Retired | B34: =COUNTIF(Clean!$E$2:$E$1001,$A34) -> 76 | C34: =SUMPRODUCT((Clean!$E$2:$E$1001=$A34)*(Clean!$G$2:$G$1001="")) -> 3 | D34: =IF(B34=0,"",C34/B34) -> 0.039473684 | E34: =COUNTIFS(Clean!$E$2:$E$1001,$A34,Clean!$G$2:$G$1001,">0") -> 73 | F34: =IFERROR(ROUND(AVERAGEIFS(Clean!$G$2:$G$1001,Clean!$E$2:$E$1001,$A34),0),"") -> 21816 | G34: {=IFERROR(MEDIAN(IF((Clean!$E$2:$E$1001=$A34)*ISNUMBER(Clean!$G$2:$G$1001),Clean!$G$2:$G$1001)),"")} -> 20700
A35: Unemployed | B35: =COUNTIF(Clean!$E$2:$E$1001,$A35) -> 52 | C35: =SUMPRODUCT((Clean!$E$2:$E$1001=$A35)*(Clean!$G$2:$G$1001="")) -> 4 | D35: =IF(B35=0,"",C35/B35) -> 0.076923077 | E35: =COUNTIFS(Clean!$E$2:$E$1001,$A35,Clean!$G$2:$G$1001,">0") -> 48 | F35: =IFERROR(ROUND(AVERAGEIFS(Clean!$G$2:$G$1001,Clean!$E$2:$E$1001,$A35),0),"") -> 5142 | G35: {=IFERROR(MEDIAN(IF((Clean!$E$2:$E$1001=$A35)*ISNUMBER(Clean!$G$2:$G$1001),Clean!$G$2:$G$1001)),"")} -> 4900
A36: (occupation missing) | B36: =SUMPRODUCT(--(Clean!$E$2:$E$1001="")) -> 24 | C36: =SUMPRODUCT((Clean!$E$2:$E$1001="")*(Clean!$G$2:$G$1001="")) -> 5 | D36: =IF(B36=0,"",C36/B36) -> 0.20833333 | E36: =SUMPRODUCT((Clean!$E$2:$E$1001="")*ISNUMBER(Clean!$G$2:$G$1001)) -> 19 | F36: → fallback: overall median
A37: All customers | B37: =B16 -> 1000 | C37: =SUMPRODUCT(--(Clean!$G$2:$G$1001="")) -> 83 | D37: =C37/B37 -> 0.083 | E37: =COUNT(Clean!$G$2:$G$1001) -> 917 | F37: =B7 -> 34752 | G37: =B8 -> 29500
A38: Read column D: if the missing rate were the same for every occupation the blanks would be MCAR. Here two groups lose far more — and they are the high-income groups — so dropping the incomplete rows removes the wealthy customers (section 5), while a global mean or median fills them with an 'employee' income. The group median (column G) is what the Imputed sheet looks up with VLOOKUP.
A40: 4. Mode for a categorical column — Preferred_Channel
A41: Channel | B41: Count
A42: Branch | B42: =COUNTIF(Clean!$J$2:$J$1001,$A42) -> 279
A43: App | B43: =COUNTIF(Clean!$J$2:$J$1001,$A43) -> 327
A44: Online Banking | B44: =COUNTIF(Clean!$J$2:$J$1001,$A44) -> 309
A45: Phone | B45: =COUNTIF(Clean!$J$2:$J$1001,$A45) -> 50
A46: Mode | B46: =INDEX($A$42:$A$45,MATCH(MAX($B$42:$B$45),$B$42:$B$45,0)) -> App
A47: Missing after cleaning | B47: =SUMPRODUCT(--(Clean!$J$2:$J$1001="")) -> 35 | C47: Excel has no MODE for text: COUNTIF frequency table + INDEX/MATCH on the MAX.
A49: 5. TRAINER ONLY — what each strategy does, measured against Ground_Truth
A50: Annual_Income_EUR (MAR) | B50: Mean | C50: Std dev | D50: MAE on the imputed cells | E50: Comment
A51: True values (Ground_Truth) | B51: =AVERAGE(Ground_Truth!$G$2:$G$1001) -> 35826.7 | C51: =STDEV(Ground_Truth!$G$2:$G$1001) -> 24367.375 | D51: — | E51: The target we are trying to recover.
A52: Complete cases only (drop the missing rows) | B52: =AVERAGE(Clean!$G$2:$G$1001) -> 34751.69 | C52: =STDEV(Clean!$G$2:$G$1001) -> 23882.975 | D52: — | E52: Biased downwards: the missing incomes are the high ones (MAR on Occupation).
A53: Mean imputation (Imputed!H) | B53: =AVERAGE(Imputed!$H$2:$H$1001) -> 34751.716 | C53: =STDEV(Imputed!$H$2:$H$1001) -> 22869.328 | D53: =SUMPRODUCT(Imputed!$K$2:$K$1001*ABS(Imputed!$H$2:$H$1001-Ground_Truth!$G$2:$G$1001))/SUM(Imputed!$K$2:$K$1001) -> 21933.59 | E53: Same biased mean, and the standard deviation shrinks: every imputed value sits on the centre.
A54: Median imputation (Imputed!I) | B54: =AVERAGE(Imputed!$I$2:$I$1001) -> 34315.8 | C54: =STDEV(Imputed!$I$2:$I$1001) -> 22915.223 | D54: =SUMPRODUCT(Imputed!$K$2:$K$1001*ABS(Imputed!$I$2:$I$1001-Ground_Truth!$G$2:$G$1001))/SUM(Imputed!$K$2:$K$1001) -> 24131.325 | E54: Robust to outliers, blind to the mechanism.
A55: Group median by Occupation (Imputed!J) | B55: =AVERAGE(Imputed!$J$2:$J$1001) -> 35513.7 | C55: =STDEV(Imputed!$J$2:$J$1001) -> 23706.052 | D55: =SUMPRODUCT(Imputed!$K$2:$K$1001*ABS(Imputed!$J$2:$J$1001-Ground_Truth!$G$2:$G$1001))/SUM(Imputed!$K$2:$K$1001) -> 11354.217 | E55: Uses the column that drives the missingness: closest mean, closest std dev, lowest error.
A57: Share of Self-employed + Business owners among all customers | B57: =SUMPRODUCT(((Ground_Truth!$E$2:$E$1001="Self-employed")+(Ground_Truth!$E$2:$E$1001="Business owner")))/B16 -> 0.166 | C57: …and among the complete cases: listwise deletion changes who is in the sample.
A58: Share of Self-employed + Business owners among customers with a known income | B58: =SUMPRODUCT(((Clean!$E$2:$E$1001="Self-employed")+(Clean!$E$2:$E$1001="Business owner"))*ISNUMBER(Clean!$G$2:$G$1001))/COUNT(Clean!$G$2:$G$1001) -> 0.12868048
A60: Savings_Balance_EUR (MNAR) | B60: Value | E60: Comment
A61: True mean (Ground_Truth) | B61: =AVERAGE(Ground_Truth!$M$2:$M$1001) -> 23506.514 | E61: What we should get.
A62: Mean of the complete cases | B62: =AVERAGE(Clean!$M$2:$M$1001) -> 21657.509 | E62: Lower: the wealthiest customers are the ones who opted out.
A63: Mean after median imputation (Imputed!Q) | B63: =AVERAGE(Imputed!$Q$2:$Q$1001) -> 20733.103 | E63: Still lower: imputing the median of the observed values cannot recover what is missing because of the value itself.
A64: True mean of the cells that are missing | B64: =SUMPRODUCT(Imputed!$R$2:$R$1001*Ground_Truth!$M$2:$M$1001)/SUM(Imputed!$R$2:$R$1001) -> 43669.469 | E64: Compare with the value we imputed in the next row.
A65: Value we imputed (median of the observed) | B65: =B9 -> 10652.68 | E65: MNAR: no formula fixes this — a missing flag, a model on Income/Products/Tenure, and a question to the data owner.
A67: Tenure_Years (deterministic) | B67: Value | E67: Comment
A68: Cells derived from Account_Open_Date | B68: =COUNTIF(Imputed!$O$2:$O$1001,"derived from date") -> 22 | E68: Imputed!O tells where each value comes from.
A69: …of which exactly equal to the true value | B69: =SUMPRODUCT((Imputed!$O$2:$O$1001="derived from date")*(Imputed!$N$2:$N$1001=Ground_Truth!$H$2:$H$1001)) -> 22 | E69: 100%: when a column is a function of another, derive it — do not impute it.
A70: Cells filled with the median (date missing too) | B70: =COUNTIF(Imputed!$O$2:$O$1001,"median (fallback)") -> 12
A71: …of which exactly equal to the true value | B71: =SUMPRODUCT((Imputed!$O$2:$O$1001="median (fallback)")*(Imputed!$N$2:$N$1001=Ground_Truth!$H$2:$H$1001)) -> 2 | E71: A median is a guess: it is 'right' only by coincidence.
A73: Preferred_Channel (categorical) | B73: Value | E73: Comment
A74: Missing cells after cleaning | B74: =SUMPRODUCT(--(Imputed!$U$2:$U$1001="")) -> 35
A75: Mode imputation: share of imputed cells that match the truth | B75: =SUMPRODUCT((Imputed!$U$2:$U$1001="")*(Imputed!$V$2:$V$1001=Ground_Truth!$J$2:$J$1001))/B74 -> 0.31428571 | E75: Roughly the frequency of the majority class: the mode is right that often and wrong the rest of the time, silently.
A76: Explicit 'Unknown' category (Imputed!W): accuracy | B76: not applicable | E76: Nothing is invented; the model or the pivot table can see that the channel was unknown.
A78: Complaints_12M (does NULL mean 0?) | B78: Value | E78: Comment
A79: Blank cells after cleaning | B79: =SUMPRODUCT(--(Clean!$V$2:$V$1001="")) -> 214
A80: …of which the true value is 0 | B80: =SUMPRODUCT((Clean!$V$2:$V$1001="")*(Ground_Truth!$V$2:$V$1001=0)) -> 201 | E80: The 'NULL means 0' rule is right most of the time…
A81: …of which hide a real complaint (true value > 0) | B81: =SUMPRODUCT((Clean!$V$2:$V$1001="")*(Ground_Truth!$V$2:$V$1001>0)) -> 13 | E81: …and these are precisely the customers a retention model needs to see. Keep the missing flag.
A82: Share of blanks that really are 0 | B82: =B80/B79 -> 0.93925234
A84: Monthly_Card_Spend_EUR (ratio imputation) | B84: Value | E84: Comment
A85: Spend cells missing while the limit is known (imputed with limit × ratio) | B85: =SUMPRODUCT((Imputed!$Y$2:$Y$1001="")*ISNUMBER(Imputed!$X$2:$X$1001)*(Imputed!$X$2:$X$1001>0)) -> 15
A86: Mean absolute error vs. the true spend (EUR) | B86: =SUMPRODUCT((Imputed!$Y$2:$Y$1001="")*ISNUMBER(Imputed!$X$2:$X$1001)*(Imputed!$X$2:$X$1001>0)*ABS(Imputed!$AA$2:$AA$1001-Ground_Truth!$R$2:$R$1001))/B85 -> 619.88133 | E86: Compare with the median-imputation error below: the linked column carries real information.
A87: Mean absolute error if we had used the median spend instead (EUR) | B87: =SUMPRODUCT((Imputed!$Y$2:$Y$1001="")*ISNUMBER(Imputed!$X$2:$X$1001)*(Imputed!$X$2:$X$1001>0)*ABS(MEDIAN(Clean!$R$2:$R$1001)-Ground_Truth!$R$2:$R$1001))/B85 -> 970.58567

Sheet Ground_Truth
A1: Customer_ID | B1: Age | C1: Gender | D1: Region | E1: Occupation | F1: Marital_Status | G1: Annual_Income_EUR | H1: Tenure_Years | I1: Account_Open_Date | J1: Preferred_Channel | K1: Num_Products | L1: Checking_Balance_EUR | M1: Savings_Balance_EUR | N1: Monthly_Transactions | O1: Avg_Transaction_EUR | P1: Monthly_ATM_Withdrawals | Q1: Card_Limit_EUR | R1: Monthly_Card_Spend_EUR | S1: Mortgage_Balance_EUR | T1: Monthly_Mortgage_Payment_EUR | U1: Credit_Score | V1: Complaints_12M
A2: CL00001 | B2: 57 | C2: F | D2: Marche | E2: Shopkeeper | F2: Married | G2: 30100 | H2: 4 | I2: 44721 | J2: Branch | K2: 2 | L2: 6763.27 | M2: 12100.75 | N2: 23 | O2: 36.84 | P2: 1 | Q2: 0 | R2: 0 | S2: 93000 | T2: 603 | U2: 698 | V2: 0
A3: CL00002 | B3: 60 | C3: M | D3: Abruzzo | E3: Business owner | F3: Married | G3: 117400 | H3: 13 | I3: 41314 | J3: Branch | K3: 3 | L3: 39402.14 | M3: 124631.07 | N3: 49 | O3: 65.95 | P3: 1 | Q3: 15000 | R3: 3434.25 | S3: 0 | T3: 0 | U3: 700 | V3: 0
A4: CL00003 | B4: 42 | C4: F | D4: Molise | E4: Business owner | F4: Married | G4: 55600 | H4: 11 | I4: 41985 | J4: App | K4: 2 | L4: 2962.55 | M4: 70371.89 | N4: 33 | O4: 85.29 | P4: 1 | Q4: 11000 | R4: 3647.56 | S4: 0 | T4: 0 | U4: 749 | V4: 0
A5: CL00004 | B5: 44 | C5: F | D5: Umbria | E5: Employee | F5: Single | G5: 30200 | H5: 13 | I5: 41353 | J5: App | K5: 2 | L5: 3055.07 | M5: 31571.98 | N5: 17 | O5: 30.81 | P5: 1 | Q5: 6000 | R5: 2242.95 | S5: 0 | T5: 0 | U5: 601 | V5: 0
A6: CL00005 | B6: 68 | C6: F | D6: Lombardia | E6: Retired | F6: Married | G6: 21800 | H6: 8 | I6: 43047 | J6: Phone | K6: 1 | L6: 1554.39 | M6: 27565.84 | N6: 24 | O6: 29.47 | P6: 4 | Q6: 5000 | R6: 1312.86 | S6: 0 | T6: 0 | U6: 568 | V6: 1
A7: CL00006 | B7: 56 | C7: F | D7: Sardegna | E7: Shopkeeper | F7: Married | G7: 42300 | H7: 25 | I7: 36979 | J7: Branch | K7: 2 | L7: 879.82 | M7: 95638.97 | N7: 34 | O7: 90.6 | P7: 4 | Q7: 4500 | R7: 1699.41 | S7: 0 | T7: 0 | U7: 618 | V7: 2
A8: CL00007 | B8: 67 | C8: F | D8: Lombardia | E8: Retired | F8: Married | G8: 28300 | H8: 2 | I8: 45278 | J8: Online Banking | K8: 2 | L8: 6616.63 | M8: 2752.06 | N8: 30 | O8: 76 | P8: 2 | Q8: 4000 | R8: 2532.26 | S8: 0 | T8: 0 | U8: 666 | V8: 0
A9: CL00008 | B9: 43 | C9: M | D9: Calabria | E9: Teacher | F9: Married | G9: 28300 | H9: 10 | I9: 42273 | J9: App | K9: 4 | L9: -56.68 | M9: 28860.26 | N9: 23 | O9: 49.11 | P9: 3 | Q9: 3000 | R9: 363.95 | S9: 49000 | T9: 228 | U9: 544 | V9: 1
A10: CL00009 | B10: 25 | C10: M | D10: Campania | E10: Manual worker | F10: Single | G10: 17700 | H10: 3 | I10: 45141 | J10: Online Banking | K10: 2 | L10: 795.78 | M10: 8855.03 | N10: 25 | O10: 32.4 | P10: 3 | Q10: 0 | R10: 0 | S10: 0 | T10: 0 | U10: 536 | V10: 0
A11: CL00010 | B11: 36 | C11: M | D11: Piemonte | E11: Employee | F11: Single | G11: 32600 | H11: 7 | I11: 43377 | J11: App | K11: 1 | L11: -244.9 | M11: 0 | N11: 33 | O11: 68.04 | P11: 0 | Q11: 6000 | R11: 1052.22 | S11: 0 | T11: 0 | U11: 662 | V11: 0
A12: CL00011 | B12: 60 | C12: M | D12: Veneto | E12: Business owner | F12: Married | G12: 105900 | H12: 21 | I12: 38567 | J12: Online Banking | K12: 2 | L12: 8804.34 | M12: 0 | N12: 59 | O12: 87.83 | P12: 5 | Q12: 15000 | R12: 6697.75 | S12: 0 | T12: 0 | U12: 703 | V12: 0
A13: CL00012 | B13: 45 | C13: F | D13: Piemonte | E13: Employee | F13: Married | G13: 49600 | H13: 15 | I13: 40620 | J13: App | K13: 4 | L13: 1885.74 | M13: 0 | N13: 30 | O13: 69.35 | P13: 1 | Q13: 5000 | R13: 1097.89 | S13: 0 | T13: 0 | U13: 679 | V13: 0
... A143: CL00142 | B143: 52 | C143: M | D143: Piemonte | E143: Manual worker | F143: Single | G143: 22600 | H143: 2 | I143: 45536 | J143: App | K143: 1 | L143: 1195.03 | M143: 5429.1 | N143: 35 | O143: 40.65 | P143: 3 | Q143: 2500 | R143: 104.07 | S143: 0 | T143: 0 | U143: 551 | V143: 2
A144: CL00143 | B144: 34 | C144: F | D144: Campania | E144: Employee | F144: Married | G144: 31500 | H144: 8 | I144: 43111 | J144: App | K144: 2 | L144: 2711.19 | M144: 18196.1 | N144: 0 | P144: 0 | Q144: 5500 | R144: 2341.95 | S144: 0 | T144: 0 | U144: 565 | V144: 0
A145: CL00144 | B145: 52 | C145: M | D145: Toscana | E145: Employee | F145: Married | G145: 21500 | H145: 3 | I145: 44911 | J145: Online Banking | K145: 1 | L145: 2144.93 | M145: 5558.92 | N145: 22 | O145: 53.67 | P145: 1 | Q145: 3000 | R145: 565.51 | S145: 0 | T145: 0 | U145: 627 | V145: 0
A146: CL00145 | B146: 49 | C146: M | D146: Friuli-Venezia Giulia | E146: Employee | F146: Married | G146: 39900 | H146: 25 | I146: 36909 | J146: App | K146: 5 | L146: 4656.95 | M146: 0 | N146: 29 | O146: 63.72 | P146: 0 | Q146: 10000 | R146: 3880.46 | S146: 71000 | T146: 417 | U146: 662 | V146: 1
A147: CL00146 | B147: 38 | C147: M | D147: Trentino-Alto Adige | E147: Executive | F147: Married | G147: 122900 | H147: 7 | I147: 43440 | J147: Online Banking | K147: 2 | L147: -1240.07 | M147: 85363.04 | N147: 64 | O147: 101.05 | P147: 4 | Q147: 15000 | R147: 7183.56 | S147: 0 | T147: 0 | U147: 755 | V147: 0
A148: CL00147 | B148: 42 | C148: F | D148: Lazio | E148: Manual worker | F148: Single | G148: 25700 | H148: 2 | I148: 45343 | J148: Online Banking | K148: 2 | L148: 714.64 | M148: 14156.76 | N148: 34 | O148: 29.76 | P148: 4 | Q148: 0 | R148: 0 | S148: 52000 | T148: 246 | U148: 656 | V148: 0
A149: CL00148 | B149: 46 | C149: M | D149: Piemonte | E149: Manual worker | F149: Divorced | G149: 18200 | H149: 8 | I149: 43220 | J149: Phone | K149: 2 | L149: 1325.26 | M149: 9932.6 | N149: 16 | O149: 20.65 | P149: 1 | Q149: 2500 | R149: 364.73 | S149: 45000 | T149: 332 | U149: 596 | V149: 0
A150: CL00149 | B150: 47 | C150: M | D150: Abruzzo | E150: Unemployed | F150: Married | G150: 3400 | H150: 14 | I150: 40962 | J150: Branch | K150: 3 | L150: 422.26 | M150: 0 | N150: 13 | O150: 23.88 | P150: 9 | Q150: 500 | R150: 50.23 | S150: 0 | T150: 0 | U150: 498 | V150: 1
A151: CL00150 | B151: 58 | C151: M | D151: Basilicata | E151: Teacher | F151: Divorced | G151: 20700 | H151: 17 | I151: 39974 | J151: Branch | K151: 4 | L151: 1996.35 | M151: 0 | N151: 23 | O151: 21.63 | P151: 4 | Q151: 5000 | R151: 1576.16 | S151: 0 | T151: 0 | U151: 575 | V151: 0
A152: CL00151 | B152: 18 | C152: F | D152: Campania | E152: Employee | F152: Married | G152: 38100 | H152: 0 | I152: 46163 | J152: Branch | K152: 1 | L152: 5348.97 | M152: 3698.23 | N152: 23 | O152: 48.54 | P152: 2 | Q152: 8000 | R152: 2918.17 | S152: 0 | T152: 0 | U152: 616 | V152: 0
A153: CL00152 | B153: 34 | C153: M | D153: Marche | E153: Employee | F153: Married | G153: 19600 | H153: 13 | I153: 41423 | J153: App | K153: 4 | L153: 2614.76 | M153: 17685.66 | N153: 24 | O153: 36.61 | P153: 3 | Q153: 2000 | R153: 509.05 | S153: 0 | T153: 0 | U153: 690 | V153: 0
A154: CL00153 | B154: 21 | C154: M | D154: Lazio | E154: Manual worker | F154: Single | G154: 24000 | H154: 0 | I154: 46116 | J154: Online Banking | K154: 1 | L154: 3246.99 | M154: 0 | N154: 22 | O154: 32.81 | P154: 2 | Q154: 3500 | R154: 22.03 | S154: 0 | T154: 0 | U154: 697 | V154: 0
A155: CL00154 | B155: 44 | C155: M | D155: Campania | E155: Manual worker | F155: Divorced | G155: 21600 | H155: 14 | I155: 41048 | J155: Online Banking | K155: 2 | L155: 508.03 | M155: 0 | N155: 33 | O155: 32.03 | P155: 4 | Q155: 0 | R155: 0 | S155: 41000 | T155: 288 | U155: 576 | V155: 0
A156: CL00155 | B156: 40 | C156: F | D156: Emilia-Romagna | E156: Manual worker | F156: Divorced | G156: 33300 | H156: 11 | I156: 42127 | J156: Branch | K156: 3 | L156: 2642.13 | M156: 43538.54 | N156: 19 | O156: 27.11 | P156: 5 | Q156: 6000 | R156: 1024.72 | S156: 107000 | T156: 531 | U156: 626 | V156: 0
... A184: CL00183 | B184: 52 | C184: F | D184: Piemonte | E184: Self-employed | F184: Married | G184: 42300 | H184: 9 | I184: 42915 | J184: Online Banking | K184: 3 | L184: -1272.18 | M184: 55648.27 | N184: 30 | O184: 81.25 | P184: 2 | Q184: 0 | R184: 0 | S184: 0 | T184: 0 | U184: 643 | V184: 0
A185: CL00184 | B185: 48 | C185: M | D185: Lazio | E185: Manual worker | F185: Single | G185: 12700 | H185: 13 | I185: 41247 | J185: App | K185: 5 | L185: 1725.38 | M185: 16807.68 | N185: 0 | P185: 0 | Q185: 0 | R185: 0 | S185: 0 | T185: 0 | U185: 650 | V185: 1
A186: CL00185 | B186: 47 | C186: M | D186: Sicilia | E186: Employee | F186: Divorced | G186: 40600 | H186: 19 | I186: 39230 | J186: App | K186: 3 | L186: 1163.3 | M186: 42797.29 | N186: 26 | O186: 62.18 | P186: 3 | Q186: 0 | R186: 0 | S186: 0 | T186: 0 | U186: 632 | V186: 0
A187: CL00186 | B187: 57 | C187: F | D187: Veneto | E187: Employee | F187: Married | G187: 40000 | H187: 21 | I187: 38420 | J187: Branch | K187: 4 | L187: 2187.09 | M187: 0 | N187: 20 | O187: 84.03 | P187: 5 | Q187: 9500 | R187: 96.34 | S187: 0 | T187: 0 | U187: 673 | V187: 1
A188: CL00187 | B188: 46 | C188: F | D188: Toscana | E188: Self-employed | F188: Married | G188: 73600 | H188: 10 | I188: 42373 | J188: App | K188: 3 | L188: 3899.94 | M188: 0 | N188: 57 | O188: 101.72 | P188: 1 | Q188: 14000 | R188: 5327.29 | S188: 0 | T188: 0 | U188: 634 | V188: 1
A189: CL00188 | B189: 56 | C189: F | D189: Campania | E189: Employee | F189: Divorced | G189: 26000 | H189: 18 | I189: 39581 | J189: Online Banking | K189: 2 | L189: 1340.89 | M189: 46592.12 | N189: 28 | O189: 39.52 | P189: 1 | Q189: 5000 | R189: 1982.9 | S189: 0 | T189: 0 | U189: 565 | V189: 0
A190: CL00189 | B190: 44 | C190: F | D190: Lombardia | E190: Manual worker | F190: Married | G190: 21800 | H190: 9 | I190: 42757 | J190: Online Banking | K190: 4 | L190: 1069.72 | M190: 10536.27 | N190: 24 | O190: 36.93 | P190: 1 | Q190: 5000 | R190: 468.63 | S190: 0 | T190: 0 | U190: 563 | V190: 0
A191: CL00190 | B191: 21 | C191: F | D191: Lazio | E191: Student | F191: Single | G191: 4800 | H191: 1 | I191: 45691 | J191: Branch | K191: 1 | L191: 786.32 | M191: 1113 | N191: 9 | O191: 29.91 | P191: 3 | Q191: 500 | R191: 316.28 | S191: 0 | T191: 0 | U191: 475 | V191: 0
A192: CL00191 | B192: 50 | C192: F | D192: Veneto | E192: Employee | F192: Married | G192: 23000 | H192: 6 | I192: 44023 | J192: Branch | K192: 1 | L192: -589.44 | M192: 7183.53 | N192: 14 | O192: 36.84 | P192: 7 | Q192: 3000 | R192: 458.16 | S192: 0 | T192: 0 | U192: 622 | V192: 0
A193: CL00192 | B193: 73 | C193: M | D193: Campania | E193: Retired | F193: Widowed | G193: 22400 | H193: 18 | I193: 39375 | J193: Branch | K193: 2 | L193: 4010.28 | M193: 11223.22 | N193: 27 | O193: 42.11 | P193: 4 | Q193: 3000 | R193: 1136.77 | S193: 0 | T193: 0 | U193: 632 | V193: 0
A194: CL00193 | B194: 29 | C194: M | D194: Marche | E194: Unemployed | F194: Single | G194: 3000 | H194: 6 | I194: 43823 | J194: Online Banking | K194: 1 | L194: 115.7 | M194: 0 | N194: 15 | O194: 62.3 | P194: 2 | Q194: 500 | R194: 3.2 | S194: 0 | T194: 0 | U194: 561 | V194: 1
A195: CL00194 | B195: 30 | C195: M | D195: Friuli-Venezia Giulia | E195: Shopkeeper | F195: Single | G195: 34800 | H195: 1 | I195: 45757 | J195: App | K195: 1 | L195: 1442.2 | M195: 14001.85 | N195: 34 | O195: 73.86 | P195: 0 | Q195: 6000 | R195: 325.56 | S195: 0 | T195: 0 | U195: 577 | V195: 0
A196: CL00195 | B196: 36 | C196: F | D196: Puglia | E196: Manual worker | F196: Married | G196: 23100 | H196: 11 | I196: 41929 | J196: Branch | K196: 3 | L196: 3106.62 | M196: 21668.71 | N196: 16 | O196: 53.45 | P196: 4 | Q196: 0 | R196: 0 | S196: 42000 | T196: 263 | U196: 585 | V196: 2
A197: CL00196 | B197: 45 | C197: M | D197: Puglia | E197: Shopkeeper | F197: Married | G197: 28600 | H197: 7 | I197: 43368 | J197: App | K197: 1 | L197: 6495.02 | M197: 0 | N197: 36 | O197: 46.84 | P197: 0 | Q197: 6500 | R197: 830.2 | S197: 0 | T197: 0 | U197: 586 | V197: 0
... A203: CL00202 | B203: 57 | C203: F | D203: Veneto | E203: Employee | F203: Married | G203: 38500 | H203: 17 | I203: 39903 | J203: Branch | K203: 3 | L203: 1181.97 | M203: 36094.64 | N203: 20 | O203: 44.26 | P203: 4 | Q203: 0 | R203: 0 | S203: 0 | T203: 0 | U203: 674 | V203: 0
A204: CL00203 | B204: 26 | C204: M | D204: Lombardia | E204: Business owner | F204: Single | G204: 66800 | H204: 6 | I204: 43728 | J204: App | K204: 2 | L204: 10151.32 | M204: 56655.53 | N204: 0 | P204: 0 | Q204: 0 | R204: 0 | S204: 0 | T204: 0 | U204: 733 | V204: 0
A205: CL00204 | B205: 50 | C205: F | D205: Valle d'Aosta | E205: Employee | F205: Married | G205: 33400 | H205: 19 | I205: 39019 | J205: Online Banking | K205: 3 | L205: 4778.58 | M205: 71840.45 | N205: 35 | O205: 88.3 | P205: 3 | Q205: 3500 | R205: 626.99 | S205: 0 | T205: 0 | U205: 687 | V205: 0
A206: CL00205 | B206: 53 | C206: M | D206: Toscana | E206: Self-employed | F206: Single | G206: 63100 | H206: 11 | I206: 42225 | J206: Branch | K206: 1 | L206: 1596.24 | M206: 0 | N206: 25 | O206: 140.8 | P206: 3 | Q206: 12500 | R206: 3499.74 | S206: 0 | T206: 0 | U206: 586 | V206: 1
A207: CL00206 | B207: 85 | C207: F | D207: Campania | E207: Retired | F207: Married | G207: 30500 | H207: 9 | I207: 42798 | J207: App | K207: 4 | L207: 1764.6 | M207: 16516.57 | N207: 37 | O207: 45.43 | P207: 0 | Q207: 4500 | R207: 259.75 | S207: 0 | T207: 0 | U207: 587 | V207: 0
A208: CL00207 | B208: 33 | C208: F | D208: Friuli-Venezia Giulia | E208: Self-employed | F208: Divorced | G208: 27300 | H208: 11 | I208: 42059 | J208: Online Banking | K208: 4 | L208: 1919.6 | M208: 24978.05 | N208: 40 | O208: 30.93 | P208: 6 | Q208: 0 | R208: 0 | S208: 111000 | T208: 610 | U208: 675 | V208: 0
A209: CL00208 | B209: 47 | C209: F | D209: Piemonte | E209: Self-employed | F209: Married | G209: 67100 | H209: 10 | I209: 42552 | J209: Online Banking | K209: 3 | L209: 13342.69 | M209: 61783.66 | N209: 38 | O209: 39.91 | P209: 3 | Q209: 0 | R209: 0 | S209: 0 | T209: 0 | U209: 663 | V209: 0
A210: CL00209 | B210: 63 | C210: M | D210: Sardegna | E210: Unemployed | F210: Widowed | G210: 3000 | H210: 7 | I210: 43601 | J210: App | K210: 1 | L210: 214.58 | M210: 1026.38 | N210: 22 | O210: 56.82 | P210: 1 | Q210: 500 | R210: 132.72 | S210: 0 | T210: 0 | U210: 608 | V210: 0
A211: CL00210 | B211: 45 | C211: F | D211: Toscana | E211: Manual worker | F211: Married | G211: 17400 | H211: 6 | I211: 44015 | J211: Branch | K211: 3 | L211: 1744.62 | M211: 0 | N211: 18 | O211: 24.19 | P211: 5 | Q211: 0 | R211: 0 | S211: 0 | T211: 0 | U211: 623 | V211: 1
A212: CL00211 | B212: 51 | C212: F | D212: Sicilia | E212: Shopkeeper | F212: Single | G212: 29800 | H212: 4 | I212: 44471 | J212: App | K212: 4 | L212: 1691.57 | M212: 14958.98 | N212: 30 | O212: 42.77 | P212: 2 | Q212: 5000 | R212: 873.91 | S212: 0 | T212: 0 | U212: 534 | V212: 1
A213: CL00212 | B213: 52 | C213: F | D213: Lazio | E213: Executive | F213: Married | G213: 73000 | H213: 13 | I213: 41195 | J213: Online Banking | K213: 1 | L213: 47689.31 | M213: 139993.7 | N213: 35 | O213: 44.8 | P213: 3 | Q213: 15000 | R213: 2100.34 | S213: 0 | T213: 0 | U213: 684 | V213: 0
A214: CL00213 | B214: 18 | C214: M | D214: Lazio | E214: Student | F214: Single | G214: 4000 | H214: 0 | I214: 46024 | J214: Online Banking | K214: 1 | L214: 691.54 | M214: 445.92 | N214: 12 | O214: 25.5 | P214: 3 | Q214: 0 | R214: 0 | S214: 0 | T214: 0 | U214: 519 | V214: 0
A215: CL00214 | B215: 39 | C215: M | D215: Lombardia | E215: Employee | F215: Married | G215: 49800 | H215: 2 | I215: 45537 | J215: Branch | K215: 2 | L215: 9436.92 | M215: 0 | N215: 39 | O215: 109.56 | P215: 7 | Q215: 11000 | R215: 4639.07 | S215: 176000 | T215: 1089 | U215: 668 | V215: 0
A216: CL00215 | B216: 46 | C216: M | D216: Sicilia | E216: Employee | F216: Single | G216: 19900 | H216: 6 | I216: 43832 | J216: Branch | K216: 6 | L216: -236.65 | M216: 27725.25 | N216: 15 | O216: 69.04 | P216: 4 | Q216: 3000 | R216: 323.14 | S216: 0 | T216: 0 | U216: 662 | V216: 0
... A256: CL00255 | B256: 55 | C256: M | D256: Puglia | E256: Employee | F256: Single | G256: 29400 | H256: 15 | I256: 40720 | J256: Branch | K256: 2 | L256: 2931.49 | M256: 26216.16 | N256: 24 | O256: 17.82 | P256: 6 | Q256: 7000 | R256: 2269.33 | S256: 59000 | T256: 391 | U256: 631 | V256: 0
A257: CL00256 | B257: 35 | C257: F | D257: Sicilia | E257: Employee | F257: Divorced | G257: 17000 | H257: 6 | I257: 43794 | J257: Online Banking | K257: 1 | L257: 1607.85 | M257: 10651.66 | N257: 0 | P257: 0 | Q257: 4000 | R257: 867.27 | S257: 0 | T257: 0 | U257: 633 | V257: 0
A258: CL00257 | B258: 20 | C258: F | D258: Emilia-Romagna | E258: Student | F258: Married | G258: 5600 | H258: 1 | I258: 45584 | J258: App | K258: 3 | L258: 338.34 | M258: 1606.02 | N258: 27 | O258: 19.98 | P258: 2 | Q258: 1000 | R258: 205.03 | S258: 0 | T258: 0 | U258: 534 | V258: 0
A259: CL00258 | B259: 21 | C259: M | D259: Lazio | E259: Student | F259: Single | G259: 5000 | H259: 0 | I259: 46266 | J259: App | K259: 3 | L259: 176.66 | M259: 0 | N259: 15 | O259: 25.53 | P259: 0 | Q259: 1000 | R259: 77.66 | S259: 0 | T259: 0 | U259: 540 | V259: 0
A260: CL00259 | B260: 48 | C260: M | D260: Sardegna | E260: Shopkeeper | F260: Married | G260: 30800 | H260: 13 | I260: 41222 | J260: Online Banking | K260: 3 | L260: 5188.25 | M260: 0 | N260: 25 | O260: 23.63 | P260: 6 | Q260: 6000 | R260: 1116.06 | S260: 0 | T260: 0 | U260: 626 | V260: 0
A261: CL00260 | B261: 57 | C261: M | D261: Lombardia | E261: Employee | F261: Divorced | G261: 34000 | H261: 16 | I261: 40388 | J261: Online Banking | K261: 1 | L261: 3147.28 | M261: 0 | N261: 36 | O261: 69.84 | P261: 4 | Q261: 0 | R261: 0 | S261: 151000 | T261: 855 | U261: 682 | V261: 1
A262: CL00261 | B262: 63 | C262: F | D262: Sicilia | E262: Self-employed | F262: Single | G262: 58700 | H262: 7 | I262: 43469 | J262: App | K262: 2 | L262: 6600.49 | M262: 36279.52 | N262: 35 | O262: 84.83 | P262: 2 | Q262: 6000 | R262: 602.72 | S262: 0 | T262: 0 | U262: 705 | V262: 0
A263: CL00262 | B263: 18 | C263: M | D263: Lombardia | E263: Manual worker | F263: Single | G263: 16100 | H263: 0 | I263: 46244 | J263: Online Banking | K263: 3 | L263: 2324.78 | M263: 3304.33 | N263: 29 | O263: 23.91 | P263: 2 | Q263: 3500 | R263: 500.83 | S263: 0 | T263: 0 | U263: 500 | V263: 0
A264: CL00263 | B264: 49 | C264: M | D264: Veneto | E264: Unemployed | F264: Married | G264: 4500 | H264: 23 | I264: 37860 | J264: Online Banking | K264: 4 | L264: 327.22 | M264: 18079.46 | N264: 0 | P264: 0 | Q264: 500 | R264: 94.21 | S264: 0 | T264: 0 | U264: 594 | V264: 0
A265: CL00264 | B265: 47 | C265: M | D265: Umbria | E265: Self-employed | F265: Single | G265: 108700 | H265: 9 | I265: 42916 | J265: Online Banking | K265: 3 | L265: 13395.55 | M265: 78209.62 | N265: 53 | O265: 116.11 | P265: 1 | Q265: 15000 | R265: 1963.77 | S265: 0 | T265: 0 | U265: 611 | V265: 0
A266: CL00265 | B266: 35 | C266: F | D266: Lombardia | E266: Employee | F266: Married | G266: 30600 | H266: 8 | I266: 43316 | J266: App | K266: 2 | L266: 891.63 | M266: 18895.77 | N266: 0 | P266: 0 | Q266: 7000 | R266: 1838.32 | S266: 68000 | T266: 434 | U266: 661 | V266: 0
A267: CL00266 | B267: 30 | C267: M | D267: Molise | E267: Employee | F267: Divorced | G267: 18100 | H267: 6 | I267: 43761 | J267: Branch | K267: 2 | L267: 2945.42 | M267: 8193.73 | N267: 14 | O267: 34.04 | P267: 5 | Q267: 0 | R267: 0 | S267: 0 | T267: 0 | U267: 604 | V267: 1
A268: CL00267 | B268: 52 | C268: F | D268: Lombardia | E268: Employee | F268: Married | G268: 35000 | H268: 4 | I268: 44650 | J268: App | K268: 1 | L268: 1277.55 | M268: 12888.36 | N268: 28 | O268: 83.5 | P268: 0 | Q268: 6000 | R268: 361.43 | S268: 0 | T268: 0 | U268: 645 | V268: 0
A269: CL00268 | B269: 42 | C269: F | D269: Lazio | E269: Employee | F269: Widowed | G269: 25300 | H269: 4 | I269: 44777 | J269: App | K269: 1 | L269: 989.63 | M269: 0 | N269: 25 | O269: 65.86 | P269: 0 | Q269: 4000 | R269: 1309.22 | S269: 83000 | T269: 618 | U269: 576 | V269: 0
A270: CL00269 | B270: 44 | C270: F | D270: Lombardia | E270: Teacher | F270: Married | G270: 29400 | H270: 11 | I270: 42250 | J270: Online Banking | K270: 1 | L270: 2122.3 | M270: 28118.64 | N270: 26 | O270: 77.06 | P270: 0 | Q270: 3500 | R270: 262.31 | S270: 78000 | T270: 373 | U270: 624 | V270: 0
A271: CL00270 | B271: 65 | C271: F | D271: Sardegna | E271: Employee | F271: Divorced | G271: 28200 | H271: 17 | I271: 39769 | J271: App | K271: 3 | L271: 2119.73 | M271: 48978.82 | N271: 33 | O271: 27.22 | P271: 0 | Q271: 4500 | R271: 596.44 | S271: 107000 | T271: 567 | U271: 642 | V271: 0
A272: CL00271 | B272: 20 | C272: F | D272: Veneto | E272: Student | F272: Single | G272: 5900 | H272: 0 | I272: 46006 | J272: App | K272: 1 | L272: 397.07 | M272: 615.04 | N272: 20 | O272: 44 | P272: 1 | Q272: 0 | R272: 0 | S272: 0 | T272: 0 | U272: 554 | V272: 0
A273: CL00272 | B273: 48 | C273: F | D273: Lombardia | E273: Employee | F273: Single | G273: 31100 | H273: 5 | I273: 44346 | J273: Branch | K273: 1 | L273: 1490.67 | M273: 0 | N273: 16 | O273: 51.6 | P273: 1 | Q273: 4500 | R273: 1923.57 | S273: 0 | T273: 0 | U273: 657 | V273: 1
A274: CL00273 | B274: 28 | C274: F | D274: Lombardia | E274: Teacher | F274: Divorced | G274: 23900 | H274: 5 | I274: 44283 | J274: App | K274: 2 | L274: 3362.71 | M274: 0 | N274: 23 | O274: 33.84 | P274: 4 | Q274: 3000 | R274: 737.52 | S274: 0 | T274: 0 | U274: 619 | V274: 0
A275: CL00274 | B275: 23 | C275: M | D275: Lombardia | E275: Employee | F275: Single | G275: 37800 | H275: 1 | I275: 45628 | J275: App | K275: 1 | L275: 2016.63 | M275: 0 | N275: 35 | O275: 70.98 | P275: 1 | Q275: 4500 | R275: 1655.87 | S275: 0 | T275: 0 | U275: 643 | V275: 0
A276: CL00275 | B276: 61 | C276: F | D276: Lazio | E276: Employee | F276: Widowed | G276: 44100 | H276: 37 | I276: 32451 | J276: Branch | K276: 2 | L276: 5092.91 | M276: 50237.47 | N276: 25 | O276: 47.12 | P276: 4 | Q276: 10000 | R276: 4278.02 | S276: 0 | T276: 0 | U276: 726 | V276: 0
A277: CL00276 | B277: 43 | C277: F | D277: Puglia | E277: Self-employed | F277: Married | G277: 57200 | H277: 7 | I277: 43458 | J277: App | K277: 2 | L277: -1741.93 | M277: 0 | N277: 49 | O277: 76.54 | P277: 0 | Q277: 9500 | R277: 2931.73 | S277: 0 | T277: 0 | U277: 674 | V277: 0
A278: CL00277 | B278: 46 | C278: M | D278: Emilia-Romagna | E278: Self-employed | F278: Single | G278: 53200 | H278: 6 | I278: 43904 | J278: Online Banking | K278: 1 | L278: 3126.55 | M278: 31539.8 | N278: 40 | O278: 110.66 | P278: 3 | Q278: 0 | R278: 0 | S278: 0 | T278: 0 | U278: 731 | V278: 0
... A282: CL00281 | B282: 44 | C282: M | D282: Marche | E282: Business owner | F282: Divorced | G282: 49900 | H282: 7 | I282: 43566 | J282: Online Banking | K282: 1 | L282: 4132.66 | M282: 17439.11 | N282: 54 | O282: 75.21 | P282: 2 | Q282: 10500 | R282: 3901.92 | S282: 0 | T282: 0 | U282: 652 | V282: 0
A283: CL00282 | B283: 35 | C283: F | D283: Lombardia | E283: Shopkeeper | F283: Married | G283: 25700 | H283: 11 | I283: 42039 | J283: Branch | K283: 3 | L283: 1391.98 | M283: 11718.62 | N283: 0 | P283: 0 | Q283: 3000 | R283: 438.67 | S283: 75000 | T283: 432 | U283: 639 | V283: 0
A284: CL00283 | B284: 59 | C284: M | D284: Friuli-Venezia Giulia | E284: Executive | F284: Married | G284: 78300 | H284: 16 | I284: 40246 | J284: Branch | K284: 2 | L284: 3152.63 | M284: 52976.86 | N284: 35 | O284: 94.51 | P284: 3 | Q284: 15000 | R284: 5636.07 | S284: 0 | T284: 0 | U284: 755 | V284: 0
A285: CL00284 | B285: 32 | C285: M | D285: Puglia | E285: Business owner | F285: Married | G285: 60300 | H285: 6 | I285: 43864 | J285: Branch | K285: 1 | L285: 12975.04 | M285: 53140.8 | N285: 25 | O285: 58.45 | P285: 3 | Q285: 11500 | R285: 1379.89 | S285: 0 | T285: 0 | U285: 680 | V285: 0
A286: CL00285 | B286: 53 | C286: F | D286: Puglia | E286: Employee | F286: Widowed | G286: 32100 | H286: 15 | I286: 40764 | J286: Branch | K286: 2 | L286: 1740.93 | M286: 21573.82 | N286: 19 | O286: 49.43 | P286: 5 | Q286: 8000 | R286: 3768.91 | S286: 0 | T286: 0 | U286: 644 | V286: 0
A287: CL00286 | B287: 54 | C287: F | D287: Lombardia | E287: Employee | F287: Widowed | G287: 24800 | H287: 20 | I287: 38934 | J287: Online Banking | K287: 1 | L287: 712.4 | M287: 22300.13 | N287: 20 | O287: 61.84 | P287: 1 | Q287: 2500 | R287: 749.34 | S287: 0 | T287: 0 | U287: 687 | V287: 0
A288: CL00287 | B288: 54 | C288: M | D288: Veneto | E288: Employee | F288: Married | G288: 34400 | H288: 29 | I288: 35512 | J288: Online Banking | K288: 4 | L288: 8470.32 | M288: 69766.22 | N288: 35 | O288: 78.77 | P288: 3 | Q288: 5000 | R288: 1001.87 | S288: 0 | T288: 0 | U288: 732 | V288: 0
A289: CL00288 | B289: 24 | C289: M | D289: Emilia-Romagna | E289: Self-employed | F289: Single | G289: 36000 | H289: 1 | I289: 45589 | J289: Phone | K289: 1 | L289: 1885.65 | M289: 0 | N289: 19 | O289: 66.03 | P289: 3 | Q289: 6000 | R289: 3522.12 | S289: 0 | T289: 0 | U289: 660 | V289: 0
A290: CL00289 | B290: 26 | C290: F | D290: Lombardia | E290: Employee | F290: Single | G290: 24100 | H290: 4 | I290: 44816 | J290: App | K290: 2 | L290: 8413.42 | M290: 0 | N290: 33 | O290: 36.9 | P290: 1 | Q290: 3000 | R290: 773.34 | S290: 0 | T290: 0 | U290: 596 | V290: 0
A291: CL00290 | B291: 64 | C291: M | D291: Lombardia | E291: Executive | F291: Married | G291: 97000 | H291: 21 | I291: 38529 | J291: Branch | K291: 3 | L291: 11704.55 | M291: 216434.1 | N291: 42 | O291: 62.15 | P291: 5 | Q291: 15000 | R291: 4055.95 | S291: 248000 | T291: 1818 | U291: 694 | V291: 0
A292: CL00291 | B292: 19 | C292: M | D292: Umbria | E292: Student | F292: Single | G292: 4500 | H292: 0 | I292: 46123 | J292: Online Banking | K292: 3 | L292: 30.47 | M292: 741.59 | N292: 29 | O292: 20.84 | P292: 2 | Q292: 500 | R292: 96.21 | S292: 0 | T292: 0 | U292: 542 | V292: 0
A293: CL00292 | B293: 36 | C293: F | D293: Piemonte | E293: Self-employed | F293: Married | G293: 46800 | H293: 5 | I293: 44187 | J293: Branch | K293: 2 | L293: 3100.37 | M293: 14266.41 | N293: 16 | O293: 61.21 | P293: 7 | Q293: 10000 | R293: 1970.78 | S293: 122000 | T293: 572 | U293: 658 | V293: 0
A294: CL00293 | B294: 46 | C294: F | D294: Piemonte | E294: Manual worker | F294: Single | G294: 28400 | H294: 12 | I294: 41618 | J294: Branch | K294: 2 | L294: 2660.64 | M294: 24525.63 | N294: 20 | O294: 27.49 | P294: 3 | Q294: 0 | R294: 0 | S294: 0 | T294: 0 | U294: 664 | V294: 0
A295: CL00294 | B295: 73 | C295: F | D295: Toscana | E295: Retired | F295: Married | G295: 15800 | H295: 18 | I295: 39594 | J295: Phone | K295: 2 | L295: 2117.66 | M295: 0 | N295: 18 | O295: 39.19 | P295: 3 | Q295: 3000 | R295: 796.01 | S295: 0 | T295: 0 | U295: 663 | V295: 0
... A346: CL00345 | B346: 35 | C346: M | D346: Puglia | E346: Business owner | F346: Single | G346: 60700 | H346: 13 | I346: 41461 | J346: App | K346: 3 | L346: 2210.2 | M346: 48378.45 | N346: 51 | O346: 98.46 | P346: 2 | Q346: 9500 | R346: 6535.24 | S346: 0 | T346: 0 | U346: 644 | V346: 0
A347: CL00346 | B347: 33 | C347: M | D347: Lombardia | E347: Executive | F347: Married | G347: 117300 | H347: 4 | I347: 44644 | J347: App | K347: 1 | L347: 22940.89 | M347: 0 | N347: 0 | P347: 0 | Q347: 0 | R347: 0 | S347: 0 | T347: 0 | U347: 643 | V347: 1
A348: CL00347 | B348: 28 | C348: M | D348: Piemonte | E348: Self-employed | F348: Married | G348: 28700 | H348: 4 | I348: 44584 | J348: App | K348: 2 | L348: 1163.53 | M348: 4340.52 | N348: 26 | O348: 78.97 | P348: 0 | Q348: 6500 | R348: 2045.76 | S348: 109000 | T348: 752 | U348: 564 | V348: 1
A349: CL00348 | B349: 46 | C349: F | D349: Lombardia | E349: Shopkeeper | F349: Married | G349: 33400 | H349: 13 | I349: 41480 | J349: App | K349: 1 | L349: 1569.67 | M349: 0 | N349: 28 | O349: 36.71 | P349: 0 | Q349: 5000 | R349: 1283.49 | S349: 0 | T349: 0 | U349: 669 | V349: 0
A350: CL00349 | B350: 18 | C350: M | D350: Piemonte | E350: Unemployed | F350: Single | G350: 4200 | H350: 0 | I350: 46219 | J350: App | K350: 1 | L350: 1172.37 | M350: 688.28 | N350: 23 | O350: 45.38 | P350: 0 | Q350: 500 | R350: 174.24 | S350: 0 | T350: 0 | U350: 522 | V350: 0
A351: CL00350 | B351: 30 | C351: F | D351: Piemonte | E351: Employee | F351: Single | G351: 19900 | H351: 11 | I351: 41969 | J351: App | K351: 1 | L351: 1497.4 | M351: 0 | N351: 19 | O351: 29.35 | P351: 2 | Q351: 2500 | R351: 137.04 | S351: 0 | T351: 0 | U351: 594 | V351: 0
A352: CL00351 | B352: 18 | C352: F | D352: Lombardia | E352: Unemployed | F352: Married | G352: 4200 | H352: 0 | I352: 45969 | J352: Phone | K352: 2 | L352: -1528.1 | M352: 703.62 | N352: 13 | O352: 24.59 | P352: 4 | Q352: 0 | R352: 0 | S352: 0 | T352: 0 | U352: 506 | V352: 1
A353: CL00352 | B353: 55 | C353: M | D353: Abruzzo | E353: Manual worker | F353: Married | G353: 20500 | H353: 5 | I353: 44286 | J353: Phone | K353: 2 | L353: 1546.03 | M353: 0 | N353: 20 | O353: 70.99 | P353: 2 | Q353: 0 | R353: 0 | S353: 0 | T353: 0 | U353: 623 | V353: 0
...

Sheet Missing_Key_Trainer
A1: Key to the injected missing values — trainer-only sheet
A2: The participants' file (bank_customers_missing.xlsx) holds only Customers and Data_Dictionary. Below: what we removed or disguised, column by column, with the mechanism and the handling we recommend; the analysis sheets (Missing_Profile → Missing_Matrix → Clean → Imputed → Strategies) apply that workflow with live formulas. 1,598 cells are effectively missing in the Customers sheet (7.3% of the table); only 295 of the 1,000 rows are complete. Seed 26091307; the Python generator reproduces both files exactly.
A4: Column | B4: How the missing values appear | C4: Mechanism | D4: Documented? | E4: Cells | F4: What we injected | G4: Recommended handling | H4: How to find / fix it in Excel
A5: Age | B5: blank / 0 | C5: MCAR + sentinel | D5: no | E5: 30 | F5: 2% of the cells blanked at random; 1% set to 0 | G5: 0 is treated as missing first; then median + missing flag. | H5: Find: =MIN(B:B) returns 0; =COUNTIF(B:B,0); =COUNTBLANK(B:B); filter > (Blanks). Fix: =IF(B2="",median,B2).
A6: Gender | B6: blank / 'Unknown' | C6: MCAR | D6: no | E6: 20 | F6: 1% + 1%, at random | G6: Keep an explicit 'Unknown' category. | H6: Find: pivot table on Gender; =COUNTIF(C:C,"Unknown").
A7: Region | B7: blank / ' ' (whitespace) / 'n.d.' | C7: MCAR + encoding | D7: no | E7: 20 | F7: random | G7: TRIM, then explicit 'Unknown'. | H7: Find: =SUMPRODUCT((LEN(D2:D1001)>0)*(LEN(TRIM(D2:D1001))=0)) for the whitespace cells — the filter shows an item that looks blank but is listed separately from (Blanks).
A8: Occupation | B8: blank / '?' | C8: MCAR + encoding | D8: no | E8: 20 | F8: random | G8: Explicit 'Unknown'; the group-based imputation of Income needs a fallback for these rows. | H8: Find: pivot table; =COUNTIF(E:E,"~?") — the tilde escapes the wildcard, otherwise ? matches any single character.
A9: Marital_Status | B9: '-' / blank | C9: MCAR + encoding | D9: no | E9: 20 | F9: random | G9: Explicit 'Unknown'. | H9: Find: pivot table; =COUNTIF(F:F,"-").
A10: Annual_Income_EUR | B10: blank / 'N/A' | C10: MAR — depends on Occupation | D10: no | E10: 69 | F10: 28% missing for Self-employed and Business owners, 3% for everybody else; 30% of them typed as 'N/A' | G10: Group median by Occupation + missing flag. Strategies §3 shows the rate by group, §5 shows the bias of listwise deletion and of the global mean. | H10: Find: missing rate by Occupation with SUMPRODUCT (Strategies §3). Fix: VLOOKUP on the group table, fallback to the overall median.
A11: Annual_Income_EUR | B11: -999 | C11: Sentinel | D11: no | E11: 10 | F11: 1% of the cells | G11: Treat as missing. | H11: Find: =MIN(G:G) = -999; =COUNTIF(G:G,-999): an identical, repeated, out-of-range value.
A12: Annual_Income_EUR | B12: number stored as text ('35000') | C12: Encoding | D12: no | E12: 6 | F12: 6 cells exported as text — Excel rows 90, 246, 693, 808, 891, 930 | G12: Convert with VALUE(). Not missing, but AVERAGE/SUM/COUNT skip them silently and a sort puts them at the bottom. | H12: Find: green triangles; =COUNTA(G:G)-COUNT(G:G); =SUMPRODUCT(ISTEXT(G2:G1001)*ISNUMBER(VALUE(G2:G1001))). Fix: =VALUE(G2) or Data > Text to Columns.
A13: Tenure_Years | B13: blank | C13: MCAR | D13: no | E13: 30 | F13: 22 derivable from the opening date, 8 with the date missing as well | G13: Derive from Account_Open_Date; median only as a fallback (Imputed!N and !O). | H13: Fix: =DATEDIF(I2,DATE(2026,9,13),"y") — full years elapsed; =INT((extraction date − I2)/365.25) is the approximate version.
A14: Account_Open_Date | B14: blank | C14: MCAR | D14: no | E14: 20 | F14: 2% of the cells | G14: Approximate from Tenure_Years (and flag as approximate) or leave blank; never impute a mean date. | H14: Find: =COUNTBLANK(I:I). Fix: =DATE(2026-H2,9,13) if an approximation is acceptable.
A15: Account_Open_Date | B15: 1970-01-01 | C15: System default (epoch) | D15: no | E15: 8 | F15: 8 cells — Excel rows 35, 43, 142, 224, 439, 642, 693, 966 | G15: Treat as missing; Tenure_Years, when present, contradicts it. | H15: Find: =MIN(I:I); =COUNTIF(I:I,DATE(1970,1,1)); pivot by year; check =DATEDIF(I2,extraction,"y")<>H2.
A16: Preferred_Channel | B16: blank / 'Unknown' / 'N/A' | C16: MCAR + encoding | D16: no | E16: 25 | F16: random | G16: Explicit 'Unknown' — Strategies §5 measures how often the mode would be right. | H16: Find: pivot table on Preferred_Channel. Fix: =IF(J2="","Unknown",J2); mode with COUNTIF + INDEX/MATCH/MAX.
... A28: Complaints_12M | B28: blank | C28: Structural ('no complaints' stored as NULL) + MCAR | D28: no | E28: 204 | F28: 25% of the customers with 0 complaints stored as blank; plus 10 blanks that hide a real complaint (1 or more) | G28: Constant 0 + missing flag, and ask the data owner whether NULL means 0. Strategies §5 counts how often it does not. | H28: Find: =COUNTBLANK(V:V); cross-check with Credit_Score (complaints lower the score) or with the CRM.
A29: Total cells listed above (includes the recoverable text numbers, which are not missing) | E29: =SUM(E5:E28) -> 1442
A30: Reconciliation: total above − text numbers + ghost records × 21 + mostly-empty records × 13 | E30: =E29-E12+4*21+6*13 -> 1598
A31: Effective missing cells counted by Missing_Profile (live) | E31: =Missing_Profile!B5 -> 1598
A33: Record-level anomalies (rows, not cells)
A34: Kind | B34: Rows | C34: Excel rows | D34: Customer IDs | E34: What we did | F34: Handling
A35: Ghost record | B35: 4 | C35: 186, 421, 860, 942 | D35: CL00185, CL00420, CL00859, CL00941 | E35: Every column except Customer_ID blanked. | F35: Drop. Missing_Matrix flags them ('Ghost record', 21 missing cells); nothing to impute.
A36: Mostly-empty record | B36: 6 | C36: 45, 321, 428, 567, 616, 667 | D36: CL00044, CL00320, CL00427, CL00566, CL00615, CL00666 | E36: The 13 behavioural columns blanked (channel, products, balances, transactions, cards, mortgage, score, complaints); demographics, income, tenure and opening date kept. | F36: Drop or send back to the source: an onboarding record the behavioural extract never joined. Imputing 13 columns would invent a customer.
A39: Strategy cheat sheet
A40: Strategy | B40: Excel pattern | D40: Watch out for
A41: Listwise deletion (complete cases) | B41: =IF(Missing_Matrix!W2=0,"keep","drop"), then filter. | D41: Few missing rows, MCAR, and the columns we use are the ones we test. | G41: Biased sample under MAR/MNAR; here it keeps a minority of the rows.
A42: Pairwise deletion | B42: Nothing to do: AVERAGE, STDEV, CORREL skip blanks on their own. | D42: Quick descriptive statistics. | G42: Every statistic is computed on a different subset of customers.
A43: Constant / domain value | B43: =IF(cell="",0,cell); =IF(cell="","Unknown",cell). | D43: Structural blanks (no card, no mortgage, dormant account); categorical columns. | G43: Turns real gaps into fake zeros: keep the missing flag next to it.
A44: Mean imputation | B44: =IF(cell="",AVERAGE(range),cell) — compute the mean once in a reference cell. | D44: Symmetric numeric columns, MCAR, few gaps (Credit_Score). | G44: Shrinks the variance, flattens correlations, wrong under MAR (Income).
A45: Median imputation | B45: =IF(cell="",MEDIAN(range),cell). | D45: Skewed numeric columns (income, balances). | G45: Same blindness to the mechanism as the mean, but robust to outliers.
A46: Mode imputation | B46: COUNTIF frequency table + INDEX(cats,MATCH(MAX(counts),counts,0)). | D46: Categorical columns with a dominant level. | G46: Inflates the majority class silently; 'Unknown' usually beats it.
A47: Group-based (conditional) | B47: AVERAGEIFS(values,group,x) or {=MEDIAN(IF(group=x,values))} + VLOOKUP. | D47: MAR: the gap depends on another observed column (Income by Occupation). | G47: Needs a fallback when the group is missing too; small groups give noisy values.
A48: Deterministic derivation | B48: =DATEDIF(open_date,extraction_date,"y") for Tenure_Years. | D48: The column is a function of other columns. | G48: Check the rule on known rows first (here it reproduces 100%).
A49: Ratio / regression | B49: =limit × SUMIFS(spend)/SUMIFS(limit) on the rows where both are known. | D49: A strong relationship with another column (spend vs limit, instalment vs balance). | G49: Assumes the relationship holds for the missing rows.
A50: Missing-indicator flag | B50: =IF(cell="",1,0) kept as an extra column next to the imputed one. | D50: Always, when the data feed a model or a pivot: the fact that a value was missing is information. | G50: None — it is cheap. Just do not forget it.
A51: Hot-deck / nearest neighbour | B51: Sort by the similar columns, take the neighbour's value (INDEX/MATCH on a key). | D51: Small tables where plausible individual values matter more than the average. | G51: Hard to reproduce and to audit in Excel at scale.
A52: Ask the data owner | B52: No formula. | D52: Undocumented codes (-999, 9999, 'n.d.'), NULL-means-0 columns, MNAR suspicions. | G52: Nothing — it is always cheaper than guessing.
A54: Suggested classroom flow (the numbers are live)
A55: 1. Missing_Profile | B55: Start from the raw Customers sheet: COUNTBLANK first, then show that whitespace, placeholders and sentinels double the count. Change the sentinel in column I and watch the counts move.
A56: 2. Missing_Matrix | B56: ="Sort by the last column: "&Strategies!B21&" ghost records and "&Strategies!B22&" mostly-empty records jump out; the shaded blocks show which columns are missing together (cards, mortgages)." -> Sort by the last column: 4 ghost records and 6 mostly-empty records jump out; the shaded blocks show which columns are missing together (cards, mortgages).
A57: 3. Clean | B57: One formula pattern for every column, one placeholder list in Codes. From here on nobody reads Customers.
A58: 4. Imputed | B58: Each strategy in its own column, always next to the clean value and the missing flag — never overwrite.
A59: 5. Strategies | B59: ="Listwise deletion keeps "&TEXT(Strategies!B18,"0.0%")&" of the rows ("&TEXT(Strategies!B20,"0.0%")&" on the 8 model columns). Income: complete cases mean "&TEXT(Strategies!B52,"#,##0")&" vs true "&TEXT(Strategies!B51,"#,##0")&"; the group median gets "&TEXT(Strategies!B55,"#,##0")&". Savings (MNAR): the missing cells are worth "&TEXT(Strategies!B64,"#,##0")&" on average, we imputed "&TEXT(Strategies!B65,"#,##0")&"." -> Listwise deletion keeps 29.5% of the rows (72.3% on the 8 model columns). Income: complete cases mean 34,752 vs true 35,827; the group median gets 35,514. Savings (MNAR): the missing cells are worth 43,669 on average, we imputed 10,653.
A60: 6. Ground_Truth | B60: Reveal it at the end: the point is not to find the exact values, but to know which strategy biases what, and to keep the flags.
